{"type": "Feature", "geometry": {"type": "Point", "coordinates": [-0.775688, 50.837795]}, "properties": {"start-date": "1950-07-05", "point": "POINT (-0.775688 50.837795)", "listed-building": "1026773", "name": "Nos. 22 to 25 (consec) Little London", "documentation-url": "https://historicengland.org.uk/listing/the-list/list-entry/1026773", "listed-building-grade": "II", "slug": "/listed-building/1026773", "entry-date": "2021-05-28"}}