{"type": "Feature", "geometry": {"type": "Point", "coordinates": [0.191762, 50.8187]}, "properties": {"name": "CARNOY MILTON", "start-date": "1981-08-12", "point": "POINT (0.191762 50.818700)", "documentation-url": "https://historicengland.org.uk/listing/the-list/list-entry/1028485", "listed-building": "1028485", "listed-building-grade": "II", "slug": "/listed-building/1028485", "entry-date": "2021-05-28"}}