{"type": "Feature", "geometry": {"type": "Point", "coordinates": [0.079586, 51.050279]}, "properties": {"documentation-url": "https://historicengland.org.uk/listing/the-list/list-entry/1027969", "point": "POINT (0.079586 51.050279)", "name": "OLD LODGE", "start-date": "1991-02-13", "listed-building": "1027969", "listed-building-grade": "II", "slug": "/listed-building/1027969", "entry-date": "2021-05-28"}}