{"type": "Feature", "geometry": {"type": "Point", "coordinates": [1.389972, 52.193095]}, "properties": {"listed-building": "1030534", "listed-building-grade": "II", "start-date": "1984-11-19", "documentation-url": "https://historicengland.org.uk/listing/the-list/list-entry/1030534", "name": "BOTANY FARMHOUSE", "point": "POINT (1.389972 52.193095)", "slug": "/listed-building/1030534", "entry-date": "2021-05-28"}}