{"type": "Feature", "geometry": {"type": "Point", "coordinates": [1.446931, 52.212715]}, "properties": {"listed-building-grade": "II", "point": "POINT (1.446931 52.212715)", "start-date": "1983-09-21", "documentation-url": "https://historicengland.org.uk/listing/the-list/list-entry/1030904", "name": "BARN 25 METRES SOUTH EAST OF SHINGLE FARMHOUSE", "listed-building": "1030904", "slug": "/listed-building/1030904", "entry-date": "2021-05-28"}}