{"type": "Feature", "geometry": {"type": "Point", "coordinates": [-1.732064, 51.518078]}, "properties": {"name": "PARSONAGE FARMHOUSE", "documentation-url": "https://historicengland.org.uk/listing/the-list/list-entry/1023313", "listed-building": "1023313", "point": "POINT (-1.732064 51.518078)", "listed-building-grade": "II", "start-date": "1979-09-20", "slug": "/listed-building/1023313", "entry-date": "2021-05-28"}}