{"type": "Feature", "geometry": {"type": "Point", "coordinates": [0.048544, 51.261232]}, "properties": {"name": "MOORHOUSE COTTAGES MOORHOUSE FARM HOUSE", "listed-building": "1029766", "start-date": "1958-06-11", "point": "POINT (0.048544 51.261232)", "documentation-url": "https://historicengland.org.uk/listing/the-list/list-entry/1029766", "listed-building-grade": "II", "slug": "/listed-building/1029766", "entry-date": "1984-11-19"}}