{"type": "Feature", "geometry": {"type": "Point", "coordinates": [0.014189, 51.25855]}, "properties": {"documentation-url": "https://historicengland.org.uk/listing/the-list/list-entry/1029756", "listed-building-grade": "II", "name": "EBBUTS, FUNERAL DIRECTORS TYRELLS COTTAGE", "point": "POINT (0.014189 51.258550)", "listed-building": "1029756", "start-date": "1984-11-19", "slug": "/listed-building/1029756", "entry-date": "2021-05-28"}}