{"type": "Feature", "geometry": {"type": "Point", "coordinates": [-0.603469, 51.346272]}, "properties": {"point": "POINT (-0.603469 51.346272)", "listed-building-grade": "II", "listed-building": "1030009", "name": "CHANCELLORS GEMMAS FASHIONS NATIONAL WESTMINSTER BANK", "documentation-url": "https://historicengland.org.uk/listing/the-list/list-entry/1030009", "start-date": "1955-02-28", "slug": "/listed-building/1030009", "entry-date": "1984-07-19"}}