{"type": "Feature", "geometry": {"type": "Point", "coordinates": [-1.565272, 52.098312]}, "properties": {"point": "POINT (-1.565272 52.098312)", "listed-building-grade": "II*", "start-date": "1966-10-13", "listed-building": "1024347", "documentation-url": "https://historicengland.org.uk/listing/the-list/list-entry/1024347", "name": "CHURCH OF ST PETER", "slug": "/listed-building/1024347", "entry-date": "1986-06-30"}}