{"type": "Feature", "geometry": {"type": "Point", "coordinates": [-2.261442, 51.438625]}, "properties": {"point": "POINT (-2.261442 51.438625)", "documentation-url": "https://historicengland.org.uk/listing/the-list/list-entry/1022914", "listed-building": "1022914", "listed-building-grade": "II", "start-date": "1985-04-29", "name": "29 AND 31 HIGH STREET", "slug": "/listed-building/1022914", "entry-date": "2021-05-28"}}