{"type": "Feature", "geometry": {"type": "Point", "coordinates": [-0.583024, 51.224162]}, "properties": {"listed-building-grade": "II", "start-date": "1985-05-21", "listed-building": "1029535", "point": "POINT (-0.583024 51.224162)", "documentation-url": "https://historicengland.org.uk/listing/the-list/list-entry/1029535", "name": "BRABOEUF MANOR", "slug": "/listed-building/1029535", "entry-date": "2021-05-28"}}