{"type": "Feature", "geometry": {"type": "Point", "coordinates": [-0.363653, 51.043072]}, "properties": {"name": "DINING HALL AND WATER TOWER TO NORTH, SCHOOL TO SOUTH, COLLANNADED WINGS TO EAST AND WEST (CHAPEL IN WEST WING) FORMING A QUADRANGLE, AND 8 H SHAPED BLOCKS (4 ON EACH SIDE OF DINING HALL) AT CHRIST'S HOSPITAL", "documentation-url": "https://historicengland.org.uk/listing/the-list/list-entry/1027034", "point": "POINT (-0.363653 51.043072)", "start-date": "1959-09-22", "listed-building": "1027034", "listed-building-grade": "II*", "slug": "/listed-building/1027034", "entry-date": "1980-11-28"}}