{"type": "Feature", "geometry": {"type": "Point", "coordinates": [-1.732563, 51.012216]}, "properties": {"point": "POINT (-1.732563 51.012216)", "listed-building-grade": "II", "listed-building": "1023908", "name": "FARMHOUSE AT HOME FARM, TRAFALGAR", "documentation-url": "https://historicengland.org.uk/listing/the-list/list-entry/1023908", "start-date": "1985-07-04", "slug": "/listed-building/1023908", "entry-date": "2021-05-28"}}