{"type": "Feature", "geometry": {"type": "Point", "coordinates": [-0.512392, 50.960716]}, "properties": {"documentation-url": "https://historicengland.org.uk/listing/the-list/list-entry/1027373", "start-date": "1955-03-15", "point": "POINT (-0.512392 50.960716)", "listed-building": "1027373", "name": "OLD PLACE MANOR", "listed-building-grade": "II", "slug": "/listed-building/1027373", "entry-date": "1980-05-09"}}