{"type": "Feature", "geometry": {"type": "Point", "coordinates": [-0.132863, 51.060575]}, "properties": {"listed-building-grade": "II", "listed-building": "1025769", "point": "POINT (-0.132863 51.060575)", "start-date": "1983-05-11", "documentation-url": "https://historicengland.org.uk/listing/the-list/list-entry/1025769", "name": "BALCOMBE STORES", "slug": "/listed-building/1025769", "entry-date": "2021-05-28"}}