{"type": "Feature", "geometry": {"type": "Point", "coordinates": [-1.892632, 55.312886]}, "properties": {"start-date": "1987-08-25", "point": "POINT (-1.892632 55.312886)", "documentation-url": "https://historicengland.org.uk/listing/the-list/list-entry/1025308", "listed-building-grade": "II", "listed-building": "1025308", "name": "ROADSIDE WALL TO WEST AND NORTH OF CRAGSIDE PARK HOUSE", "slug": "/listed-building/1025308", "entry-date": "2021-05-28"}}