{"type": "Feature", "geometry": {"type": "Point", "coordinates": [-2.10739, 51.278618]}, "properties": {"listed-building": "1021485", "start-date": "1987-11-05", "point": "POINT (-2.107390 51.278618)", "documentation-url": "https://historicengland.org.uk/listing/the-list/list-entry/1021485", "listed-building-grade": "II", "name": "TWO ORAM MONUMENTS IN THE CHURCHYARD ABOUT 10 METRES SOUTH WEST OF CHURCH OF ST MARY, ST KATEHERINE AND ALL SAINTS", "slug": "/listed-building/1021485", "entry-date": "2021-05-28"}}