{"type": "Feature", "geometry": {"type": "Point", "coordinates": [-2.611201, 51.469368]}, "properties": {"point": "POINT (-2.611201 51.469368)", "documentation-url": "https://historicengland.org.uk/listing/the-list/list-entry/1025114", "listed-building": "1025114", "start-date": "1977-03-04", "listed-building-grade": "II", "name": "NUMBERS 1 TO 7 (CONSECUTIVE) AND ATTACHED FRONT GARDEN WALLS AND PIERS", "slug": "/listed-building/1025114", "entry-date": "1994-12-30"}}