{"type": "Feature", "geometry": {"type": "Point", "coordinates": [-1.776389, 51.037207]}, "properties": {"listed-building": "1023833", "listed-building-grade": "II", "documentation-url": "https://historicengland.org.uk/listing/the-list/list-entry/1023833", "start-date": "1985-03-28", "name": "LARGE GRANARY AT LONGFORD FARM", "point": "POINT (-1.776389 51.037207)", "slug": "/listed-building/1023833", "entry-date": "2021-05-28"}}