{"type": "Feature", "geometry": {"type": "Point", "coordinates": [-0.486215, 50.842022]}, "properties": {"listed-building-grade": "II", "name": "THE OLD COTTAGE", "start-date": "1984-09-20", "listed-building": "1027714", "point": "POINT (-0.486215 50.842022)", "documentation-url": "https://historicengland.org.uk/listing/the-list/list-entry/1027714", "slug": "/listed-building/1027714", "entry-date": "2021-05-28"}}