{"type": "Feature", "geometry": {"type": "Point", "coordinates": [1.356186, 52.120156]}, "properties": {"listed-building-grade": "I", "start-date": "1966-03-16", "listed-building": "1030273", "documentation-url": "https://historicengland.org.uk/listing/the-list/list-entry/1030273", "point": "POINT (1.356186 52.120156)", "name": "CHURCH OF ST MARY", "slug": "/listed-building/1030273", "entry-date": "2021-05-28"}}