{"type": "Feature", "geometry": {"type": "Point", "coordinates": [-2.269306, 51.414887]}, "properties": {"documentation-url": "https://historicengland.org.uk/listing/the-list/list-entry/1022721", "name": "BARN TO NORTH EAST OF ASHLEY FARM HOUSE", "listed-building-grade": "II", "listed-building": "1022721", "start-date": "1960-12-20", "point": "POINT (-2.269306 51.414887)", "slug": "/listed-building/1022721", "entry-date": "1985-07-24"}}