{"type": "Feature", "geometry": {"type": "Point", "coordinates": [1.485291, 52.199977]}, "properties": {"documentation-url": "https://historicengland.org.uk/listing/the-list/list-entry/1030906", "point": "POINT (1.485291 52.199977)", "name": "7 AND 8, BENHALL GREEN", "listed-building-grade": "II", "start-date": "1951-10-25", "listed-building": "1030906", "slug": "/listed-building/1030906", "entry-date": "2021-05-28"}}