{"type": "Feature", "geometry": {"type": "Point", "coordinates": [-0.870302, 50.874349]}, "properties": {"listed-building": "1026131", "point": "POINT (-0.870302 50.874349)", "start-date": "1986-01-28", "documentation-url": "https://historicengland.org.uk/listing/the-list/list-entry/1026131", "listed-building-grade": "II", "name": "THE LODGE OF ADSDEAN HOUSE TO THE SOUTH EAST OF THE HOUSE", "slug": "/listed-building/1026131", "entry-date": "2021-05-28"}}