{"type": "Feature", "geometry": {"type": "Point", "coordinates": [-0.655059, 51.258518]}, "properties": {"name": "CHAPEL FARM HOUSE", "listed-building": "1029657", "documentation-url": "https://historicengland.org.uk/listing/the-list/list-entry/1029657", "point": "POINT (-0.655059 51.258518)", "listed-building-grade": "II", "start-date": "1984-12-13", "slug": "/listed-building/1029657", "entry-date": "2021-05-28"}}