{"type": "Feature", "geometry": {"type": "Point", "coordinates": [0.057317, 51.021049]}, "properties": {"listed-building-grade": "II", "start-date": "1975-11-05", "listed-building": "1028422", "name": "THE OLD HOUSE, FUNNELLS FARM", "point": "POINT (0.057317 51.021049)", "documentation-url": "https://historicengland.org.uk/listing/the-list/list-entry/1028422", "slug": "/listed-building/1028422", "entry-date": "2021-05-28"}}