{"type": "Feature", "geometry": {"type": "Point", "coordinates": [-0.129239, 51.219352]}, "properties": {"name": "CRAB HILL FARM HOUSE", "start-date": "1984-04-25", "point": "POINT (-0.129239 51.219352)", "documentation-url": "https://historicengland.org.uk/listing/the-list/list-entry/1029865", "listed-building-grade": "II", "listed-building": "1029865", "slug": "/listed-building/1029865", "entry-date": "2021-05-28"}}