{"type": "Feature", "geometry": {"type": "Point", "coordinates": [-0.093632, 51.152256]}, "properties": {"start-date": "1984-04-25", "listed-building-grade": "II", "name": "CHERRY GARDENS", "listed-building": "1029939", "point": "POINT (-0.093632 51.152256)", "documentation-url": "https://historicengland.org.uk/listing/the-list/list-entry/1029939", "slug": "/listed-building/1029939", "entry-date": "2021-05-28"}}