{"type": "Feature", "geometry": {"type": "Point", "coordinates": [-1.504533, 52.409139]}, "properties": {"documentation-url": "https://historicengland.org.uk/listing/the-list/list-entry/1021930", "listed-building-grade": "II", "name": "Coventry Central Baths (original part including sunbathing terraces), part of Coventry Sports and Leisure Centre", "point": "POINT (-1.504533 52.409139)", "start-date": "1997-12-02", "listed-building": "1021930", "slug": "/listed-building/1021930", "entry-date": "2015-08-13"}}