{"type": "Feature", "geometry": {"type": "Point", "coordinates": [-1.795411, 51.070612]}, "properties": {"documentation-url": "https://historicengland.org.uk/listing/the-list/list-entry/1023580", "name": "PUBLIC LIBRARY YOUNG GALLERY", "point": "POINT (-1.795411 51.070612)", "listed-building": "1023580", "start-date": "1972-10-12", "listed-building-grade": "II", "slug": "/listed-building/1023580", "entry-date": "2021-05-28"}}