{"type": "Feature", "geometry": {"type": "Point", "coordinates": [-1.804699, 51.071383]}, "properties": {"documentation-url": "https://historicengland.org.uk/listing/the-list/list-entry/1023672", "point": "POINT (-1.804699 51.071383)", "name": "LONDON HOTEL", "listed-building": "1023672", "listed-building-grade": "II", "start-date": "1972-10-12", "slug": "/listed-building/1023672", "entry-date": "2021-05-28"}}