{"type": "Feature", "geometry": {"type": "Point", "coordinates": [-0.678513, 50.781749]}, "properties": {"documentation-url": "https://historicengland.org.uk/listing/the-list/list-entry/1027759", "point": "POINT (-0.678513 50.781749)", "start-date": "1975-11-07", "listed-building-grade": "II", "name": "THORNEYCROFT", "listed-building": "1027759", "slug": "/listed-building/1027759", "entry-date": "2021-05-28"}}