{"type": "Feature", "geometry": {"type": "Point", "coordinates": [-0.77608, 50.834352]}, "properties": {"name": "GATE PIERS AND WALL AT ENTRANCE TO FRIARY CLOSE TO NORTH", "listed-building-grade": "II", "documentation-url": "https://historicengland.org.uk/listing/the-list/list-entry/1026759", "start-date": "1971-07-16", "listed-building": "1026759", "point": "POINT (-0.776080 50.834352)", "slug": "/listed-building/1026759", "entry-date": "2021-05-28"}}