{"type": "Feature", "geometry": {"type": "Point", "coordinates": [0.10011, 50.977208]}, "properties": {"documentation-url": "https://historicengland.org.uk/listing/the-list/list-entry/1028089", "listed-building": "1028089", "name": "HENLEY HOUSE", "listed-building-grade": "II", "start-date": "1982-12-31", "point": "POINT (0.100110 50.977208)", "slug": "/listed-building/1028089", "entry-date": "2021-05-28"}}