{"type": "Feature", "geometry": {"type": "Point", "coordinates": [-0.203395, 50.995168]}, "properties": {"name": "THE BAKERY", "documentation-url": "https://historicengland.org.uk/listing/the-list/list-entry/1025718", "listed-building-grade": "II", "listed-building": "1025718", "start-date": "1983-05-11", "point": "POINT (-0.203395 50.995168)", "slug": "/listed-building/1025718", "entry-date": "2021-05-28"}}