{"type": "Feature", "geometry": {"type": "Point", "coordinates": [-2.238789, 51.414243]}, "properties": {"point": "POINT (-2.238789 51.414243)", "name": "ENCLOSING WALLS TO NORTH AND WEST OF HAZELBURY MANOR AND TERRACE IN WEST GARDEN", "start-date": "1985-07-24", "listed-building-grade": "II", "listed-building": "1022780", "documentation-url": "https://historicengland.org.uk/listing/the-list/list-entry/1022780", "slug": "/listed-building/1022780", "entry-date": "2021-05-28"}}