{"type": "Feature", "geometry": {"type": "Point", "coordinates": [-1.638819, 52.113609]}, "properties": {"name": "LINWOOD", "listed-building": "1024038", "start-date": "1988-05-16", "point": "POINT (-1.638819 52.113609)", "listed-building-grade": "II", "documentation-url": "https://historicengland.org.uk/listing/the-list/list-entry/1024038", "slug": "/listed-building/1024038", "entry-date": "2021-05-28"}}