{"type": "Feature", "geometry": {"type": "Point", "coordinates": [-0.20211, 50.93492]}, "properties": {"documentation-url": "https://historicengland.org.uk/listing/the-list/list-entry/1025784", "start-date": "1983-05-11", "listed-building": "1025784", "listed-building-grade": "II", "name": "BOUNTY COTTAGE", "point": "POINT (-0.202110 50.934920)", "slug": "/listed-building/1025784", "entry-date": "2021-05-28"}}