{"type": "Feature", "geometry": {"type": "Point", "coordinates": [0.140726, 51.026151]}, "properties": {"start-date": "1982-12-31", "documentation-url": "https://historicengland.org.uk/listing/the-list/list-entry/1028474", "name": "GROVEHURST", "listed-building-grade": "II", "listed-building": "1028474", "point": "POINT (0.140726 51.026151)", "slug": "/listed-building/1028474", "entry-date": "2021-05-28"}}