{"type": "Feature", "geometry": {"type": "Point", "coordinates": [-1.911735, 55.309415]}, "properties": {"point": "POINT (-1.911735 55.309415)", "name": "ROTHBURY CROSS", "listed-building-grade": "II", "listed-building": "1025321", "documentation-url": "https://historicengland.org.uk/listing/the-list/list-entry/1025321", "start-date": "1953-10-21", "slug": "/listed-building/1025321", "entry-date": "2021-05-28"}}