{"type": "Feature", "geometry": {"type": "Point", "coordinates": [-0.228299, 50.981852]}, "properties": {"listed-building": "1025759", "listed-building-grade": "II", "name": "DAWE'S FARMHOUSE", "documentation-url": "https://historicengland.org.uk/listing/the-list/list-entry/1025759", "point": "POINT (-0.228299 50.981852)", "start-date": "1957-10-28", "slug": "/listed-building/1025759", "entry-date": "2021-05-28"}}