{"type": "Feature", "geometry": {"type": "Point", "coordinates": [-0.781302, 50.835323]}, "properties": {"start-date": "1971-10-08", "listed-building": "1026835", "documentation-url": "https://historicengland.org.uk/listing/the-list/list-entry/1026835", "point": "POINT (-0.781302 50.835323)", "name": "GATES AND GATEWAY TO THE DEANERY", "listed-building-grade": "II", "slug": "/listed-building/1026835", "entry-date": "2021-05-28"}}