{"type": "Feature", "geometry": {"type": "Point", "coordinates": [-2.008196, 51.520613]}, "properties": {"documentation-url": "https://historicengland.org.uk/listing/the-list/list-entry/1022489", "point": "POINT (-2.008196 51.520613)", "listed-building": "1022489", "listed-building-grade": "II", "start-date": "1987-11-25", "name": "HOPE HOUSE", "slug": "/listed-building/1022489", "entry-date": "2021-05-28"}}