{"type": "Feature", "geometry": {"type": "Point", "coordinates": [-1.392908, 52.167774]}, "properties": {"listed-building-grade": "II", "documentation-url": "https://historicengland.org.uk/listing/the-list/list-entry/1024237", "point": "POINT (-1.392908 52.167774)", "listed-building": "1024237", "start-date": "1987-04-08", "name": "THE OLD BAKEHOUSE", "slug": "/listed-building/1024237", "entry-date": "2021-05-28"}}