{"type": "Feature", "geometry": {"type": "Point", "coordinates": [1.546726, 52.115598]}, "properties": {"name": "CRAG FARM COTTAGES", "listed-building-grade": "II", "start-date": "1984-01-16", "point": "POINT (1.546726 52.115598)", "listed-building": "1030845", "documentation-url": "https://historicengland.org.uk/listing/the-list/list-entry/1030845", "slug": "/listed-building/1030845", "entry-date": "2021-05-28"}}