{"type": "Feature", "geometry": {"type": "Point", "coordinates": [-1.884858, 51.579998]}, "properties": {"listed-building": "1023186", "listed-building-grade": "II", "point": "POINT (-1.884858 51.579998)", "documentation-url": "https://historicengland.org.uk/listing/the-list/list-entry/1023186", "name": "MILESTONE ON CORNER OF MUD LANE", "start-date": "1986-04-17", "slug": "/listed-building/1023186", "entry-date": "2021-05-28"}}