{"type": "Feature", "geometry": {"type": "Point", "coordinates": [-1.929845, 52.25351]}, "properties": {"start-date": "1985-10-23", "documentation-url": "https://historicengland.org.uk/listing/the-list/list-entry/1024514", "listed-building": "1024514", "point": "POINT (-1.929845 52.253510)", "name": "STABLE, BARN AND ATTACHED COWHOUSES APPROXIMATELY 7 METRES NORTH EAST OF SAMBOURNE WARREN FARMHOUSE", "listed-building-grade": "II", "slug": "/listed-building/1024514", "entry-date": "2021-05-28"}}