{"type": "Feature", "geometry": {"type": "Point", "coordinates": [-2.102233, 51.473265]}, "properties": {"documentation-url": "https://historicengland.org.uk/listing/the-list/list-entry/1022357", "start-date": "1960-12-22", "listed-building-grade": "II*", "name": "KILVERT'S PARSONAGE", "point": "POINT (-2.102233 51.473265)", "listed-building": "1022357", "slug": "/listed-building/1022357", "entry-date": "2021-05-28"}}