{"type": "Feature", "geometry": {"type": "Point", "coordinates": [-0.753056, 50.910543]}, "properties": {"documentation-url": "https://historicengland.org.uk/listing/the-list/list-entry/1026204", "listed-building": "1026204", "point": "POINT (-0.753056 50.910543)", "listed-building-grade": "II", "start-date": "1986-01-28", "name": "TWO WAYS", "slug": "/listed-building/1026204", "entry-date": "2021-05-28"}}