{"type": "Feature", "geometry": {"type": "Point", "coordinates": [-1.624513, 54.98337]}, "properties": {"documentation-url": "https://historicengland.org.uk/listing/the-list/list-entry/1024906", "listed-building-grade": "II", "point": "POINT (-1.624513 54.983370)", "name": "HALL OF CHURCH OF ST LUKE", "start-date": "1987-03-30", "listed-building": "1024906", "slug": "/listed-building/1024906", "entry-date": "2021-05-28"}}