{"type": "Feature", "geometry": {"type": "Point", "coordinates": [-0.662599, 51.221249]}, "properties": {"listed-building-grade": "II", "name": "FARM COTTAGE", "listed-building": "1029635", "start-date": "1984-12-13", "point": "POINT (-0.662599 51.221249)", "documentation-url": "https://historicengland.org.uk/listing/the-list/list-entry/1029635", "slug": "/listed-building/1029635", "entry-date": "2021-05-28"}}