{"type": "Feature", "geometry": {"type": "Point", "coordinates": [-2.166344, 51.512142]}, "properties": {"point": "POINT (-2.166344 51.512142)", "listed-building-grade": "II", "listed-building": "1022292", "documentation-url": "https://historicengland.org.uk/listing/the-list/list-entry/1022292", "name": "LEIGH DELAMERE HOUSE", "start-date": "1988-02-29", "slug": "/listed-building/1022292", "entry-date": "2021-05-28"}}