{"type": "Feature", "geometry": {"type": "Point", "coordinates": [-0.405178, 51.071767]}, "properties": {"listed-building-grade": "II", "name": "K6 TELEPHONE KIOSK OPPOSITE KINGS HEAD PUBLIC HOUSE", "listed-building": "1026852", "documentation-url": "https://historicengland.org.uk/listing/the-list/list-entry/1026852", "start-date": "1989-08-08", "point": "POINT (-0.405178 51.071767)", "slug": "/listed-building/1026852", "entry-date": "2021-05-28"}}