{"type": "Feature", "geometry": {"type": "Point", "coordinates": [-0.201976, 50.934005]}, "properties": {"documentation-url": "https://historicengland.org.uk/listing/the-list/list-entry/1025788", "listed-building": "1025788", "start-date": "1957-10-28", "name": "THE ARCHES", "point": "POINT (-0.201976 50.934005)", "listed-building-grade": "II", "slug": "/listed-building/1025788", "entry-date": "1983-05-11"}}