{"type": "Feature", "geometry": {"type": "Point", "coordinates": [-0.530164, 51.407881]}, "properties": {"documentation-url": "https://historicengland.org.uk/listing/the-list/list-entry/1028931", "listed-building-grade": "II", "listed-building": "1028931", "name": "SPELTHORNE ST MARY", "point": "POINT (-0.530164 51.407881)", "start-date": "1976-01-14", "slug": "/listed-building/1028931", "entry-date": "2021-05-28"}}