{"type": "Feature", "geometry": {"type": "Point", "coordinates": [-2.156309, 51.384296]}, "properties": {"name": "STABLES AT SHAW HOUSE", "point": "POINT (-2.156309 51.384296)", "listed-building": "1021751", "documentation-url": "https://historicengland.org.uk/listing/the-list/list-entry/1021751", "start-date": "1985-02-13", "listed-building-grade": "II", "slug": "/listed-building/1021751", "entry-date": "2021-05-28"}}