{"type": "Feature", "geometry": {"type": "Point", "coordinates": [-0.631031, 51.221649]}, "properties": {"name": "LIMNERSLEASE, THE GREAT STUDIO AND THE WEST WING", "documentation-url": "https://historicengland.org.uk/listing/the-list/list-entry/1029544", "start-date": "1967-06-14", "listed-building-grade": "II", "listed-building": "1029544", "point": "POINT (-0.631031 51.221649)", "slug": "/listed-building/1029544", "entry-date": "2021-05-28"}}