{"type": "Feature", "geometry": {"type": "Point", "coordinates": [-0.389013, 50.930805]}, "properties": {"listed-building-grade": "II", "name": "THE LORNIES", "start-date": "1955-03-15", "documentation-url": "https://historicengland.org.uk/listing/the-list/list-entry/1027160", "listed-building": "1027160", "point": "POINT (-0.389013 50.930805)", "slug": "/listed-building/1027160", "entry-date": "1980-05-09"}}