{"type": "Feature", "geometry": {"type": "Point", "coordinates": [-0.885698, 50.856331]}, "properties": {"documentation-url": "https://historicengland.org.uk/listing/the-list/list-entry/1026176", "listed-building-grade": "II", "point": "POINT (-0.885698 50.856331)", "listed-building": "1026176", "start-date": "1986-01-28", "name": "NEWELL HOUSE", "slug": "/listed-building/1026176", "entry-date": "2021-05-28"}}