{"type": "Feature", "geometry": {"type": "Point", "coordinates": [-2.182099, 51.434462]}, "properties": {"listed-building-grade": "II", "point": "POINT (-2.182099 51.434462)", "documentation-url": "https://historicengland.org.uk/listing/the-list/list-entry/1021987", "start-date": "1986-08-01", "name": "SWEATMAN MONUMENT IN CHURCHYARD ABOUT 3 METRES SOUTH OF CHURCHYARD NORTH WALL, NORTH OF NORTH TRANSEPT OF CHURCH OF ST BARTHOLOMEW", "listed-building": "1021987", "slug": "/listed-building/1021987", "entry-date": "2021-05-28"}}