{"type": "Feature", "geometry": {"type": "Point", "coordinates": [-2.287649, 51.329341]}, "properties": {"listed-building-grade": "II", "start-date": "1988-06-14", "name": "GATE PIERS AT WEST END OF GREAT TERRACE IN GARDENS AT IFORD MANOR", "documentation-url": "https://historicengland.org.uk/listing/the-list/list-entry/1021879", "listed-building": "1021879", "point": "POINT (-2.287649 51.329341)", "slug": "/listed-building/1021879", "entry-date": "2021-05-28"}}