{"type": "Feature", "geometry": {"type": "Point", "coordinates": [-0.085221, 51.282094]}, "properties": {"documentation-url": "https://historicengland.org.uk/listing/the-list/list-entry/1029816", "listed-building": "1029816", "listed-building-grade": "II", "point": "POINT (-0.085221 51.282094)", "name": "CHURCH OF ST MARY", "start-date": "1984-11-19", "slug": "/listed-building/1029816", "entry-date": "2021-05-28"}}