{"type": "Feature", "geometry": {"type": "Point", "coordinates": [-0.562406, 50.958284]}, "properties": {"documentation-url": "https://historicengland.org.uk/listing/the-list/list-entry/1026494", "name": "The Terrace or Restharrow", "start-date": "1985-05-22", "listed-building": "1026494", "listed-building-grade": "II", "point": "POINT (-0.562406 50.958284)", "slug": "/listed-building/1026494", "entry-date": "1991-06-12"}}