{"type": "Feature", "geometry": {"type": "Point", "coordinates": [-2.084942, 51.519854]}, "properties": {"start-date": "1988-02-29", "listed-building": "1022394", "point": "POINT (-2.084942 51.519854)", "listed-building-grade": "II", "name": "BARN AT HARDINGS FARM", "documentation-url": "https://historicengland.org.uk/listing/the-list/list-entry/1022394", "slug": "/listed-building/1022394", "entry-date": "2021-05-28"}}