{"type": "Feature", "geometry": {"type": "Point", "coordinates": [-0.779191, 50.836518]}, "properties": {"point": "POINT (-0.779191 50.836518)", "start-date": "1950-07-05", "documentation-url": "https://historicengland.org.uk/listing/the-list/list-entry/1026826", "listed-building": "1026826", "listed-building-grade": "I", "name": "THE MARKET CROSS", "slug": "/listed-building/1026826", "entry-date": "2021-05-28"}}