{"type": "Feature", "geometry": {"type": "Point", "coordinates": [-1.971443, 51.475527]}, "properties": {"listed-building-grade": "II", "start-date": "1987-11-25", "documentation-url": "https://historicengland.org.uk/listing/the-list/list-entry/1022492", "listed-building": "1022492", "point": "POINT (-1.971443 51.475527)", "name": "THE OLD FORGE", "slug": "/listed-building/1022492", "entry-date": "2021-05-28"}}