{"type": "Feature", "geometry": {"type": "Point", "coordinates": [1.546571, 52.274008]}, "properties": {"listed-building-grade": "II", "point": "POINT (1.546571 52.274008)", "documentation-url": "https://historicengland.org.uk/listing/the-list/list-entry/1030665", "name": "TUDOR COTTAGE", "start-date": "1984-07-27", "listed-building": "1030665", "slug": "/listed-building/1030665", "entry-date": "2021-05-28"}}