{"type": "Feature", "geometry": {"type": "Point", "coordinates": [-0.840054, 50.969456]}, "properties": {"start-date": "1987-11-26", "listed-building-grade": "II", "listed-building": "1025988", "point": "POINT (-0.840054 50.969456)", "name": "MILL COTTAGE", "documentation-url": "https://historicengland.org.uk/listing/the-list/list-entry/1025988", "slug": "/listed-building/1025988", "entry-date": "2021-05-28"}}