{"type": "Feature", "geometry": {"type": "Point", "coordinates": [-2.403209, 52.958399]}, "properties": {"listed-building": "1029842", "name": "METHODIST CHURCH", "point": "POINT (-2.403209 52.958399)", "documentation-url": "https://historicengland.org.uk/listing/the-list/list-entry/1029842", "listed-building-grade": "II", "start-date": "1985-05-14", "slug": "/listed-building/1029842", "entry-date": "2021-05-28"}}