{"type": "Feature", "geometry": {"type": "Point", "coordinates": [0.881219, 52.321738]}, "properties": {"documentation-url": "https://historicengland.org.uk/listing/the-list/list-entry/1031227", "listed-building-grade": "II", "name": "DORSET COTTAGE", "point": "POINT (0.881219 52.321738)", "start-date": "1984-09-27", "listed-building": "1031227", "slug": "/listed-building/1031227", "entry-date": "2021-05-28"}}