{"type": "Feature", "geometry": {"type": "Point", "coordinates": [-0.219209, 51.02095]}, "properties": {"start-date": "1983-05-11", "documentation-url": "https://historicengland.org.uk/listing/the-list/list-entry/1025573", "name": "ROSE COTTAGE", "listed-building": "1025573", "listed-building-grade": "II", "point": "POINT (-0.219209 51.020950)", "slug": "/listed-building/1025573", "entry-date": "2021-05-28"}}