{"type": "Feature", "geometry": {"type": "Point", "coordinates": [-0.143628, 51.004773]}, "properties": {"point": "POINT (-0.143628 51.004773)", "listed-building-grade": "II", "name": "MONUMENT TO ROBERT CHATFIELD APPROXIMATELY 5 METRES SOUTH OF TOWER OF CHURCH", "start-date": "1987-12-11", "documentation-url": "https://historicengland.org.uk/listing/the-list/list-entry/1025549", "listed-building": "1025549", "slug": "/listed-building/1025549", "entry-date": "2021-05-28"}}