{"type": "Feature", "geometry": {"type": "Point", "coordinates": [-0.326994, 50.887593]}, "properties": {"listed-building": "1027308", "listed-building-grade": "II", "point": "POINT (-0.326994 50.887593)", "documentation-url": "https://historicengland.org.uk/listing/the-list/list-entry/1027308", "name": "ORWELL COTTAGE", "start-date": "1955-03-15", "slug": "/listed-building/1027308", "entry-date": "2021-05-28"}}