{"type": "Feature", "geometry": {"type": "Point", "coordinates": [-2.208842, 51.320634]}, "properties": {"listed-building": "1021558", "point": "POINT (-2.208842 51.320634)", "listed-building-grade": "II", "name": "HOME MILLS MAIN BLOCK", "start-date": "1976-11-26", "documentation-url": "https://historicengland.org.uk/listing/the-list/list-entry/1021558", "slug": "/listed-building/1021558", "entry-date": "2021-05-28"}}