{"type": "Feature", "geometry": {"type": "Point", "coordinates": [1.420927, 52.30177]}, "properties": {"documentation-url": "https://historicengland.org.uk/listing/the-list/list-entry/1030466", "listed-building-grade": "I", "listed-building": "1030466", "start-date": "1966-12-07", "point": "POINT (1.420927 52.301770)", "name": "CHURCH OF ST MARGARET", "slug": "/listed-building/1030466", "entry-date": "2021-05-28"}}