{"type": "Feature", "geometry": {"type": "Point", "coordinates": [-0.161432, 50.941635]}, "properties": {"name": "HIGHFIELDS FARMHOUSE", "listed-building": "1025663", "start-date": "1983-05-11", "point": "POINT (-0.161432 50.941635)", "documentation-url": "https://historicengland.org.uk/listing/the-list/list-entry/1025663", "listed-building-grade": "II", "slug": "/listed-building/1025663", "entry-date": "2021-05-28"}}