{"type": "Feature", "geometry": {"type": "Point", "coordinates": [-1.866299, 51.081496]}, "properties": {"name": "The Victoria Arms Inn", "documentation-url": "https://historicengland.org.uk/listing/the-list/list-entry/1023756", "listed-building": "1023756", "listed-building-grade": "II", "start-date": "1978-06-08", "point": "POINT (-1.866299 51.081496)", "slug": "/listed-building/1023756", "entry-date": "2021-05-28"}}