{"type": "Feature", "geometry": {"type": "Point", "coordinates": [-1.497468, 55.045196]}, "properties": {"listed-building": "1025400", "start-date": "1986-02-19", "listed-building-grade": "II", "point": "POINT (-1.497468 55.045196)", "documentation-url": "https://historicengland.org.uk/listing/the-list/list-entry/1025400", "name": "OVEN SOUTH OF THE GARTH AND WALL ATTACHED", "slug": "/listed-building/1025400", "entry-date": "2021-05-28"}}