{"type": "Feature", "geometry": {"type": "Point", "coordinates": [-0.274587, 50.951123]}, "properties": {"point": "POINT (-0.274587 50.951123)", "name": "NYMANS FARMHOUSE", "start-date": "1980-05-09", "documentation-url": "https://historicengland.org.uk/listing/the-list/list-entry/1027380", "listed-building-grade": "II", "listed-building": "1027380", "slug": "/listed-building/1027380", "entry-date": "2021-05-28"}}