{"type": "Feature", "geometry": {"type": "Point", "coordinates": [0.884474, 52.32404]}, "properties": {"start-date": "1984-09-27", "name": "WILLOW HOUSE", "point": "POINT (0.884474 52.324040)", "listed-building": "1031229", "documentation-url": "https://historicengland.org.uk/listing/the-list/list-entry/1031229", "listed-building-grade": "II", "slug": "/listed-building/1031229", "entry-date": "2021-05-28"}}