{"type": "Feature", "geometry": {"type": "Point", "coordinates": [-2.286122, 51.328648]}, "properties": {"start-date": "1962-11-13", "name": "THE CLOISTERS", "point": "POINT (-2.286122 51.328648)", "documentation-url": "https://historicengland.org.uk/listing/the-list/list-entry/1021878", "listed-building-grade": "II*", "listed-building": "1021878", "slug": "/listed-building/1021878", "entry-date": "2021-05-28"}}