{"type": "Feature", "geometry": {"type": "Point", "coordinates": [-0.440678, 51.032245]}, "properties": {"point": "POINT (-0.440678 51.032245)", "start-date": "1984-11-09", "documentation-url": "https://historicengland.org.uk/listing/the-list/list-entry/1026849", "listed-building": "1026849", "name": "GARDEN BUILDING AT SUMMERS PLACE", "listed-building-grade": "II", "slug": "/listed-building/1026849", "entry-date": "2021-05-28"}}