{"type": "Feature", "geometry": {"type": "Point", "coordinates": [-0.095882, 51.521816]}, "properties": {"listed-building": "1021948", "start-date": "1997-12-04", "documentation-url": "https://historicengland.org.uk/listing/the-list/list-entry/1021948", "point": "POINT (-0.095882 51.521816)", "listed-building-grade": "II", "name": "Cuthbert Harrowing House", "slug": "/listed-building/1021948", "entry-date": "2021-05-28"}}