{"type": "Feature", "geometry": {"type": "Point", "coordinates": [-0.476801, 51.366932]}, "properties": {"documentation-url": "https://historicengland.org.uk/listing/the-list/list-entry/1029190", "start-date": "1972-06-09", "name": "EASTERN BLOCK OF COXES LOCK MILLS", "point": "POINT (-0.476801 51.366932)", "listed-building": "1029190", "listed-building-grade": "II", "slug": "/listed-building/1029190", "entry-date": "2021-05-28"}}