{"type": "Feature", "geometry": {"type": "Point", "coordinates": [-1.391971, 52.166354]}, "properties": {"start-date": "1987-04-08", "point": "POINT (-1.391971 52.166354)", "documentation-url": "https://historicengland.org.uk/listing/the-list/list-entry/1024227", "name": "ROSE COTTAGE AND ATTACHED OUTBUILDING", "listed-building-grade": "II", "listed-building": "1024227", "slug": "/listed-building/1024227", "entry-date": "2021-05-28"}}