{"type": "Feature", "geometry": {"type": "Point", "coordinates": [-1.742168, 51.02292]}, "properties": {"listed-building": "1023911", "start-date": "1985-07-04", "listed-building-grade": "II", "name": "SMALL GRANARY TO NORTH OF WITHERINGTON FARMHOUSE", "point": "POINT (-1.742168 51.022920)", "documentation-url": "https://historicengland.org.uk/listing/the-list/list-entry/1023911", "slug": "/listed-building/1023911", "entry-date": "2021-05-28"}}