{"type": "Feature", "geometry": {"type": "Point", "coordinates": [-0.110834, 51.146654]}, "properties": {"documentation-url": "https://historicengland.org.uk/listing/the-list/list-entry/1029960", "listed-building": "1029960", "listed-building-grade": "II", "point": "POINT (-0.110834 51.146654)", "start-date": "1984-04-25", "name": "ALLINGHAM FARM HOUSE", "slug": "/listed-building/1029960", "entry-date": "2021-05-28"}}