{"type": "Feature", "geometry": {"type": "Point", "coordinates": [1.315926, 52.092929]}, "properties": {"name": "FORMER NO 8 NOW INCORPORATED WITH NO 6 (SUFFOLK SEED STORE)", "start-date": "1971-12-20", "documentation-url": "https://historicengland.org.uk/listing/the-list/list-entry/1031089", "listed-building": "1031089", "listed-building-grade": "II", "point": "POINT (1.315926 52.092929)", "slug": "/listed-building/1031089", "entry-date": "2021-05-28"}}