{"type": "Feature", "geometry": {"type": "Point", "coordinates": [-1.764089, 52.246125]}, "properties": {"name": "AQUEDUCT, STRATFORD ON AVON CANAL", "documentation-url": "https://historicengland.org.uk/listing/the-list/list-entry/1024550", "listed-building": "1024550", "listed-building-grade": "II*", "start-date": "1985-10-23", "point": "POINT (-1.764089 52.246125)", "slug": "/listed-building/1024550", "entry-date": "2021-05-28"}}