{"type": "Feature", "geometry": {"type": "Point", "coordinates": [-0.317116, 51.379783]}, "properties": {"listed-building": "1030091", "documentation-url": "https://historicengland.org.uk/listing/the-list/list-entry/1030091", "point": "POINT (-0.317116 51.379783)", "start-date": "1984-11-16", "listed-building-grade": "II", "name": "URQUART TOMB, 2 YARDS SOUTH WEST OF GARDEN OF REST", "slug": "/listed-building/1030091", "entry-date": "2021-05-28"}}