{"type": "Feature", "geometry": {"type": "Point", "coordinates": [-0.928889, 50.888552]}, "properties": {"start-date": "1958-06-05", "name": "THE NORTH LODGE OF STANSTED HOUSE", "listed-building": "1026189", "documentation-url": "https://historicengland.org.uk/listing/the-list/list-entry/1026189", "listed-building-grade": "II", "point": "POINT (-0.928889 50.888552)", "slug": "/listed-building/1026189", "entry-date": "1986-01-28"}}