{"type": "Feature", "geometry": {"type": "Point", "coordinates": [-0.448067, 51.274742]}, "properties": {"documentation-url": "https://historicengland.org.uk/listing/the-list/list-entry/1029327", "point": "POINT (-0.448067 51.274742)", "listed-building": "1029327", "listed-building-grade": "II", "name": "LOLLESWORTH FARM HOUSE", "start-date": "1967-06-14", "slug": "/listed-building/1029327", "entry-date": "2021-05-28"}}