{"type": "Feature", "geometry": {"type": "Point", "coordinates": [-0.278806, 51.123032]}, "properties": {"listed-building": "1026950", "documentation-url": "https://historicengland.org.uk/listing/the-list/list-entry/1026950", "start-date": "1959-09-22", "listed-building-grade": "II", "point": "POINT (-0.278806 51.123032)", "name": "GHYLL MANOR COTTAGE", "slug": "/listed-building/1026950", "entry-date": "1980-11-28"}}