{"type": "Feature", "geometry": {"type": "Point", "coordinates": [-1.903892, 51.21064]}, "properties": {"listed-building-grade": "II", "documentation-url": "https://historicengland.org.uk/listing/the-list/list-entry/1023974", "listed-building": "1023974", "name": "BARN AND ATTACHED FARMBUILDINGS AT ELSTON HILL FARM", "point": "POINT (-1.903892 51.210640)", "start-date": "1992-01-09", "slug": "/listed-building/1023974", "entry-date": "2021-05-28"}}