{"type": "Feature", "geometry": {"type": "Point", "coordinates": [-0.260211, 51.330508]}, "properties": {"point": "POINT (-0.260211 51.330508)", "listed-building": "1028589", "documentation-url": "https://historicengland.org.uk/listing/the-list/list-entry/1028589", "name": "24A AND 24B, CHURCH STREET", "start-date": "1974-03-22", "listed-building-grade": "II", "slug": "/listed-building/1028589", "entry-date": "2021-05-28"}}