{"type": "Feature", "geometry": {"type": "Point", "coordinates": [-0.036873, 51.038722]}, "properties": {"start-date": "1983-05-11", "name": "WATERBURY CASTLE", "documentation-url": "https://historicengland.org.uk/listing/the-list/list-entry/1025690", "listed-building": "1025690", "point": "POINT (-0.036873 51.038722)", "listed-building-grade": "II", "slug": "/listed-building/1025690", "entry-date": "2021-05-28"}}