{"type": "Feature", "geometry": {"type": "Point", "coordinates": [-1.871995, 51.50043]}, "properties": {"point": "POINT (-1.871995 51.500430)", "documentation-url": "https://historicengland.org.uk/listing/the-list/list-entry/1022647", "start-date": "1978-11-20", "listed-building-grade": "II", "listed-building": "1022647", "name": "47 AND 48, BROAD TOWN ROAD", "slug": "/listed-building/1022647", "entry-date": "2021-05-28"}}