{"type": "Feature", "geometry": {"type": "Point", "coordinates": [-0.743054, 50.841268]}, "properties": {"start-date": "1986-01-28", "documentation-url": "https://historicengland.org.uk/listing/the-list/list-entry/1026291", "listed-building": "1026291", "name": "GATE PIERS AT NORTH WEST ENTRANCE TO SHOPWYKE HOUSE", "point": "POINT (-0.743054 50.841268)", "listed-building-grade": "II", "slug": "/listed-building/1026291", "entry-date": "2021-05-28"}}