{"type": "Feature", "geometry": {"type": "Point", "coordinates": [-1.137667, 51.547901]}, "properties": {"listed-building-grade": "II", "start-date": "1986-01-13", "name": "HEADSTONE APPROXIMATELY 5 METRES SOUTH WEST OF PORCH OF CHURCH OF ST ANDREW", "listed-building": "1025303", "documentation-url": "https://historicengland.org.uk/listing/the-list/list-entry/1025303", "point": "POINT (-1.137667 51.547901)", "slug": "/listed-building/1025303", "entry-date": "2021-05-28"}}