{"type": "Feature", "geometry": {"type": "Point", "coordinates": [-2.184614, 51.433493]}, "properties": {"start-date": "1960-12-20", "listed-building-grade": "II", "listed-building": "1022041", "point": "POINT (-2.184614 51.433493)", "name": "CHEVIOT HOUSE", "documentation-url": "https://historicengland.org.uk/listing/the-list/list-entry/1022041", "slug": "/listed-building/1022041", "entry-date": "2021-05-28"}}