{"type": "Feature", "geometry": {"type": "Point", "coordinates": [-0.746784, 51.017026]}, "properties": {"listed-building-grade": "II*", "point": "POINT (-0.746784 51.017026)", "listed-building": "1026020", "name": "The former King Edward VII Hospital", "start-date": "1973-03-02", "documentation-url": "https://historicengland.org.uk/listing/the-list/list-entry/1026020", "slug": "/listed-building/1026020", "entry-date": "1987-11-26"}}