{"type": "Feature", "geometry": {"type": "Point", "coordinates": [1.18204, 52.138089]}, "properties": {"start-date": "1985-01-25", "listed-building-grade": "II", "point": "POINT (1.182040 52.138089)", "listed-building": "1030522", "name": "NELSON FARMHOUSE", "documentation-url": "https://historicengland.org.uk/listing/the-list/list-entry/1030522", "slug": "/listed-building/1030522", "entry-date": "2021-05-28"}}