{"type": "Feature", "geometry": {"type": "Point", "coordinates": [1.488186, 52.234317]}, "properties": {"listed-building": "1030673", "point": "POINT (1.488186 52.234317)", "listed-building-grade": "II", "start-date": "1984-07-27", "name": "ROBINS PATCH AND CHERRY TREE COTTAGE", "documentation-url": "https://historicengland.org.uk/listing/the-list/list-entry/1030673", "slug": "/listed-building/1030673", "entry-date": "2021-05-28"}}