{"type": "Feature", "geometry": {"type": "Point", "coordinates": [-1.311432, 52.199667]}, "properties": {"documentation-url": "https://historicengland.org.uk/listing/the-list/list-entry/1024416", "point": "POINT (-1.311432 52.199667)", "listed-building": "1024416", "listed-building-grade": "II", "start-date": "1967-05-30", "name": "HILL FARMHOUSE", "slug": "/listed-building/1024416", "entry-date": "1986-04-21"}}