{"type": "Feature", "geometry": {"type": "Point", "coordinates": [-2.274524, 51.49365]}, "properties": {"point": "POINT (-2.274524 51.493650)", "start-date": "1985-12-09", "listed-building-grade": "II", "listed-building": "1022970", "name": "GATES AND RAILINGS TO SOUTH OF MANOR FARMHOUSE", "documentation-url": "https://historicengland.org.uk/listing/the-list/list-entry/1022970", "slug": "/listed-building/1022970", "entry-date": "2021-05-28"}}