{"type": "Feature", "geometry": {"type": "Point", "coordinates": [-0.311033, 51.306208]}, "properties": {"listed-building-grade": "II", "documentation-url": "https://historicengland.org.uk/listing/the-list/list-entry/1028679", "listed-building": "1028679", "point": "POINT (-0.311033 51.306208)", "name": "60 AND 62, AGATES LANE", "start-date": "1973-11-23", "slug": "/listed-building/1028679", "entry-date": "2021-05-28"}}