{"type": "Feature", "geometry": {"type": "Point", "coordinates": [-0.750535, 50.950245]}, "properties": {"listed-building": "1026064", "listed-building-grade": "II", "start-date": "1987-11-26", "documentation-url": "https://historicengland.org.uk/listing/the-list/list-entry/1026064", "name": "184 AND 185, CHURCH PATH", "point": "POINT (-0.750535 50.950245)", "slug": "/listed-building/1026064", "entry-date": "1996-02-01"}}