{"type": "Feature", "geometry": {"type": "Point", "coordinates": [1.32335, 52.010112]}, "properties": {"name": "OLD RECTORY", "start-date": "1983-05-25", "documentation-url": "https://historicengland.org.uk/listing/the-list/list-entry/1030921", "listed-building-grade": "II", "listed-building": "1030921", "point": "POINT (1.323350 52.010112)", "slug": "/listed-building/1030921", "entry-date": "1983-07-29"}}