{"type": "Feature", "geometry": {"type": "Point", "coordinates": [-1.970066, 51.511043]}, "properties": {"listed-building-grade": "II", "start-date": "1985-08-15", "point": "POINT (-1.970066 51.511043)", "documentation-url": "https://historicengland.org.uk/listing/the-list/list-entry/1022674", "name": "POUND FARMHOUSE", "listed-building": "1022674", "slug": "/listed-building/1022674", "entry-date": "2021-05-28"}}