{"type": "Feature", "geometry": {"type": "Point", "coordinates": [-0.034938, 51.065229]}, "properties": {"listed-building-grade": "II", "point": "POINT (-0.034938 51.065229)", "listed-building": "1025591", "name": "ALDERN HOUSE", "documentation-url": "https://historicengland.org.uk/listing/the-list/list-entry/1025591", "start-date": "1957-10-28", "slug": "/listed-building/1025591", "entry-date": "1983-05-11"}}