{"type": "Feature", "geometry": {"type": "Point", "coordinates": [-0.21155, 51.269233]}, "properties": {"documentation-url": "https://historicengland.org.uk/listing/the-list/list-entry/1029052", "listed-building-grade": "I", "name": "CHURCH OF JESUS CHRIST AND THE WISDOM OF GOD", "point": "POINT (-0.211550 51.269233)", "listed-building": "1029052", "start-date": "1983-09-29", "slug": "/listed-building/1029052", "entry-date": "2021-05-28"}}