{"type": "Feature", "geometry": {"type": "Point", "coordinates": [-0.255108, 51.246684]}, "properties": {"listed-building-grade": "II", "name": "PETTYS FARM HOUSE", "listed-building": "1028756", "documentation-url": "https://historicengland.org.uk/listing/the-list/list-entry/1028756", "start-date": "1987-09-29", "point": "POINT (-0.255108 51.246684)", "slug": "/listed-building/1028756", "entry-date": "2021-05-28"}}