{"type": "Feature", "geometry": {"type": "Point", "coordinates": [-0.861178, 50.870249]}, "properties": {"point": "POINT (-0.861178 50.870249)", "listed-building-grade": "II", "listed-building": "1026354", "name": "FUNTINGTON LODGE", "start-date": "1958-06-05", "documentation-url": "https://historicengland.org.uk/listing/the-list/list-entry/1026354", "slug": "/listed-building/1026354", "entry-date": "1996-04-29"}}