{"type": "Feature", "geometry": {"type": "Point", "coordinates": [-0.863133, 50.969764]}, "properties": {"listed-building": "1025983", "listed-building-grade": "II", "point": "POINT (-0.863133 50.969764)", "documentation-url": "https://historicengland.org.uk/listing/the-list/list-entry/1025983", "name": "MARDEN FARMHOUSE", "start-date": "1987-11-26", "slug": "/listed-building/1025983", "entry-date": "2021-05-28"}}