{"type": "Feature", "geometry": {"type": "Point", "coordinates": [-0.575114, 50.934771]}, "properties": {"documentation-url": "https://historicengland.org.uk/listing/the-list/list-entry/1026562", "listed-building-grade": "II", "listed-building": "1026562", "name": "FLINT COTTAGE", "point": "POINT (-0.575114 50.934771)", "start-date": "1985-05-22", "slug": "/listed-building/1026562", "entry-date": "2021-05-28"}}