{"type": "Feature", "geometry": {"type": "Point", "coordinates": [-1.913911, 51.59548]}, "properties": {"listed-building": "1023075", "listed-building-grade": "II", "documentation-url": "https://historicengland.org.uk/listing/the-list/list-entry/1023075", "point": "POINT (-1.913911 51.595480)", "name": "RED LODGE", "start-date": "1986-04-17", "slug": "/listed-building/1023075", "entry-date": "2021-05-28"}}