{"type": "Feature", "geometry": {"type": "Point", "coordinates": [-1.744168, 51.610707]}, "properties": {"listed-building-grade": "II", "documentation-url": "https://historicengland.org.uk/listing/the-list/list-entry/1023410", "start-date": "1979-09-20", "point": "POINT (-1.744168 51.610707)", "name": "LODGE AND GATE PIERS TO STANTON HOUSE", "listed-building": "1023410", "slug": "/listed-building/1023410", "entry-date": "2021-05-28"}}