{"type": "Feature", "geometry": {"type": "Point", "coordinates": [-1.988815, 51.562504]}, "properties": {"documentation-url": "https://historicengland.org.uk/listing/the-list/list-entry/1022208", "name": "WALDRONS FARMHOUSE", "point": "POINT (-1.988815 51.562504)", "start-date": "1987-07-16", "listed-building": "1022208", "listed-building-grade": "II", "slug": "/listed-building/1022208", "entry-date": "2021-05-28"}}