{"type": "Feature", "geometry": {"type": "Point", "coordinates": [-0.50638, 50.97192]}, "properties": {"documentation-url": "https://historicengland.org.uk/listing/the-list/list-entry/1027337", "name": "CODMORE HILL FARMHOUSE", "listed-building": "1027337", "start-date": "1955-03-15", "point": "POINT (-0.506380 50.971920)", "listed-building-grade": "II", "slug": "/listed-building/1027337", "entry-date": "1980-05-09"}}