{"type": "Feature", "geometry": {"type": "Point", "coordinates": [-0.027743, 51.038407]}, "properties": {"point": "POINT (-0.027743 51.038407)", "name": "SPLINTERS TIMBERS", "listed-building-grade": "II", "start-date": "1983-05-11", "documentation-url": "https://historicengland.org.uk/listing/the-list/list-entry/1025686", "listed-building": "1025686", "slug": "/listed-building/1025686", "entry-date": "2021-05-28"}}