{"type": "Feature", "geometry": {"type": "Point", "coordinates": [-0.925929, 50.862122]}, "properties": {"listed-building": "1026144", "point": "POINT (-0.925929 50.862122)", "listed-building-grade": "II", "name": "CHALK COTTAGE J AND VJ LAIN, WATCHMAKER AND JEWELLER LAMB COTTAGE WESTBOURNE ANTIQUES", "start-date": "1986-01-28", "documentation-url": "https://historicengland.org.uk/listing/the-list/list-entry/1026144", "slug": "/listed-building/1026144", "entry-date": "2021-05-28"}}