{"type": "Feature", "geometry": {"type": "Point", "coordinates": [-0.578182, 51.234934]}, "properties": {"start-date": "1988-03-15", "name": "DH SALES", "point": "POINT (-0.578182 51.234934)", "listed-building": "1029245", "documentation-url": "https://historicengland.org.uk/listing/the-list/list-entry/1029245", "listed-building-grade": "II", "slug": "/listed-building/1029245", "entry-date": "2021-05-28"}}