{"type": "Feature", "geometry": {"type": "Point", "coordinates": [-0.013526, 51.179224]}, "properties": {"listed-building-grade": "II", "name": "LITTLE LULLENDEN COTTAGE", "start-date": "1984-04-25", "point": "POINT (-0.013526 51.179224)", "documentation-url": "https://historicengland.org.uk/listing/the-list/list-entry/1029899", "listed-building": "1029899", "slug": "/listed-building/1029899", "entry-date": "2021-05-28"}}