{"type": "Feature", "geometry": {"type": "Point", "coordinates": [-2.157548, 51.43588]}, "properties": {"listed-building": "1022011", "start-date": "1986-08-01", "documentation-url": "https://historicengland.org.uk/listing/the-list/list-entry/1022011", "listed-building-grade": "II", "name": "BARN TO EAST OF EASTON FARMHOUSE", "point": "POINT (-2.157548 51.435880)", "slug": "/listed-building/1022011", "entry-date": "2021-05-28"}}