{"type": "Feature", "geometry": {"type": "Point", "coordinates": [-2.245483, 51.292032]}, "properties": {"documentation-url": "https://historicengland.org.uk/listing/the-list/list-entry/1021847", "listed-building-grade": "II", "point": "POINT (-2.245483 51.292032)", "start-date": "1988-06-14", "name": "DUNKIRK FARMHOUSE", "listed-building": "1021847", "slug": "/listed-building/1021847", "entry-date": "2021-05-28"}}