{"type": "Feature", "geometry": {"type": "Point", "coordinates": [-1.862265, 51.079639]}, "properties": {"documentation-url": "https://historicengland.org.uk/listing/the-list/list-entry/1023709", "start-date": "1978-06-08", "listed-building-grade": "II", "name": "GEORGIAN COTTAGE", "listed-building": "1023709", "point": "POINT (-1.862265 51.079639)", "slug": "/listed-building/1023709", "entry-date": "2021-05-28"}}