{"type": "Feature", "geometry": {"type": "Point", "coordinates": [-1.472163, 54.980107]}, "properties": {"name": "MONASTERY OF ST PAUL RUINS OF JARROW MONASTERY", "start-date": "1949-01-18", "listed-building-grade": "I", "listed-building": "1025198", "documentation-url": "https://historicengland.org.uk/listing/the-list/list-entry/1025198", "point": "POINT (-1.472163 54.980107)", "slug": "/listed-building/1025198", "entry-date": "1985-02-26"}}