{"type": "Feature", "geometry": {"type": "Point", "coordinates": [1.311556, 52.093774]}, "properties": {"listed-building-grade": "II", "point": "POINT (1.311556 52.093774)", "name": "PRIORY LODGE", "start-date": "1951-01-25", "listed-building": "1031024", "documentation-url": "https://historicengland.org.uk/listing/the-list/list-entry/1031024", "slug": "/listed-building/1031024", "entry-date": "2021-05-28"}}