{"type": "Feature", "geometry": {"type": "Point", "coordinates": [0.237079, 52.023564]}, "properties": {"listed-building": "1025113", "listed-building-grade": "II", "start-date": "1994-10-31", "name": "WALL ON EAST SIDE OF GARDEN OF WALDEN PLACE", "documentation-url": "https://historicengland.org.uk/listing/the-list/list-entry/1025113", "point": "POINT (0.237079 52.023564)", "slug": "/listed-building/1025113", "entry-date": "2021-05-28"}}