{"type": "Feature", "geometry": {"type": "Point", "coordinates": [-0.503972, 51.324847]}, "properties": {"listed-building-grade": "II", "start-date": "1953-07-22", "listed-building": "1028572", "point": "POINT (-0.503972 51.324847)", "name": "BLUEGATE COTTAGE WEEM COTTAGE", "documentation-url": "https://historicengland.org.uk/listing/the-list/list-entry/1028572", "slug": "/listed-building/1028572", "entry-date": "1984-01-06"}}