{"type": "Feature", "geometry": {"type": "Point", "coordinates": [-2.201524, 51.353502]}, "properties": {"listed-building": "1021797", "start-date": "1988-06-14", "listed-building-grade": "II", "name": "RAILED ENCLOSURE IN THE CHURCHYARD ABOUT 11 METRES NORTH OF CHURCH OF ST KATHERINE", "point": "POINT (-2.201524 51.353502)", "documentation-url": "https://historicengland.org.uk/listing/the-list/list-entry/1021797", "slug": "/listed-building/1021797", "entry-date": "2021-05-28"}}