{"type": "Feature", "geometry": {"type": "Point", "coordinates": [-1.799315, 51.066566]}, "properties": {"listed-building": "1023620", "name": "WREN HALL", "point": "POINT (-1.799315 51.066566)", "start-date": "1952-02-28", "listed-building-grade": "I", "documentation-url": "https://historicengland.org.uk/listing/the-list/list-entry/1023620", "slug": "/listed-building/1023620", "entry-date": "1972-10-12"}}