{"type": "Feature", "geometry": {"type": "Point", "coordinates": [-0.431287, 51.263961]}, "properties": {"documentation-url": "https://historicengland.org.uk/listing/the-list/list-entry/1029421", "point": "POINT (-0.431287 51.263961)", "start-date": "1985-11-25", "name": "CHURCHYARD WALLS TO EAST OF CHURCH OF ST MARTIN", "listed-building-grade": "II", "listed-building": "1029421", "slug": "/listed-building/1029421", "entry-date": "2021-05-28"}}