{"type": "Feature", "geometry": {"type": "Point", "coordinates": [-1.743276, 50.993665]}, "properties": {"listed-building-grade": "I", "point": "POINT (-1.743276 50.993665)", "start-date": "1960-03-23", "listed-building": "1023875", "name": "CHURCH OF ST LAURENCE", "documentation-url": "https://historicengland.org.uk/listing/the-list/list-entry/1023875", "slug": "/listed-building/1023875", "entry-date": "2021-05-28"}}