{"type": "Feature", "geometry": {"type": "Point", "coordinates": [-0.259718, 50.95778]}, "properties": {"documentation-url": "https://historicengland.org.uk/listing/the-list/list-entry/1027295", "listed-building-grade": "II", "name": "SAKEHAM FARMHOUSE", "start-date": "1955-03-15", "listed-building": "1027295", "point": "POINT (-0.259718 50.957780)", "slug": "/listed-building/1027295", "entry-date": "2021-05-28"}}