{"type": "Feature", "geometry": {"type": "Point", "coordinates": [-1.838407, 51.518542]}, "properties": {"name": "Roman Walk Farmhouse", "point": "POINT (-1.838407 51.518542)", "documentation-url": "https://historicengland.org.uk/listing/the-list/list-entry/1022713", "listed-building": "1022713", "listed-building-grade": "II", "start-date": "1988-07-21", "slug": "/listed-building/1022713", "entry-date": "2021-05-28"}}