{"type": "Feature", "geometry": {"type": "Point", "coordinates": [-2.423928, 52.900382]}, "properties": {"point": "POINT (-2.423928 52.900382)", "start-date": "1985-05-14", "listed-building": "1029861", "name": "STABLE BLOCK ABOUT 130 METRES SOUTH EAST OF HALES HALL", "listed-building-grade": "II", "documentation-url": "https://historicengland.org.uk/listing/the-list/list-entry/1029861", "slug": "/listed-building/1029861", "entry-date": "2021-05-28"}}