{"type": "Feature", "geometry": {"type": "Point", "coordinates": [-0.633533, 51.24957]}, "properties": {"point": "POINT (-0.633533 51.249570)", "listed-building": "1029588", "listed-building-grade": "II", "name": "NIGHTINGALE OLD FARMHOUSE", "start-date": "1984-12-13", "documentation-url": "https://historicengland.org.uk/listing/the-list/list-entry/1029588", "slug": "/listed-building/1029588", "entry-date": "2021-05-28"}}