{"type": "Feature", "geometry": {"type": "Point", "coordinates": [1.519064, 52.3109]}, "properties": {"listed-building": "1030658", "start-date": "1984-07-27", "documentation-url": "https://historicengland.org.uk/listing/the-list/list-entry/1030658", "point": "POINT (1.519064 52.310900)", "name": "OCCUPIED BY MRS FOSTER AND MR GLANFIELD", "listed-building-grade": "II", "slug": "/listed-building/1030658", "entry-date": "2021-05-28"}}