{"type": "Feature", "geometry": {"type": "Point", "coordinates": [-0.651814, 51.298388]}, "properties": {"documentation-url": "https://historicengland.org.uk/listing/the-list/list-entry/1029631", "start-date": "1984-12-13", "point": "POINT (-0.651814 51.298388)", "listed-building-grade": "II", "name": "CAUSEWAY FARM HOUSE", "listed-building": "1029631", "slug": "/listed-building/1029631", "entry-date": "2021-05-28"}}