{"type": "Feature", "geometry": {"type": "Point", "coordinates": [-0.739592, 51.082527]}, "properties": {"listed-building": "1025905", "documentation-url": "https://historicengland.org.uk/listing/the-list/list-entry/1025905", "start-date": "1987-11-26", "name": "THE RAMBLERS", "listed-building-grade": "II", "point": "POINT (-0.739592 51.082527)", "slug": "/listed-building/1025905", "entry-date": "2021-05-28"}}