{"type": "Feature", "geometry": {"type": "Point", "coordinates": [-0.28979, 51.234129]}, "properties": {"point": "POINT (-0.289790 51.234129)", "name": "18 AND 20, THE BOROUGH", "listed-building": "1028910", "documentation-url": "https://historicengland.org.uk/listing/the-list/list-entry/1028910", "start-date": "1973-06-11", "listed-building-grade": "II", "slug": "/listed-building/1028910", "entry-date": "2021-05-28"}}