{"type": "Feature", "geometry": {"type": "Point", "coordinates": [0.259246, 51.014062]}, "properties": {"listed-building-grade": "II", "documentation-url": "https://historicengland.org.uk/listing/the-list/list-entry/1028153", "start-date": "1973-03-18", "name": "CRANESDEN", "listed-building": "1028153", "point": "POINT (0.259246 51.014062)", "slug": "/listed-building/1028153", "entry-date": "2021-05-28"}}