{"type": "Feature", "geometry": {"type": "Point", "coordinates": [-1.456108, 54.818183]}, "properties": {"documentation-url": "https://historicengland.org.uk/listing/the-list/list-entry/1025440", "listed-building": "1025440", "name": "SMITHY", "start-date": "1985-07-15", "listed-building-grade": "II", "point": "POINT (-1.456108 54.818183)", "slug": "/listed-building/1025440", "entry-date": "2021-05-28"}}