{"type": "Feature", "geometry": {"type": "Point", "coordinates": [-0.427976, 51.350038]}, "properties": {"listed-building": "1030146", "point": "POINT (-0.427976 51.350038)", "documentation-url": "https://historicengland.org.uk/listing/the-list/list-entry/1030146", "listed-building-grade": "II", "start-date": "1984-11-16", "name": "44 AND 44A, OCTAGON ROAD", "slug": "/listed-building/1030146", "entry-date": "2021-05-28"}}