{"type": "Feature", "geometry": {"type": "Point", "coordinates": [-0.399449, 51.271911]}, "properties": {"point": "POINT (-0.399449 51.271911)", "documentation-url": "https://historicengland.org.uk/listing/the-list/list-entry/1029385", "name": "THE OLD POST COTTAGE", "listed-building": "1029385", "listed-building-grade": "II", "start-date": "1985-11-25", "slug": "/listed-building/1029385", "entry-date": "2021-05-28"}}