{"type": "Feature", "geometry": {"type": "Point", "coordinates": [1.340386, 52.001871]}, "properties": {"point": "POINT (1.340386 52.001871)", "name": "THE DOG HOUSE", "listed-building": "1030917", "start-date": "1983-05-25", "documentation-url": "https://historicengland.org.uk/listing/the-list/list-entry/1030917", "listed-building-grade": "II", "slug": "/listed-building/1030917", "entry-date": "1983-07-29"}}