{"type": "Feature", "geometry": {"type": "Point", "coordinates": [-1.741603, 50.993834]}, "properties": {"start-date": "1985-07-04", "name": "WELLESLEY COTTAGE", "point": "POINT (-1.741603 50.993834)", "listed-building-grade": "II", "documentation-url": "https://historicengland.org.uk/listing/the-list/list-entry/1023854", "listed-building": "1023854", "slug": "/listed-building/1023854", "entry-date": "2021-05-28"}}