{"type": "Feature", "geometry": {"type": "Point", "coordinates": [-1.617582, 51.970483]}, "properties": {"documentation-url": "https://historicengland.org.uk/listing/the-list/list-entry/1024284", "start-date": "1987-04-09", "listed-building-grade": "II", "name": "BLACKSMITH'S COTTAGE", "listed-building": "1024284", "point": "POINT (-1.617582 51.970483)", "slug": "/listed-building/1024284", "entry-date": "2021-05-28"}}