{"type": "Feature", "geometry": {"type": "Point", "coordinates": [0.80775, 52.335397]}, "properties": {"listed-building": "1031292", "point": "POINT (0.807750 52.335397)", "start-date": "1955-07-14", "documentation-url": "https://historicengland.org.uk/listing/the-list/list-entry/1031292", "name": "CORNER THATCH HEATHFIELD LODGE", "listed-building-grade": "II", "slug": "/listed-building/1031292", "entry-date": "1983-12-14"}}