{"type": "Feature", "geometry": {"type": "Point", "coordinates": [-2.286367, 51.468868]}, "properties": {"name": "HOME FARMHOUSE", "start-date": "1985-12-09", "point": "POINT (-2.286367 51.468868)", "listed-building": "1023015", "listed-building-grade": "II", "documentation-url": "https://historicengland.org.uk/listing/the-list/list-entry/1023015", "slug": "/listed-building/1023015", "entry-date": "2021-05-28"}}