{"type": "Feature", "geometry": {"type": "Point", "coordinates": [-1.7488, 51.080584]}, "properties": {"listed-building-grade": "II", "listed-building": "1023951", "start-date": "1987-05-29", "name": "GRANARY AT QUEEN MANOR FARM AND COB WALL TO REAR", "point": "POINT (-1.748800 51.080584)", "documentation-url": "https://historicengland.org.uk/listing/the-list/list-entry/1023951", "slug": "/listed-building/1023951", "entry-date": "2021-05-28"}}