{"type": "Feature", "geometry": {"type": "Point", "coordinates": [-0.490386, 50.945973]}, "properties": {"start-date": "1980-05-09", "point": "POINT (-0.490386 50.945973)", "name": "BANKS COTTAGE", "listed-building": "1027365", "listed-building-grade": "II", "documentation-url": "https://historicengland.org.uk/listing/the-list/list-entry/1027365", "slug": "/listed-building/1027365", "entry-date": "2021-05-28"}}