{"type": "Feature", "geometry": {"type": "Point", "coordinates": [-0.266474, 51.233337]}, "properties": {"point": "POINT (-0.266474 51.233337)", "documentation-url": "https://historicengland.org.uk/listing/the-list/list-entry/1028787", "listed-building-grade": "II", "listed-building": "1028787", "start-date": "1966-11-11", "name": "GATEWAY TO GARDENS AT BETCHWORTH HOUSE", "slug": "/listed-building/1028787", "entry-date": "2021-05-28"}}