{"type": "Feature", "geometry": {"type": "Point", "coordinates": [-0.485995, 50.830373]}, "properties": {"point": "POINT (-0.485995 50.830373)", "name": "ELMHURST", "start-date": "1984-09-20", "documentation-url": "https://historicengland.org.uk/listing/the-list/list-entry/1027710", "listed-building": "1027710", "listed-building-grade": "II", "slug": "/listed-building/1027710", "entry-date": "2021-05-28"}}