{"type": "Feature", "geometry": {"type": "Point", "coordinates": [-2.047636, 51.610454]}, "properties": {"listed-building": "1022229", "name": "BARN TO THE SOUTH OF BAMBURY HILL FARMHOUSE", "start-date": "1987-07-16", "listed-building-grade": "II", "documentation-url": "https://historicengland.org.uk/listing/the-list/list-entry/1022229", "point": "POINT (-2.047636 51.610454)", "slug": "/listed-building/1022229", "entry-date": "2021-05-28"}}