{"type": "Feature", "geometry": {"type": "Point", "coordinates": [-2.193883, 51.228864]}, "properties": {"listed-building-grade": "II*", "listed-building": "1021515", "documentation-url": "https://historicengland.org.uk/listing/the-list/list-entry/1021515", "point": "POINT (-2.193883 51.228864)", "start-date": "1969-07-24", "name": "PARKS COURT", "slug": "/listed-building/1021515", "entry-date": "1987-11-05"}}