{"type": "Feature", "geometry": {"type": "Point", "coordinates": [-0.088522, 51.223288]}, "properties": {"listed-building-grade": "II", "start-date": "1984-04-25", "name": "CUCKSEY'S FARM HOUSE", "point": "POINT (-0.088522 51.223288)", "listed-building": "1029985", "documentation-url": "https://historicengland.org.uk/listing/the-list/list-entry/1029985", "slug": "/listed-building/1029985", "entry-date": "2021-05-28"}}