{"type": "Feature", "geometry": {"type": "Point", "coordinates": [-0.446601, 51.080043]}, "properties": {"point": "POINT (-0.446601 51.080043)", "listed-building": "1026978", "start-date": "1980-11-28", "documentation-url": "https://historicengland.org.uk/listing/the-list/list-entry/1026978", "listed-building-grade": "II", "name": "WARHAMS COTTAGE", "slug": "/listed-building/1026978", "entry-date": "2021-05-28"}}