{"type": "Feature", "geometry": {"type": "Point", "coordinates": [-0.410861, 51.185241]}, "properties": {"name": "NEALE COTTAGE", "documentation-url": "https://historicengland.org.uk/listing/the-list/list-entry/1029454", "listed-building": "1029454", "listed-building-grade": "II", "point": "POINT (-0.410861 51.185241)", "start-date": "1985-05-21", "slug": "/listed-building/1029454", "entry-date": "2021-05-28"}}