{"type": "Feature", "geometry": {"type": "Point", "coordinates": [-0.783767, 50.828704]}, "properties": {"listed-building": "1026626", "listed-building-grade": "II", "documentation-url": "https://historicengland.org.uk/listing/the-list/list-entry/1026626", "name": "STOCKBRIDGE HOUSE", "point": "POINT (-0.783767 50.828704)", "start-date": "1971-10-08", "slug": "/listed-building/1026626", "entry-date": "2021-05-28"}}