{"type": "Feature", "geometry": {"type": "Point", "coordinates": [-0.634421, 51.346538]}, "properties": {"point": "POINT (-0.634421 51.346538)", "start-date": "1984-07-19", "listed-building-grade": "II", "documentation-url": "https://historicengland.org.uk/listing/the-list/list-entry/1029990", "name": "PANKHURST", "listed-building": "1029990", "slug": "/listed-building/1029990", "entry-date": "2021-05-28"}}