{"type": "Feature", "geometry": {"type": "Point", "coordinates": [-1.6226, 52.109513]}, "properties": {"point": "POINT (-1.622600 52.109513)", "listed-building": "1024364", "listed-building-grade": "II", "documentation-url": "https://historicengland.org.uk/listing/the-list/list-entry/1024364", "start-date": "1966-10-13", "name": "GABLE END", "slug": "/listed-building/1024364", "entry-date": "1986-06-30"}}