{"type": "Feature", "geometry": {"type": "Point", "coordinates": [-1.88538, 52.20428]}, "properties": {"documentation-url": "https://historicengland.org.uk/listing/the-list/list-entry/1024695", "listed-building": "1024695", "start-date": "1967-02-01", "listed-building-grade": "II*", "point": "POINT (-1.885380 52.204280)", "name": "RAGLEY HALL, PRINCIPAL ENTRANCE LODGE (SOUTH)", "slug": "/listed-building/1024695", "entry-date": "1984-12-13"}}