{"type": "Feature", "geometry": {"type": "Point", "coordinates": [-0.571309, 51.235912]}, "properties": {"listed-building-grade": "II", "name": "152 AND 154, HIGH STREET", "start-date": "1953-05-01", "documentation-url": "https://historicengland.org.uk/listing/the-list/list-entry/1029257", "listed-building": "1029257", "point": "POINT (-0.571309 51.235912)", "slug": "/listed-building/1029257", "entry-date": "2021-05-28"}}