{"type": "Feature", "geometry": {"type": "Point", "coordinates": [-1.943001, 51.432276]}, "properties": {"start-date": "1987-11-25", "point": "POINT (-1.943001 51.432276)", "documentation-url": "https://historicengland.org.uk/listing/the-list/list-entry/1022452", "listed-building": "1022452", "name": "UPPER FARMHOUSE", "listed-building-grade": "II", "slug": "/listed-building/1022452", "entry-date": "2021-05-28"}}