{"type": "Feature", "geometry": {"type": "Point", "coordinates": [-0.142886, 51.00516]}, "properties": {"point": "POINT (-0.142886 51.005160)", "listed-building-grade": "II", "listed-building": "1025519", "name": "CHURCHYARD COTTAGES", "start-date": "1970-04-06", "documentation-url": "https://historicengland.org.uk/listing/the-list/list-entry/1025519", "slug": "/listed-building/1025519", "entry-date": "1987-12-11"}}