{"type": "Feature", "geometry": {"type": "Point", "coordinates": [-0.021054, 51.174505]}, "properties": {"point": "POINT (-0.021054 51.174505)", "listed-building-grade": "II", "name": "BRICKLANDS FARM HOUSE", "start-date": "1958-06-11", "listed-building": "1029894", "documentation-url": "https://historicengland.org.uk/listing/the-list/list-entry/1029894", "slug": "/listed-building/1029894", "entry-date": "2021-05-28"}}