{"type": "Feature", "geometry": {"type": "Point", "coordinates": [-0.837264, 50.779158]}, "properties": {"listed-building": "1026340", "name": "THATCHED COTTAGE", "listed-building-grade": "II", "start-date": "1986-01-28", "documentation-url": "https://historicengland.org.uk/listing/the-list/list-entry/1026340", "point": "POINT (-0.837264 50.779158)", "slug": "/listed-building/1026340", "entry-date": "2021-05-28"}}