{"type": "Feature", "geometry": {"type": "Point", "coordinates": [-1.864107, 51.604937]}, "properties": {"documentation-url": "https://historicengland.org.uk/listing/the-list/list-entry/1023181", "listed-building": "1023181", "point": "POINT (-1.864107 51.604937)", "name": "PACKHORSE CORNER, AND NUMBERS 5 AND 6", "start-date": "1986-04-17", "listed-building-grade": "II", "slug": "/listed-building/1023181", "entry-date": "2021-05-28"}}