{"type": "Feature", "geometry": {"type": "Point", "coordinates": [0.13011, 51.05588]}, "properties": {"point": "POINT (0.130110 51.055880)", "documentation-url": "https://historicengland.org.uk/listing/the-list/list-entry/1028020", "listed-building-grade": "II", "name": "WARREN HOUSE", "listed-building": "1028020", "start-date": "1982-12-31", "slug": "/listed-building/1028020", "entry-date": "2021-05-28"}}