{"type": "Feature", "geometry": {"type": "Point", "coordinates": [-0.724425, 51.234097]}, "properties": {"documentation-url": "https://historicengland.org.uk/listing/the-list/list-entry/1029609", "start-date": "1967-06-14", "name": "THE OLD FARMHOUSE", "point": "POINT (-0.724425 51.234097)", "listed-building-grade": "II", "listed-building": "1029609", "slug": "/listed-building/1029609", "entry-date": "1984-12-13"}}