{"type": "Feature", "geometry": {"type": "Point", "coordinates": [-1.667318, 51.547633]}, "properties": {"listed-building-grade": "II", "listed-building": "1023271", "documentation-url": "https://historicengland.org.uk/listing/the-list/list-entry/1023271", "point": "POINT (-1.667318 51.547633)", "name": "GREYSTONES THE LITTLE COTTAGE THREEWAYS", "start-date": "1979-09-20", "slug": "/listed-building/1023271", "entry-date": "2021-05-28"}}