{"type": "Feature", "geometry": {"type": "Point", "coordinates": [0.937065, 50.985274]}, "properties": {"listed-building": "1025300", "name": "SOUTHLANDS HOSPITAL", "documentation-url": "https://historicengland.org.uk/listing/the-list/list-entry/1025300", "point": "POINT (0.937065 50.985274)", "start-date": "1951-08-28", "listed-building-grade": "II", "slug": "/listed-building/1025300", "entry-date": "2021-05-28"}}