{"type": "Feature", "geometry": {"type": "Point", "coordinates": [-0.413841, 50.86483]}, "properties": {"name": "FINDON PLACE", "documentation-url": "https://historicengland.org.uk/listing/the-list/list-entry/1027620", "listed-building-grade": "II*", "listed-building": "1027620", "point": "POINT (-0.413841 50.864830)", "start-date": "1954-10-12", "slug": "/listed-building/1027620", "entry-date": "1984-09-20"}}