{"type": "Feature", "geometry": {"type": "Point", "coordinates": [-0.121499, 50.998952]}, "properties": {"listed-building": "1025547", "documentation-url": "https://historicengland.org.uk/listing/the-list/list-entry/1025547", "name": "PADDOCKS FARMHOUSE", "start-date": "1987-12-11", "point": "POINT (-0.121499 50.998952)", "listed-building-grade": "II", "slug": "/listed-building/1025547", "entry-date": "2021-05-28"}}