{"type": "Feature", "geometry": {"type": "Point", "coordinates": [-1.710213, 51.631331]}, "properties": {"listed-building": "1023383", "listed-building-grade": "II", "start-date": "1979-09-20", "point": "POINT (-1.710213 51.631331)", "documentation-url": "https://historicengland.org.uk/listing/the-list/list-entry/1023383", "name": "BREWER'S HOUSE", "slug": "/listed-building/1023383", "entry-date": "2021-05-28"}}