{"type": "Feature", "geometry": {"type": "Point", "coordinates": [-0.267717, 51.323677]}, "properties": {"name": "CHALK LANE HOTEL", "listed-building": "1028580", "documentation-url": "https://historicengland.org.uk/listing/the-list/list-entry/1028580", "point": "POINT (-0.267717 51.323677)", "listed-building-grade": "II", "start-date": "1973-07-20", "slug": "/listed-building/1028580", "entry-date": "2021-05-28"}}