{"type": "Feature", "geometry": {"type": "Point", "coordinates": [-2.125603, 51.417887]}, "properties": {"start-date": "1987-01-07", "listed-building-grade": "II", "name": "THE OLD RECTORY", "listed-building": "1022142", "point": "POINT (-2.125603 51.417887)", "documentation-url": "https://historicengland.org.uk/listing/the-list/list-entry/1022142", "slug": "/listed-building/1022142", "entry-date": "2021-05-28"}}