{"type": "Feature", "geometry": {"type": "Point", "coordinates": [1.339695, 52.178206]}, "properties": {"point": "POINT (1.339695 52.178206)", "name": "DOWNTON COTTAGE", "listed-building": "1030550", "documentation-url": "https://historicengland.org.uk/listing/the-list/list-entry/1030550", "start-date": "1984-11-19", "listed-building-grade": "II", "slug": "/listed-building/1030550", "entry-date": "2021-05-28"}}