{"type": "Feature", "geometry": {"type": "Point", "coordinates": [-2.201909, 51.502609]}, "properties": {"start-date": "1988-02-29", "name": "BARN AT WEST SEVINGTON FARM", "documentation-url": "https://historicengland.org.uk/listing/the-list/list-entry/1022308", "listed-building": "1022308", "point": "POINT (-2.201909 51.502609)", "listed-building-grade": "II", "slug": "/listed-building/1022308", "entry-date": "2021-05-28"}}