{"type": "Feature", "geometry": {"type": "Point", "coordinates": [-1.67446, 51.051167]}, "properties": {"listed-building-grade": "II", "point": "POINT (-1.674460 51.051167)", "documentation-url": "https://historicengland.org.uk/listing/the-list/list-entry/1023817", "start-date": "1985-03-28", "name": "LITTLE HAWKSGROVE", "listed-building": "1023817", "slug": "/listed-building/1023817", "entry-date": "2021-05-28"}}