{"type": "Feature", "geometry": {"type": "Point", "coordinates": [-1.400083, 52.148626]}, "properties": {"listed-building": "1024251", "documentation-url": "https://historicengland.org.uk/listing/the-list/list-entry/1024251", "start-date": "1987-04-08", "name": "HEADSTONE AGAINST SOUTH WALL OF NAVE OF CHURCH OF ST JOHN THE BAPTIST", "listed-building-grade": "II", "point": "POINT (-1.400083 52.148626)", "slug": "/listed-building/1024251", "entry-date": "2021-05-28"}}