{"type": "Feature", "geometry": {"type": "Point", "coordinates": [-1.853582, 51.076131]}, "properties": {"name": "BOAT HOUSE", "listed-building-grade": "II", "point": "POINT (-1.853582 51.076131)", "listed-building": "1023776", "start-date": "1978-06-08", "documentation-url": "https://historicengland.org.uk/listing/the-list/list-entry/1023776", "slug": "/listed-building/1023776", "entry-date": "2021-05-28"}}