{"type": "Feature", "geometry": {"type": "Point", "coordinates": [0.06327, 50.947935]}, "properties": {"documentation-url": "https://historicengland.org.uk/listing/the-list/list-entry/1028280", "start-date": "1982-12-31", "name": "OLD RECTORY FARM", "listed-building": "1028280", "listed-building-grade": "II", "point": "POINT (0.063270 50.947935)", "slug": "/listed-building/1028280", "entry-date": "2021-05-28"}}