{"type": "Feature", "geometry": {"type": "Point", "coordinates": [0.269454, 51.097523]}, "properties": {"documentation-url": "https://historicengland.org.uk/listing/the-list/list-entry/1028348", "name": "FRANT CHURCH OF ENGLAND SCHOOL", "start-date": "1982-12-31", "listed-building-grade": "II", "listed-building": "1028348", "point": "POINT (0.269454 51.097523)", "slug": "/listed-building/1028348", "entry-date": "2021-05-28"}}