{"type": "Feature", "geometry": {"type": "Point", "coordinates": [-1.369979, 52.144334]}, "properties": {"documentation-url": "https://historicengland.org.uk/listing/the-list/list-entry/1024470", "start-date": "1986-04-21", "listed-building-grade": "II", "name": "THE CLOSE", "point": "POINT (-1.369979 52.144334)", "listed-building": "1024470", "slug": "/listed-building/1024470", "entry-date": "2021-05-28"}}