{"type": "Feature", "geometry": {"type": "Point", "coordinates": [-1.615705, 54.970119]}, "properties": {"point": "POINT (-1.615705 54.970119)", "listed-building": "1024728", "documentation-url": "https://historicengland.org.uk/listing/the-list/list-entry/1024728", "start-date": "1954-06-14", "listed-building-grade": "I", "name": "CHURCH OF ST JOHN THE BAPTIST", "slug": "/listed-building/1024728", "entry-date": "2021-05-28"}}