{"type": "Feature", "geometry": {"type": "Point", "coordinates": [-0.444389, 51.068347]}, "properties": {"listed-building-grade": "II", "listed-building": "1026967", "documentation-url": "https://historicengland.org.uk/listing/the-list/list-entry/1026967", "name": "TITTLESFOLD FARMHOUSE", "point": "POINT (-0.444389 51.068347)", "start-date": "1959-09-22", "slug": "/listed-building/1026967", "entry-date": "2021-05-28"}}