{"type": "Feature", "geometry": {"type": "Point", "coordinates": [-1.609601, 54.977228]}, "properties": {"point": "POINT (-1.609601 54.977228)", "listed-building": "1024921", "documentation-url": "https://historicengland.org.uk/listing/the-list/list-entry/1024921", "listed-building-grade": "II", "start-date": "1971-12-17", "name": "WALLS, PIERS, GATES AND RAILINGS IN FRONT OF CAREERS CENTRE", "slug": "/listed-building/1024921", "entry-date": "2021-05-28"}}