{"type": "Feature", "geometry": {"type": "Point", "coordinates": [-1.813131, 52.258184]}, "properties": {"documentation-url": "https://historicengland.org.uk/listing/the-list/list-entry/1024554", "listed-building-grade": "II", "listed-building": "1024554", "start-date": "1985-10-23", "name": "SHELFIELD PARK FARMHOUSE", "point": "POINT (-1.813131 52.258184)", "slug": "/listed-building/1024554", "entry-date": "2021-05-28"}}