{"type": "Feature", "geometry": {"type": "Point", "coordinates": [-1.858077, 51.640095]}, "properties": {"listed-building-grade": "II", "point": "POINT (-1.858077 51.640095)", "name": "SMART MONUMENT IN CHURCHYARD, 37 METRES SOUTH OF SOUTH TRANCEPT, CHURCH OF ST SAMPSON", "start-date": "1976-11-11", "documentation-url": "https://historicengland.org.uk/listing/the-list/list-entry/1023084", "listed-building": "1023084", "slug": "/listed-building/1023084", "entry-date": "2021-05-28"}}