{"type": "Feature", "geometry": {"type": "Point", "coordinates": [-1.857957, 51.640555]}, "properties": {"listed-building": "1023081", "documentation-url": "https://historicengland.org.uk/listing/the-list/list-entry/1023081", "start-date": "1955-01-17", "listed-building-grade": "I", "name": "CHURCH OF ST SAMPSON", "point": "POINT (-1.857957 51.640555)", "slug": "/listed-building/1023081", "entry-date": "2021-05-28"}}