{"type": "Feature", "geometry": {"type": "Point", "coordinates": [0.270126, 51.091403]}, "properties": {"documentation-url": "https://historicengland.org.uk/listing/the-list/list-entry/1028366", "point": "POINT (0.270126 51.091403)", "listed-building": "1028366", "listed-building-grade": "II", "name": "SHERNFOLD PARK", "start-date": "1982-12-31", "slug": "/listed-building/1028366", "entry-date": "2021-05-28"}}