{"type": "Feature", "geometry": {"type": "Point", "coordinates": [-1.773307, 51.551331]}, "properties": {"start-date": "1951-10-02", "documentation-url": "https://historicengland.org.uk/listing/the-list/list-entry/1023523", "point": "POINT (-1.773307 51.551331)", "name": "CORN EXCHANGE AND TOWN HALL", "listed-building-grade": "II", "listed-building": "1023523", "slug": "/listed-building/1023523", "entry-date": "1986-04-23"}}