{"type": "Feature", "geometry": {"type": "Point", "coordinates": [1.257305, 52.106041]}, "properties": {"start-date": "1966-03-16", "listed-building-grade": "II", "documentation-url": "https://historicengland.org.uk/listing/the-list/list-entry/1030727", "listed-building": "1030727", "name": "BRIDGE HOUSE", "point": "POINT (1.257305 52.106041)", "slug": "/listed-building/1030727", "entry-date": "1988-08-31"}}