{"type": "Feature", "geometry": {"type": "Point", "coordinates": [-1.463642, 54.842696]}, "properties": {"name": "NUMBER 16, AREA RAILINGS AND DWARF WALL IN FRONT", "documentation-url": "https://historicengland.org.uk/listing/the-list/list-entry/1025416", "listed-building-grade": "II", "listed-building": "1025416", "start-date": "1985-07-15", "point": "POINT (-1.463642 54.842696)", "slug": "/listed-building/1025416", "entry-date": "2021-05-28"}}