{"type": "Feature", "geometry": {"type": "Point", "coordinates": [-0.300163, 51.308263]}, "properties": {"listed-building-grade": "II", "listed-building": "1028657", "name": "18 AND 20, RECTORY LANE", "point": "POINT (-0.300163 51.308263)", "documentation-url": "https://historicengland.org.uk/listing/the-list/list-entry/1028657", "start-date": "1973-11-23", "slug": "/listed-building/1028657", "entry-date": "2021-05-28"}}