{"type": "Feature", "geometry": {"type": "Point", "coordinates": [-1.311296, 52.201851]}, "properties": {"start-date": "1986-04-21", "name": "GROUP OF A CHEST TOMB, HEADSTONE AND ROW OF 4 HEADSTONES APPROXIMATELY 8 METRES SOUTH OF SOUTH WEST CORNER OF CHURCH OF ST MARY", "documentation-url": "https://historicengland.org.uk/listing/the-list/list-entry/1024457", "listed-building-grade": "II", "listed-building": "1024457", "point": "POINT (-1.311296 52.201851)", "slug": "/listed-building/1024457", "entry-date": "2021-05-28"}}