{"type": "Feature", "geometry": {"type": "Point", "coordinates": [-1.871716, 52.311784]}, "properties": {"listed-building": "1024488", "documentation-url": "https://historicengland.org.uk/listing/the-list/list-entry/1024488", "start-date": "1967-02-01", "point": "POINT (-1.871716 52.311784)", "name": "RIGHT GATEPIER AND GARDEN WALL APPROXIMATELY 10 METRES SOUTH EAST OF GORCOTT HALL", "listed-building-grade": "II", "slug": "/listed-building/1024488", "entry-date": "1985-10-23"}}