{"type": "Feature", "geometry": {"type": "Point", "coordinates": [0.115056, 51.116301]}, "properties": {"listed-building-grade": "II", "listed-building": "1028288", "documentation-url": "https://historicengland.org.uk/listing/the-list/list-entry/1028288", "start-date": "1982-12-31", "name": "BARN TO THE SOUTH WEST OF BOLEBROKE MILL HOUSE", "point": "POINT (0.115056 51.116301)", "slug": "/listed-building/1028288", "entry-date": "2021-05-28"}}