{"type": "Feature", "geometry": {"type": "Point", "coordinates": [-2.164665, 51.466198]}, "properties": {"documentation-url": "https://historicengland.org.uk/listing/the-list/list-entry/1022907", "listed-building": "1022907", "point": "POINT (-2.164665 51.466198)", "start-date": "1960-12-20", "listed-building-grade": "I", "name": "SHELDON MANOR", "slug": "/listed-building/1022907", "entry-date": "2021-05-28"}}