{"type": "Feature", "geometry": {"type": "Point", "coordinates": [-2.229538, 51.493306]}, "properties": {"listed-building": "1022870", "listed-building-grade": "II", "name": "JAMES ARCHER TOMB IN CHURCHYARD, ABOUT 1 METRE SOUTH OF SEALY TOMB, SOUTH EAST OF PORCH OF CHURCH OF ST ANDREW", "point": "POINT (-2.229538 51.493306)", "documentation-url": "https://historicengland.org.uk/listing/the-list/list-entry/1022870", "start-date": "1985-12-09", "slug": "/listed-building/1022870", "entry-date": "2021-05-28"}}