{"type": "Feature", "geometry": {"type": "Point", "coordinates": [-2.242011, 51.381785]}, "properties": {"name": "TWO UNIDENTIFIED MONUMENTS IN THE CHURCHYARD ABOUT 1 METRES WEST OF CHURCH OF ST JAMES", "listed-building-grade": "II", "listed-building": "1021868", "documentation-url": "https://historicengland.org.uk/listing/the-list/list-entry/1021868", "point": "POINT (-2.242011 51.381785)", "start-date": "1988-06-14", "slug": "/listed-building/1021868", "entry-date": "2021-05-28"}}