{"type": "Feature", "geometry": {"type": "Point", "coordinates": [0.245546, 51.048619]}, "properties": {"point": "POINT (0.245546 51.048619)", "start-date": "1953-11-26", "listed-building-grade": "II", "documentation-url": "https://historicengland.org.uk/listing/the-list/list-entry/1028157", "name": "BLETCHINGLYE FARMHOUSE", "listed-building": "1028157", "slug": "/listed-building/1028157", "entry-date": "2021-05-28"}}