{"type": "Feature", "geometry": {"type": "Point", "coordinates": [-0.064043, 51.172141]}, "properties": {"listed-building-grade": "II", "point": "POINT (-0.064043 51.172141)", "documentation-url": "https://historicengland.org.uk/listing/the-list/list-entry/1029936", "name": "SEPTEMBER COTTAGE", "start-date": "1984-04-25", "listed-building": "1029936", "slug": "/listed-building/1029936", "entry-date": "2021-05-28"}}