{"type": "Feature", "geometry": {"type": "Point", "coordinates": [-2.228655, 51.492248]}, "properties": {"listed-building": "1022888", "listed-building-grade": "II", "documentation-url": "https://historicengland.org.uk/listing/the-list/list-entry/1022888", "name": "2 AND 3, WATER LANE", "start-date": "1960-12-20", "point": "POINT (-2.228655 51.492248)", "slug": "/listed-building/1022888", "entry-date": "1985-12-09"}}