{"type": "Feature", "geometry": {"type": "Point", "coordinates": [-1.792634, 51.526371]}, "properties": {"name": "THE OLD MILL AND ATTACHED STABLE", "listed-building": "1023446", "listed-building-grade": "II", "point": "POINT (-1.792634 51.526371)", "documentation-url": "https://historicengland.org.uk/listing/the-list/list-entry/1023446", "start-date": "1979-09-20", "slug": "/listed-building/1023446", "entry-date": "1987-04-22"}}