{"type": "Feature", "geometry": {"type": "Point", "coordinates": [-0.533653, 50.909545]}, "properties": {"name": "THE WHITE HOUSE", "listed-building": "1027471", "start-date": "1955-03-15", "point": "POINT (-0.533653 50.909545)", "listed-building-grade": "II", "documentation-url": "https://historicengland.org.uk/listing/the-list/list-entry/1027471", "slug": "/listed-building/1027471", "entry-date": "2021-05-28"}}