{"type": "Feature", "geometry": {"type": "Point", "coordinates": [-1.3697, 52.142381]}, "properties": {"name": "WALNUT BANK COTTAGE WALNUT COTTAGE", "listed-building": "1024474", "documentation-url": "https://historicengland.org.uk/listing/the-list/list-entry/1024474", "point": "POINT (-1.369700 52.142381)", "start-date": "1986-04-21", "listed-building-grade": "II", "slug": "/listed-building/1024474", "entry-date": "2021-05-28"}}