{"type": "Feature", "geometry": {"type": "Point", "coordinates": [-0.761776, 50.814066]}, "properties": {"documentation-url": "https://historicengland.org.uk/listing/the-list/list-entry/1026286", "start-date": "1986-01-28", "listed-building": "1026286", "name": "1760 COTTAGE", "point": "POINT (-0.761776 50.814066)", "listed-building-grade": "II", "slug": "/listed-building/1026286", "entry-date": "2021-05-28"}}