{"type": "Feature", "geometry": {"type": "Point", "coordinates": [-0.098621, 51.241287]}, "properties": {"documentation-url": "https://historicengland.org.uk/listing/the-list/list-entry/1029968", "point": "POINT (-0.098621 51.241287)", "name": "COURT LODGE FARM HOUSE", "listed-building": "1029968", "listed-building-grade": "II", "start-date": "1958-06-11", "slug": "/listed-building/1029968", "entry-date": "2021-05-28"}}