{"type": "Feature", "geometry": {"type": "Point", "coordinates": [-2.165262, 51.432452]}, "properties": {"name": "SUMMERHOUSE IN WALLED GARDEN OF OLD HOUSE", "start-date": "1960-12-20", "documentation-url": "https://historicengland.org.uk/listing/the-list/list-entry/1022123", "listed-building": "1022123", "listed-building-grade": "II", "point": "POINT (-2.165262 51.432452)", "slug": "/listed-building/1022123", "entry-date": "1986-08-01"}}