{"type": "Feature", "geometry": {"type": "Point", "coordinates": [-1.854863, 51.077868]}, "properties": {"listed-building-grade": "II", "start-date": "1978-06-08", "name": "WHISPERING SEAT", "point": "POINT (-1.854863 51.077868)", "documentation-url": "https://historicengland.org.uk/listing/the-list/list-entry/1023772", "listed-building": "1023772", "slug": "/listed-building/1023772", "entry-date": "2021-05-28"}}