{"type": "Feature", "geometry": {"type": "Point", "coordinates": [-1.62521, 51.97048]}, "properties": {"start-date": "1982-10-27", "name": "PILBRIDGE HOUSE", "listed-building": "1024294", "documentation-url": "https://historicengland.org.uk/listing/the-list/list-entry/1024294", "listed-building-grade": "II", "point": "POINT (-1.625210 51.970480)", "slug": "/listed-building/1024294", "entry-date": "2021-05-28"}}