{"type": "Feature", "geometry": {"type": "Point", "coordinates": [-0.671582, 50.842085]}, "properties": {"listed-building": "1027702", "listed-building-grade": "II", "start-date": "1984-09-20", "point": "POINT (-0.671582 50.842085)", "documentation-url": "https://historicengland.org.uk/listing/the-list/list-entry/1027702", "name": "NYTON LODGE", "slug": "/listed-building/1027702", "entry-date": "2021-05-28"}}