{"type": "Feature", "geometry": {"type": "Point", "coordinates": [-1.784694, 51.521405]}, "properties": {"listed-building": "1023440", "name": "THE KNOLE", "documentation-url": "https://historicengland.org.uk/listing/the-list/list-entry/1023440", "start-date": "1979-09-20", "listed-building-grade": "II", "point": "POINT (-1.784694 51.521405)", "slug": "/listed-building/1023440", "entry-date": "2021-05-28"}}