{"type": "Feature", "geometry": {"type": "Point", "coordinates": [-0.451894, 51.335312]}, "properties": {"listed-building-grade": "II", "start-date": "1975-10-10", "name": "OCTAGONAL STORAGE SHED SOUTH OF MODEL FARM", "listed-building": "1030096", "point": "POINT (-0.451894 51.335312)", "documentation-url": "https://historicengland.org.uk/listing/the-list/list-entry/1030096", "slug": "/listed-building/1030096", "entry-date": "2021-05-28"}}