{"type": "Feature", "geometry": {"type": "Point", "coordinates": [-0.053271, 51.079349]}, "properties": {"listed-building-grade": "II", "point": "POINT (-0.053271 51.079349)", "name": "RED HOUSE COTTAGE THE RED HOUSE", "start-date": "1983-05-11", "documentation-url": "https://historicengland.org.uk/listing/the-list/list-entry/1025553", "listed-building": "1025553", "slug": "/listed-building/1025553", "entry-date": "2021-05-28"}}