{"type": "Feature", "geometry": {"type": "Point", "coordinates": [-1.797337, 51.067513]}, "properties": {"listed-building": "1023690", "name": "29 AND 31, HIGH STREET", "start-date": "1972-10-12", "documentation-url": "https://historicengland.org.uk/listing/the-list/list-entry/1023690", "point": "POINT (-1.797337 51.067513)", "listed-building-grade": "II", "slug": "/listed-building/1023690", "entry-date": "2021-05-28"}}