{"type": "Feature", "geometry": {"type": "Point", "coordinates": [-0.147288, 51.164166]}, "properties": {"start-date": "1984-04-26", "point": "POINT (-0.147288 51.164166)", "documentation-url": "https://historicengland.org.uk/listing/the-list/list-entry/1028988", "listed-building-grade": "II", "name": "YEW TREE COTTAGE", "listed-building": "1028988", "slug": "/listed-building/1028988", "entry-date": "2021-05-28"}}