{"type": "Feature", "geometry": {"type": "Point", "coordinates": [-0.6299, 54.469749]}, "properties": {"listed-building": "1025869", "start-date": "1972-12-04", "documentation-url": "https://historicengland.org.uk/listing/the-list/list-entry/1025869", "listed-building-grade": "II", "name": "MULGROVE COTTAGE", "point": "POINT (-0.629900 54.469749)", "slug": "/listed-building/1025869", "entry-date": "2021-05-28"}}