{"type": "Feature", "geometry": {"type": "Point", "coordinates": [-0.297431, 51.144259]}, "properties": {"listed-building": "1028741", "point": "POINT (-0.297431 51.144259)", "documentation-url": "https://historicengland.org.uk/listing/the-list/list-entry/1028741", "listed-building-grade": "II", "name": "PIGSTIES AT TEMPLE BARNS", "start-date": "1987-09-29", "slug": "/listed-building/1028741", "entry-date": "2021-05-28"}}