{"type": "Feature", "geometry": {"type": "Point", "coordinates": [-0.160259, 51.020721]}, "properties": {"documentation-url": "https://historicengland.org.uk/listing/the-list/list-entry/1025738", "name": "LITTLE MIZBROOKS", "point": "POINT (-0.160259 51.020721)", "listed-building": "1025738", "start-date": "1983-05-11", "listed-building-grade": "II", "slug": "/listed-building/1025738", "entry-date": "2021-05-28"}}