{"type": "Feature", "geometry": {"type": "Point", "coordinates": [0.355455, 51.075361]}, "properties": {"documentation-url": "https://historicengland.org.uk/listing/the-list/list-entry/1028101", "point": "POINT (0.355455 51.075361)", "name": "QUARRY COTTAGES", "listed-building": "1028101", "listed-building-grade": "II", "start-date": "1982-12-31", "slug": "/listed-building/1028101", "entry-date": "2021-05-28"}}