{"type": "Feature", "geometry": {"type": "Point", "coordinates": [-1.952686, 51.457259]}, "properties": {"listed-building-grade": "II", "name": "MANOR COTTAGE", "listed-building": "1022482", "start-date": "1987-11-25", "point": "POINT (-1.952686 51.457259)", "documentation-url": "https://historicengland.org.uk/listing/the-list/list-entry/1022482", "slug": "/listed-building/1022482", "entry-date": "2021-05-28"}}