{"type": "Feature", "geometry": {"type": "Point", "coordinates": [-2.142874, 51.384646]}, "properties": {"point": "POINT (-2.142874 51.384646)", "listed-building-grade": "II", "start-date": "1985-02-13", "documentation-url": "https://historicengland.org.uk/listing/the-list/list-entry/1021693", "name": "GAZEBO IN GARDEN OF NO 5 HALFWAY FARMHOUSE", "listed-building": "1021693", "slug": "/listed-building/1021693", "entry-date": "2021-05-28"}}