{"type": "Feature", "geometry": {"type": "Point", "coordinates": [0.330316, 50.950834]}, "properties": {"name": "GOLDRINGS'S FARMHOUSE", "listed-building": "1028541", "start-date": "1981-08-12", "listed-building-grade": "II", "point": "POINT (0.330316 50.950834)", "documentation-url": "https://historicengland.org.uk/listing/the-list/list-entry/1028541", "slug": "/listed-building/1028541", "entry-date": "2021-05-28"}}