{"type": "Feature", "geometry": {"type": "Point", "coordinates": [-0.328889, 51.293555]}, "properties": {"listed-building": "1028620", "documentation-url": "https://historicengland.org.uk/listing/the-list/list-entry/1028620", "name": "THE MANSION", "listed-building-grade": "II", "start-date": "1951-09-07", "point": "POINT (-0.328889 51.293555)", "slug": "/listed-building/1028620", "entry-date": "2021-05-28"}}