{"type": "Feature", "geometry": {"type": "Point", "coordinates": [-1.615234, 54.970893]}, "properties": {"listed-building": "1024867", "start-date": "1987-03-30", "listed-building-grade": "II", "name": "VICTORIA BUILDINGS", "documentation-url": "https://historicengland.org.uk/listing/the-list/list-entry/1024867", "point": "POINT (-1.615234 54.970893)", "slug": "/listed-building/1024867", "entry-date": "2021-05-28"}}