{"type": "Feature", "geometry": {"type": "Point", "coordinates": [-0.33338, 51.062608]}, "properties": {"name": "26 AND 28, WORTHING ROAD", "start-date": "1974-07-26", "documentation-url": "https://historicengland.org.uk/listing/the-list/list-entry/1027494", "listed-building-grade": "II", "point": "POINT (-0.333380 51.062608)", "listed-building": "1027494", "slug": "/listed-building/1027494", "entry-date": "2021-05-28"}}