{"type": "Feature", "geometry": {"type": "Point", "coordinates": [-2.024627, 51.522184]}, "properties": {"listed-building": "1022472", "point": "POINT (-2.024627 51.522184)", "name": "MALFORD HOUSE", "start-date": "1987-11-25", "documentation-url": "https://historicengland.org.uk/listing/the-list/list-entry/1022472", "listed-building-grade": "II", "slug": "/listed-building/1022472", "entry-date": "2021-05-28"}}