{"type": "Feature", "geometry": {"type": "Point", "coordinates": [-2.118186, 51.421983]}, "properties": {"start-date": "1987-01-07", "name": "PIGEON HOUSE TO SOUTH OF NO 8", "point": "POINT (-2.118186 51.421983)", "documentation-url": "https://historicengland.org.uk/listing/the-list/list-entry/1022192", "listed-building": "1022192", "listed-building-grade": "II", "slug": "/listed-building/1022192", "entry-date": "2021-05-28"}}