{"type": "Feature", "geometry": {"type": "Point", "coordinates": [-0.152546, 51.184443]}, "properties": {"documentation-url": "https://historicengland.org.uk/listing/the-list/list-entry/1028990", "start-date": "1984-04-26", "point": "POINT (-0.152546 51.184443)", "name": "BARN 50 YARDS SOUTH OF GREAT LAKES FARM", "listed-building-grade": "II", "listed-building": "1028990", "slug": "/listed-building/1028990", "entry-date": "2021-05-28"}}