{"type": "Feature", "geometry": {"type": "Point", "coordinates": [-1.51741, 54.994001]}, "properties": {"point": "POINT (-1.517410 54.994001)", "listed-building": "1025326", "listed-building-grade": "II*", "start-date": "1947-08-18", "documentation-url": "https://historicengland.org.uk/listing/the-list/list-entry/1025326", "name": "CHURCH OF ST PETER", "slug": "/listed-building/1025326", "entry-date": "2021-05-28"}}