{"type": "Feature", "geometry": {"type": "Point", "coordinates": [-0.14336, 51.004724]}, "properties": {"listed-building": "1025512", "documentation-url": "https://historicengland.org.uk/listing/the-list/list-entry/1025512", "start-date": "1987-12-11", "listed-building-grade": "II", "point": "POINT (-0.143360 51.004724)", "name": "MONUMENT APPROXIMATELY 1/2 METRE SOUTH OF ITEM 8/26", "slug": "/listed-building/1025512", "entry-date": "2021-05-28"}}