{"type": "Feature", "geometry": {"type": "Point", "coordinates": [-1.606971, 54.982749]}, "properties": {"listed-building-grade": "II", "point": "POINT (-1.606971 54.982749)", "listed-building": "1024894", "start-date": "1987-03-30", "name": "PIERS FROM HOSPITAL OF THE VIRGIN MARY OF ROYAL GRAMMAR SCHOOL", "documentation-url": "https://historicengland.org.uk/listing/the-list/list-entry/1024894", "slug": "/listed-building/1024894", "entry-date": "2021-05-28"}}