{"type": "Feature", "geometry": {"type": "Point", "coordinates": [-0.284129, 51.146753]}, "properties": {"documentation-url": "https://historicengland.org.uk/listing/the-list/list-entry/1028728", "listed-building": "1028728", "start-date": "1986-10-24", "point": "POINT (-0.284129 51.146753)", "name": "MARELANDS FARM BARN", "listed-building-grade": "II", "slug": "/listed-building/1028728", "entry-date": "2021-05-28"}}