{"type": "Feature", "geometry": {"type": "Point", "coordinates": [0.064552, 50.980729]}, "properties": {"documentation-url": "https://historicengland.org.uk/listing/the-list/list-entry/1028434", "listed-building": "1028434", "name": "THE OLD POST", "start-date": "1982-12-31", "listed-building-grade": "II", "point": "POINT (0.064552 50.980729)", "slug": "/listed-building/1028434", "entry-date": "2021-05-28"}}