{"type": "Feature", "geometry": {"type": "Point", "coordinates": [-1.777528, 51.5724]}, "properties": {"start-date": "1970-02-17", "listed-building": "1023482", "name": "CHURCH OF ST BARNABAS", "point": "POINT (-1.777528 51.572400)", "listed-building-grade": "II", "documentation-url": "https://historicengland.org.uk/listing/the-list/list-entry/1023482", "slug": "/listed-building/1023482", "entry-date": "2021-05-28"}}