{"type": "Feature", "geometry": {"type": "Point", "coordinates": [-1.896703, 52.274919]}, "properties": {"listed-building-grade": "II", "point": "POINT (-1.896703 52.274919)", "documentation-url": "https://historicengland.org.uk/listing/the-list/list-entry/1024496", "start-date": "1985-10-23", "listed-building": "1024496", "name": "29 AND 31, REDDITCH ROAD", "slug": "/listed-building/1024496", "entry-date": "2021-05-28"}}