{"type": "Feature", "geometry": {"type": "Point", "coordinates": [-2.208198, 51.346225]}, "properties": {"listed-building-grade": "II", "point": "POINT (-2.208198 51.346225)", "start-date": "1988-06-14", "documentation-url": "https://historicengland.org.uk/listing/the-list/list-entry/1021874", "name": "WESLEYAN CHAPEL", "listed-building": "1021874", "slug": "/listed-building/1021874", "entry-date": "2021-05-28"}}