{"type": "Feature", "geometry": {"type": "Point", "coordinates": [-0.42887, 51.355391]}, "properties": {"name": "LAMP POST, 90 YARDS NORTH OF BRIDGE", "listed-building": "1030178", "point": "POINT (-0.428870 51.355391)", "documentation-url": "https://historicengland.org.uk/listing/the-list/list-entry/1030178", "start-date": "1984-11-16", "listed-building-grade": "II", "slug": "/listed-building/1030178", "entry-date": "2021-05-28"}}