{"type": "Feature", "geometry": {"type": "Point", "coordinates": [-0.17275, 50.931848]}, "properties": {"documentation-url": "https://historicengland.org.uk/listing/the-list/list-entry/1025668", "start-date": "1983-05-11", "listed-building-grade": "II", "name": "Gate piers to drive of Hampton Lodge to the north-east of the house", "point": "POINT (-0.172750 50.931848)", "listed-building": "1025668", "slug": "/listed-building/1025668", "entry-date": "2021-05-28"}}