{"type": "Feature", "geometry": {"type": "Point", "coordinates": [1.568163, 52.278493]}, "properties": {"name": "RED HOUSE FARMHOUSE", "listed-building-grade": "II", "point": "POINT (1.568163 52.278493)", "documentation-url": "https://historicengland.org.uk/listing/the-list/list-entry/1030687", "start-date": "1951-10-25", "listed-building": "1030687", "slug": "/listed-building/1030687", "entry-date": "1984-01-16"}}