{"type": "Feature", "geometry": {"type": "Point", "coordinates": [-0.177484, 50.93337]}, "properties": {"listed-building": "1025675", "point": "POINT (-0.177484 50.933370)", "documentation-url": "https://historicengland.org.uk/listing/the-list/list-entry/1025675", "start-date": "1983-05-11", "name": "DOWN HOUSE", "listed-building-grade": "II", "slug": "/listed-building/1025675", "entry-date": "2021-05-28"}}