{"type": "Feature", "geometry": {"type": "Point", "coordinates": [-0.787168, 50.836644]}, "properties": {"start-date": "1950-07-05", "name": "37 AND 39, WESTGATE", "point": "POINT (-0.787168 50.836644)", "documentation-url": "https://historicengland.org.uk/listing/the-list/list-entry/1026594", "listed-building": "1026594", "listed-building-grade": "II", "slug": "/listed-building/1026594", "entry-date": "1971-10-08"}}