{"type": "Feature", "geometry": {"type": "Point", "coordinates": [1.552233, 52.247655]}, "properties": {"point": "POINT (1.552233 52.247655)", "start-date": "1984-07-27", "documentation-url": "https://historicengland.org.uk/listing/the-list/list-entry/1030643", "listed-building": "1030643", "name": "HILL FARMHOUSE", "listed-building-grade": "II", "slug": "/listed-building/1030643", "entry-date": "2021-05-28"}}