{"type": "Feature", "geometry": {"type": "Point", "coordinates": [-0.788945, 50.736058]}, "properties": {"listed-building-grade": "II", "listed-building": "1026267", "point": "POINT (-0.788945 50.736058)", "name": "BARN ADJOINING NO 20 ON THE NORTH WEST", "start-date": "1986-01-28", "documentation-url": "https://historicengland.org.uk/listing/the-list/list-entry/1026267", "slug": "/listed-building/1026267", "entry-date": "2021-05-28"}}