{"type": "Feature", "geometry": {"type": "Point", "coordinates": [-0.715322, 51.247253]}, "properties": {"point": "POINT (-0.715322 51.247253)", "name": "NOS 1, 2 AND 3 INCLUDING THE OLD RECTORY THE OLD RECTORY", "start-date": "1967-06-14", "listed-building": "1029654", "documentation-url": "https://historicengland.org.uk/listing/the-list/list-entry/1029654", "listed-building-grade": "II", "slug": "/listed-building/1029654", "entry-date": "2021-05-28"}}