{"type": "Feature", "geometry": {"type": "Point", "coordinates": [-2.259904, 52.986333]}, "properties": {"listed-building": "1027839", "start-date": "1985-05-14", "listed-building-grade": "II", "name": "IVY COTTAGE", "point": "POINT (-2.259904 52.986333)", "documentation-url": "https://historicengland.org.uk/listing/the-list/list-entry/1027839", "slug": "/listed-building/1027839", "entry-date": "2021-05-28"}}