{"type": "Feature", "geometry": {"type": "Point", "coordinates": [-0.279201, 50.928303]}, "properties": {"listed-building": "1027382", "point": "POINT (-0.279201 50.928303)", "start-date": "1980-05-09", "name": "WISTARIA COTTAGE", "listed-building-grade": "II", "documentation-url": "https://historicengland.org.uk/listing/the-list/list-entry/1027382", "slug": "/listed-building/1027382", "entry-date": "2021-05-28"}}