{"type": "Feature", "geometry": {"type": "Point", "coordinates": [-1.322474, 52.252883]}, "properties": {"listed-building": "1024440", "start-date": "1986-04-21", "name": "THE OLD FARM HOUSE", "point": "POINT (-1.322474 52.252883)", "listed-building-grade": "II", "documentation-url": "https://historicengland.org.uk/listing/the-list/list-entry/1024440", "slug": "/listed-building/1024440", "entry-date": "2021-05-28"}}