{"type": "Feature", "geometry": {"type": "Point", "coordinates": [0.846768, 52.325973]}, "properties": {"listed-building": "1031344", "name": "BELL COTTAGE", "point": "POINT (0.846768 52.325973)", "documentation-url": "https://historicengland.org.uk/listing/the-list/list-entry/1031344", "listed-building-grade": "II", "start-date": "1983-12-14", "slug": "/listed-building/1031344", "entry-date": "1988-04-14"}}