{"type": "Feature", "geometry": {"type": "Point", "coordinates": [-0.669453, 50.977745]}, "properties": {"listed-building": "1025890", "start-date": "1987-11-26", "name": "HURLANDS", "point": "POINT (-0.669453 50.977745)", "listed-building-grade": "II", "documentation-url": "https://historicengland.org.uk/listing/the-list/list-entry/1025890", "slug": "/listed-building/1025890", "entry-date": "2021-05-28"}}