{"type": "Feature", "geometry": {"type": "Point", "coordinates": [-2.311933, 51.341877]}, "properties": {"listed-building": "1021819", "listed-building-grade": "II", "name": "TWO UNIDENTIFIED MONUMENTS IN THE CHURCHYARD BETWEEN 1 AND 4 METRES NORTH EAST OF PORCH OF CHURCH OF ST MARY", "point": "POINT (-2.311933 51.341877)", "start-date": "1988-06-14", "documentation-url": "https://historicengland.org.uk/listing/the-list/list-entry/1021819", "slug": "/listed-building/1021819", "entry-date": "2021-05-28"}}