{"type": "Feature", "geometry": {"type": "Point", "coordinates": [-0.594369, 50.931497]}, "properties": {"point": "POINT (-0.594369 50.931497)", "documentation-url": "https://historicengland.org.uk/listing/the-list/list-entry/1026551", "listed-building": "1026551", "name": "THE FORMER FARM BUILDINGS OF BIGNOR PARK TO THE NORTH WEST OF THE STABLES", "start-date": "1984-05-02", "listed-building-grade": "II", "slug": "/listed-building/1026551", "entry-date": "2021-05-28"}}