{"type": "Feature", "geometry": {"type": "Point", "coordinates": [-4.724107, 50.471419]}, "properties": {"listed-building": "1025084", "listed-building-grade": "II", "point": "POINT (-4.724107 50.471419)", "documentation-url": "https://historicengland.org.uk/listing/the-list/list-entry/1025084", "name": "BARLEY SHEAF PUBLIC HOUSE AND ATTACHED MOUNTING BLOCK", "start-date": "1972-06-08", "slug": "/listed-building/1025084", "entry-date": "1994-01-07"}}