{"type": "Feature", "geometry": {"type": "Point", "coordinates": [-0.427338, 51.328825]}, "properties": {"documentation-url": "https://historicengland.org.uk/listing/the-list/list-entry/1030124", "start-date": "1984-11-16", "listed-building": "1030124", "point": "POINT (-0.427338 51.328825)", "listed-building-grade": "II*", "name": "THE GOTHIC TEMPLE", "slug": "/listed-building/1030124", "entry-date": "2021-05-28"}}