{"type": "Feature", "geometry": {"type": "Point", "coordinates": [-2.232424, 51.464042]}, "properties": {"documentation-url": "https://historicengland.org.uk/listing/the-list/list-entry/1022847", "start-date": "1985-12-09", "point": "POINT (-2.232424 51.464042)", "listed-building-grade": "II", "listed-building": "1022847", "name": "ROSEWOOD COTTAGE", "slug": "/listed-building/1022847", "entry-date": "2021-05-28"}}