{"type": "Feature", "geometry": {"type": "Point", "coordinates": [0.891103, 52.322127]}, "properties": {"documentation-url": "https://historicengland.org.uk/listing/the-list/list-entry/1031194", "start-date": "1984-09-27", "point": "POINT (0.891103 52.322127)", "listed-building": "1031194", "listed-building-grade": "II", "name": "MILL FARMHOUSE", "slug": "/listed-building/1031194", "entry-date": "2021-05-28"}}