{"type": "Feature", "geometry": {"type": "Point", "coordinates": [-0.474209, 51.007436]}, "properties": {"documentation-url": "https://historicengland.org.uk/listing/the-list/list-entry/1027124", "listed-building-grade": "II", "point": "POINT (-0.474209 51.007436)", "name": "THE LORDINGS", "listed-building": "1027124", "start-date": "1980-11-28", "slug": "/listed-building/1027124", "entry-date": "2021-05-28"}}