{"type": "Feature", "geometry": {"type": "Point", "coordinates": [-0.452221, 51.022283]}, "properties": {"point": "POINT (-0.452221 51.022283)", "documentation-url": "https://historicengland.org.uk/listing/the-list/list-entry/1027097", "listed-building": "1027097", "name": "SOUTHDOWN HOUSE", "start-date": "1980-11-28", "listed-building-grade": "II", "slug": "/listed-building/1027097", "entry-date": "2021-05-28"}}