{"type": "Feature", "geometry": {"type": "Point", "coordinates": [0.219999, 50.943063]}, "properties": {"listed-building-grade": "II", "start-date": "1985-06-19", "documentation-url": "https://historicengland.org.uk/listing/the-list/list-entry/1028489", "name": "OAST 100 METRES WEST SOUTH WEST OF TANNERS MANOR HOUSE", "point": "POINT (0.219999 50.943063)", "listed-building": "1028489", "slug": "/listed-building/1028489", "entry-date": "2021-05-28"}}