{"type": "Feature", "geometry": {"type": "Point", "coordinates": [-1.673966, 50.977141]}, "properties": {"listed-building": "1023931", "name": "STABLE COTTAGES AND ATTACHED STABLES, CARRIAGE HOUSE AND RAILINGS, AT HAMPTWORTH LODGE", "listed-building-grade": "II", "point": "POINT (-1.673966 50.977141)", "start-date": "1985-07-04", "documentation-url": "https://historicengland.org.uk/listing/the-list/list-entry/1023931", "slug": "/listed-building/1023931", "entry-date": "2021-05-28"}}