{"type": "Feature", "geometry": {"type": "Point", "coordinates": [-0.239534, 51.242925]}, "properties": {"point": "POINT (-0.239534 51.242925)", "listed-building-grade": "II", "documentation-url": "https://historicengland.org.uk/listing/the-list/list-entry/1028758", "start-date": "1966-11-11", "listed-building": "1028758", "name": "THE OLD COTTAGE", "slug": "/listed-building/1028758", "entry-date": "2021-05-28"}}