{"type": "Feature", "geometry": {"type": "Point", "coordinates": [-0.171612, 51.038759]}, "properties": {"documentation-url": "https://historicengland.org.uk/listing/the-list/list-entry/1025730", "name": "LITTLE TYES", "start-date": "1983-05-11", "listed-building": "1025730", "listed-building-grade": "II", "point": "POINT (-0.171612 51.038759)", "slug": "/listed-building/1025730", "entry-date": "2021-05-28"}}