{"type": "Feature", "geometry": {"type": "Point", "coordinates": [-0.492816, 51.299865]}, "properties": {"name": "CEDAR HOUSE AND TUDOR HOUSE", "documentation-url": "https://historicengland.org.uk/listing/the-list/list-entry/1029375", "listed-building": "1029375", "listed-building-grade": "II", "start-date": "1967-06-14", "point": "POINT (-0.492816 51.299865)", "slug": "/listed-building/1029375", "entry-date": "2021-05-28"}}