{"type": "Feature", "geometry": {"type": "Point", "coordinates": [0.91575, 52.335756]}, "properties": {"start-date": "1955-07-14", "name": "CHURCH OF ST PETER", "documentation-url": "https://historicengland.org.uk/listing/the-list/list-entry/1031214", "point": "POINT (0.915750 52.335756)", "listed-building-grade": "II*", "listed-building": "1031214", "slug": "/listed-building/1031214", "entry-date": "2021-05-28"}}