{"type": "Feature", "geometry": {"type": "Point", "coordinates": [-0.007329, 51.235659]}, "properties": {"name": "BARN AND OASTHOUSE 15 YARDS SOUTH OF STOCKETTS MANOR", "listed-building": "1029742", "listed-building-grade": "II", "documentation-url": "https://historicengland.org.uk/listing/the-list/list-entry/1029742", "point": "POINT (-0.007329 51.235659)", "start-date": "1984-11-19", "slug": "/listed-building/1029742", "entry-date": "2021-05-28"}}