{"type": "Feature", "geometry": {"type": "Point", "coordinates": [-1.822122, 52.292523]}, "properties": {"point": "POINT (-1.822122 52.292523)", "listed-building-grade": "II", "documentation-url": "https://historicengland.org.uk/listing/the-list/list-entry/1024502", "start-date": "1985-10-23", "listed-building": "1024502", "name": "OLDBERROW COURT, OUTBUILDING APPROXIMATELY 1 METRE NORTH WEST", "slug": "/listed-building/1024502", "entry-date": "2021-05-28"}}