{"type": "Feature", "geometry": {"type": "Point", "coordinates": [-2.269457, 51.41361]}, "properties": {"name": "GATEPIERS TO ASHLEY MANOR", "documentation-url": "https://historicengland.org.uk/listing/the-list/list-entry/1022718", "listed-building-grade": "II", "start-date": "1985-07-24", "point": "POINT (-2.269457 51.413610)", "listed-building": "1022718", "slug": "/listed-building/1022718", "entry-date": "2021-05-28"}}