{"type": "Feature", "geometry": {"type": "Point", "coordinates": [-1.952532, 51.230476]}, "properties": {"name": "BELL COTTAGE", "listed-building": "1023972", "documentation-url": "https://historicengland.org.uk/listing/the-list/list-entry/1023972", "listed-building-grade": "II", "point": "POINT (-1.952532 51.230476)", "start-date": "1985-07-04", "slug": "/listed-building/1023972", "entry-date": "2021-05-28"}}