{"type": "Feature", "geometry": {"type": "Point", "coordinates": [-1.904903, 51.541714]}, "properties": {"name": "STOCKS BELOW TOWN HALL", "point": "POINT (-1.904903 51.541714)", "start-date": "1985-08-15", "documentation-url": "https://historicengland.org.uk/listing/the-list/list-entry/1022697", "listed-building-grade": "II", "listed-building": "1022697", "slug": "/listed-building/1022697", "entry-date": "2021-05-28"}}