{"type": "Feature", "geometry": {"type": "Point", "coordinates": [-1.545802, 52.009207]}, "properties": {"listed-building": "1024241", "listed-building-grade": "II", "documentation-url": "https://historicengland.org.uk/listing/the-list/list-entry/1024241", "name": "WALL APPROXIMATELY 15 METRES SOUTH OF WHICHFORD", "point": "POINT (-1.545802 52.009207)", "start-date": "1987-04-09", "slug": "/listed-building/1024241", "entry-date": "2021-05-28"}}