{"type": "Feature", "geometry": {"type": "Point", "coordinates": [-0.697688, 51.008747]}, "properties": {"point": "POINT (-0.697688 51.008747)", "documentation-url": "https://historicengland.org.uk/listing/the-list/list-entry/1026051", "name": "GREVATTS", "listed-building": "1026051", "listed-building-grade": "II", "start-date": "1987-11-26", "slug": "/listed-building/1026051", "entry-date": "2021-05-28"}}