{"type": "Feature", "geometry": {"type": "Point", "coordinates": [-1.856665, 51.082264]}, "properties": {"documentation-url": "https://historicengland.org.uk/listing/the-list/list-entry/1023707", "name": "MAGDALENE HOSPITAL", "listed-building-grade": "II", "listed-building": "1023707", "start-date": "1978-06-08", "point": "POINT (-1.856665 51.082264)", "slug": "/listed-building/1023707", "entry-date": "2021-05-28"}}