{"type": "Feature", "geometry": {"type": "Point", "coordinates": [-1.826493, 51.033192]}, "properties": {"point": "POINT (-1.826493 51.033192)", "documentation-url": "https://historicengland.org.uk/listing/the-list/list-entry/1023807", "start-date": "1960-03-23", "listed-building": "1023807", "listed-building-grade": "II*", "name": "CHURCH OF ST MARY THE VIRGIN", "slug": "/listed-building/1023807", "entry-date": "2021-05-28"}}