{"type": "Feature", "geometry": {"type": "Point", "coordinates": [0.728561, 52.249708]}, "properties": {"documentation-url": "https://historicengland.org.uk/listing/the-list/list-entry/1022541", "listed-building-grade": "II", "point": "POINT (0.728561 52.249708)", "start-date": "1972-07-12", "name": "BOUNDARY WALLS TO ST NICHOLAS AND CHAPEL COTTAGE (CHAPEL COTTAGE NOT INCLUDED)", "listed-building": "1022541", "slug": "/listed-building/1022541", "entry-date": "1997-10-30"}}