{"type": "Feature", "geometry": {"type": "Point", "coordinates": [-0.811249, 50.833483]}, "properties": {"documentation-url": "https://historicengland.org.uk/listing/the-list/list-entry/1026734", "listed-building-grade": "II", "point": "POINT (-0.811249 50.833483)", "listed-building": "1026734", "start-date": "1950-07-05", "name": "SALTMILL HOUSE", "slug": "/listed-building/1026734", "entry-date": "2021-05-28"}}