{"type": "Feature", "geometry": {"type": "Point", "coordinates": [0.022361, 51.211012]}, "properties": {"listed-building-grade": "II", "point": "POINT (0.022361 51.211012)", "start-date": "1958-06-11", "listed-building": "1029935", "documentation-url": "https://historicengland.org.uk/listing/the-list/list-entry/1029935", "name": "BOMBERS FARM HOUSE", "slug": "/listed-building/1029935", "entry-date": "2021-05-28"}}