{"type": "Feature", "geometry": {"type": "Point", "coordinates": [-0.263165, 51.231299]}, "properties": {"documentation-url": "https://historicengland.org.uk/listing/the-list/list-entry/1028778", "name": "FRYLEIGH COTTAGES", "point": "POINT (-0.263165 51.231299)", "start-date": "1987-09-29", "listed-building": "1028778", "listed-building-grade": "II", "slug": "/listed-building/1028778", "entry-date": "2021-05-28"}}