{"type": "Feature", "geometry": {"type": "Point", "coordinates": [-2.043916, 51.467466]}, "properties": {"documentation-url": "https://historicengland.org.uk/listing/the-list/list-entry/1022446", "listed-building-grade": "II", "point": "POINT (-2.043916 51.467466)", "start-date": "1987-11-25", "name": "WICK BRIDGE FARMHOUSE", "listed-building": "1022446", "slug": "/listed-building/1022446", "entry-date": "2021-05-28"}}