{"type": "Feature", "geometry": {"type": "Point", "coordinates": [1.350916, 52.260579]}, "properties": {"start-date": "1951-10-25", "listed-building-grade": "II", "documentation-url": "https://historicengland.org.uk/listing/the-list/list-entry/1030819", "name": "JACKSONS FARMHOUSE", "listed-building": "1030819", "point": "POINT (1.350916 52.260579)", "slug": "/listed-building/1030819", "entry-date": "2021-05-28"}}