{"type": "Feature", "geometry": {"type": "Point", "coordinates": [-0.448211, 51.195097]}, "properties": {"point": "POINT (-0.448211 51.195097)", "name": "HAZEL HILL INCLUDING FORMER STABLES TO REAR", "start-date": "1967-06-14", "documentation-url": "https://historicengland.org.uk/listing/the-list/list-entry/1029480", "listed-building-grade": "II", "listed-building": "1029480", "slug": "/listed-building/1029480", "entry-date": "1985-05-21"}}