{"type": "Feature", "geometry": {"type": "Point", "coordinates": [-0.539562, 50.809648]}, "properties": {"listed-building": "1027809", "name": "7 AND 9, CHURCH STREET", "point": "POINT (-0.539562 50.809648)", "listed-building-grade": "II", "start-date": "1949-05-11", "documentation-url": "https://historicengland.org.uk/listing/the-list/list-entry/1027809", "slug": "/listed-building/1027809", "entry-date": "1975-08-27"}}