{"type": "Feature", "geometry": {"type": "Point", "coordinates": [-0.436096, 51.27978]}, "properties": {"documentation-url": "https://historicengland.org.uk/listing/the-list/list-entry/1029418", "start-date": "1985-11-25", "listed-building": "1029418", "point": "POINT (-0.436096 51.279780)", "listed-building-grade": "II", "name": "LITTLE MALT HOUSE MALT HOUSE", "slug": "/listed-building/1029418", "entry-date": "2021-05-28"}}