{"type": "Feature", "geometry": {"type": "Point", "coordinates": [0.089163, 51.081405]}, "properties": {"listed-building-grade": "II", "start-date": "1982-12-31", "name": "MARSH GREEN FARMHOUSE", "point": "POINT (0.089163 51.081405)", "listed-building": "1028294", "documentation-url": "https://historicengland.org.uk/listing/the-list/list-entry/1028294", "slug": "/listed-building/1028294", "entry-date": "2021-05-28"}}