{"type": "Feature", "geometry": {"type": "Point", "coordinates": [-2.196647, 51.460845]}, "properties": {"listed-building-grade": "II", "point": "POINT (-2.196647 51.460845)", "documentation-url": "https://historicengland.org.uk/listing/the-list/list-entry/1022836", "start-date": "1960-12-20", "name": "WILLOW HOUSE WITH GATE PIERS AND WALLS", "listed-building": "1022836", "slug": "/listed-building/1022836", "entry-date": "1985-12-09"}}