{"type": "Feature", "geometry": {"type": "Point", "coordinates": [-1.557773, 52.052844]}, "properties": {"name": "SUNNYVIEW AND COTTAGE TO LEFT", "start-date": "1986-06-30", "point": "POINT (-1.557773 52.052844)", "documentation-url": "https://historicengland.org.uk/listing/the-list/list-entry/1024391", "listed-building-grade": "II", "listed-building": "1024391", "slug": "/listed-building/1024391", "entry-date": "2021-05-28"}}