{"type": "Feature", "geometry": {"type": "Point", "coordinates": [-1.67956, 51.180361]}, "properties": {"listed-building": "1023947", "documentation-url": "https://historicengland.org.uk/listing/the-list/list-entry/1023947", "point": "POINT (-1.679560 51.180361)", "start-date": "1953-01-10", "name": "RANGE OF BARNS NORTH OF THE MANOR HOUSE", "listed-building-grade": "II", "slug": "/listed-building/1023947", "entry-date": "2021-05-28"}}