{"type": "Feature", "geometry": {"type": "Point", "coordinates": [0.476855, 51.196325]}, "properties": {"listed-building-grade": "II", "point": "POINT (0.476855 51.196325)", "documentation-url": "https://historicengland.org.uk/listing/the-list/list-entry/1031338", "name": "BARN ABOUT 15 METRES WEST SOUTH WEST OF NEW LODGE HOUSE", "listed-building": "1031338", "start-date": "1987-03-23", "slug": "/listed-building/1031338", "entry-date": "2021-05-28"}}