{"type": "Feature", "geometry": {"type": "Point", "coordinates": [-1.76141, 52.218895]}, "properties": {"listed-building-grade": "II", "documentation-url": "https://historicengland.org.uk/listing/the-list/list-entry/1024542", "name": "WILMCOTE CHURCH OF ENGLAND JUNIOR AND INFANT SCHOOL", "start-date": "1969-12-11", "point": "POINT (-1.761410 52.218895)", "listed-building": "1024542", "slug": "/listed-building/1024542", "entry-date": "1985-10-23"}}