{"type": "Feature", "geometry": {"type": "Point", "coordinates": [-1.905388, 51.193143]}, "properties": {"documentation-url": "https://historicengland.org.uk/listing/the-list/list-entry/1023959", "name": "CHURCH OF ST MARY", "start-date": "1958-02-18", "point": "POINT (-1.905388 51.193143)", "listed-building": "1023959", "listed-building-grade": "II*", "slug": "/listed-building/1023959", "entry-date": "2021-05-28"}}