{"type": "Feature", "geometry": {"type": "Point", "coordinates": [-1.743585, 50.993802]}, "properties": {"listed-building-grade": "II", "point": "POINT (-1.743585 50.993802)", "start-date": "1985-07-04", "name": "GIBBS MONUMENT IN THE CHURCHYARD ABOUT 6 METRES NORTH OF CHURCH OF ST LAURENCE*", "documentation-url": "https://historicengland.org.uk/listing/the-list/list-entry/1023877", "listed-building": "1023877", "slug": "/listed-building/1023877", "entry-date": "2021-05-28"}}