{"type": "Feature", "geometry": {"type": "Point", "coordinates": [-0.761923, 50.952278]}, "properties": {"start-date": "1987-11-26", "listed-building-grade": "II", "listed-building": "1026061", "documentation-url": "https://historicengland.org.uk/listing/the-list/list-entry/1026061", "point": "POINT (-0.761923 50.952278)", "name": "HORLEY COTTAGE", "slug": "/listed-building/1026061", "entry-date": "2021-05-28"}}