{"type": "Feature", "geometry": {"type": "Point", "coordinates": [-1.696006, 52.089434]}, "properties": {"listed-building": "1024112", "documentation-url": "https://historicengland.org.uk/listing/the-list/list-entry/1024112", "start-date": "1987-05-16", "point": "POINT (-1.696006 52.089434)", "listed-building-grade": "II", "name": "BASSETT COTTAGE", "slug": "/listed-building/1024112", "entry-date": "2021-05-28"}}