{"type": "Feature", "geometry": {"type": "Point", "coordinates": [0.194476, 51.041855]}, "properties": {"documentation-url": "https://historicengland.org.uk/listing/the-list/list-entry/1028152", "point": "POINT (0.194476 51.041855)", "start-date": "1982-12-31", "listed-building-grade": "II", "listed-building": "1028152", "name": "JARVIS BROOK, NORTH WEST GATEWAY TO ROTHERFIELD HALL AND ATTACHED FLANKING WALLS", "slug": "/listed-building/1028152", "entry-date": "1989-05-22"}}