{"type": "Feature", "geometry": {"type": "Point", "coordinates": [-0.852648, 50.92575]}, "properties": {"name": "THE RECTORY", "documentation-url": "https://historicengland.org.uk/listing/the-list/list-entry/1026315", "listed-building-grade": "II", "point": "POINT (-0.852648 50.925750)", "listed-building": "1026315", "start-date": "1986-01-28", "slug": "/listed-building/1026315", "entry-date": "2021-05-28"}}