{"type": "Feature", "geometry": {"type": "Point", "coordinates": [-2.346371, 52.993892]}, "properties": {"name": "MILEPOST AT NGR SJ 7687 4413", "listed-building-grade": "II", "documentation-url": "https://historicengland.org.uk/listing/the-list/list-entry/1027999", "point": "POINT (-2.346371 52.993892)", "start-date": "1985-05-14", "listed-building": "1027999", "slug": "/listed-building/1027999", "entry-date": "2021-05-28"}}