{"type": "Feature", "geometry": {"type": "Point", "coordinates": [-0.604943, 51.353115]}, "properties": {"listed-building": "1030049", "point": "POINT (-0.604943 51.353115)", "name": "FOWLERS WELLS", "start-date": "1973-04-09", "listed-building-grade": "II", "documentation-url": "https://historicengland.org.uk/listing/the-list/list-entry/1030049", "slug": "/listed-building/1030049", "entry-date": "1984-07-19"}}