{"type": "Feature", "geometry": {"type": "Point", "coordinates": [-1.45557, 52.123884]}, "properties": {"start-date": "1952-01-07", "documentation-url": "https://historicengland.org.uk/listing/the-list/list-entry/1024196", "listed-building-grade": "II*", "name": "The Castle Inn", "point": "POINT (-1.455570 52.123884)", "listed-building": "1024196", "slug": "/listed-building/1024196", "entry-date": "1987-04-08"}}