{"type": "Feature", "geometry": {"type": "Point", "coordinates": [1.262568, 52.104312]}, "properties": {"point": "POINT (1.262568 52.104312)", "listed-building": "1030730", "name": "THORPE HALL FARMHOUSE", "start-date": "1966-03-16", "listed-building-grade": "II", "documentation-url": "https://historicengland.org.uk/listing/the-list/list-entry/1030730", "slug": "/listed-building/1030730", "entry-date": "1988-08-31"}}