{"type": "Feature", "geometry": {"type": "Point", "coordinates": [-0.883493, 50.969448]}, "properties": {"point": "POINT (-0.883493 50.969448)", "listed-building-grade": "II", "start-date": "1977-04-06", "listed-building": "1025960", "documentation-url": "https://historicengland.org.uk/listing/the-list/list-entry/1025960", "name": "FFOWLERS BUCKE", "slug": "/listed-building/1025960", "entry-date": "2021-05-28"}}