{"type": "Feature", "geometry": {"type": "Point", "coordinates": [-1.843492, 52.159668]}, "properties": {"listed-building": "1024677", "point": "POINT (-1.843492 52.159668)", "listed-building-grade": "II", "documentation-url": "https://historicengland.org.uk/listing/the-list/list-entry/1024677", "name": "Dovecote approximately 65 metres north of No.25 (The Malt House)", "start-date": "1967-02-01", "slug": "/listed-building/1024677", "entry-date": "2021-05-28"}}