{"type": "Feature", "geometry": {"type": "Point", "coordinates": [-1.865391, 52.209474]}, "properties": {"start-date": "1967-02-01", "name": "THRUSH GREEN COTTAGE", "listed-building": "1024585", "listed-building-grade": "II", "point": "POINT (-1.865391 52.209474)", "documentation-url": "https://historicengland.org.uk/listing/the-list/list-entry/1024585", "slug": "/listed-building/1024585", "entry-date": "2021-05-28"}}