{"type": "Feature", "geometry": {"type": "Point", "coordinates": [-1.887687, 51.663351]}, "properties": {"listed-building-grade": "II", "start-date": "1985-11-01", "point": "POINT (-1.887687 51.663351)", "name": "THE ROUND HOUSE AND LOCK", "documentation-url": "https://historicengland.org.uk/listing/the-list/list-entry/1023127", "listed-building": "1023127", "slug": "/listed-building/1023127", "entry-date": "2021-05-28"}}