{"type": "Feature", "geometry": {"type": "Point", "coordinates": [-1.580191, 51.990243]}, "properties": {"documentation-url": "https://historicengland.org.uk/listing/the-list/list-entry/1024299", "start-date": "1987-04-09", "name": "58 AND 59, BUTLERS ROAD", "listed-building-grade": "II", "point": "POINT (-1.580191 51.990243)", "listed-building": "1024299", "slug": "/listed-building/1024299", "entry-date": "2021-05-28"}}