{"type": "Feature", "geometry": {"type": "Point", "coordinates": [-0.614104, 51.345412]}, "properties": {"point": "POINT (-0.614104 51.345412)", "listed-building": "1030020", "start-date": "1955-02-28", "name": "PENNYPOT COTTAGE", "documentation-url": "https://historicengland.org.uk/listing/the-list/list-entry/1030020", "listed-building-grade": "II", "slug": "/listed-building/1030020", "entry-date": "2021-05-28"}}