{"type": "Feature", "geometry": {"type": "Point", "coordinates": [-0.379368, 51.03669]}, "properties": {"listed-building": "1027050", "name": "SHARPENHURST FARMHOUSE", "documentation-url": "https://historicengland.org.uk/listing/the-list/list-entry/1027050", "start-date": "1959-09-22", "point": "POINT (-0.379368 51.036690)", "listed-building-grade": "II", "slug": "/listed-building/1027050", "entry-date": "2021-05-28"}}