{"type": "Feature", "geometry": {"type": "Point", "coordinates": [-0.389074, 51.071429]}, "properties": {"name": "THEALE FARMHOUSE", "listed-building-grade": "II", "point": "POINT (-0.389074 51.071429)", "start-date": "1980-11-28", "listed-building": "1026939", "documentation-url": "https://historicengland.org.uk/listing/the-list/list-entry/1026939", "slug": "/listed-building/1026939", "entry-date": "2021-05-28"}}