{"type": "Feature", "geometry": {"type": "Point", "coordinates": [0.096197, 50.973148]}, "properties": {"listed-building-grade": "II", "point": "POINT (0.096197 50.973148)", "listed-building": "1028112", "name": "14 AND 16, CHURCH STREET", "documentation-url": "https://historicengland.org.uk/listing/the-list/list-entry/1028112", "start-date": "1982-12-31", "slug": "/listed-building/1028112", "entry-date": "1997-01-23"}}