{"type": "Feature", "geometry": {"type": "Point", "coordinates": [-0.877298, 50.826898]}, "properties": {"start-date": "1958-06-05", "name": "CHIDMERE HOUSE", "point": "POINT (-0.877298 50.826898)", "documentation-url": "https://historicengland.org.uk/listing/the-list/list-entry/1026420", "listed-building": "1026420", "listed-building-grade": "II", "slug": "/listed-building/1026420", "entry-date": "1993-06-30"}}