{"type": "Feature", "geometry": {"type": "Point", "coordinates": [-1.742529, 54.982867]}, "properties": {"documentation-url": "https://historicengland.org.uk/listing/the-list/list-entry/1024979", "name": "WAR MEMORIAL", "listed-building-grade": "II", "point": "POINT (-1.742529 54.982867)", "listed-building": "1024979", "start-date": "1987-03-30", "slug": "/listed-building/1024979", "entry-date": "2021-05-28"}}