{"type": "Feature", "geometry": {"type": "Point", "coordinates": [-1.743585, 50.993831]}, "properties": {"listed-building": "1023878", "point": "POINT (-1.743585 50.993831)", "name": "GIBBS MONUMENT IN THE CHURCHYARD ABOUT 9 METRES NORTH OF CHURCH OF ST LAURENCE", "start-date": "1985-07-04", "documentation-url": "https://historicengland.org.uk/listing/the-list/list-entry/1023878", "listed-building-grade": "II", "slug": "/listed-building/1023878", "entry-date": "2021-05-28"}}