{"type": "Feature", "geometry": {"type": "Point", "coordinates": [-1.620146, 54.970866]}, "properties": {"listed-building": "1024941", "name": "9 AND 10, CHARLOTTE SQUARE", "start-date": "1987-03-30", "listed-building-grade": "II", "point": "POINT (-1.620146 54.970866)", "documentation-url": "https://historicengland.org.uk/listing/the-list/list-entry/1024941", "slug": "/listed-building/1024941", "entry-date": "2021-05-28"}}