{"type": "Feature", "geometry": {"type": "Point", "coordinates": [-0.621321, 50.790817]}, "properties": {"listed-building-grade": "II", "name": "FLINT COTTAGE", "start-date": "1984-09-20", "listed-building": "1027611", "documentation-url": "https://historicengland.org.uk/listing/the-list/list-entry/1027611", "point": "POINT (-0.621321 50.790817)", "slug": "/listed-building/1027611", "entry-date": "2021-05-28"}}