{"type": "Feature", "geometry": {"type": "Point", "coordinates": [-0.779237, 50.835632]}, "properties": {"listed-building-grade": "II", "point": "POINT (-0.779237 50.835632)", "name": "THE WHITE HOUSE", "start-date": "1950-07-05", "listed-building": "1026618", "documentation-url": "https://historicengland.org.uk/listing/the-list/list-entry/1026618", "slug": "/listed-building/1026618", "entry-date": "2021-05-28"}}