{"type": "Feature", "geometry": {"type": "Point", "coordinates": [-1.876584, 52.231485]}, "properties": {"start-date": "1969-12-12", "listed-building-grade": "II", "documentation-url": "https://historicengland.org.uk/listing/the-list/list-entry/1024621", "listed-building": "1024621", "name": "KINGS COUGHTON MILL HOUSE", "point": "POINT (-1.876584 52.231485)", "slug": "/listed-building/1024621", "entry-date": "2021-05-28"}}