{"type": "Feature", "geometry": {"type": "Point", "coordinates": [1.34166, 52.221361]}, "properties": {"documentation-url": "https://historicengland.org.uk/listing/the-list/list-entry/1030378", "name": "ANCIENT HOUSE", "start-date": "1951-10-25", "listed-building-grade": "II*", "listed-building": "1030378", "point": "POINT (1.341660 52.221361)", "slug": "/listed-building/1030378", "entry-date": "1985-12-18"}}