{"type": "Feature", "geometry": {"type": "Point", "coordinates": [1.258849, 52.092777]}, "properties": {"documentation-url": "https://historicengland.org.uk/listing/the-list/list-entry/1030753", "point": "POINT (1.258849 52.092777)", "listed-building-grade": "II", "start-date": "1988-08-31", "name": "THE OLD RECTORY", "listed-building": "1030753", "slug": "/listed-building/1030753", "entry-date": "2021-05-28"}}