{"type": "Feature", "geometry": {"type": "Point", "coordinates": [-0.489761, 50.812547]}, "properties": {"name": "THE PARISH CHURCH OF ST MARY", "listed-building": "1027649", "start-date": "1954-10-12", "documentation-url": "https://historicengland.org.uk/listing/the-list/list-entry/1027649", "point": "POINT (-0.489761 50.812547)", "listed-building-grade": "I", "slug": "/listed-building/1027649", "entry-date": "1984-09-20"}}