{"type": "Feature", "geometry": {"type": "Point", "coordinates": [-0.842874, 50.778288]}, "properties": {"listed-building-grade": "II", "start-date": "1986-01-28", "point": "POINT (-0.842874 50.778288)", "name": "MILL HOUSE", "listed-building": "1026401", "documentation-url": "https://historicengland.org.uk/listing/the-list/list-entry/1026401", "slug": "/listed-building/1026401", "entry-date": "2021-05-28"}}