{"type": "Feature", "geometry": {"type": "Point", "coordinates": [-0.795263, 50.798571]}, "properties": {"start-date": "1986-01-28", "name": "HARDINGS FARMHOUSE", "point": "POINT (-0.795263 50.798571)", "documentation-url": "https://historicengland.org.uk/listing/the-list/list-entry/1026400", "listed-building": "1026400", "listed-building-grade": "II", "slug": "/listed-building/1026400", "entry-date": "2021-05-28"}}