{"type": "Feature", "geometry": {"type": "Point", "coordinates": [-0.528574, 50.844605]}, "properties": {"name": "CROSSBUSH LODGE", "listed-building-grade": "II", "documentation-url": "https://historicengland.org.uk/listing/the-list/list-entry/1027596", "point": "POINT (-0.528574 50.844605)", "listed-building": "1027596", "start-date": "1984-09-20", "slug": "/listed-building/1027596", "entry-date": "2021-05-28"}}