{"type": "Feature", "geometry": {"type": "Point", "coordinates": [-0.440597, 51.265443]}, "properties": {"name": "STABLE BLOCK TO SOUTH EAST OF WEST HORSLEY PLACE", "start-date": "1967-06-14", "documentation-url": "https://historicengland.org.uk/listing/the-list/list-entry/1029322", "point": "POINT (-0.440597 51.265443)", "listed-building-grade": "II", "listed-building": "1029322", "slug": "/listed-building/1029322", "entry-date": "1985-11-25"}}