{"type": "Feature", "geometry": {"type": "Point", "coordinates": [-2.240856, 53.79336]}, "properties": {"name": "BURNLEY COLLEGE ADULT EDUCATION CENTRE", "listed-building-grade": "II", "documentation-url": "https://historicengland.org.uk/listing/the-list/list-entry/1022616", "listed-building": "1022616", "point": "POINT (-2.240856 53.793360)", "start-date": "1977-09-29", "slug": "/listed-building/1022616", "entry-date": "1997-11-19"}}