{"type": "Feature", "geometry": {"type": "Point", "coordinates": [0.035021, 51.240299]}, "properties": {"start-date": "1958-06-11", "documentation-url": "https://historicengland.org.uk/listing/the-list/list-entry/1029762", "name": "TENCHLEYS MANOR", "listed-building": "1029762", "listed-building-grade": "II*", "point": "POINT (0.035021 51.240299)", "slug": "/listed-building/1029762", "entry-date": "2021-05-28"}}