{"type": "Feature", "geometry": {"type": "Point", "coordinates": [1.27993, 52.617234]}, "properties": {"listed-building": "1025110", "documentation-url": "https://historicengland.org.uk/listing/the-list/list-entry/1025110", "listed-building-grade": "II", "start-date": "1972-06-05", "name": "2 AND 2A, FAIRFIELD ROAD", "point": "POINT (1.279930 52.617234)", "slug": "/listed-building/1025110", "entry-date": "2021-05-28"}}