{"type": "Feature", "geometry": {"type": "Point", "coordinates": [-0.89292, 50.877205]}, "properties": {"name": "RACTON CHURCH", "start-date": "1958-06-05", "listed-building": "1026186", "documentation-url": "https://historicengland.org.uk/listing/the-list/list-entry/1026186", "listed-building-grade": "I", "point": "POINT (-0.892920 50.877205)", "slug": "/listed-building/1026186", "entry-date": "2021-05-28"}}