{"type": "Feature", "geometry": {"type": "Point", "coordinates": [-2.183749, 51.434773]}, "properties": {"point": "POINT (-2.183749 51.434773)", "listed-building-grade": "II*", "listed-building": "1022044", "start-date": "1960-12-20", "documentation-url": "https://historicengland.org.uk/listing/the-list/list-entry/1022044", "name": "110 AND 112, HIGH STREET", "slug": "/listed-building/1022044", "entry-date": "1986-08-01"}}