{"type": "Feature", "geometry": {"type": "Point", "coordinates": [-1.622887, 54.982887]}, "properties": {"listed-building-grade": "II", "listed-building": "1024901", "point": "POINT (-1.622887 54.982887)", "documentation-url": "https://historicengland.org.uk/listing/the-list/list-entry/1024901", "start-date": "1987-03-30", "name": "22 AND 23, FRAMLINGTON PLACE", "slug": "/listed-building/1024901", "entry-date": "2021-05-28"}}