{"type": "Feature", "geometry": {"type": "Point", "coordinates": [-0.782369, 50.751934]}, "properties": {"listed-building": "1026298", "start-date": "1986-01-28", "documentation-url": "https://historicengland.org.uk/listing/the-list/list-entry/1026298", "point": "POINT (-0.782369 50.751934)", "name": "MICHAELMAS COTTAGE AND MEADOW COTTAGE", "listed-building-grade": "II", "slug": "/listed-building/1026298", "entry-date": "2021-05-28"}}