{"type": "Feature", "geometry": {"type": "Point", "coordinates": [1.24547, 52.112627]}, "properties": {"start-date": "1988-08-31", "listed-building-grade": "II", "point": "POINT (1.245470 52.112627)", "listed-building": "1030719", "documentation-url": "https://historicengland.org.uk/listing/the-list/list-entry/1030719", "name": "THE GABLES WILLIAM'S STORE", "slug": "/listed-building/1030719", "entry-date": "2021-05-28"}}