{"type": "Feature", "geometry": {"type": "Point", "coordinates": [-2.184357, 51.330323]}, "properties": {"listed-building": "1021778", "point": "POINT (-2.184357 51.330323)", "listed-building-grade": "II", "documentation-url": "https://historicengland.org.uk/listing/the-list/list-entry/1021778", "start-date": "1988-06-14", "name": "Woodcote", "slug": "/listed-building/1021778", "entry-date": "1989-04-27"}}