{"type": "Feature", "geometry": {"type": "Point", "coordinates": [-0.443121, 50.819827]}, "properties": {"documentation-url": "https://historicengland.org.uk/listing/the-list/list-entry/1027653", "name": "CLEMATIS COTTAGE JASMINE COTTAGE", "start-date": "1984-09-20", "point": "POINT (-0.443121 50.819827)", "listed-building": "1027653", "listed-building-grade": "II", "slug": "/listed-building/1027653", "entry-date": "1987-01-21"}}