{"type": "Feature", "geometry": {"type": "Point", "coordinates": [-0.360678, 51.149049]}, "properties": {"listed-building": "1028702", "start-date": "1966-11-11", "listed-building-grade": "II", "documentation-url": "https://historicengland.org.uk/listing/the-list/list-entry/1028702", "name": "THE BAKERY AND POST OFFICE", "point": "POINT (-0.360678 51.149049)", "slug": "/listed-building/1028702", "entry-date": "1987-09-29"}}