{"type": "Feature", "geometry": {"type": "Point", "coordinates": [-1.970871, 51.490525]}, "properties": {"listed-building": "1022498", "start-date": "1987-11-25", "name": "PEAR TREE COTTAGE", "point": "POINT (-1.970871 51.490525)", "listed-building-grade": "II", "documentation-url": "https://historicengland.org.uk/listing/the-list/list-entry/1022498", "slug": "/listed-building/1022498", "entry-date": "2021-05-28"}}