{"type": "Feature", "geometry": {"type": "Point", "coordinates": [-0.842388, 50.781889]}, "properties": {"start-date": "1986-01-28", "listed-building": "1026379", "point": "POINT (-0.842388 50.781889)", "documentation-url": "https://historicengland.org.uk/listing/the-list/list-entry/1026379", "name": "SOMERLEY HOUSE", "listed-building-grade": "II", "slug": "/listed-building/1026379", "entry-date": "2021-05-28"}}