{"type": "Feature", "geometry": {"type": "Point", "coordinates": [-2.21253, 51.432142]}, "properties": {"listed-building": "1021962", "documentation-url": "https://historicengland.org.uk/listing/the-list/list-entry/1021962", "name": "MILESTONE ON SOUTH SIDE OPPOSITE R.N. STORES, COPENACRE", "listed-building-grade": "II", "start-date": "1986-08-01", "point": "POINT (-2.212530 51.432142)", "slug": "/listed-building/1021962", "entry-date": "2021-05-28"}}