{"type": "Feature", "geometry": {"type": "Point", "coordinates": [-2.264312, 51.503816]}, "properties": {"name": "THE GREEN COTTAGE", "start-date": "1985-12-09", "listed-building-grade": "II", "listed-building": "1022966", "documentation-url": "https://historicengland.org.uk/listing/the-list/list-entry/1022966", "point": "POINT (-2.264312 51.503816)", "slug": "/listed-building/1022966", "entry-date": "2021-05-28"}}