{"type": "Feature", "geometry": {"type": "Point", "coordinates": [-1.430065, 50.811624]}, "properties": {"listed-building": "1031137", "start-date": "1997-12-10", "point": "POINT (-1.430065 50.811624)", "name": "SPENCE HOUSE", "listed-building-grade": "II", "documentation-url": "https://historicengland.org.uk/listing/the-list/list-entry/1031137", "slug": "/listed-building/1031137", "entry-date": "2021-05-28"}}