{"type": "Feature", "geometry": {"type": "Point", "coordinates": [-2.186574, 51.332055]}, "properties": {"listed-building-grade": "II", "name": "CHURCH OF ST MICHAEL AND ALL ANGELS", "documentation-url": "https://historicengland.org.uk/listing/the-list/list-entry/1021792", "listed-building": "1021792", "point": "POINT (-2.186574 51.332055)", "start-date": "1962-11-13", "slug": "/listed-building/1021792", "entry-date": "2021-05-28"}}