{"type": "Feature", "geometry": {"type": "Point", "coordinates": [-1.793285, 51.071481]}, "properties": {"documentation-url": "https://historicengland.org.uk/listing/the-list/list-entry/1023534", "listed-building": "1023534", "start-date": "1952-02-28", "listed-building-grade": "II*", "point": "POINT (-1.793285 51.071481)", "name": "FROWDS ALMSHOUSES", "slug": "/listed-building/1023534", "entry-date": "2021-05-28"}}