{"type": "Feature", "geometry": {"type": "Point", "coordinates": [-0.648368, 51.34001]}, "properties": {"name": "BRENTMOOR DENE HOUSE", "listed-building-grade": "II", "documentation-url": "https://historicengland.org.uk/listing/the-list/list-entry/1029994", "listed-building": "1029994", "start-date": "1984-07-19", "point": "POINT (-0.648368 51.340010)", "slug": "/listed-building/1029994", "entry-date": "2021-05-28"}}