{"type": "Feature", "geometry": {"type": "Point", "coordinates": [-0.384118, 51.154496]}, "properties": {"listed-building": "1028815", "start-date": "1987-03-11", "name": "GRANARY AT GOSTERWOOD FARMHOUSE", "listed-building-grade": "II", "documentation-url": "https://historicengland.org.uk/listing/the-list/list-entry/1028815", "point": "POINT (-0.384118 51.154496)", "slug": "/listed-building/1028815", "entry-date": "2021-05-28"}}