{"type": "Feature", "geometry": {"type": "Point", "coordinates": [-0.356644, 51.087965]}, "properties": {"documentation-url": "https://historicengland.org.uk/listing/the-list/list-entry/1026918", "listed-building": "1026918", "start-date": "1980-11-28", "listed-building-grade": "II", "name": "PAN'S GARDEN", "point": "POINT (-0.356644 51.087965)", "slug": "/listed-building/1026918", "entry-date": "1989-08-07"}}