{"type": "Feature", "geometry": {"type": "Point", "coordinates": [-0.202136, 50.996332]}, "properties": {"listed-building": "1025749", "name": "WATERSHIPPE DOWN", "start-date": "1983-05-11", "point": "POINT (-0.202136 50.996332)", "documentation-url": "https://historicengland.org.uk/listing/the-list/list-entry/1025749", "listed-building-grade": "II", "slug": "/listed-building/1025749", "entry-date": "2021-05-28"}}