{"type": "Feature", "geometry": {"type": "Point", "coordinates": [-0.244026, 51.247984]}, "properties": {"point": "POINT (-0.244026 51.247984)", "start-date": "1987-09-29", "listed-building": "1028753", "documentation-url": "https://historicengland.org.uk/listing/the-list/list-entry/1028753", "name": "THE HARVESTERS", "listed-building-grade": "II", "slug": "/listed-building/1028753", "entry-date": "2021-05-28"}}