{"type": "Feature", "geometry": {"type": "Point", "coordinates": [-2.13975, 51.389933]}, "properties": {"point": "POINT (-2.139750 51.389933)", "listed-building-grade": "II", "documentation-url": "https://historicengland.org.uk/listing/the-list/list-entry/1021761", "listed-building": "1021761", "name": "STABLES AT BEECHFIELD HOUSE", "start-date": "1979-06-05", "slug": "/listed-building/1021761", "entry-date": "2021-05-28"}}