{"type": "Feature", "geometry": {"type": "Point", "coordinates": [-1.457647, 52.131093]}, "properties": {"listed-building-grade": "II", "name": "STABLE APPROXIMATELY 7 METRES SOUTH OF LEES HOUSE", "documentation-url": "https://historicengland.org.uk/listing/the-list/list-entry/1024203", "start-date": "1987-04-08", "point": "POINT (-1.457647 52.131093)", "listed-building": "1024203", "slug": "/listed-building/1024203", "entry-date": "2021-05-28"}}