{"type": "Feature", "geometry": {"type": "Point", "coordinates": [-0.554375, 51.219378]}, "properties": {"point": "POINT (-0.554375 51.219378)", "listed-building-grade": "II", "listed-building": "1029313", "documentation-url": "https://historicengland.org.uk/listing/the-list/list-entry/1029313", "start-date": "1953-05-01", "name": "MANOR HOUSE", "slug": "/listed-building/1029313", "entry-date": "2021-05-28"}}