{"type": "Feature", "geometry": {"type": "Point", "coordinates": [-0.031725, 51.179928]}, "properties": {"listed-building-grade": "II", "point": "POINT (-0.031725 51.179928)", "documentation-url": "https://historicengland.org.uk/listing/the-list/list-entry/1029917", "start-date": "1958-06-11", "name": "FORMER GRANARY, NOW COWMANS COTTAGE 15 YARDS SOUTH WEST OF LYNEHOUSE FARM HOUSE", "listed-building": "1029917", "slug": "/listed-building/1029917", "entry-date": "2021-05-28"}}