{"type": "Feature", "geometry": {"type": "Point", "coordinates": [-0.333041, 51.380373]}, "properties": {"listed-building-grade": "II", "start-date": "1982-11-30", "documentation-url": "https://historicengland.org.uk/listing/the-list/list-entry/1030164", "point": "POINT (-0.333041 51.380373)", "listed-building": "1030164", "name": "MANOR FARM HOUSE", "slug": "/listed-building/1030164", "entry-date": "1984-11-16"}}