{"type": "Feature", "geometry": {"type": "Point", "coordinates": [-0.403646, 51.406976]}, "properties": {"documentation-url": "https://historicengland.org.uk/listing/the-list/list-entry/1029681", "point": "POINT (-0.403646 51.406976)", "name": "NELLIE MCQUEENS EATING HOUSE AND POST BOX ATTACHED", "listed-building": "1029681", "listed-building-grade": "II", "start-date": "1987-09-24", "slug": "/listed-building/1029681", "entry-date": "2021-05-28"}}