{"type": "Feature", "geometry": {"type": "Point", "coordinates": [-1.906651, 51.496129]}, "properties": {"documentation-url": "https://historicengland.org.uk/listing/the-list/list-entry/1022653", "start-date": "1955-01-17", "listed-building": "1022653", "listed-building-grade": "II", "point": "POINT (-1.906651 51.496129)", "name": "MERRYTHATCH", "slug": "/listed-building/1022653", "entry-date": "1985-08-15"}}