{"type": "Feature", "geometry": {"type": "Point", "coordinates": [0.225937, 51.016366]}, "properties": {"point": "POINT (0.225937 51.016366)", "listed-building-grade": "II", "listed-building": "1028206", "documentation-url": "https://historicengland.org.uk/listing/the-list/list-entry/1028206", "start-date": "1982-12-31", "name": "BARN TO THE SOUTH EAST OF HORLEIGH GREEN FARMHOUSE", "slug": "/listed-building/1028206", "entry-date": "2021-05-28"}}