{"type": "Feature", "geometry": {"type": "Point", "coordinates": [-1.871013, 52.213508]}, "properties": {"point": "POINT (-1.871013 52.213508)", "start-date": "1967-02-01", "name": "LLOYDS BANK", "listed-building": "1024595", "listed-building-grade": "II", "documentation-url": "https://historicengland.org.uk/listing/the-list/list-entry/1024595", "slug": "/listed-building/1024595", "entry-date": "2021-05-28"}}