{"type": "Feature", "geometry": {"type": "Point", "coordinates": [-1.756973, 51.038212]}, "properties": {"start-date": "1985-03-28", "point": "POINT (-1.756973 51.038212)", "documentation-url": "https://historicengland.org.uk/listing/the-list/list-entry/1023842", "name": "STATUE OF FAME IN CUPOLA, AT SOUTH END OF PARTERRE", "listed-building-grade": "II*", "listed-building": "1023842", "slug": "/listed-building/1023842", "entry-date": "2021-05-28"}}