{"type": "Feature", "geometry": {"type": "Point", "coordinates": [-0.329015, 50.888332]}, "properties": {"listed-building-grade": "II", "start-date": "1980-05-09", "name": "46 48 AND 50, HIGH STREET", "documentation-url": "https://historicengland.org.uk/listing/the-list/list-entry/1027270", "point": "POINT (-0.329015 50.888332)", "listed-building": "1027270", "slug": "/listed-building/1027270", "entry-date": "2021-05-28"}}