{"type": "Feature", "geometry": {"type": "Point", "coordinates": [-0.85823, 50.828565]}, "properties": {"start-date": "1963-04-26", "point": "POINT (-0.858230 50.828565)", "listed-building-grade": "II", "listed-building": "1026458", "documentation-url": "https://historicengland.org.uk/listing/the-list/list-entry/1026458", "name": "THE ANCHOR BLEU INN", "slug": "/listed-building/1026458", "entry-date": "2021-05-28"}}