{"type": "Feature", "geometry": {"type": "Point", "coordinates": [-1.76108, 51.519876]}, "properties": {"listed-building": "1023307", "listed-building-grade": "II*", "name": "BURDEROP PARK", "documentation-url": "https://historicengland.org.uk/listing/the-list/list-entry/1023307", "point": "POINT (-1.761080 51.519876)", "start-date": "1955-01-21", "slug": "/listed-building/1023307", "entry-date": "2021-05-28"}}