{"type": "Feature", "geometry": {"type": "Point", "coordinates": [-0.837503, 50.850169]}, "properties": {"documentation-url": "https://historicengland.org.uk/listing/the-list/list-entry/1026346", "listed-building": "1026346", "listed-building-grade": "II", "name": "THE TWO BARNS ADJOINING THE HOUSE NAMED DOUBLE BARN ON THE NORTH", "point": "POINT (-0.837503 50.850169)", "start-date": "1986-01-28", "slug": "/listed-building/1026346", "entry-date": "2021-05-28"}}