{"type": "Feature", "geometry": {"type": "Point", "coordinates": [-0.35946, 51.299028]}, "properties": {"documentation-url": "https://historicengland.org.uk/listing/the-list/list-entry/1028661", "point": "POINT (-0.359460 51.299028)", "listed-building-grade": "II", "name": "MONKS GREEN FARMHOUSE", "start-date": "1990-08-24", "listed-building": "1028661", "slug": "/listed-building/1028661", "entry-date": "2021-05-28"}}