{"type": "Feature", "geometry": {"type": "Point", "coordinates": [-0.305295, 50.945646]}, "properties": {"start-date": "1959-09-22", "listed-building-grade": "II", "name": "BINES FARMHOUSE", "point": "POINT (-0.305295 50.945646)", "documentation-url": "https://historicengland.org.uk/listing/the-list/list-entry/1026867", "listed-building": "1026867", "slug": "/listed-building/1026867", "entry-date": "2021-05-28"}}