{"type": "Feature", "geometry": {"type": "Point", "coordinates": [0.161531, 51.060447]}, "properties": {"listed-building": "1028443", "name": "THE CROSS HOTEL", "start-date": "1953-11-26", "listed-building-grade": "II", "documentation-url": "https://historicengland.org.uk/listing/the-list/list-entry/1028443", "point": "POINT (0.161531 51.060447)", "slug": "/listed-building/1028443", "entry-date": "2021-05-28"}}