{"type": "Feature", "geometry": {"type": "Point", "coordinates": [-0.016825, 51.200046]}, "properties": {"point": "POINT (-0.016825 51.200046)", "listed-building-grade": "II", "start-date": "1982-03-09", "name": "DOVECOT 25 YARDS NORTH OF CROWHURST PLACE", "listed-building": "1029925", "documentation-url": "https://historicengland.org.uk/listing/the-list/list-entry/1029925", "slug": "/listed-building/1029925", "entry-date": "1984-04-25"}}