{"type": "Feature", "geometry": {"type": "Point", "coordinates": [0.184694, 51.115902]}, "properties": {"documentation-url": "https://historicengland.org.uk/listing/the-list/list-entry/1027983", "point": "POINT (0.184694 51.115902)", "listed-building": "1027983", "listed-building-grade": "II", "start-date": "1984-12-19", "name": "POLLIES HALL", "slug": "/listed-building/1027983", "entry-date": "2021-05-28"}}