{"type": "Feature", "geometry": {"type": "Point", "coordinates": [-1.178809, 52.334657]}, "properties": {"name": "MODEL OF ENTRANCE TO KILSBY TUNNEL APPROXIMATELY 3 METRES SOUTH WEST OF CEDAR LODGE", "start-date": "1987-03-11", "point": "POINT (-1.178809 52.334657)", "listed-building-grade": "II", "documentation-url": "https://historicengland.org.uk/listing/the-list/list-entry/1025850", "listed-building": "1025850", "slug": "/listed-building/1025850", "entry-date": "2021-05-28"}}