{"type": "Feature", "geometry": {"type": "Point", "coordinates": [-0.929047, 50.869902]}, "properties": {"point": "POINT (-0.929047 50.869902)", "listed-building-grade": "II", "listed-building": "1026134", "name": "MONK'S FARMHOUSE", "start-date": "1986-01-28", "documentation-url": "https://historicengland.org.uk/listing/the-list/list-entry/1026134", "slug": "/listed-building/1026134", "entry-date": "2021-05-28"}}