{"type": "Feature", "geometry": {"type": "Point", "coordinates": [-2.610299, 51.455706]}, "properties": {"start-date": "1994-12-30", "listed-building-grade": "II", "documentation-url": "https://historicengland.org.uk/listing/the-list/list-entry/1025021", "point": "POINT (-2.610299 51.455706)", "listed-building": "1025021", "name": "WALLS AND STEPS TO FOOTPATH LEADING TO MERIDIAN VALE", "slug": "/listed-building/1025021", "entry-date": "2021-05-28"}}