{"type": "Feature", "geometry": {"type": "Point", "coordinates": [-1.67315, 54.945606]}, "properties": {"point": "POINT (-1.673150 54.945606)", "listed-building-grade": "II", "documentation-url": "https://historicengland.org.uk/listing/the-list/list-entry/1025148", "name": "K6 TELEPHONE KIOSK ADJACENT TO COUNCIL OFFICES", "listed-building": "1025148", "start-date": "1987-10-19", "slug": "/listed-building/1025148", "entry-date": "2021-05-28"}}