{"type": "Feature", "geometry": {"type": "Point", "coordinates": [1.265613, 52.22048]}, "properties": {"point": "POINT (1.265613 52.220480)", "start-date": "1984-11-19", "listed-building": "1030576", "documentation-url": "https://historicengland.org.uk/listing/the-list/list-entry/1030576", "name": "BUILDING 15 METRES EAST NORTH EAST OF MERLIN HOUSE", "listed-building-grade": "II", "slug": "/listed-building/1030576", "entry-date": "2021-05-28"}}