{"type": "Feature", "geometry": {"type": "Point", "coordinates": [-0.375519, 51.308982]}, "properties": {"point": "POINT (-0.375519 51.308982)", "documentation-url": "https://historicengland.org.uk/listing/the-list/list-entry/1028670", "start-date": "1951-09-07", "listed-building-grade": "I", "name": "SLYFIELD FARMHOUSE, WITH ATTACHED GARDEN WALL", "listed-building": "1028670", "slug": "/listed-building/1028670", "entry-date": "1990-08-24"}}