{"type": "Feature", "geometry": {"type": "Point", "coordinates": [-0.430809, 51.349491]}, "properties": {"listed-building-grade": "II", "documentation-url": "https://historicengland.org.uk/listing/the-list/list-entry/1030152", "name": "82 AND 84, OCTAGON ROAD", "listed-building": "1030152", "point": "POINT (-0.430809 51.349491)", "start-date": "1984-11-16", "slug": "/listed-building/1030152", "entry-date": "2021-05-28"}}