{"type": "Feature", "geometry": {"type": "Point", "coordinates": [-0.85637, 50.829177]}, "properties": {"listed-building": "1026431", "listed-building-grade": "II", "documentation-url": "https://historicengland.org.uk/listing/the-list/list-entry/1026431", "name": "COB COTTAGE", "start-date": "1986-01-28", "point": "POINT (-0.856370 50.829177)", "slug": "/listed-building/1026431", "entry-date": "2021-05-28"}}