{"type": "Feature", "geometry": {"type": "Point", "coordinates": [-0.14311, 51.0049]}, "properties": {"documentation-url": "https://historicengland.org.uk/listing/the-list/list-entry/1025517", "listed-building-grade": "II", "listed-building": "1025517", "start-date": "1987-12-11", "point": "POINT (-0.143110 51.004900)", "name": "MONUMENT TO HENRY BOWLES, 1 METRE EAST OF EAST WINDOW OF CHURCH", "slug": "/listed-building/1025517", "entry-date": "2021-05-28"}}