{"type": "Feature", "geometry": {"type": "Point", "coordinates": [-0.417377, 51.314119]}, "properties": {"listed-building-grade": "II", "listed-building": "1030060", "start-date": "1992-05-07", "name": "Chilbrook Farmhouse", "point": "POINT (-0.417377 51.314119)", "documentation-url": "https://historicengland.org.uk/listing/the-list/list-entry/1030060", "slug": "/listed-building/1030060", "entry-date": "2021-05-28"}}