{"type": "Feature", "geometry": {"type": "Point", "coordinates": [-0.708709, 50.866819]}, "properties": {"point": "POINT (-0.708709 50.866819)", "documentation-url": "https://historicengland.org.uk/listing/the-list/list-entry/1026402", "listed-building": "1026402", "name": "BROADLANDS", "listed-building-grade": "II", "start-date": "1986-01-28", "slug": "/listed-building/1026402", "entry-date": "2021-05-28"}}