{"type": "Feature", "geometry": {"type": "Point", "coordinates": [-0.001237, 51.157378]}, "properties": {"point": "POINT (-0.001237 51.157378)", "documentation-url": "https://historicengland.org.uk/listing/the-list/list-entry/1029878", "name": "NOBLES", "listed-building-grade": "II", "listed-building": "1029878", "start-date": "1988-12-06", "slug": "/listed-building/1029878", "entry-date": "2021-05-28"}}