{"type": "Feature", "geometry": {"type": "Point", "coordinates": [-1.858235, 51.640482]}, "properties": {"listed-building": "1023085", "name": "GROUP OF 3 POULTON MONUMENTS IN CHURCHYARD, 4 METRES SOUTH OF SOUTH TRANCEPT, CHURCH OF ST SAMPSON", "start-date": "1976-11-11", "point": "POINT (-1.858235 51.640482)", "listed-building-grade": "II", "documentation-url": "https://historicengland.org.uk/listing/the-list/list-entry/1023085", "slug": "/listed-building/1023085", "entry-date": "2021-05-28"}}