{"type": "Feature", "geometry": {"type": "Point", "coordinates": [-0.532983, 50.824013]}, "properties": {"documentation-url": "https://historicengland.org.uk/listing/the-list/list-entry/1027798", "listed-building": "1027798", "start-date": "1949-05-11", "name": "TODDINGTON HOUSE STABLES AND BARN GARDEN SHED IMMEDIATELY SOUTH EAST OF HOUSE", "point": "POINT (-0.532983 50.824013)", "listed-building-grade": "II", "slug": "/listed-building/1027798", "entry-date": "1975-08-21"}}