{"type": "Feature", "geometry": {"type": "Point", "coordinates": [-0.293151, 50.941791]}, "properties": {"listed-building": "1027389", "start-date": "1980-05-09", "name": "GREAT BETLEY FARMHOUSE", "listed-building-grade": "II", "point": "POINT (-0.293151 50.941791)", "documentation-url": "https://historicengland.org.uk/listing/the-list/list-entry/1027389", "slug": "/listed-building/1027389", "entry-date": "2021-05-28"}}