{"type": "Feature", "geometry": {"type": "Point", "coordinates": [-0.143781, 51.005039]}, "properties": {"point": "POINT (-0.143781 51.005039)", "listed-building-grade": "II", "documentation-url": "https://historicengland.org.uk/listing/the-list/list-entry/1025518", "start-date": "1987-12-11", "listed-building": "1025518", "name": "LYCHGATE, WALL AND 4 GATE PIERS TO NORTH WEST OF CHURCH", "slug": "/listed-building/1025518", "entry-date": "2021-05-28"}}