{"type": "Feature", "geometry": {"type": "Point", "coordinates": [1.286239, 52.079097]}, "properties": {"listed-building": "1030897", "documentation-url": "https://historicengland.org.uk/listing/the-list/list-entry/1030897", "name": "5 AND 6, THE STREET", "point": "POINT (1.286239 52.079097)", "start-date": "1966-03-16", "listed-building-grade": "II", "slug": "/listed-building/1030897", "entry-date": "1983-07-12"}}