{"type": "Feature", "geometry": {"type": "Point", "coordinates": [-1.519045, 52.073849]}, "properties": {"name": "COMPTON WYNYATES", "listed-building": "1024349", "point": "POINT (-1.519045 52.073849)", "documentation-url": "https://historicengland.org.uk/listing/the-list/list-entry/1024349", "start-date": "1952-09-02", "listed-building-grade": "I", "slug": "/listed-building/1024349", "entry-date": "1986-06-30"}}