{"type": "Feature", "geometry": {"type": "Point", "coordinates": [-1.82712, 51.033328]}, "properties": {"start-date": "1985-03-28", "documentation-url": "https://historicengland.org.uk/listing/the-list/list-entry/1023806", "name": "WESTENDE", "point": "POINT (-1.827120 51.033328)", "listed-building": "1023806", "listed-building-grade": "II", "slug": "/listed-building/1023806", "entry-date": "2021-05-28"}}