{"type": "Feature", "geometry": {"type": "Point", "coordinates": [-0.53069, 50.803902]}, "properties": {"point": "POINT (-0.530690 50.803902)", "start-date": "1949-05-11", "listed-building": "1027786", "listed-building-grade": "II", "documentation-url": "https://historicengland.org.uk/listing/the-list/list-entry/1027786", "name": "5 AND 6, SOUTH TERRACE", "slug": "/listed-building/1027786", "entry-date": "2021-05-28"}}