{"type": "Feature", "geometry": {"type": "Point", "coordinates": [0.872695, 52.36638]}, "properties": {"listed-building-grade": "II", "listed-building": "1031179", "documentation-url": "https://historicengland.org.uk/listing/the-list/list-entry/1031179", "start-date": "1955-07-14", "point": "POINT (0.872695 52.366380)", "name": "THE OLD PARSONAGE", "slug": "/listed-building/1031179", "entry-date": "1985-01-25"}}