{"type": "Feature", "geometry": {"type": "Point", "coordinates": [-1.475895, 54.857227]}, "properties": {"name": "NEWBOTTLE WORKING MEN'S CLUB", "point": "POINT (-1.475895 54.857227)", "start-date": "1950-04-26", "documentation-url": "https://historicengland.org.uk/listing/the-list/list-entry/1025409", "listed-building": "1025409", "listed-building-grade": "II", "slug": "/listed-building/1025409", "entry-date": "1985-07-15"}}