{"type": "Feature", "geometry": {"type": "Point", "coordinates": [-1.742727, 51.040438]}, "properties": {"listed-building": "1023788", "start-date": "1960-03-23", "point": "POINT (-1.742727 51.040438)", "documentation-url": "https://historicengland.org.uk/listing/the-list/list-entry/1023788", "listed-building-grade": "II*", "name": "ALDERBURY HOUSE", "slug": "/listed-building/1023788", "entry-date": "2021-05-28"}}