{"type": "Feature", "geometry": {"type": "Point", "coordinates": [-2.231532, 51.545704]}, "properties": {"listed-building": "1022364", "listed-building-grade": "II", "point": "POINT (-2.231532 51.545704)", "documentation-url": "https://historicengland.org.uk/listing/the-list/list-entry/1022364", "start-date": "1988-02-29", "name": "NEW FARM COTTAGES", "slug": "/listed-building/1022364", "entry-date": "2021-05-28"}}