{"type": "Feature", "geometry": {"type": "Point", "coordinates": [-2.186789, 51.33192]}, "properties": {"start-date": "1988-06-14", "documentation-url": "https://historicengland.org.uk/listing/the-list/list-entry/1021794", "name": "HOOPER MONUMENT IN THE CHURCHYARD ABOUT 7 METRES SOUTH WEST OF TOWER OF CHURCH OF ST MICHAEL AND ALL ANGELS", "point": "POINT (-2.186789 51.331920)", "listed-building": "1021794", "listed-building-grade": "II", "slug": "/listed-building/1021794", "entry-date": "2021-05-28"}}