{"type": "Feature", "geometry": {"type": "Point", "coordinates": [-0.688958, 50.802883]}, "properties": {"start-date": "1977-09-16", "documentation-url": "https://historicengland.org.uk/listing/the-list/list-entry/1027693", "name": "THE MANOR HOUSE", "listed-building": "1027693", "listed-building-grade": "II", "point": "POINT (-0.688958 50.802883)", "slug": "/listed-building/1027693", "entry-date": "2021-05-28"}}