{"type": "Feature", "geometry": {"type": "Point", "coordinates": [-2.237979, 51.4133]}, "properties": {"start-date": "1985-07-24", "documentation-url": "https://historicengland.org.uk/listing/the-list/list-entry/1022779", "listed-building": "1022779", "listed-building-grade": "II", "name": "STABLES AT HAZELBURY MANOR", "point": "POINT (-2.237979 51.413300)", "slug": "/listed-building/1022779", "entry-date": "2021-05-28"}}