{"type": "Feature", "geometry": {"type": "Point", "coordinates": [-0.776453, 50.811388]}, "properties": {"start-date": "1986-01-28", "documentation-url": "https://historicengland.org.uk/listing/the-list/list-entry/1026333", "point": "POINT (-0.776453 50.811388)", "listed-building": "1026333", "listed-building-grade": "II", "name": "THE SPOTTED COW PUBLIC HOUSE", "slug": "/listed-building/1026333", "entry-date": "2021-05-28"}}