{"type": "Feature", "geometry": {"type": "Point", "coordinates": [-0.068129, 51.16405]}, "properties": {"listed-building-grade": "II", "point": "POINT (-0.068129 51.164050)", "start-date": "1984-04-25", "listed-building": "1029941", "name": "LITTLE BROOK FARMHOUSE", "documentation-url": "https://historicengland.org.uk/listing/the-list/list-entry/1029941", "slug": "/listed-building/1029941", "entry-date": "2021-05-28"}}