{"type": "Feature", "geometry": {"type": "Point", "coordinates": [1.269725, 52.222332]}, "properties": {"point": "POINT (1.269725 52.222332)", "documentation-url": "https://historicengland.org.uk/listing/the-list/list-entry/1030579", "listed-building-grade": "II", "name": "NORFOLK HOUSE", "listed-building": "1030579", "start-date": "1984-11-19", "slug": "/listed-building/1030579", "entry-date": "2021-05-28"}}