{"type": "Feature", "geometry": {"type": "Point", "coordinates": [-1.752257, 50.99191]}, "properties": {"start-date": "1960-03-23", "name": "THE COURTHOUSE", "listed-building-grade": "II*", "documentation-url": "https://historicengland.org.uk/listing/the-list/list-entry/1023905", "point": "POINT (-1.752257 50.991910)", "listed-building": "1023905", "slug": "/listed-building/1023905", "entry-date": "1985-07-04"}}