{"type": "Feature", "geometry": {"type": "Point", "coordinates": [-0.429985, 51.350928]}, "properties": {"listed-building-grade": "II", "name": "LAMP POST, 30 YARDS NORTH WEST OF THE MONUMENT", "documentation-url": "https://historicengland.org.uk/listing/the-list/list-entry/1030172", "point": "POINT (-0.429985 51.350928)", "listed-building": "1030172", "start-date": "1984-11-16", "slug": "/listed-building/1030172", "entry-date": "2021-05-28"}}