{"type": "Feature", "geometry": {"type": "Point", "coordinates": [-0.338043, 50.910662]}, "properties": {"start-date": "1980-05-09", "name": "WATER TOWER AND SUN ROOM AT WAPPINGTHORN TO THE NORTH EAST OF THE HOUSE AND TO THE NORTH WEST OF THE FARM BUILDINGS", "documentation-url": "https://historicengland.org.uk/listing/the-list/list-entry/1027254", "point": "POINT (-0.338043 50.910662)", "listed-building-grade": "II", "listed-building": "1027254", "slug": "/listed-building/1027254", "entry-date": "2005-04-21"}}