{"type": "Feature", "geometry": {"type": "Point", "coordinates": [-0.454775, 51.063907]}, "properties": {"point": "POINT (-0.454775 51.063907)", "listed-building": "1027004", "listed-building-grade": "II", "documentation-url": "https://historicengland.org.uk/listing/the-list/list-entry/1027004", "name": "The Blue Ship", "start-date": "1980-11-28", "slug": "/listed-building/1027004", "entry-date": "2020-02-03"}}