{"type": "Feature", "geometry": {"type": "Point", "coordinates": [-0.678262, 50.781575]}, "properties": {"listed-building-grade": "II", "name": "ROSELEIGH", "documentation-url": "https://historicengland.org.uk/listing/the-list/list-entry/1027758", "start-date": "1975-11-07", "point": "POINT (-0.678262 50.781575)", "listed-building": "1027758", "slug": "/listed-building/1027758", "entry-date": "2021-05-28"}}