{"type": "Feature", "geometry": {"type": "Point", "coordinates": [-2.167901, 51.414591]}, "properties": {"point": "POINT (-2.167901 51.414591)", "listed-building-grade": "II", "start-date": "1986-08-01", "name": "OUTBUILDING TO NORTH WEST OF NO 19 (VELLEY COTTAGE)", "listed-building": "1022119", "documentation-url": "https://historicengland.org.uk/listing/the-list/list-entry/1022119", "slug": "/listed-building/1022119", "entry-date": "2021-05-28"}}