{"type": "Feature", "geometry": {"type": "Point", "coordinates": [-2.228153, 51.472772]}, "properties": {"name": "CHURCH FARMHOUSE", "listed-building": "1023012", "documentation-url": "https://historicengland.org.uk/listing/the-list/list-entry/1023012", "point": "POINT (-2.228153 51.472772)", "start-date": "1985-12-09", "listed-building-grade": "II", "slug": "/listed-building/1023012", "entry-date": "2021-05-28"}}