{"type": "Feature", "geometry": {"type": "Point", "coordinates": [-1.757697, 50.992783]}, "properties": {"listed-building": "1023887", "name": "SPRINGFIELD", "point": "POINT (-1.757697 50.992783)", "start-date": "1960-03-23", "documentation-url": "https://historicengland.org.uk/listing/the-list/list-entry/1023887", "listed-building-grade": "II", "slug": "/listed-building/1023887", "entry-date": "1985-07-04"}}