{"type": "Feature", "geometry": {"type": "Point", "coordinates": [0.15161, 50.978456]}, "properties": {"start-date": "1982-12-31", "listed-building-grade": "II", "listed-building": "1028468", "point": "POINT (0.151610 50.978456)", "name": "FIRELOCKS", "documentation-url": "https://historicengland.org.uk/listing/the-list/list-entry/1028468", "slug": "/listed-building/1028468", "entry-date": "2021-05-28"}}