{"type": "Feature", "geometry": {"type": "Point", "coordinates": [-2.0763, 51.52334]}, "properties": {"documentation-url": "https://historicengland.org.uk/listing/the-list/list-entry/1022391", "name": "DOVECOTE AT MANOR FARM", "start-date": "1960-12-20", "listed-building-grade": "II", "listed-building": "1022391", "point": "POINT (-2.076300 51.523340)", "slug": "/listed-building/1022391", "entry-date": "2021-05-28"}}