{"type": "Feature", "geometry": {"type": "Point", "coordinates": [-1.694928, 51.556381]}, "properties": {"start-date": "1979-09-20", "listed-building-grade": "II", "point": "POINT (-1.694928 51.556381)", "documentation-url": "https://historicengland.org.uk/listing/the-list/list-entry/1023423", "name": "THE COTTAGE", "listed-building": "1023423", "slug": "/listed-building/1023423", "entry-date": "2021-05-28"}}