{"type": "Feature", "geometry": {"type": "Point", "coordinates": [1.327814, 52.163232]}, "properties": {"point": "POINT (1.327814 52.163232)", "documentation-url": "https://historicengland.org.uk/listing/the-list/list-entry/1030297", "listed-building": "1030297", "start-date": "1966-03-16", "name": "BARN AT LETHERINGHAM LODGE", "listed-building-grade": "II", "slug": "/listed-building/1030297", "entry-date": "1988-08-15"}}