{"type": "Feature", "geometry": {"type": "Point", "coordinates": [1.376577, 52.18185]}, "properties": {"documentation-url": "https://historicengland.org.uk/listing/the-list/list-entry/1030560", "start-date": "1984-11-19", "point": "POINT (1.376577 52.181850)", "name": "CHERRY TREE HOUSE", "listed-building-grade": "II", "listed-building": "1030560", "slug": "/listed-building/1030560", "entry-date": "2021-05-28"}}