{"type": "Feature", "geometry": {"type": "Point", "coordinates": [-0.660906, 50.91616]}, "properties": {"listed-building": "1026166", "name": "BARN AT CHURCH FARM TO THE NORTH OF THE FARMHOUSE", "documentation-url": "https://historicengland.org.uk/listing/the-list/list-entry/1026166", "point": "POINT (-0.660906 50.916160)", "listed-building-grade": "II", "start-date": "1986-01-28", "slug": "/listed-building/1026166", "entry-date": "2021-05-28"}}