{"type": "Feature", "geometry": {"type": "Point", "coordinates": [-0.473453, 51.2978]}, "properties": {"name": "OCKHAM PARK HOUSE", "listed-building": "1029400", "start-date": "1967-06-14", "documentation-url": "https://historicengland.org.uk/listing/the-list/list-entry/1029400", "listed-building-grade": "II", "point": "POINT (-0.473453 51.297800)", "slug": "/listed-building/1029400", "entry-date": "2021-05-28"}}