{"type": "Feature", "geometry": {"type": "Point", "coordinates": [-0.479428, 51.009105]}, "properties": {"documentation-url": "https://historicengland.org.uk/listing/the-list/list-entry/1027126", "start-date": "1980-11-28", "listed-building": "1027126", "listed-building-grade": "II", "name": "TANNERS COTTAGE", "point": "POINT (-0.479428 51.009105)", "slug": "/listed-building/1027126", "entry-date": "2021-05-28"}}