{"type": "Feature", "geometry": {"type": "Point", "coordinates": [-0.036961, 51.286628]}, "properties": {"listed-building": "1029790", "name": "CHURCH OF ST PAUL", "start-date": "1984-11-19", "listed-building-grade": "II", "point": "POINT (-0.036961 51.286628)", "documentation-url": "https://historicengland.org.uk/listing/the-list/list-entry/1029790", "slug": "/listed-building/1029790", "entry-date": "2021-05-28"}}