{"type": "Feature", "geometry": {"type": "Point", "coordinates": [-1.743177, 51.622151]}, "properties": {"listed-building": "1023406", "documentation-url": "https://historicengland.org.uk/listing/the-list/list-entry/1023406", "listed-building-grade": "II", "start-date": "1979-09-20", "name": "MILESTONE", "point": "POINT (-1.743177 51.622151)", "slug": "/listed-building/1023406", "entry-date": "2021-05-28"}}