{"type": "Feature", "geometry": {"type": "Point", "coordinates": [-0.535063, 50.9095]}, "properties": {"point": "POINT (-0.535063 50.909500)", "start-date": "1955-03-15", "documentation-url": "https://historicengland.org.uk/listing/the-list/list-entry/1027479", "listed-building-grade": "II", "name": "THE THATCHED COTTAGE", "listed-building": "1027479", "slug": "/listed-building/1027479", "entry-date": "2021-05-28"}}