{"type": "Feature", "geometry": {"type": "Point", "coordinates": [-0.661292, 51.199302]}, "properties": {"documentation-url": "https://historicengland.org.uk/listing/the-list/list-entry/1029517", "point": "POINT (-0.661292 51.199302)", "listed-building-grade": "II", "name": "ROKERS", "start-date": "1985-05-21", "listed-building": "1029517", "slug": "/listed-building/1029517", "entry-date": "2021-05-28"}}