{"type": "Feature", "geometry": {"type": "Point", "coordinates": [0.197081, 51.040232]}, "properties": {"start-date": "1989-05-22", "listed-building-grade": "II*", "name": "JARVIS BROOK, SERIES OF 4 BRIDGES OVER STREAM AND INLET TO WEST OF ROTHERFIELD HALL", "documentation-url": "https://historicengland.org.uk/listing/the-list/list-entry/1027954", "listed-building": "1027954", "point": "POINT (0.197081 51.040232)", "slug": "/listed-building/1027954", "entry-date": "2021-05-28"}}