{"type": "Feature", "geometry": {"type": "Point", "coordinates": [0.335154, 51.043886]}, "properties": {"listed-building-grade": "II", "documentation-url": "https://historicengland.org.uk/listing/the-list/list-entry/1028086", "listed-building": "1028086", "point": "POINT (0.335154 51.043886)", "start-date": "1982-12-31", "name": "BOUNDARY WALL TO THE SOUTH EAST OF SCRAG OAK", "slug": "/listed-building/1028086", "entry-date": "2021-05-28"}}