{"type": "Feature", "geometry": {"type": "Point", "coordinates": [0.219086, 51.046076]}, "properties": {"listed-building": "1028161", "name": "CHURCH COTTAGE", "start-date": "1982-12-31", "documentation-url": "https://historicengland.org.uk/listing/the-list/list-entry/1028161", "point": "POINT (0.219086 51.046076)", "listed-building-grade": "II", "slug": "/listed-building/1028161", "entry-date": "2021-05-28"}}