{"type": "Feature", "geometry": {"type": "Point", "coordinates": [-0.453128, 51.388186]}, "properties": {"listed-building": "1029695", "listed-building-grade": "II", "point": "POINT (-0.453128 51.388186)", "start-date": "1982-06-18", "name": "STABLE BLOCK TO THE WEST OF THE MANOR HOUSE", "documentation-url": "https://historicengland.org.uk/listing/the-list/list-entry/1029695", "slug": "/listed-building/1029695", "entry-date": "2021-05-28"}}