{"type": "Feature", "geometry": {"type": "Point", "coordinates": [1.537581, 52.142717]}, "properties": {"start-date": "1984-05-02", "listed-building": "1030856", "documentation-url": "https://historicengland.org.uk/listing/the-list/list-entry/1030856", "listed-building-grade": "II", "point": "POINT (1.537581 52.142717)", "name": "HILL FARMHOUSE", "slug": "/listed-building/1030856", "entry-date": "2021-05-28"}}