{"type": "Feature", "geometry": {"type": "Point", "coordinates": [1.460861, 52.0713]}, "properties": {"start-date": "1966-03-16", "listed-building": "1030738", "listed-building-grade": "II", "name": "CHURCH OF ST ANDREW", "point": "POINT (1.460861 52.071300)", "documentation-url": "https://historicengland.org.uk/listing/the-list/list-entry/1030738", "slug": "/listed-building/1030738", "entry-date": "2021-05-28"}}