{"type": "Feature", "geometry": {"type": "Point", "coordinates": [1.203875, 52.07529]}, "properties": {"start-date": "1991-06-20", "documentation-url": "https://historicengland.org.uk/listing/the-list/list-entry/1030483", "point": "POINT (1.203875 52.075290)", "name": "BARN ABOUT 60 METRES EAST NORTH EAST OF HILL FARM HOUSE", "listed-building": "1030483", "listed-building-grade": "II", "slug": "/listed-building/1030483", "entry-date": "2021-05-28"}}