{"type": "Feature", "geometry": {"type": "Point", "coordinates": [-0.927808, 50.860397]}, "properties": {"name": "THE PARISH CHURCH OF ST JOHN THE BAPTIST", "listed-building-grade": "I", "point": "POINT (-0.927808 50.860397)", "start-date": "1958-06-05", "documentation-url": "https://historicengland.org.uk/listing/the-list/list-entry/1026167", "listed-building": "1026167", "slug": "/listed-building/1026167", "entry-date": "2021-05-28"}}