{"type": "Feature", "geometry": {"type": "Point", "coordinates": [-0.455397, 51.373729]}, "properties": {"start-date": "1951-10-19", "point": "POINT (-0.455397 51.373729)", "listed-building-grade": "II", "name": "YORK COLUMN", "documentation-url": "https://historicengland.org.uk/listing/the-list/list-entry/1030168", "listed-building": "1030168", "slug": "/listed-building/1030168", "entry-date": "1984-11-16"}}