{"type": "Feature", "geometry": {"type": "Point", "coordinates": [-0.767497, 51.334795]}, "properties": {"point": "POINT (-0.767497 51.334795)", "name": "THE TERRACE", "listed-building": "1030040", "listed-building-grade": "II", "start-date": "1984-07-19", "documentation-url": "https://historicengland.org.uk/listing/the-list/list-entry/1030040", "slug": "/listed-building/1030040", "entry-date": "2021-05-28"}}