{"type": "Feature", "geometry": {"type": "Point", "coordinates": [0.784674, 52.368812]}, "properties": {"documentation-url": "https://historicengland.org.uk/listing/the-list/list-entry/1031257", "start-date": "1955-07-14", "listed-building-grade": "II", "name": "BLACKBOURNE (ESTATE OFFICE)", "point": "POINT (0.784674 52.368812)", "listed-building": "1031257", "slug": "/listed-building/1031257", "entry-date": "1984-04-12"}}