{"type": "Feature", "geometry": {"type": "Point", "coordinates": [-2.259017, 51.438873]}, "properties": {"name": "UNIDENTIFIED TOMB IN CHURCHYARD CIRCA 7 METRES SOUTH OF SOUTH PORCH OF CHURCH OF ST JOHN", "point": "POINT (-2.259017 51.438873)", "documentation-url": "https://historicengland.org.uk/listing/the-list/list-entry/1022923", "listed-building": "1022923", "start-date": "1985-12-09", "listed-building-grade": "II", "slug": "/listed-building/1022923", "entry-date": "2021-05-28"}}