{"type": "Feature", "geometry": {"type": "Point", "coordinates": [-0.573074, 51.233789]}, "properties": {"start-date": "1953-05-01", "point": "POINT (-0.573074 51.233789)", "documentation-url": "https://historicengland.org.uk/listing/the-list/list-entry/1029306", "listed-building-grade": "I", "name": "FORMER PRIVATE APARTMENTS AT GUILDFORD CASTLE", "listed-building": "1029306", "slug": "/listed-building/1029306", "entry-date": "1988-03-15"}}