{"type": "Feature", "geometry": {"type": "Point", "coordinates": [0.028773, 51.232133]}, "properties": {"documentation-url": "https://historicengland.org.uk/listing/the-list/list-entry/1029746", "point": "POINT (0.028773 51.232133)", "listed-building": "1029746", "name": "STABLES 20 YARDS SOUTH WEST OF STOCKENDEN", "start-date": "1984-11-19", "listed-building-grade": "II", "slug": "/listed-building/1029746", "entry-date": "2021-05-28"}}