{"type": "Feature", "geometry": {"type": "Point", "coordinates": [0.232434, 51.010045]}, "properties": {"listed-building": "1028208", "listed-building-grade": "II", "point": "POINT (0.232434 51.010045)", "start-date": "1982-12-31", "name": "UPPER CRAB FARMHOUSE", "documentation-url": "https://historicengland.org.uk/listing/the-list/list-entry/1028208", "slug": "/listed-building/1028208", "entry-date": "2021-05-28"}}