{"type": "Feature", "geometry": {"type": "Point", "coordinates": [-2.121572, 51.414936]}, "properties": {"documentation-url": "https://historicengland.org.uk/listing/the-list/list-entry/1022163", "listed-building": "1022163", "start-date": "1960-12-20", "name": "CHAMBERLAIN'S HOUSE", "listed-building-grade": "II", "point": "POINT (-2.121572 51.414936)", "slug": "/listed-building/1022163", "entry-date": "2021-05-28"}}