{"type": "Feature", "geometry": {"type": "Point", "coordinates": [-0.766403, 50.830806]}, "properties": {"listed-building-grade": "II", "start-date": "1950-07-05", "name": "GATES HOUSE", "listed-building": "1026586", "point": "POINT (-0.766403 50.830806)", "documentation-url": "https://historicengland.org.uk/listing/the-list/list-entry/1026586", "slug": "/listed-building/1026586", "entry-date": "2021-05-28"}}