{"type": "Feature", "geometry": {"type": "Point", "coordinates": [1.318882, 52.094461]}, "properties": {"listed-building": "1031019", "documentation-url": "https://historicengland.org.uk/listing/the-list/list-entry/1031019", "name": "CHURCH ROOMS", "start-date": "1971-12-20", "point": "POINT (1.318882 52.094461)", "listed-building-grade": "II", "slug": "/listed-building/1031019", "entry-date": "1972-09-08"}}