{"type": "Feature", "geometry": {"type": "Point", "coordinates": [-0.407958, 50.866063]}, "properties": {"start-date": "1984-09-20", "name": "HOLMCROFT", "listed-building-grade": "II", "point": "POINT (-0.407958 50.866063)", "listed-building": "1027622", "documentation-url": "https://historicengland.org.uk/listing/the-list/list-entry/1027622", "slug": "/listed-building/1027622", "entry-date": "2021-05-28"}}