{"type": "Feature", "geometry": {"type": "Point", "coordinates": [1.403848, 52.151951]}, "properties": {"point": "POINT (1.403848 52.151951)", "documentation-url": "https://historicengland.org.uk/listing/the-list/list-entry/1030827", "name": "THE OLD RECTORY", "start-date": "1984-10-25", "listed-building": "1030827", "listed-building-grade": "II", "slug": "/listed-building/1030827", "entry-date": "2021-05-28"}}