{"type": "Feature", "geometry": {"type": "Point", "coordinates": [-2.415994, 52.917399]}, "properties": {"listed-building-grade": "II", "start-date": "1985-05-14", "name": "Milepost at NGR SJ 72126 35634", "point": "POINT (-2.415994 52.917399)", "listed-building": "1029857", "documentation-url": "https://historicengland.org.uk/listing/the-list/list-entry/1029857", "slug": "/listed-building/1029857", "entry-date": "2021-05-28"}}