{"type": "Feature", "geometry": {"type": "Point", "coordinates": [0.316842, 50.939859]}, "properties": {"point": "POINT (0.316842 50.939859)", "listed-building": "1028537", "start-date": "1981-08-12", "documentation-url": "https://historicengland.org.uk/listing/the-list/list-entry/1028537", "listed-building-grade": "II", "name": "LITTLE STREAM COTTAGE", "slug": "/listed-building/1028537", "entry-date": "2021-05-28"}}