{"type": "Feature", "geometry": {"type": "Point", "coordinates": [0.040369, 51.028343]}, "properties": {"documentation-url": "https://historicengland.org.uk/listing/the-list/list-entry/1028256", "listed-building": "1028256", "listed-building-grade": "II", "start-date": "1982-12-31", "point": "POINT (0.040369 51.028343)", "name": "BARN TO THE NORTH WEST OF HOLE AND ALCHORNE FARMHOUSE", "slug": "/listed-building/1028256", "entry-date": "2021-05-28"}}