{"type": "Feature", "geometry": {"type": "Point", "coordinates": [-0.360882, 51.149637]}, "properties": {"point": "POINT (-0.360882 51.149637)", "name": "VILLAGE PUMP AND COVER", "listed-building": "1028706", "start-date": "1973-07-03", "documentation-url": "https://historicengland.org.uk/listing/the-list/list-entry/1028706", "listed-building-grade": "II", "slug": "/listed-building/1028706", "entry-date": "2021-05-28"}}