{"type": "Feature", "geometry": {"type": "Point", "coordinates": [1.356738, 51.962315]}, "properties": {"documentation-url": "https://historicengland.org.uk/listing/the-list/list-entry/1030404", "point": "POINT (1.356738 51.962315)", "listed-building-grade": "II", "name": "GARDEN WALL ADJOINING HARVEST HOUSE TO NORTH WEST AND WEST", "start-date": "1986-02-10", "listed-building": "1030404", "slug": "/listed-building/1030404", "entry-date": "2021-05-28"}}