{"type": "Feature", "geometry": {"type": "Point", "coordinates": [-0.321906, 50.83795]}, "properties": {"documentation-url": "https://historicengland.org.uk/listing/the-list/list-entry/1027893", "listed-building": "1027893", "name": "FRIAR'S ACRE", "start-date": "1954-10-12", "listed-building-grade": "II", "point": "POINT (-0.321906 50.837950)", "slug": "/listed-building/1027893", "entry-date": "1984-07-27"}}