{"type": "Feature", "geometry": {"type": "Point", "coordinates": [-1.862733, 51.080683]}, "properties": {"documentation-url": "https://historicengland.org.uk/listing/the-list/list-entry/1023732", "listed-building": "1023732", "point": "POINT (-1.862733 51.080683)", "start-date": "1978-06-08", "listed-building-grade": "II", "name": "1 AND 3, RUSSELL STREET", "slug": "/listed-building/1023732", "entry-date": "2021-05-28"}}