{"type": "Feature", "geometry": {"type": "Point", "coordinates": [-0.775333, 50.906799]}, "properties": {"listed-building": "1026086", "listed-building-grade": "II", "name": "PALM HOUSE 50 METRES TO NORTH OF MAIN BUILDING", "documentation-url": "https://historicengland.org.uk/listing/the-list/list-entry/1026086", "point": "POINT (-0.775333 50.906799)", "start-date": "1987-12-18", "slug": "/listed-building/1026086", "entry-date": "2021-05-28"}}