{"type": "Feature", "geometry": {"type": "Point", "coordinates": [-0.531215, 51.255528]}, "properties": {"start-date": "1953-05-01", "name": "TANGLEWOOD", "listed-building": "1029271", "documentation-url": "https://historicengland.org.uk/listing/the-list/list-entry/1029271", "point": "POINT (-0.531215 51.255528)", "listed-building-grade": "II", "slug": "/listed-building/1029271", "entry-date": "2021-05-28"}}