{"type": "Feature", "geometry": {"type": "Point", "coordinates": [-1.400011, 52.148527]}, "properties": {"name": "HEADSTONE APPROXIMATELY 5 METRES SOUTH OF CHANCEL OF CHURCH OF ST JOHN THE BAPTIST", "documentation-url": "https://historicengland.org.uk/listing/the-list/list-entry/1024253", "point": "POINT (-1.400011 52.148527)", "start-date": "1987-04-08", "listed-building": "1024253", "listed-building-grade": "II", "slug": "/listed-building/1024253", "entry-date": "2021-05-28"}}