{"type": "Feature", "geometry": {"type": "Point", "coordinates": [-0.250548, 51.010758]}, "properties": {"documentation-url": "https://historicengland.org.uk/listing/the-list/list-entry/1027090", "name": "GORSE DEAN MILL", "listed-building": "1027090", "start-date": "1959-09-22", "point": "POINT (-0.250548 51.010758)", "listed-building-grade": "II", "slug": "/listed-building/1027090", "entry-date": "1980-11-28"}}