{"type": "Feature", "geometry": {"type": "Point", "coordinates": [-0.605506, 51.215233]}, "properties": {"name": "LOSELEY HOUSE", "listed-building": "1029573", "point": "POINT (-0.605506 51.215233)", "listed-building-grade": "I", "start-date": "1958-02-18", "documentation-url": "https://historicengland.org.uk/listing/the-list/list-entry/1029573", "slug": "/listed-building/1029573", "entry-date": "2021-05-28"}}