{"type": "Feature", "geometry": {"type": "Point", "coordinates": [-0.532476, 51.288411]}, "properties": {"listed-building": "1029341", "point": "POINT (-0.532476 51.288411)", "start-date": "1967-06-14", "name": "WILLINGHAM COTTAGE", "documentation-url": "https://historicengland.org.uk/listing/the-list/list-entry/1029341", "listed-building-grade": "II", "slug": "/listed-building/1029341", "entry-date": "2021-05-28"}}