{"type": "Feature", "geometry": {"type": "Point", "coordinates": [1.224829, 51.299637]}, "properties": {"listed-building": "1025865", "listed-building-grade": "II", "point": "POINT (1.224829 51.299637)", "start-date": "1987-11-26", "documentation-url": "https://historicengland.org.uk/listing/the-list/list-entry/1025865", "name": "GRANARY, ABOUT 20 METRES NORTH WEST OF MOSSEY'S FARM SHOP", "slug": "/listed-building/1025865", "entry-date": "2021-05-28"}}