{"type": "Feature", "geometry": {"type": "Point", "coordinates": [-1.917507, 51.210165]}, "properties": {"listed-building": "1023991", "documentation-url": "https://historicengland.org.uk/listing/the-list/list-entry/1023991", "start-date": "1985-07-04", "listed-building-grade": "II", "name": "THE ROOKERY", "point": "POINT (-1.917507 51.210165)", "slug": "/listed-building/1023991", "entry-date": "2021-05-28"}}