{"type": "Feature", "geometry": {"type": "Point", "coordinates": [-0.884305, 50.968241]}, "properties": {"point": "POINT (-0.884305 50.968241)", "start-date": "1987-11-26", "name": "COBBLERS COTTAGE AND BROOKSIDE", "listed-building": "1025958", "listed-building-grade": "II", "documentation-url": "https://historicengland.org.uk/listing/the-list/list-entry/1025958", "slug": "/listed-building/1025958", "entry-date": "1988-11-01"}}