{"type": "Feature", "geometry": {"type": "Point", "coordinates": [-1.989105, 51.618052]}, "properties": {"documentation-url": "https://historicengland.org.uk/listing/the-list/list-entry/1022260", "listed-building": "1022260", "start-date": "1987-07-16", "listed-building-grade": "II", "point": "POINT (-1.989105 51.618052)", "name": "THE OLD INN", "slug": "/listed-building/1022260", "entry-date": "2021-05-28"}}