{"type": "Feature", "geometry": {"type": "Point", "coordinates": [-0.181545, 50.921931]}, "properties": {"documentation-url": "https://historicengland.org.uk/listing/the-list/list-entry/1025660", "listed-building": "1025660", "name": "RANDOLPH'S FARMHOUSE", "listed-building-grade": "II", "point": "POINT (-0.181545 50.921931)", "start-date": "1957-10-28", "slug": "/listed-building/1025660", "entry-date": "2021-05-28"}}