{"type": "Feature", "geometry": {"type": "Point", "coordinates": [-1.948745, 51.230727]}, "properties": {"start-date": "1985-07-04", "listed-building-grade": "II", "name": "LOWER FARMHOUSE", "listed-building": "1023966", "point": "POINT (-1.948745 51.230727)", "documentation-url": "https://historicengland.org.uk/listing/the-list/list-entry/1023966", "slug": "/listed-building/1023966", "entry-date": "2021-05-28"}}