{"type": "Feature", "geometry": {"type": "Point", "coordinates": [-0.782369, 50.835842]}, "properties": {"start-date": "1950-07-05", "listed-building-grade": "II", "documentation-url": "https://historicengland.org.uk/listing/the-list/list-entry/1026834", "listed-building": "1026834", "point": "POINT (-0.782369 50.835842)", "name": "WALL SEPARATING THE DRIVE FROM THE PALACE GARDENS AND KITCHEN GARDEN", "slug": "/listed-building/1026834", "entry-date": "2021-05-28"}}