{"type": "Feature", "geometry": {"type": "Point", "coordinates": [0.884475, 52.323084]}, "properties": {"listed-building": "1031190", "name": "THE COCK INN", "documentation-url": "https://historicengland.org.uk/listing/the-list/list-entry/1031190", "start-date": "1984-09-27", "listed-building-grade": "II", "point": "POINT (0.884475 52.323084)", "slug": "/listed-building/1031190", "entry-date": "2021-05-28"}}