{"type": "Feature", "geometry": {"type": "Point", "coordinates": [0.224063, 51.099915]}, "properties": {"listed-building": "1028328", "start-date": "1982-12-31", "listed-building-grade": "II", "point": "POINT (0.224063 51.099915)", "documentation-url": "https://historicengland.org.uk/listing/the-list/list-entry/1028328", "name": "THE NEVILL CREST AND GUN HOTEL", "slug": "/listed-building/1028328", "entry-date": "2021-05-28"}}