{"type": "Feature", "geometry": {"type": "Point", "coordinates": [-2.250173, 51.289513]}, "properties": {"point": "POINT (-2.250173 51.289513)", "name": "WHITAKERS FARMHOUSE", "start-date": "1968-09-11", "listed-building": "1021849", "listed-building-grade": "II", "documentation-url": "https://historicengland.org.uk/listing/the-list/list-entry/1021849", "slug": "/listed-building/1021849", "entry-date": "2021-05-28"}}