{"type": "Feature", "geometry": {"type": "Point", "coordinates": [-0.492866, 50.919449]}, "properties": {"documentation-url": "https://historicengland.org.uk/listing/the-list/list-entry/1027358", "start-date": "1955-03-15", "point": "POINT (-0.492866 50.919449)", "name": "THE ORANGERY AT PARHAM PARK TO NORTH OF THE STABLES AND LAUNDRY WING", "listed-building": "1027358", "listed-building-grade": "II", "slug": "/listed-building/1027358", "entry-date": "2021-05-28"}}