{"type": "Feature", "geometry": {"type": "Point", "coordinates": [1.274962, 52.207696]}, "properties": {"point": "POINT (1.274962 52.207696)", "start-date": "1984-11-19", "name": "OAK FARMHOUSE", "listed-building-grade": "II", "documentation-url": "https://historicengland.org.uk/listing/the-list/list-entry/1030572", "listed-building": "1030572", "slug": "/listed-building/1030572", "entry-date": "2021-05-28"}}