{"type": "Feature", "geometry": {"type": "Point", "coordinates": [-0.749388, 51.339792]}, "properties": {"start-date": "1984-07-19", "listed-building": "1030035", "point": "POINT (-0.749388 51.339792)", "documentation-url": "https://historicengland.org.uk/listing/the-list/list-entry/1030035", "name": "LAMP POST 8 YARDS EAST OF WAR MEMORIAL IN THE STAFF COLLEGE - SU 87216082", "listed-building-grade": "II", "slug": "/listed-building/1030035", "entry-date": "1984-09-27"}}