{"type": "Feature", "geometry": {"type": "Point", "coordinates": [-0.373544, 51.278398]}, "properties": {"listed-building": "1028639", "name": "FAIRFIELD HOUSE", "documentation-url": "https://historicengland.org.uk/listing/the-list/list-entry/1028639", "point": "POINT (-0.373544 51.278398)", "listed-building-grade": "II", "start-date": "1951-09-07", "slug": "/listed-building/1028639", "entry-date": "2021-05-28"}}