{"type": "Feature", "geometry": {"type": "Point", "coordinates": [-2.156742, 51.443811]}, "properties": {"listed-building-grade": "II", "point": "POINT (-2.156742 51.443811)", "start-date": "1986-08-01", "documentation-url": "https://historicengland.org.uk/listing/the-list/list-entry/1021971", "listed-building": "1021971", "name": "OLD ROAD COTTAGE", "slug": "/listed-building/1021971", "entry-date": "2021-05-28"}}