{"type": "Feature", "geometry": {"type": "Point", "coordinates": [-1.58254, 51.994303]}, "properties": {"documentation-url": "https://historicengland.org.uk/listing/the-list/list-entry/1024303", "name": "48 AND 49, MAIN STREET", "start-date": "1987-04-09", "listed-building-grade": "II", "listed-building": "1024303", "point": "POINT (-1.582540 51.994303)", "slug": "/listed-building/1024303", "entry-date": "2021-05-28"}}