{"type": "Feature", "geometry": {"type": "Point", "coordinates": [-1.628147, 51.991933]}, "properties": {"point": "POINT (-1.628147 51.991933)", "start-date": "1987-04-09", "documentation-url": "https://historicengland.org.uk/listing/the-list/list-entry/1024308", "name": "SHELTERSHED APPROXIMATELY 30 METRES NORTH EAST OF BARTON HOUSE", "listed-building-grade": "II", "listed-building": "1024308", "slug": "/listed-building/1024308", "entry-date": "2021-05-28"}}