{"type": "Feature", "geometry": {"type": "Point", "coordinates": [-0.20799, 51.038279]}, "properties": {"listed-building-grade": "II*", "point": "POINT (-0.207990 51.038279)", "documentation-url": "https://historicengland.org.uk/listing/the-list/list-entry/1025603", "name": "THE PARISH OF ST MARY", "start-date": "1957-10-28", "listed-building": "1025603", "slug": "/listed-building/1025603", "entry-date": "2021-05-28"}}