{"type": "Feature", "geometry": {"type": "Point", "coordinates": [0.714176, 52.244968]}, "properties": {"listed-building": "1021959", "point": "POINT (0.714176 52.244968)", "documentation-url": "https://historicengland.org.uk/listing/the-list/list-entry/1021959", "start-date": "1972-07-12", "name": "16 AND 16A, ABBEYGATE STREET", "listed-building-grade": "II", "slug": "/listed-building/1021959", "entry-date": "1997-10-30"}}