{"type": "Feature", "geometry": {"type": "Point", "coordinates": [-1.402722, 52.123988]}, "properties": {"listed-building": "1024161", "name": "HEADSTONE APPROXIMATELY 12 METRES SOUTH OF SOUTH EAST CORNER OF CHANCEL OF CHURCH OF ST MICHAEL", "point": "POINT (-1.402722 52.123988)", "start-date": "1987-04-08", "documentation-url": "https://historicengland.org.uk/listing/the-list/list-entry/1024161", "listed-building-grade": "II", "slug": "/listed-building/1024161", "entry-date": "2021-05-28"}}