{"type": "Feature", "geometry": {"type": "Point", "coordinates": [-1.706138, 52.191663]}, "properties": {"listed-building-grade": "II", "listed-building": "1025100", "start-date": "1972-02-09", "point": "POINT (-1.706138 52.191663)", "name": "BANCROFT HOUSE", "documentation-url": "https://historicengland.org.uk/listing/the-list/list-entry/1025100", "slug": "/listed-building/1025100", "entry-date": "2021-05-28"}}