{"type": "Feature", "geometry": {"type": "Point", "coordinates": [-1.940803, 51.648402]}, "properties": {"listed-building": "1023050", "listed-building-grade": "II", "point": "POINT (-1.940803 51.648402)", "name": "BRISTOW MONUMENT IN CHURCHYARD, 7 METRES EAST OF EAST WALL OF NORTH CHAPEL, CHURCH OF THE HOLY CROSS", "documentation-url": "https://historicengland.org.uk/listing/the-list/list-entry/1023050", "start-date": "1986-04-17", "slug": "/listed-building/1023050", "entry-date": "2021-05-28"}}