{"type": "Feature", "geometry": {"type": "Point", "coordinates": [-1.888641, 52.158262]}, "properties": {"point": "POINT (-1.888641 52.158262)", "start-date": "1969-12-11", "name": "CHURCH HOUSE", "documentation-url": "https://historicengland.org.uk/listing/the-list/list-entry/1024650", "listed-building-grade": "II", "listed-building": "1024650", "slug": "/listed-building/1024650", "entry-date": "2021-05-28"}}