{"type": "Feature", "geometry": {"type": "Point", "coordinates": [1.27999, 52.109836]}, "properties": {"listed-building": "1030731", "point": "POINT (1.279990 52.109836)", "listed-building-grade": "II", "documentation-url": "https://historicengland.org.uk/listing/the-list/list-entry/1030731", "name": "GULL FARMHOUSE", "start-date": "1988-08-31", "slug": "/listed-building/1030731", "entry-date": "2021-05-28"}}