{"type": "Feature", "geometry": {"type": "Point", "coordinates": [0.126857, 50.990034]}, "properties": {"listed-building-grade": "II", "start-date": "1982-12-31", "documentation-url": "https://historicengland.org.uk/listing/the-list/list-entry/1028442", "point": "POINT (0.126857 50.990034)", "name": "THE OLD MILL", "listed-building": "1028442", "slug": "/listed-building/1028442", "entry-date": "2021-05-28"}}