{"type": "Feature", "geometry": {"type": "Point", "coordinates": [1.436089, 52.334986]}, "properties": {"listed-building": "1030492", "name": "BUSH HILL FARMHOUSE", "point": "POINT (1.436089 52.334986)", "start-date": "1985-03-19", "documentation-url": "https://historicengland.org.uk/listing/the-list/list-entry/1030492", "listed-building-grade": "II", "slug": "/listed-building/1030492", "entry-date": "2021-05-28"}}