{"type": "Feature", "geometry": {"type": "Point", "coordinates": [-0.413224, 51.188296]}, "properties": {"documentation-url": "https://historicengland.org.uk/listing/the-list/list-entry/1029485", "start-date": "1967-06-14", "point": "POINT (-0.413224 51.188296)", "name": "Church of St Mary", "listed-building-grade": "I", "listed-building": "1029485", "slug": "/listed-building/1029485", "entry-date": "2021-05-28"}}