{"type": "Feature", "geometry": {"type": "Point", "coordinates": [-1.762128, 52.242692]}, "properties": {"start-date": "1985-10-23", "point": "POINT (-1.762128 52.242692)", "listed-building": "1024574", "documentation-url": "https://historicengland.org.uk/listing/the-list/list-entry/1024574", "name": "DRAPER BRIDGE, STRATFORD ON AVON CANAL", "listed-building-grade": "II", "slug": "/listed-building/1024574", "entry-date": "2021-05-28"}}