{"type": "Feature", "geometry": {"type": "Point", "coordinates": [-2.102852, 51.492596]}, "properties": {"listed-building": "1022321", "listed-building-grade": "II*", "start-date": "1960-12-20", "name": "THE GREATHOUSE", "point": "POINT (-2.102852 51.492596)", "documentation-url": "https://historicengland.org.uk/listing/the-list/list-entry/1022321", "slug": "/listed-building/1022321", "entry-date": "2021-05-28"}}