{"type": "Feature", "geometry": {"type": "Point", "coordinates": [-2.184747, 51.43397]}, "properties": {"listed-building-grade": "II", "listed-building": "1022051", "start-date": "1960-12-20", "point": "POINT (-2.184747 51.433970)", "name": "THE PACKHORSE INN", "documentation-url": "https://historicengland.org.uk/listing/the-list/list-entry/1022051", "slug": "/listed-building/1022051", "entry-date": "2021-05-28"}}