{"type": "Feature", "geometry": {"type": "Point", "coordinates": [0.213525, 51.082947]}, "properties": {"listed-building": "1028173", "name": "DAIRY HOUSE AT HAMSELL MANOR", "documentation-url": "https://historicengland.org.uk/listing/the-list/list-entry/1028173", "listed-building-grade": "II", "point": "POINT (0.213525 51.082947)", "start-date": "1982-02-18", "slug": "/listed-building/1028173", "entry-date": "2021-05-28"}}