{"type": "Feature", "geometry": {"type": "Point", "coordinates": [0.269701, 51.09643]}, "properties": {"start-date": "1973-04-18", "name": "GREENWOOD LODGE", "documentation-url": "https://historicengland.org.uk/listing/the-list/list-entry/1028346", "point": "POINT (0.269701 51.096430)", "listed-building": "1028346", "listed-building-grade": "II", "slug": "/listed-building/1028346", "entry-date": "1982-12-31"}}