{"type": "Feature", "geometry": {"type": "Point", "coordinates": [-0.30015, 51.307858]}, "properties": {"listed-building": "1028658", "start-date": "1973-11-23", "name": "FORGE COTTAGE WISTARIA COTTAGE", "point": "POINT (-0.300150 51.307858)", "listed-building-grade": "II", "documentation-url": "https://historicengland.org.uk/listing/the-list/list-entry/1028658", "slug": "/listed-building/1028658", "entry-date": "2021-05-28"}}