{"type": "Feature", "geometry": {"type": "Point", "coordinates": [-1.868489, 52.215834]}, "properties": {"documentation-url": "https://historicengland.org.uk/listing/the-list/list-entry/1024606", "start-date": "1956-02-10", "name": "TOWN HALL", "point": "POINT (-1.868489 52.215834)", "listed-building-grade": "I", "listed-building": "1024606", "slug": "/listed-building/1024606", "entry-date": "2021-05-28"}}