{"type": "Feature", "geometry": {"type": "Point", "coordinates": [-1.864085, 51.544674]}, "properties": {"name": "MILESTONE NEAR SPITTLEBOROUGH FARM, AT NGR SU 095828", "point": "POINT (-1.864085 51.544674)", "documentation-url": "https://historicengland.org.uk/listing/the-list/list-entry/1022661", "listed-building": "1022661", "listed-building-grade": "II", "start-date": "1985-08-15", "slug": "/listed-building/1022661", "entry-date": "2021-05-28"}}