{"type": "Feature", "geometry": {"type": "Point", "coordinates": [-0.866669, 50.806112]}, "properties": {"listed-building": "1026104", "listed-building-grade": "II", "start-date": "1986-01-28", "name": "RICHMOND COTTAGE THE BOLLARD", "point": "POINT (-0.866669 50.806112)", "documentation-url": "https://historicengland.org.uk/listing/the-list/list-entry/1026104", "slug": "/listed-building/1026104", "entry-date": "2021-05-28"}}