{"type": "Feature", "geometry": {"type": "Point", "coordinates": [-2.199442, 51.495393]}, "properties": {"listed-building": "1023019", "name": "BROOMS FARMHOUSE", "point": "POINT (-2.199442 51.495393)", "start-date": "1985-12-09", "listed-building-grade": "II", "documentation-url": "https://historicengland.org.uk/listing/the-list/list-entry/1023019", "slug": "/listed-building/1023019", "entry-date": "2021-05-28"}}