{"type": "Feature", "geometry": {"type": "Point", "coordinates": [-0.493097, 51.376828]}, "properties": {"name": "THE GEORGE INN", "documentation-url": "https://historicengland.org.uk/listing/the-list/list-entry/1029175", "listed-building-grade": "II", "start-date": "1951-09-26", "point": "POINT (-0.493097 51.376828)", "listed-building": "1029175", "slug": "/listed-building/1029175", "entry-date": "2021-05-28"}}