{"type": "Feature", "geometry": {"type": "Point", "coordinates": [-2.670603, 53.770119]}, "properties": {"documentation-url": "https://historicengland.org.uk/listing/the-list/list-entry/1025276", "start-date": "1991-12-20", "listed-building": "1025276", "point": "POINT (-2.670603 53.770119)", "listed-building-grade": "II", "name": "CROSS ON SOUTH SIDE OF JUNCTION WITH RIBBLETON AVENUE", "slug": "/listed-building/1025276", "entry-date": "2021-05-28"}}