{"type": "Feature", "geometry": {"type": "Point", "coordinates": [0.030691, 50.990272]}, "properties": {"name": "NORTH CARVERS SOUTH CARVERS", "point": "POINT (0.030691 50.990272)", "start-date": "1953-11-26", "listed-building": "1028413", "listed-building-grade": "II", "documentation-url": "https://historicengland.org.uk/listing/the-list/list-entry/1028413", "slug": "/listed-building/1028413", "entry-date": "2021-05-28"}}