{"type": "Feature", "geometry": {"type": "Point", "coordinates": [0.337654, 51.062921]}, "properties": {"point": "POINT (0.337654 51.062921)", "listed-building-grade": "II", "listed-building": "1028069", "start-date": "1982-12-31", "documentation-url": "https://historicengland.org.uk/listing/the-list/list-entry/1028069", "name": "HILL VIEW WITH THE GARAGE AND WORKSHOP ADJOINING TO THE NORTH WEST PUMP COTTAGE THE COTTAGE", "slug": "/listed-building/1028069", "entry-date": "2021-05-28"}}