{"type": "Feature", "geometry": {"type": "Point", "coordinates": [-0.402616, 51.156911]}, "properties": {"documentation-url": "https://historicengland.org.uk/listing/the-list/list-entry/1028845", "point": "POINT (-0.402616 51.156911)", "listed-building": "1028845", "listed-building-grade": "II", "name": "BARN TO REAR OF WATERLAND FARM HOUSE", "start-date": "1987-03-11", "slug": "/listed-building/1028845", "entry-date": "2021-05-28"}}