{"type": "Feature", "geometry": {"type": "Point", "coordinates": [-0.585146, 51.227821]}, "properties": {"point": "POINT (-0.585146 51.227821)", "documentation-url": "https://historicengland.org.uk/listing/the-list/list-entry/1029317", "start-date": "1972-01-13", "name": "LITTLECROFT", "listed-building-grade": "II", "listed-building": "1029317", "slug": "/listed-building/1029317", "entry-date": "2021-05-28"}}