{"type": "Feature", "geometry": {"type": "Point", "coordinates": [-0.503776, 51.251439]}, "properties": {"point": "POINT (-0.503776 51.251439)", "listed-building": "1029354", "listed-building-grade": "II", "documentation-url": "https://historicengland.org.uk/listing/the-list/list-entry/1029354", "name": "STRANGEWAYS", "start-date": "1976-03-10", "slug": "/listed-building/1029354", "entry-date": "2021-05-28"}}