{"type": "Feature", "geometry": {"type": "Point", "coordinates": [-0.729316, 51.062547]}, "properties": {"start-date": "1987-11-26", "listed-building": "1026000", "name": "BARN TO NORTH OF MOSES HILL FARM", "listed-building-grade": "II", "documentation-url": "https://historicengland.org.uk/listing/the-list/list-entry/1026000", "point": "POINT (-0.729316 51.062547)", "slug": "/listed-building/1026000", "entry-date": "2021-05-28"}}