{"type": "Feature", "geometry": {"type": "Point", "coordinates": [-0.456111, 51.373855]}, "properties": {"listed-building-grade": "II", "listed-building": "1030169", "point": "POINT (-0.456111 51.373855)", "name": "THE SHIP HOTEL", "documentation-url": "https://historicengland.org.uk/listing/the-list/list-entry/1030169", "start-date": "1951-10-19", "slug": "/listed-building/1030169", "entry-date": "2021-05-28"}}