{"type": "Feature", "geometry": {"type": "Point", "coordinates": [-0.532479, 51.40819]}, "properties": {"point": "POINT (-0.532479 51.408190)", "name": "SHEILA COTTAGE", "documentation-url": "https://historicengland.org.uk/listing/the-list/list-entry/1028938", "listed-building-grade": "II", "start-date": "1986-11-17", "listed-building": "1028938", "slug": "/listed-building/1028938", "entry-date": "2021-05-28"}}