{"type": "Feature", "geometry": {"type": "Point", "coordinates": [-0.025643, 51.205716]}, "properties": {"listed-building": "1029967", "listed-building-grade": "II", "documentation-url": "https://historicengland.org.uk/listing/the-list/list-entry/1029967", "start-date": "1984-04-25", "point": "POINT (-0.025643 51.205716)", "name": "STOCKS FARM HOUSE", "slug": "/listed-building/1029967", "entry-date": "2021-05-28"}}