{"type": "Feature", "geometry": {"type": "Point", "coordinates": [0.745787, 52.378236]}, "properties": {"start-date": "1984-04-12", "point": "POINT (0.745787 52.378236)", "documentation-url": "https://historicengland.org.uk/listing/the-list/list-entry/1031283", "listed-building": "1031283", "name": "WALNUT TREE COTTAGE", "listed-building-grade": "II", "slug": "/listed-building/1031283", "entry-date": "2021-05-28"}}