{"type": "Feature", "geometry": {"type": "Point", "coordinates": [-1.966927, 51.50758]}, "properties": {"listed-building": "1022671", "name": "CHURCH OF ST MICHAEL AND ALL ANGELS AND RAF CHAPEL", "point": "POINT (-1.966927 51.507580)", "listed-building-grade": "II", "start-date": "1955-01-17", "documentation-url": "https://historicengland.org.uk/listing/the-list/list-entry/1022671", "slug": "/listed-building/1022671", "entry-date": "2021-05-28"}}