{"type": "Feature", "geometry": {"type": "Point", "coordinates": [-0.359744, 51.070967]}, "properties": {"start-date": "1980-11-28", "point": "POINT (-0.359744 51.070967)", "name": "OLD POST COTTAGES", "listed-building": "1027054", "listed-building-grade": "II", "documentation-url": "https://historicengland.org.uk/listing/the-list/list-entry/1027054", "slug": "/listed-building/1027054", "entry-date": "2021-05-28"}}