{"type": "Feature", "geometry": {"type": "Point", "coordinates": [-0.014392, 51.175695]}, "properties": {"name": "THE BARN", "listed-building": "1029912", "listed-building-grade": "II", "documentation-url": "https://historicengland.org.uk/listing/the-list/list-entry/1029912", "point": "POINT (-0.014392 51.175695)", "start-date": "1984-04-25", "slug": "/listed-building/1029912", "entry-date": "2021-05-28"}}