{"type": "Feature", "geometry": {"type": "Point", "coordinates": [-0.267216, 51.025971]}, "properties": {"listed-building": "1027009", "name": "OLD CHURCH HOUSE THE GLEBE", "documentation-url": "https://historicengland.org.uk/listing/the-list/list-entry/1027009", "point": "POINT (-0.267216 51.025971)", "listed-building-grade": "II", "start-date": "1980-11-28", "slug": "/listed-building/1027009", "entry-date": "2021-05-28"}}