{"type": "Feature", "geometry": {"type": "Point", "coordinates": [-0.304791, 51.00877]}, "properties": {"name": "YEW COTTAGE", "listed-building-grade": "II", "start-date": "1980-11-28", "listed-building": "1027022", "point": "POINT (-0.304791 51.008770)", "documentation-url": "https://historicengland.org.uk/listing/the-list/list-entry/1027022", "slug": "/listed-building/1027022", "entry-date": "2021-05-28"}}