{"type": "Feature", "geometry": {"type": "Point", "coordinates": [-0.552182, 50.988068]}, "properties": {"start-date": "1985-05-22", "listed-building": "1026517", "listed-building-grade": "II", "documentation-url": "https://historicengland.org.uk/listing/the-list/list-entry/1026517", "point": "POINT (-0.552182 50.988068)", "name": "MANOR COTTAGE", "slug": "/listed-building/1026517", "entry-date": "2021-05-28"}}