{"type": "Feature", "geometry": {"type": "Point", "coordinates": [0.005304, 51.089853]}, "properties": {"start-date": "1953-11-26", "documentation-url": "https://historicengland.org.uk/listing/the-list/list-entry/1028403", "listed-building-grade": "II", "name": "MUDBROOKS HOUSE", "listed-building": "1028403", "point": "POINT (0.005304 51.089853)", "slug": "/listed-building/1028403", "entry-date": "1982-12-31"}}