{"type": "Feature", "geometry": {"type": "Point", "coordinates": [-0.427707, 51.350331]}, "properties": {"start-date": "1984-11-16", "point": "POINT (-0.427707 51.350331)", "documentation-url": "https://historicengland.org.uk/listing/the-list/list-entry/1030147", "listed-building-grade": "II", "name": "LAMP POST OPPOSITE NUMBER 40", "listed-building": "1030147", "slug": "/listed-building/1030147", "entry-date": "2021-05-28"}}