{"type": "Feature", "geometry": {"type": "Point", "coordinates": [0.225375, 51.12277]}, "properties": {"start-date": "1982-12-31", "listed-building": "1028345", "point": "POINT (0.225375 51.122770)", "listed-building-grade": "II", "documentation-url": "https://historicengland.org.uk/listing/the-list/list-entry/1028345", "name": "HIGH ROCKS INN", "slug": "/listed-building/1028345", "entry-date": "2021-05-28"}}