{"type": "Feature", "geometry": {"type": "Point", "coordinates": [-0.148686, 51.003415]}, "properties": {"listed-building-grade": "II", "start-date": "1987-12-11", "documentation-url": "https://historicengland.org.uk/listing/the-list/list-entry/1025543", "point": "POINT (-0.148686 51.003415)", "name": "LODGE TO CUCKFIELD PARK", "listed-building": "1025543", "slug": "/listed-building/1025543", "entry-date": "2021-05-28"}}