{"type": "Feature", "geometry": {"type": "Point", "coordinates": [-0.199304, 50.932575]}, "properties": {"start-date": "1983-05-11", "name": "TIPNOAKS", "documentation-url": "https://historicengland.org.uk/listing/the-list/list-entry/1025644", "listed-building": "1025644", "listed-building-grade": "II", "point": "POINT (-0.199304 50.932575)", "slug": "/listed-building/1025644", "entry-date": "2021-05-28"}}