{"type": "Feature", "geometry": {"type": "Point", "coordinates": [-2.165674, 51.498395]}, "properties": {"start-date": "1988-02-29", "documentation-url": "https://historicengland.org.uk/listing/the-list/list-entry/1022326", "name": "BARN AT MANOR FARM", "listed-building": "1022326", "point": "POINT (-2.165674 51.498395)", "listed-building-grade": "II", "slug": "/listed-building/1022326", "entry-date": "2021-05-28"}}