{"type": "Feature", "geometry": {"type": "Point", "coordinates": [0.201119, 51.003692]}, "properties": {"listed-building": "1028321", "start-date": "1982-12-31", "name": "LITTLE BROADREED FARMHOUSE", "point": "POINT (0.201119 51.003692)", "listed-building-grade": "II", "documentation-url": "https://historicengland.org.uk/listing/the-list/list-entry/1028321", "slug": "/listed-building/1028321", "entry-date": "2021-05-28"}}