{"type": "Feature", "geometry": {"type": "Point", "coordinates": [-2.240016, 53.792382]}, "properties": {"start-date": "1977-09-29", "name": "CHAFFER MONUMENT APPROXIMATELY 12 METRES SOUTH OF CHURCH OF ST PETER", "point": "POINT (-2.240016 53.792382)", "listed-building-grade": "II", "documentation-url": "https://historicengland.org.uk/listing/the-list/list-entry/1022643", "listed-building": "1022643", "slug": "/listed-building/1022643", "entry-date": "1997-11-19"}}