{"type": "Feature", "geometry": {"type": "Point", "coordinates": [-0.228677, 51.288319]}, "properties": {"listed-building": "1029053", "documentation-url": "https://historicengland.org.uk/listing/the-list/list-entry/1029053", "listed-building-grade": "II", "name": "HUNTERS HALL", "point": "POINT (-0.228677 51.288319)", "start-date": "1983-09-29", "slug": "/listed-building/1029053", "entry-date": "2021-05-28"}}