{"type": "Feature", "geometry": {"type": "Point", "coordinates": [-0.532605, 50.934739]}, "properties": {"listed-building": "1027353", "name": "BRIDGE COTTAGES", "listed-building-grade": "II", "documentation-url": "https://historicengland.org.uk/listing/the-list/list-entry/1027353", "start-date": "1980-05-09", "point": "POINT (-0.532605 50.934739)", "slug": "/listed-building/1027353", "entry-date": "2021-05-28"}}