{"type": "Feature", "geometry": {"type": "Point", "coordinates": [-1.864521, 51.079588]}, "properties": {"name": "20 AND 24, SOUTH STREET", "listed-building-grade": "II", "documentation-url": "https://historicengland.org.uk/listing/the-list/list-entry/1023743", "point": "POINT (-1.864521 51.079588)", "listed-building": "1023743", "start-date": "1978-06-08", "slug": "/listed-building/1023743", "entry-date": "2021-05-28"}}