{"type": "Feature", "geometry": {"type": "Point", "coordinates": [-1.547479, 55.034599]}, "properties": {"name": "EAST HOUSE FARMHOUSE", "listed-building": "1025386", "start-date": "1977-10-07", "point": "POINT (-1.547479 55.034599)", "listed-building-grade": "II", "documentation-url": "https://historicengland.org.uk/listing/the-list/list-entry/1025386", "slug": "/listed-building/1025386", "entry-date": "2021-05-28"}}