{"type": "Feature", "geometry": {"type": "Point", "coordinates": [1.197944, 52.090723]}, "properties": {"documentation-url": "https://historicengland.org.uk/listing/the-list/list-entry/1030516", "name": "CHURCH OF ST MARTIN", "listed-building-grade": "I", "start-date": "1966-03-16", "listed-building": "1030516", "point": "POINT (1.197944 52.090723)", "slug": "/listed-building/1030516", "entry-date": "2021-05-28"}}