{"type": "Feature", "geometry": {"type": "Point", "coordinates": [-0.07778, 51.016038]}, "properties": {"listed-building-grade": "II", "listed-building": "1025433", "point": "POINT (-0.077780 51.016038)", "name": "DONKEY WHEEL SITUATED APPROXIMATELY 60 METRES TO SOUTH OF OLD PLACE", "documentation-url": "https://historicengland.org.uk/listing/the-list/list-entry/1025433", "start-date": "1987-12-11", "slug": "/listed-building/1025433", "entry-date": "2021-05-28"}}