{"type": "Feature", "geometry": {"type": "Point", "coordinates": [0.037253, 50.997262]}, "properties": {"start-date": "1982-12-31", "point": "POINT (0.037253 50.997262)", "name": "KNABBS FARMHOUSE", "documentation-url": "https://historicengland.org.uk/listing/the-list/list-entry/1028428", "listed-building-grade": "II", "listed-building": "1028428", "slug": "/listed-building/1028428", "entry-date": "2021-05-28"}}