{"type": "Feature", "geometry": {"type": "Point", "coordinates": [-0.422185, 51.3886]}, "properties": {"name": "OLD MANOR HOUSE", "point": "POINT (-0.422185 51.388600)", "listed-building": "1030163", "start-date": "1951-10-19", "listed-building-grade": "I", "documentation-url": "https://historicengland.org.uk/listing/the-list/list-entry/1030163", "slug": "/listed-building/1030163", "entry-date": "2021-05-28"}}