{"type": "Feature", "geometry": {"type": "Point", "coordinates": [1.287645, 52.195112]}, "properties": {"listed-building-grade": "I", "point": "POINT (1.287645 52.195112)", "listed-building": "1030603", "documentation-url": "https://historicengland.org.uk/listing/the-list/list-entry/1030603", "name": "CHURCH OF ALL SAINTS", "start-date": "1966-12-07", "slug": "/listed-building/1030603", "entry-date": "2021-05-28"}}