{"type": "Feature", "geometry": {"type": "Point", "coordinates": [-1.712058, 54.933617]}, "properties": {"point": "POINT (-1.712058 54.933617)", "listed-building": "1025137", "documentation-url": "https://historicengland.org.uk/listing/the-list/list-entry/1025137", "listed-building-grade": "I", "name": "OLD HOLLINSIDE", "start-date": "1950-02-01", "slug": "/listed-building/1025137", "entry-date": "1985-11-18"}}