{"type": "Feature", "geometry": {"type": "Point", "coordinates": [-1.791238, 51.071702]}, "properties": {"point": "POINT (-1.791238 51.071702)", "listed-building": "1023541", "documentation-url": "https://historicengland.org.uk/listing/the-list/list-entry/1023541", "name": "CROFT HOUSE", "listed-building-grade": "II", "start-date": "1952-02-28", "slug": "/listed-building/1023541", "entry-date": "2021-05-28"}}