{"type": "Feature", "geometry": {"type": "Point", "coordinates": [-0.143498, 51.004619]}, "properties": {"name": "MONUMENT TO PETER BECKLEY APPROXIMATELY 3 METRES SOUTH OF ITEM 8/22", "listed-building": "1025510", "listed-building-grade": "II", "start-date": "1987-12-11", "point": "POINT (-0.143498 51.004619)", "documentation-url": "https://historicengland.org.uk/listing/the-list/list-entry/1025510", "slug": "/listed-building/1025510", "entry-date": "2021-05-28"}}