{"type": "Feature", "geometry": {"type": "Point", "coordinates": [-2.203408, 51.353958]}, "properties": {"listed-building": "1021801", "listed-building-grade": "II", "name": "ELM COTTAGE", "start-date": "1988-06-14", "documentation-url": "https://historicengland.org.uk/listing/the-list/list-entry/1021801", "point": "POINT (-2.203408 51.353958)", "slug": "/listed-building/1021801", "entry-date": "2021-05-28"}}