{"type": "Feature", "geometry": {"type": "Point", "coordinates": [-0.216694, 51.28373]}, "properties": {"point": "POINT (-0.216694 51.283730)", "start-date": "1989-01-27", "name": "KINGSWOOD COURT", "documentation-url": "https://historicengland.org.uk/listing/the-list/list-entry/1029015", "listed-building": "1029015", "listed-building-grade": "II", "slug": "/listed-building/1029015", "entry-date": "2021-05-28"}}