{"type": "Feature", "geometry": {"type": "Point", "coordinates": [-0.038245, 50.998806]}, "properties": {"documentation-url": "https://historicengland.org.uk/listing/the-list/list-entry/1025627", "name": "BARN AT VIEWLANDS FARM TO THE NORTH OF THE HOUSE KNOWN AS VIEWLANDS", "listed-building-grade": "II", "point": "POINT (-0.038245 50.998806)", "listed-building": "1025627", "start-date": "1983-05-11", "slug": "/listed-building/1025627", "entry-date": "2021-05-28"}}