{"type": "Feature", "geometry": {"type": "Point", "coordinates": [-0.312285, 51.277018]}, "properties": {"point": "POINT (-0.312285 51.277018)", "start-date": "1990-08-24", "listed-building": "1028629", "listed-building-grade": "II", "name": "CHERKLEY COURT, WITH ATTACHED GARDEN WALLS", "documentation-url": "https://historicengland.org.uk/listing/the-list/list-entry/1028629", "slug": "/listed-building/1028629", "entry-date": "2021-05-28"}}