{"type": "Feature", "geometry": {"type": "Point", "coordinates": [0.100882, 50.954531]}, "properties": {"documentation-url": "https://historicengland.org.uk/listing/the-list/list-entry/1028088", "listed-building": "1028088", "listed-building-grade": "II", "point": "POINT (0.100882 50.954531)", "name": "RIDGEWOOD HOUSE", "start-date": "1982-12-31", "slug": "/listed-building/1028088", "entry-date": "2021-05-28"}}