{"type": "Feature", "geometry": {"type": "Point", "coordinates": [-1.890517, 52.203719]}, "properties": {"listed-building": "1024693", "listed-building-grade": "II", "point": "POINT (-1.890517 52.203719)", "name": "RAGLEY HALL, KITCHEN GARDEN WALLS, GATEPIERS AND GATES", "start-date": "1967-02-01", "documentation-url": "https://historicengland.org.uk/listing/the-list/list-entry/1024693", "slug": "/listed-building/1024693", "entry-date": "2021-05-28"}}