{"type": "Feature", "geometry": {"type": "Point", "coordinates": [0.688829, 52.271816]}, "properties": {"point": "POINT (0.688829 52.271816)", "name": "SHRUBLANDS", "listed-building-grade": "II", "listed-building": "1031303", "start-date": "1985-03-28", "documentation-url": "https://historicengland.org.uk/listing/the-list/list-entry/1031303", "slug": "/listed-building/1031303", "entry-date": "2021-05-28"}}