{"type": "Feature", "geometry": {"type": "Point", "coordinates": [-0.295126, 51.165439]}, "properties": {"documentation-url": "https://historicengland.org.uk/listing/the-list/list-entry/1028730", "name": "KINGSLAND FARMHOUSE OLD KINGSLAND COTTAGE", "point": "POINT (-0.295126 51.165439)", "listed-building-grade": "II", "start-date": "1966-11-11", "listed-building": "1028730", "slug": "/listed-building/1028730", "entry-date": "1994-09-14"}}