{"type": "Feature", "geometry": {"type": "Point", "coordinates": [-0.652317, 50.791485]}, "properties": {"documentation-url": "https://historicengland.org.uk/listing/the-list/list-entry/1027782", "name": "THATCHED ROOF", "point": "POINT (-0.652317 50.791485)", "listed-building-grade": "II", "start-date": "1975-11-07", "listed-building": "1027782", "slug": "/listed-building/1027782", "entry-date": "2021-05-28"}}