{"type": "Feature", "geometry": {"type": "Point", "coordinates": [-1.45979, 55.001595]}, "properties": {"listed-building": "1025346", "start-date": "1986-02-19", "name": "Smith's Dock Company War Memorial in West Park", "point": "POINT (-1.459790 55.001595)", "listed-building-grade": "II", "documentation-url": "https://historicengland.org.uk/listing/the-list/list-entry/1025346", "slug": "/listed-building/1025346", "entry-date": "2021-05-28"}}