{"type": "Feature", "geometry": {"type": "Point", "coordinates": [-0.571504, 50.806756]}, "properties": {"documentation-url": "https://historicengland.org.uk/listing/the-list/list-entry/1027674", "listed-building": "1027674", "start-date": "1984-09-20", "name": "KENT'S FARMHOUSE", "point": "POINT (-0.571504 50.806756)", "listed-building-grade": "II", "slug": "/listed-building/1027674", "entry-date": "2021-05-28"}}