{"type": "Feature", "geometry": {"type": "Point", "coordinates": [1.434068, 52.277806]}, "properties": {"listed-building": "1030792", "start-date": "1951-10-25", "point": "POINT (1.434068 52.277806)", "listed-building-grade": "II", "documentation-url": "https://historicengland.org.uk/listing/the-list/list-entry/1030792", "name": "LODGE FARMHOUSE", "slug": "/listed-building/1030792", "entry-date": "1984-12-21"}}