{"type": "Feature", "geometry": {"type": "Point", "coordinates": [-0.124367, 50.945857]}, "properties": {"documentation-url": "https://historicengland.org.uk/listing/the-list/list-entry/1025857", "listed-building": "1025857", "point": "POINT (-0.124367 50.945857)", "name": "HIGH CHIMNEYS", "start-date": "1950-04-22", "listed-building-grade": "II", "slug": "/listed-building/1025857", "entry-date": "2021-05-28"}}