{"type": "Feature", "geometry": {"type": "Point", "coordinates": [1.400946, 51.990665]}, "properties": {"name": "GARDENER'S COTTAGE CIRCA 40 YARDS NORTH WEST OF BAWDSEY MANOR", "documentation-url": "https://historicengland.org.uk/listing/the-list/list-entry/1030775", "listed-building": "1030775", "start-date": "1984-03-28", "listed-building-grade": "II", "point": "POINT (1.400946 51.990665)", "slug": "/listed-building/1030775", "entry-date": "1988-08-31"}}