{"type": "Feature", "geometry": {"type": "Point", "coordinates": [-0.503835, 51.261107]}, "properties": {"listed-building": "1029358", "documentation-url": "https://historicengland.org.uk/listing/the-list/list-entry/1029358", "name": "BROWNLOW COTTAGE WEST CLANDON STORES", "listed-building-grade": "II", "start-date": "1985-11-25", "point": "POINT (-0.503835 51.261107)", "slug": "/listed-building/1029358", "entry-date": "2021-05-28"}}