{"type": "Feature", "geometry": {"type": "Point", "coordinates": [-2.036706, 51.451643]}, "properties": {"name": "HAZELAND FARMHOUSE", "start-date": "1987-11-25", "point": "POINT (-2.036706 51.451643)", "listed-building": "1022423", "documentation-url": "https://historicengland.org.uk/listing/the-list/list-entry/1022423", "listed-building-grade": "II", "slug": "/listed-building/1022423", "entry-date": "2021-05-28"}}