{"type": "Feature", "geometry": {"type": "Point", "coordinates": [-0.822319, 50.765978]}, "properties": {"point": "POINT (-0.822319 50.765978)", "listed-building-grade": "II", "listed-building": "1026249", "name": "BARN AT EAST FARM TO THE SOUTH WEST OF THE FARMHOUSE", "start-date": "1986-01-28", "documentation-url": "https://historicengland.org.uk/listing/the-list/list-entry/1026249", "slug": "/listed-building/1026249", "entry-date": "2021-05-28"}}