{"type": "Feature", "geometry": {"type": "Point", "coordinates": [-2.242218, 51.420917]}, "properties": {"documentation-url": "https://historicengland.org.uk/listing/the-list/list-entry/1022731", "name": "GROVE FARM", "listed-building": "1022731", "start-date": "1985-07-24", "listed-building-grade": "II", "point": "POINT (-2.242218 51.420917)", "slug": "/listed-building/1022731", "entry-date": "2021-05-28"}}