{"type": "Feature", "geometry": {"type": "Point", "coordinates": [-0.416605, 51.24157]}, "properties": {"name": "OCTAGON LODGE", "start-date": "1975-10-10", "point": "POINT (-0.416605 51.241570)", "listed-building": "1029388", "documentation-url": "https://historicengland.org.uk/listing/the-list/list-entry/1029388", "listed-building-grade": "II", "slug": "/listed-building/1029388", "entry-date": "1985-11-25"}}