{"type": "Feature", "geometry": {"type": "Point", "coordinates": [-0.904546, 50.916599]}, "properties": {"point": "POINT (-0.904546 50.916599)", "listed-building-grade": "II", "listed-building": "1026391", "documentation-url": "https://historicengland.org.uk/listing/the-list/list-entry/1026391", "start-date": "1986-01-28", "name": "WEST MARDEN FARMHOUSE", "slug": "/listed-building/1026391", "entry-date": "2021-05-28"}}