{"type": "Feature", "geometry": {"type": "Point", "coordinates": [-0.112154, 50.999916]}, "properties": {"point": "POINT (-0.112154 50.999916)", "name": "THE SERGISON ARMS PUBLIC HOUSE", "documentation-url": "https://historicengland.org.uk/listing/the-list/list-entry/1025473", "start-date": "1987-12-11", "listed-building-grade": "II", "listed-building": "1025473", "slug": "/listed-building/1025473", "entry-date": "2021-05-28"}}