{"type": "Feature", "geometry": {"type": "Point", "coordinates": [-2.229472, 51.546158]}, "properties": {"listed-building-grade": "II*", "point": "POINT (-2.229472 51.546158)", "name": "CHURCH OF ST GILES", "documentation-url": "https://historicengland.org.uk/listing/the-list/list-entry/1022362", "listed-building": "1022362", "start-date": "1959-10-28", "slug": "/listed-building/1022362", "entry-date": "2021-05-28"}}