{"type": "Feature", "geometry": {"type": "Point", "coordinates": [-0.336714, 50.839807]}, "properties": {"start-date": "1984-07-27", "name": "BARN AT HALEWICK FARM TO THE WEST OF THE FARMHOUSE", "point": "POINT (-0.336714 50.839807)", "listed-building": "1027847", "documentation-url": "https://historicengland.org.uk/listing/the-list/list-entry/1027847", "listed-building-grade": "II", "slug": "/listed-building/1027847", "entry-date": "2021-05-28"}}