{"type": "Feature", "geometry": {"type": "Point", "coordinates": [-0.603564, 51.347414]}, "properties": {"start-date": "1984-07-19", "listed-building-grade": "II", "name": "87 AND 89, VICARAGE ROAD (See details for further address information)", "listed-building": "1030012", "point": "POINT (-0.603564 51.347414)", "documentation-url": "https://historicengland.org.uk/listing/the-list/list-entry/1030012", "slug": "/listed-building/1030012", "entry-date": "2021-05-28"}}