{"type": "Feature", "geometry": {"type": "Point", "coordinates": [-1.973011, 51.476903]}, "properties": {"listed-building-grade": "II", "listed-building": "1022524", "start-date": "1987-11-25", "point": "POINT (-1.973011 51.476903)", "name": "TWO UNIDENTIFIED MONUMENTS IN CHURCHYARD ABOUT 5 METRES WEST OF SOUTH WEST ANGLE OF TOWER OF CHURCH OF ST LAURENCE", "documentation-url": "https://historicengland.org.uk/listing/the-list/list-entry/1022524", "slug": "/listed-building/1022524", "entry-date": "2021-05-28"}}