{"type": "Feature", "geometry": {"type": "Point", "coordinates": [-0.527876, 51.408851]}, "properties": {"start-date": "1985-09-03", "listed-building-grade": "II", "point": "POINT (-0.527876 51.408851)", "name": "WALL ON NORTH SIDE", "listed-building": "1028929", "documentation-url": "https://historicengland.org.uk/listing/the-list/list-entry/1028929", "slug": "/listed-building/1028929", "entry-date": "2021-05-28"}}