{"type": "Feature", "geometry": {"type": "Point", "coordinates": [-2.0602, 51.599542]}, "properties": {"name": "GATE PIERS AND GATES TO CHARLTON PARK", "listed-building-grade": "II", "listed-building": "1022223", "documentation-url": "https://historicengland.org.uk/listing/the-list/list-entry/1022223", "start-date": "1987-07-16", "point": "POINT (-2.060200 51.599542)", "slug": "/listed-building/1022223", "entry-date": "2021-05-28"}}