{"type": "Feature", "geometry": {"type": "Point", "coordinates": [-2.201248, 51.323183]}, "properties": {"listed-building": "1021611", "name": "BELLEFIELD HOUSE", "listed-building-grade": "II", "point": "POINT (-2.201248 51.323183)", "start-date": "1976-11-26", "documentation-url": "https://historicengland.org.uk/listing/the-list/list-entry/1021611", "slug": "/listed-building/1021611", "entry-date": "2021-05-28"}}