{"type": "Feature", "geometry": {"type": "Point", "coordinates": [-0.253888, 50.941903]}, "properties": {"name": "PARK FARMHOUSE", "listed-building": "1027122", "start-date": "1980-05-09", "listed-building-grade": "II", "documentation-url": "https://historicengland.org.uk/listing/the-list/list-entry/1027122", "point": "POINT (-0.253888 50.941903)", "slug": "/listed-building/1027122", "entry-date": "2021-05-28"}}