{"type": "Feature", "geometry": {"type": "Point", "coordinates": [-1.822938, 51.505078]}, "properties": {"point": "POINT (-1.822938 51.505078)", "name": "MILESTONE", "listed-building": "1023432", "start-date": "1979-09-20", "listed-building-grade": "II", "documentation-url": "https://historicengland.org.uk/listing/the-list/list-entry/1023432", "slug": "/listed-building/1023432", "entry-date": "2021-05-28"}}