{"type": "Feature", "geometry": {"type": "Point", "coordinates": [-1.839721, 52.270819]}, "properties": {"listed-building-grade": "II*", "listed-building": "1024499", "documentation-url": "https://historicengland.org.uk/listing/the-list/list-entry/1024499", "point": "POINT (-1.839721 52.270819)", "name": "GREENHILL FARMHOUSE", "start-date": "1967-02-01", "slug": "/listed-building/1024499", "entry-date": "2021-05-28"}}