{"type": "Feature", "geometry": {"type": "Point", "coordinates": [0.267776, 51.096216]}, "properties": {"listed-building-grade": "II", "point": "POINT (0.267776 51.096216)", "documentation-url": "https://historicengland.org.uk/listing/the-list/list-entry/1028340", "listed-building": "1028340", "name": "PARK VIEW", "start-date": "1982-12-31", "slug": "/listed-building/1028340", "entry-date": "2021-05-28"}}