{"type": "Feature", "geometry": {"type": "Point", "coordinates": [0.051167, 50.983142]}, "properties": {"listed-building-grade": "II", "listed-building": "1028431", "point": "POINT (0.051167 50.983142)", "name": "SONA TAIGH", "start-date": "1982-12-31", "documentation-url": "https://historicengland.org.uk/listing/the-list/list-entry/1028431", "slug": "/listed-building/1028431", "entry-date": "1983-09-08"}}