{"type": "Feature", "geometry": {"type": "Point", "coordinates": [-0.2805, 50.965626]}, "properties": {"listed-building": "1027330", "documentation-url": "https://historicengland.org.uk/listing/the-list/list-entry/1027330", "listed-building-grade": "II", "point": "POINT (-0.280500 50.965626)", "start-date": "1980-05-09", "name": "MORLEY", "slug": "/listed-building/1027330", "entry-date": "2021-05-28"}}