{"type": "Feature", "geometry": {"type": "Point", "coordinates": [-0.750189, 50.951601]}, "properties": {"point": "POINT (-0.750189 50.951601)", "start-date": "1987-11-26", "listed-building": "1026068", "name": "THE OLD SCHOOL", "documentation-url": "https://historicengland.org.uk/listing/the-list/list-entry/1026068", "listed-building-grade": "II", "slug": "/listed-building/1026068", "entry-date": "2021-05-28"}}