{"type": "Feature", "geometry": {"type": "Point", "coordinates": [-2.15248, 51.499007]}, "properties": {"documentation-url": "https://historicengland.org.uk/listing/the-list/list-entry/1022340", "listed-building": "1022340", "listed-building-grade": "II*", "point": "POINT (-2.152480 51.499007)", "start-date": "1960-12-20", "name": "PRIORY MANOR", "slug": "/listed-building/1022340", "entry-date": "1988-02-29"}}