{"type": "Feature", "geometry": {"type": "Point", "coordinates": [-0.477395, 51.014159]}, "properties": {"start-date": "1959-09-22", "documentation-url": "https://historicengland.org.uk/listing/the-list/list-entry/1027127", "listed-building": "1027127", "listed-building-grade": "II", "point": "POINT (-0.477395 51.014159)", "name": "STREELE", "slug": "/listed-building/1027127", "entry-date": "1980-11-28"}}