{"type": "Feature", "geometry": {"type": "Point", "coordinates": [-1.855024, 51.643305]}, "properties": {"documentation-url": "https://historicengland.org.uk/listing/the-list/list-entry/1023107", "listed-building": "1023107", "point": "POINT (-1.855024 51.643305)", "start-date": "1976-08-26", "name": "58 AND 59, HIGH STREET", "listed-building-grade": "II", "slug": "/listed-building/1023107", "entry-date": "2021-05-28"}}