{"type": "Feature", "geometry": {"type": "Point", "coordinates": [0.71548, 52.246395]}, "properties": {"point": "POINT (0.715480 52.246395)", "listed-building": "1022592", "start-date": "1972-07-12", "name": "GARDEN WALL TO REGENCY HOUSE HOTEL", "documentation-url": "https://historicengland.org.uk/listing/the-list/list-entry/1022592", "listed-building-grade": "II", "slug": "/listed-building/1022592", "entry-date": "1997-10-30"}}