{"type": "Feature", "geometry": {"type": "Point", "coordinates": [-1.649271, 51.553206]}, "properties": {"listed-building-grade": "II", "point": "POINT (-1.649271 51.553206)", "listed-building": "1023267", "start-date": "1979-09-20", "name": "CUE'S FARMHOUSE", "documentation-url": "https://historicengland.org.uk/listing/the-list/list-entry/1023267", "slug": "/listed-building/1023267", "entry-date": "2021-05-28"}}