{"type": "Feature", "geometry": {"type": "Point", "coordinates": [-1.619082, 52.106049]}, "properties": {"start-date": "1966-10-13", "listed-building": "1024359", "name": "THE FOLLY", "point": "POINT (-1.619082 52.106049)", "documentation-url": "https://historicengland.org.uk/listing/the-list/list-entry/1024359", "listed-building-grade": "II", "slug": "/listed-building/1024359", "entry-date": "2021-05-28"}}