{"type": "Feature", "geometry": {"type": "Point", "coordinates": [-0.573545, 51.233426]}, "properties": {"listed-building-grade": "II", "listed-building": "1029227", "name": "NATIONAL WESTMINSTER BANK AREA OFFICE", "start-date": "1953-05-01", "documentation-url": "https://historicengland.org.uk/listing/the-list/list-entry/1029227", "point": "POINT (-0.573545 51.233426)", "slug": "/listed-building/1029227", "entry-date": "1988-03-15"}}