{"type": "Feature", "geometry": {"type": "Point", "coordinates": [-2.151757, 51.545709]}, "properties": {"documentation-url": "https://historicengland.org.uk/listing/the-list/list-entry/1023202", "start-date": "1986-12-03", "listed-building": "1023202", "point": "POINT (-2.151757 51.545709)", "name": "BARN IN COURTYARD TO THE SOUTH EAST OF BRADFIELD MANOR FARMHOUSE", "listed-building-grade": "II", "slug": "/listed-building/1023202", "entry-date": "2021-05-28"}}