{"type": "Feature", "geometry": {"type": "Point", "coordinates": [-2.281087, 51.343016]}, "properties": {"point": "POINT (-2.281087 51.343016)", "name": "BARN RANGE AT TURLEIGH FARMHOUSE", "start-date": "1988-06-14", "documentation-url": "https://historicengland.org.uk/listing/the-list/list-entry/1021912", "listed-building-grade": "II", "listed-building": "1021912", "slug": "/listed-building/1021912", "entry-date": "2021-05-28"}}