{"type": "Feature", "geometry": {"type": "Point", "coordinates": [-2.274567, 51.493704]}, "properties": {"point": "POINT (-2.274567 51.493704)", "documentation-url": "https://historicengland.org.uk/listing/the-list/list-entry/1022971", "name": "BARN RANGE TO NORTH OF MANOR FARMHOUSE", "start-date": "1985-12-09", "listed-building": "1022971", "listed-building-grade": "II", "slug": "/listed-building/1022971", "entry-date": "2021-05-28"}}