{"type": "Feature", "geometry": {"type": "Point", "coordinates": [-0.081064, 51.012819]}, "properties": {"start-date": "1951-09-10", "point": "POINT (-0.081064 51.012819)", "listed-building-grade": "II", "name": "THE TOLL HOUSE", "documentation-url": "https://historicengland.org.uk/listing/the-list/list-entry/1025456", "listed-building": "1025456", "slug": "/listed-building/1025456", "entry-date": "1987-12-11"}}