{"type": "Feature", "geometry": {"type": "Point", "coordinates": [-0.210231, 50.983411]}, "properties": {"name": "BARN TO NORTH WEST OF GARSTON'S FARMHOUSE", "documentation-url": "https://historicengland.org.uk/listing/the-list/list-entry/1025747", "listed-building": "1025747", "start-date": "1983-05-11", "listed-building-grade": "II", "point": "POINT (-0.210231 50.983411)", "slug": "/listed-building/1025747", "entry-date": "2021-05-28"}}