{"type": "Feature", "geometry": {"type": "Point", "coordinates": [-0.430604, 51.352969]}, "properties": {"listed-building-grade": "II", "name": "CHAPEL OF EASE, 11 YARDS WEST OF CHURCH OF ST MARK", "documentation-url": "https://historicengland.org.uk/listing/the-list/list-entry/1030120", "listed-building": "1030120", "point": "POINT (-0.430604 51.352969)", "start-date": "1984-11-16", "slug": "/listed-building/1030120", "entry-date": "2021-05-28"}}