{"type": "Feature", "geometry": {"type": "Point", "coordinates": [-2.119026, 51.447749]}, "properties": {"documentation-url": "https://historicengland.org.uk/listing/the-list/list-entry/1022194", "listed-building": "1022194", "point": "POINT (-2.119026 51.447749)", "name": "ROWDEN FARMHOUSE WITH BARN, OUTBUILDINGS AND GATEPIERS ATTACHED", "start-date": "1986-06-16", "listed-building-grade": "II*", "slug": "/listed-building/1022194", "entry-date": "2021-05-28"}}