{"type": "Feature", "geometry": {"type": "Point", "coordinates": [-0.772776, 50.83688]}, "properties": {"name": "10 AND 11, ST PANCRAS", "listed-building-grade": "II", "start-date": "1971-10-08", "listed-building": "1026666", "documentation-url": "https://historicengland.org.uk/listing/the-list/list-entry/1026666", "point": "POINT (-0.772776 50.836880)", "slug": "/listed-building/1026666", "entry-date": "2021-05-28"}}