{"type": "Feature", "geometry": {"type": "Point", "coordinates": [-0.33224, 51.262061]}, "properties": {"listed-building": "1028887", "listed-building-grade": "II", "point": "POINT (-0.332240 51.262061)", "documentation-url": "https://historicengland.org.uk/listing/the-list/list-entry/1028887", "name": "COWSLIP COTTAGE", "start-date": "1973-06-11", "slug": "/listed-building/1028887", "entry-date": "2021-05-28"}}