{"type": "Feature", "geometry": {"type": "Point", "coordinates": [-0.732747, 50.987019]}, "properties": {"name": "THE FORMER STABLES OF OLD COWDRAY HOUSE", "start-date": "1959-06-18", "point": "POINT (-0.732747 50.987019)", "documentation-url": "https://historicengland.org.uk/listing/the-list/list-entry/1026037", "listed-building-grade": "II", "listed-building": "1026037", "slug": "/listed-building/1026037", "entry-date": "2021-05-28"}}