{"type": "Feature", "geometry": {"type": "Point", "coordinates": [-1.710098, 51.631103]}, "properties": {"name": "CHURCH HOUSE", "documentation-url": "https://historicengland.org.uk/listing/the-list/list-entry/1023377", "start-date": "1955-01-26", "listed-building": "1023377", "listed-building-grade": "II", "point": "POINT (-1.710098 51.631103)", "slug": "/listed-building/1023377", "entry-date": "2021-05-28"}}