{"type": "Feature", "geometry": {"type": "Point", "coordinates": [-0.580078, 51.407642]}, "properties": {"listed-building-grade": "II", "documentation-url": "https://historicengland.org.uk/listing/the-list/list-entry/1028903", "start-date": "1988-05-19", "point": "POINT (-0.580078 51.407642)", "listed-building": "1028903", "name": "TOMB OF COUNT AND COUNTESS DE MORELLA APPROXIMATELY 45 METRES TO NORTH EAST OF NORTH TRANSEPT OF CHRIST CHURCH", "slug": "/listed-building/1028903", "entry-date": "2021-05-28"}}