{"type": "Feature", "geometry": {"type": "Point", "coordinates": [-0.747241, 50.812463]}, "properties": {"point": "POINT (-0.747241 50.812463)", "start-date": "1986-01-28", "documentation-url": "https://historicengland.org.uk/listing/the-list/list-entry/1026319", "listed-building": "1026319", "name": "MANOR COTTAGE", "listed-building-grade": "II", "slug": "/listed-building/1026319", "entry-date": "2021-05-28"}}