{"type": "Feature", "geometry": {"type": "Point", "coordinates": [-0.53355, 50.908426]}, "properties": {"point": "POINT (-0.533550 50.908426)", "start-date": "1980-05-09", "name": "BARN BEHIND AND TO SOUTH EAST OF MARTINS", "documentation-url": "https://historicengland.org.uk/listing/the-list/list-entry/1027475", "listed-building-grade": "II", "listed-building": "1027475", "slug": "/listed-building/1027475", "entry-date": "2021-05-28"}}