{"type": "Feature", "geometry": {"type": "Point", "coordinates": [-0.581255, 51.219752]}, "properties": {"listed-building-grade": "II", "listed-building": "1029537", "name": "THE SHIELING", "point": "POINT (-0.581255 51.219752)", "documentation-url": "https://historicengland.org.uk/listing/the-list/list-entry/1029537", "start-date": "1967-06-14", "slug": "/listed-building/1029537", "entry-date": "2021-05-28"}}