{"type": "Feature", "geometry": {"type": "Point", "coordinates": [-1.982426, 51.558772]}, "properties": {"start-date": "1987-07-16", "listed-building-grade": "II", "listed-building": "1022214", "documentation-url": "https://historicengland.org.uk/listing/the-list/list-entry/1022214", "point": "POINT (-1.982426 51.558772)", "name": "TWO YOUNG MONUMENTS IN THE CHURCHYARD, 10 METRES NORTH EAST OF CHANCEL, CHURCH OF ST MICHAEL AND ALL ANGELS", "slug": "/listed-building/1022214", "entry-date": "2021-05-28"}}