{"type": "Feature", "geometry": {"type": "Point", "coordinates": [-0.416933, 51.057608]}, "properties": {"start-date": "1980-11-28", "listed-building-grade": "II", "documentation-url": "https://historicengland.org.uk/listing/the-list/list-entry/1026906", "name": "Littlegate House", "point": "POINT (-0.416933 51.057608)", "listed-building": "1026906", "slug": "/listed-building/1026906", "entry-date": "2021-05-28"}}