{"type": "Feature", "geometry": {"type": "Point", "coordinates": [-2.192068, 51.492205]}, "properties": {"documentation-url": "https://historicengland.org.uk/listing/the-list/list-entry/1023020", "listed-building-grade": "II", "listed-building": "1023020", "name": "FOLLY FARMHOUSE", "point": "POINT (-2.192068 51.492205)", "start-date": "1985-12-09", "slug": "/listed-building/1023020", "entry-date": "2021-05-28"}}