{"type": "Feature", "geometry": {"type": "Point", "coordinates": [-0.080515, 51.011622]}, "properties": {"point": "POINT (-0.080515 51.011622)", "start-date": "1987-12-11", "listed-building": "1025435", "listed-building-grade": "II", "name": "CARRIERS", "documentation-url": "https://historicengland.org.uk/listing/the-list/list-entry/1025435", "slug": "/listed-building/1025435", "entry-date": "2021-05-28"}}