{"type": "Feature", "geometry": {"type": "Point", "coordinates": [0.939673, 52.353131]}, "properties": {"name": "WARDS FARMHOUSE", "start-date": "1984-09-27", "point": "POINT (0.939673 52.353131)", "listed-building": "1031200", "listed-building-grade": "II", "documentation-url": "https://historicengland.org.uk/listing/the-list/list-entry/1031200", "slug": "/listed-building/1031200", "entry-date": "2021-05-28"}}