{"type": "Feature", "geometry": {"type": "Point", "coordinates": [-1.621191, 52.075973]}, "properties": {"documentation-url": "https://historicengland.org.uk/listing/the-list/list-entry/1024054", "listed-building-grade": "II", "point": "POINT (-1.621191 52.075973)", "start-date": "1988-05-16", "name": "OLD TOLLBAR COTTAGE GATEPIERS APPROXIMATELY 5 METRES NORTH OF HOUSE", "listed-building": "1024054", "slug": "/listed-building/1024054", "entry-date": "2021-05-28"}}