{"type": "Feature", "geometry": {"type": "Point", "coordinates": [-0.439303, 50.983557]}, "properties": {"name": "BROOK HOUSE FARMHOUSE", "listed-building": "1027169", "point": "POINT (-0.439303 50.983557)", "start-date": "1980-05-09", "documentation-url": "https://historicengland.org.uk/listing/the-list/list-entry/1027169", "listed-building-grade": "II", "slug": "/listed-building/1027169", "entry-date": "2021-05-28"}}