{"type": "Feature", "geometry": {"type": "Point", "coordinates": [-0.892378, 50.95286]}, "properties": {"start-date": "1959-06-18", "point": "POINT (-0.892378 50.952860)", "listed-building-grade": "II", "listed-building": "1025980", "documentation-url": "https://historicengland.org.uk/listing/the-list/list-entry/1025980", "name": "THE DAIRY AT UP PARK TO THE WEST OF THE STABLE BLOCK", "slug": "/listed-building/1025980", "entry-date": "2021-05-28"}}