{"type": "Feature", "geometry": {"type": "Point", "coordinates": [-0.28491, 51.034937]}, "properties": {"listed-building": "1027027", "point": "POINT (-0.284910 51.034937)", "name": "MONK'S GATE COTTAGE", "start-date": "1980-11-28", "listed-building-grade": "II", "documentation-url": "https://historicengland.org.uk/listing/the-list/list-entry/1027027", "slug": "/listed-building/1027027", "entry-date": "2021-05-28"}}