{"type": "Feature", "geometry": {"type": "Point", "coordinates": [-1.711748, 51.630084]}, "properties": {"documentation-url": "https://historicengland.org.uk/listing/the-list/list-entry/1023380", "listed-building": "1023380", "listed-building-grade": "II", "point": "POINT (-1.711748 51.630084)", "name": "BURFORD HOUSE", "start-date": "1979-09-20", "slug": "/listed-building/1023380", "entry-date": "2021-05-28"}}