{"type": "Feature", "geometry": {"type": "Point", "coordinates": [-1.916048, 51.209337]}, "properties": {"listed-building": "1023987", "start-date": "1985-07-04", "name": "ORCHESTON HOUSE AND THE WING, ORCHESTON HOUSE", "documentation-url": "https://historicengland.org.uk/listing/the-list/list-entry/1023987", "listed-building-grade": "II", "point": "POINT (-1.916048 51.209337)", "slug": "/listed-building/1023987", "entry-date": "2021-05-28"}}