{"type": "Feature", "geometry": {"type": "Point", "coordinates": [1.35701, 52.144721]}, "properties": {"listed-building": "1030267", "documentation-url": "https://historicengland.org.uk/listing/the-list/list-entry/1030267", "point": "POINT (1.357010 52.144721)", "name": "PETTISTREE COTTAGE", "start-date": "1988-08-15", "listed-building-grade": "II", "slug": "/listed-building/1030267", "entry-date": "2021-05-28"}}