{"type": "Feature", "geometry": {"type": "Point", "coordinates": [-0.198468, 51.267588]}, "properties": {"point": "POINT (-0.198468 51.267588)", "listed-building": "1029050", "name": "THATCHED COTTAGE", "listed-building-grade": "II", "start-date": "1983-09-29", "documentation-url": "https://historicengland.org.uk/listing/the-list/list-entry/1029050", "slug": "/listed-building/1029050", "entry-date": "1983-12-20"}}