{"type": "Feature", "geometry": {"type": "Point", "coordinates": [-0.504408, 51.253614]}, "properties": {"start-date": "1985-11-25", "documentation-url": "https://historicengland.org.uk/listing/the-list/list-entry/1029359", "listed-building": "1029359", "listed-building-grade": "II", "name": "CLANDON CHURCH OF ENGLAND FIRST SCHOOL", "point": "POINT (-0.504408 51.253614)", "slug": "/listed-building/1029359", "entry-date": "2021-05-28"}}