{"type": "Feature", "geometry": {"type": "Point", "coordinates": [-0.840429, 50.873121]}, "properties": {"listed-building-grade": "II", "name": "Woodend", "start-date": "1986-01-28", "listed-building": "1026331", "documentation-url": "https://historicengland.org.uk/listing/the-list/list-entry/1026331", "point": "POINT (-0.840429 50.873121)", "slug": "/listed-building/1026331", "entry-date": "2021-05-28"}}