{"type": "Feature", "geometry": {"type": "Point", "coordinates": [-1.400259, 54.954371]}, "properties": {"documentation-url": "https://historicengland.org.uk/listing/the-list/list-entry/1025210", "listed-building-grade": "II", "name": "GATES AND GATE PIERS AT NORTH EAST CORNER OF JUNCTION WITH SUNDERLAND ROAD", "point": "POINT (-1.400259 54.954371)", "listed-building": "1025210", "start-date": "1973-01-30", "slug": "/listed-building/1025210", "entry-date": "1985-02-26"}}