{"type": "Feature", "geometry": {"type": "Point", "coordinates": [-0.328888, 51.233138]}, "properties": {"listed-building": "1028864", "start-date": "1973-06-11", "documentation-url": "https://historicengland.org.uk/listing/the-list/list-entry/1028864", "name": "SURREY YEOMAN HOUSE", "listed-building-grade": "II", "point": "POINT (-0.328888 51.233138)", "slug": "/listed-building/1028864", "entry-date": "2021-05-28"}}