{"type": "Feature", "geometry": {"type": "Point", "coordinates": [-0.016489, 51.252505]}, "properties": {"start-date": "1958-06-11", "listed-building-grade": "II", "documentation-url": "https://historicengland.org.uk/listing/the-list/list-entry/1029743", "name": "BEAM COTTAGE FORGE COTTAGE OAK COTTAGE", "point": "POINT (-0.016489 51.252505)", "listed-building": "1029743", "slug": "/listed-building/1029743", "entry-date": "1984-11-19"}}