{"type": "Feature", "geometry": {"type": "Point", "coordinates": [1.363484, 52.20668]}, "properties": {"listed-building-grade": "II", "listed-building": "1030377", "documentation-url": "https://historicengland.org.uk/listing/the-list/list-entry/1030377", "point": "POINT (1.363484 52.206680)", "name": "GATE PIER 100 METRES SOUTH OF PARHAM HOUSE", "start-date": "1985-12-18", "slug": "/listed-building/1030377", "entry-date": "2021-05-28"}}