{"type": "Feature", "geometry": {"type": "Point", "coordinates": [-0.718294, 50.9075]}, "properties": {"documentation-url": "https://historicengland.org.uk/listing/the-list/list-entry/1026373", "listed-building-grade": "II", "point": "POINT (-0.718294 50.907500)", "start-date": "1986-01-28", "listed-building": "1026373", "name": "MANOR HOUSE", "slug": "/listed-building/1026373", "entry-date": "2021-05-28"}}