{"type": "Feature", "geometry": {"type": "Point", "coordinates": [-0.187758, 50.953917]}, "properties": {"point": "POINT (-0.187758 50.953917)", "listed-building-grade": "II", "listed-building": "1025641", "start-date": "1983-05-11", "name": "GOLDBRIDGE HOUSE", "documentation-url": "https://historicengland.org.uk/listing/the-list/list-entry/1025641", "slug": "/listed-building/1025641", "entry-date": "2021-05-28"}}