{"type": "Feature", "geometry": {"type": "Point", "coordinates": [1.367895, 52.320771]}, "properties": {"point": "POINT (1.367895 52.320771)", "listed-building": "1030459", "documentation-url": "https://historicengland.org.uk/listing/the-list/list-entry/1030459", "start-date": "1985-03-19", "listed-building-grade": "II", "name": "ROSE FARMHOUSE", "slug": "/listed-building/1030459", "entry-date": "2021-05-28"}}