{"type": "Feature", "geometry": {"type": "Point", "coordinates": [1.363615, 52.207638]}, "properties": {"start-date": "1951-10-25", "listed-building": "1030529", "documentation-url": "https://historicengland.org.uk/listing/the-list/list-entry/1030529", "name": "PARHAM HOUSE", "point": "POINT (1.363615 52.207638)", "listed-building-grade": "II", "slug": "/listed-building/1030529", "entry-date": "2021-05-28"}}