{"type": "Feature", "geometry": {"type": "Point", "coordinates": [-0.776386, 50.836395]}, "properties": {"point": "POINT (-0.776386 50.836395)", "listed-building": "1026781", "name": "31 AND 32, EAST STREET", "listed-building-grade": "II", "documentation-url": "https://historicengland.org.uk/listing/the-list/list-entry/1026781", "start-date": "1971-10-08", "slug": "/listed-building/1026781", "entry-date": "2021-05-28"}}