{"type": "Feature", "geometry": {"type": "Point", "coordinates": [-0.786148, 50.836561]}, "properties": {"start-date": "1971-10-08", "listed-building-grade": "II", "point": "POINT (-0.786148 50.836561)", "name": "WALL ENCLOSING GARDEN BEHIND NOS 23 AND 25 ON SOUTH EAST SIDE", "listed-building": "1026637", "documentation-url": "https://historicengland.org.uk/listing/the-list/list-entry/1026637", "slug": "/listed-building/1026637", "entry-date": "2021-05-28"}}