{"type": "Feature", "geometry": {"type": "Point", "coordinates": [1.363902, 51.968012]}, "properties": {"documentation-url": "https://historicengland.org.uk/listing/the-list/list-entry/1030410", "start-date": "1986-02-10", "point": "POINT (1.363902 51.968012)", "listed-building": "1030410", "name": "TYNDALE HOUSE", "listed-building-grade": "II", "slug": "/listed-building/1030410", "entry-date": "2021-05-28"}}