{"type": "Feature", "geometry": {"type": "Point", "coordinates": [-1.742451, 50.989794]}, "properties": {"listed-building": "1023900", "point": "POINT (-1.742451 50.989794)", "name": "BARN AND ATTACHED STABLE TO SOUTH OF MOOT FARMHOUSE", "documentation-url": "https://historicengland.org.uk/listing/the-list/list-entry/1023900", "start-date": "1985-07-04", "listed-building-grade": "II", "slug": "/listed-building/1023900", "entry-date": "2021-05-28"}}