{"type": "Feature", "geometry": {"type": "Point", "coordinates": [0.803865, 52.336406]}, "properties": {"documentation-url": "https://historicengland.org.uk/listing/the-list/list-entry/1031288", "start-date": "1983-12-14", "name": "HONINGTON HALL", "listed-building": "1031288", "point": "POINT (0.803865 52.336406)", "listed-building-grade": "II", "slug": "/listed-building/1031288", "entry-date": "2021-05-28"}}