{"type": "Feature", "geometry": {"type": "Point", "coordinates": [-0.338285, 51.058766]}, "properties": {"point": "POINT (-0.338285 51.058766)", "start-date": "1949-05-20", "listed-building": "1027571", "documentation-url": "https://historicengland.org.uk/listing/the-list/list-entry/1027571", "name": "NETHERLEDYS THE NEEDLES", "listed-building-grade": "II*", "slug": "/listed-building/1027571", "entry-date": "1974-07-27"}}