{"type": "Feature", "geometry": {"type": "Point", "coordinates": [-0.322105, 50.932633]}, "properties": {"listed-building": "1027457", "point": "POINT (-0.322105 50.932633)", "documentation-url": "https://historicengland.org.uk/listing/the-list/list-entry/1027457", "start-date": "1980-05-09", "name": "THE FOUNTAIN INN", "listed-building-grade": "II", "slug": "/listed-building/1027457", "entry-date": "2021-05-28"}}