{"type": "Feature", "geometry": {"type": "Point", "coordinates": [-2.1819, 51.434407]}, "properties": {"listed-building-grade": "II", "name": "ISAAC MONUMENT ABOUT 4 METRES SOUTH OF NORTH BOUNDARY WALL, IN NORTH EAST ANGLE OF CHURCHYARD OF CHURCH OF ST BARTHOLOMEW", "documentation-url": "https://historicengland.org.uk/listing/the-list/list-entry/1021993", "start-date": "1986-08-01", "point": "POINT (-2.181900 51.434407)", "listed-building": "1021993", "slug": "/listed-building/1021993", "entry-date": "2021-05-28"}}