{"type": "Feature", "geometry": {"type": "Point", "coordinates": [-1.539199, 54.913379]}, "properties": {"name": "BLUE HOUSE VILLA", "point": "POINT (-1.539199 54.913379)", "listed-building-grade": "II", "documentation-url": "https://historicengland.org.uk/listing/the-list/list-entry/1025424", "listed-building": "1025424", "start-date": "1985-07-15", "slug": "/listed-building/1025424", "entry-date": "2021-05-28"}}