{"type": "Feature", "geometry": {"type": "Point", "coordinates": [-1.643836, 54.971665]}, "properties": {"name": "CONRAD HOUSE AND WESTERN HOUSE", "listed-building-grade": "II", "start-date": "1971-12-17", "documentation-url": "https://historicengland.org.uk/listing/the-list/list-entry/1024955", "point": "POINT (-1.643836 54.971665)", "listed-building": "1024955", "slug": "/listed-building/1024955", "entry-date": "2021-05-28"}}