{"type": "Feature", "geometry": {"type": "Point", "coordinates": [0.033768, 51.096753]}, "properties": {"start-date": "1982-12-31", "point": "POINT (0.033768 51.096753)", "name": "YEW TREE COTTAGE", "documentation-url": "https://historicengland.org.uk/listing/the-list/list-entry/1028371", "listed-building-grade": "II", "listed-building": "1028371", "slug": "/listed-building/1028371", "entry-date": "2021-05-28"}}