{"type": "Feature", "geometry": {"type": "Point", "coordinates": [-0.775734, 50.835617]}, "properties": {"point": "POINT (-0.775734 50.835617)", "listed-building-grade": "II", "name": "THE SOUTHERN HALF OF THE FORMER CORN EXCHANGE NOW OCCUPIED BY JOHN WILEY AND SONS", "documentation-url": "https://historicengland.org.uk/listing/the-list/list-entry/1026830", "start-date": "1950-07-05", "listed-building": "1026830", "slug": "/listed-building/1026830", "entry-date": "1971-10-08"}}