{"type": "Feature", "geometry": {"type": "Point", "coordinates": [0.958759, 52.365334]}, "properties": {"name": "IVY COTTAGE", "documentation-url": "https://historicengland.org.uk/listing/the-list/list-entry/1031205", "point": "POINT (0.958759 52.365334)", "start-date": "1984-09-27", "listed-building": "1031205", "listed-building-grade": "II", "slug": "/listed-building/1031205", "entry-date": "2021-05-28"}}