{"type": "Feature", "geometry": {"type": "Point", "coordinates": [-0.443988, 51.40979]}, "properties": {"start-date": "1951-09-11", "name": "THE HARROW PUBLIC HOUSE", "point": "POINT (-0.443988 51.409790)", "listed-building": "1029689", "documentation-url": "https://historicengland.org.uk/listing/the-list/list-entry/1029689", "listed-building-grade": "II", "slug": "/listed-building/1029689", "entry-date": "1987-09-24"}}