{"type": "Feature", "geometry": {"type": "Point", "coordinates": [-0.742774, 51.005571]}, "properties": {"name": "LOCKS COTTAGES", "documentation-url": "https://historicengland.org.uk/listing/the-list/list-entry/1026014", "start-date": "1959-06-18", "listed-building-grade": "II", "point": "POINT (-0.742774 51.005571)", "listed-building": "1026014", "slug": "/listed-building/1026014", "entry-date": "2021-05-28"}}