{"type": "Feature", "geometry": {"type": "Point", "coordinates": [-1.671565, 54.973505]}, "properties": {"name": "FORMER LODGE TO BENWELL TOWERS", "point": "POINT (-1.671565 54.973505)", "start-date": "1987-03-30", "listed-building": "1024957", "documentation-url": "https://historicengland.org.uk/listing/the-list/list-entry/1024957", "listed-building-grade": "II", "slug": "/listed-building/1024957", "entry-date": "2021-05-28"}}