{"type": "Feature", "geometry": {"type": "Point", "coordinates": [-0.782256, 50.72954]}, "properties": {"listed-building-grade": "II", "point": "POINT (-0.782256 50.729540)", "documentation-url": "https://historicengland.org.uk/listing/the-list/list-entry/1026296", "listed-building": "1026296", "start-date": "1986-01-28", "name": "FERN COTTAGE THE CORNER HOUSE", "slug": "/listed-building/1026296", "entry-date": "2021-05-28"}}