{"type": "Feature", "geometry": {"type": "Point", "coordinates": [-3.002781, 51.129173]}, "properties": {"listed-building-grade": "II", "listed-building": "1025050", "start-date": "1974-12-16", "name": "12 AND 14, QUEEN STREET", "point": "POINT (-3.002781 51.129173)", "documentation-url": "https://historicengland.org.uk/listing/the-list/list-entry/1025050", "slug": "/listed-building/1025050", "entry-date": "2021-05-28"}}