{"type": "Feature", "geometry": {"type": "Point", "coordinates": [0.09692, 50.973111]}, "properties": {"documentation-url": "https://historicengland.org.uk/listing/the-list/list-entry/1028121", "name": "THE MAIDEN'S HEAD HOTEL", "point": "POINT (0.096920 50.973111)", "start-date": "1953-11-26", "listed-building-grade": "II", "listed-building": "1028121", "slug": "/listed-building/1028121", "entry-date": "2021-05-28"}}