{"type": "Feature", "geometry": {"type": "Point", "coordinates": [1.35777, 52.144701]}, "properties": {"listed-building-grade": "II", "name": "THE GREYHOUND", "documentation-url": "https://historicengland.org.uk/listing/the-list/list-entry/1030268", "start-date": "1966-03-16", "listed-building": "1030268", "point": "POINT (1.357770 52.144701)", "slug": "/listed-building/1030268", "entry-date": "1988-08-15"}}