{"type": "Feature", "geometry": {"type": "Point", "coordinates": [0.353532, 50.858694]}, "properties": {"point": "POINT (0.353532 50.858694)", "listed-building-grade": "II", "name": "WARTLING PLACE", "start-date": "1981-08-12", "documentation-url": "https://historicengland.org.uk/listing/the-list/list-entry/1028512", "listed-building": "1028512", "slug": "/listed-building/1028512", "entry-date": "2021-05-28"}}