{"type": "Feature", "geometry": {"type": "Point", "coordinates": [-0.334037, 51.106314]}, "properties": {"start-date": "1980-11-28", "listed-building-grade": "II", "name": "BURCOMBE COTTAGE", "documentation-url": "https://historicengland.org.uk/listing/the-list/list-entry/1026893", "point": "POINT (-0.334037 51.106314)", "listed-building": "1026893", "slug": "/listed-building/1026893", "entry-date": "1982-01-28"}}