{"type": "Feature", "geometry": {"type": "Point", "coordinates": [-2.963176, 53.437784]}, "properties": {"name": "MAIN ENTRANCE TO ANFIELD CEMETERY", "listed-building": "1025284", "point": "POINT (-2.963176 53.437784)", "documentation-url": "https://historicengland.org.uk/listing/the-list/list-entry/1025284", "listed-building-grade": "II", "start-date": "1975-03-14", "slug": "/listed-building/1025284", "entry-date": "1985-06-19"}}