{"type": "Feature", "geometry": {"type": "Point", "coordinates": [-2.098697, 51.549137]}, "properties": {"listed-building-grade": "II", "documentation-url": "https://historicengland.org.uk/listing/the-list/list-entry/1022279", "point": "POINT (-2.098697 51.549137)", "listed-building": "1022279", "name": "THE DOWER HOUSE", "start-date": "1987-07-16", "slug": "/listed-building/1022279", "entry-date": "2021-05-28"}}