{"type": "Feature", "geometry": {"type": "Point", "coordinates": [-1.501185, 55.045759]}, "properties": {"start-date": "1986-02-19", "documentation-url": "https://historicengland.org.uk/listing/the-list/list-entry/1025397", "point": "POINT (-1.501185 55.045759)", "listed-building-grade": "II", "name": "EDWARD ECCLES CHURCH HALL AND WALLS AND PIERS IN FRONT", "listed-building": "1025397", "slug": "/listed-building/1025397", "entry-date": "2021-05-28"}}