{"type": "Feature", "geometry": {"type": "Point", "coordinates": [-1.905679, 51.541031]}, "properties": {"point": "POINT (-1.905679 51.541031)", "documentation-url": "https://historicengland.org.uk/listing/the-list/list-entry/1022714", "start-date": "1989-02-02", "listed-building": "1022714", "listed-building-grade": "II", "name": "K6 TELEPHONE KIOSK OUTSIDE NUMBER 152, HIGH STREET", "slug": "/listed-building/1022714", "entry-date": "2021-05-28"}}