{"type": "Feature", "geometry": {"type": "Point", "coordinates": [-2.792064, 53.209934]}, "properties": {"documentation-url": "https://historicengland.org.uk/listing/the-list/list-entry/1024989", "listed-building-grade": "II", "point": "POINT (-2.792064 53.209934)", "start-date": "1984-08-22", "name": "THE WHITE HOUSE", "listed-building": "1024989", "slug": "/listed-building/1024989", "entry-date": "2021-05-28"}}