{"type": "Feature", "geometry": {"type": "Point", "coordinates": [0.145225, 50.99201]}, "properties": {"point": "POINT (0.145225 50.992010)", "listed-building-grade": "II", "documentation-url": "https://historicengland.org.uk/listing/the-list/list-entry/1028475", "listed-building": "1028475", "start-date": "1982-12-31", "name": "THE OLD FARMHOUSE", "slug": "/listed-building/1028475", "entry-date": "2021-05-28"}}