{"type": "Feature", "geometry": {"type": "Point", "coordinates": [-2.185157, 51.433285]}, "properties": {"point": "POINT (-2.185157 51.433285)", "documentation-url": "https://historicengland.org.uk/listing/the-list/list-entry/1022049", "start-date": "1972-12-01", "name": "35 AND 37, HIGH STREET", "listed-building-grade": "II", "listed-building": "1022049", "slug": "/listed-building/1022049", "entry-date": "1986-08-01"}}