{"type": "Feature", "geometry": {"type": "Point", "coordinates": [-2.283827, 52.968345]}, "properties": {"listed-building": "1027845", "listed-building-grade": "II*", "point": "POINT (-2.283827 52.968345)", "start-date": "1966-11-17", "documentation-url": "https://historicengland.org.uk/listing/the-list/list-entry/1027845", "name": "Old stable block", "slug": "/listed-building/1027845", "entry-date": "1985-05-14"}}