{"type": "Feature", "geometry": {"type": "Point", "coordinates": [1.380065, 52.257685]}, "properties": {"point": "POINT (1.380065 52.257685)", "listed-building": "1030803", "start-date": "1951-10-25", "name": "THE WHITE HORSE", "listed-building-grade": "II", "documentation-url": "https://historicengland.org.uk/listing/the-list/list-entry/1030803", "slug": "/listed-building/1030803", "entry-date": "1984-12-21"}}