{"type": "Feature", "geometry": {"type": "Point", "coordinates": [-0.577257, 51.434556]}, "properties": {"name": "CASTLE HILL FARM DAIRY", "documentation-url": "https://historicengland.org.uk/listing/the-list/list-entry/1028963", "listed-building": "1028963", "start-date": "1985-06-05", "listed-building-grade": "II", "point": "POINT (-0.577257 51.434556)", "slug": "/listed-building/1028963", "entry-date": "1986-11-17"}}