{"type": "Feature", "geometry": {"type": "Point", "coordinates": [-1.580622, 52.02512]}, "properties": {"documentation-url": "https://historicengland.org.uk/listing/the-list/list-entry/1024322", "name": "CHERINGTON HOUSE", "listed-building": "1024322", "point": "POINT (-1.580622 52.025120)", "start-date": "1966-10-13", "listed-building-grade": "II", "slug": "/listed-building/1024322", "entry-date": "2021-05-28"}}