{"type": "Feature", "geometry": {"type": "Point", "coordinates": [1.343137, 52.222099]}, "properties": {"listed-building": "1030373", "name": "FLAMINGO", "point": "POINT (1.343137 52.222099)", "start-date": "1985-12-18", "listed-building-grade": "II", "documentation-url": "https://historicengland.org.uk/listing/the-list/list-entry/1030373", "slug": "/listed-building/1030373", "entry-date": "2021-05-28"}}