{"type": "Feature", "geometry": {"type": "Point", "coordinates": [1.312592, 52.094454]}, "properties": {"documentation-url": "https://historicengland.org.uk/listing/the-list/list-entry/1030996", "start-date": "1951-01-25", "listed-building": "1030996", "point": "POINT (1.312592 52.094454)", "name": "ANGEL INN", "listed-building-grade": "II*", "slug": "/listed-building/1030996", "entry-date": "2021-05-28"}}