{"type": "Feature", "geometry": {"type": "Point", "coordinates": [-2.557915, 52.704893]}, "properties": {"listed-building": "1030934", "name": "GARDEN WALLS ADJOINING NORTH WEST AND SOUTH EAST OF THE OLD VICARAGE", "listed-building-grade": "II", "point": "POINT (-2.557915 52.704893)", "documentation-url": "https://historicengland.org.uk/listing/the-list/list-entry/1030934", "start-date": "1983-04-08", "slug": "/listed-building/1030934", "entry-date": "2021-05-28"}}