{"type": "Feature", "geometry": {"type": "Point", "coordinates": [-1.699596, 51.631819]}, "properties": {"name": "GATEWAYS", "listed-building": "1023344", "listed-building-grade": "II", "documentation-url": "https://historicengland.org.uk/listing/the-list/list-entry/1023344", "start-date": "1979-09-20", "point": "POINT (-1.699596 51.631819)", "slug": "/listed-building/1023344", "entry-date": "2021-05-28"}}