{"type": "Feature", "geometry": {"type": "Point", "coordinates": [-1.599808, 54.978655]}, "properties": {"point": "POINT (-1.599808 54.978655)", "documentation-url": "https://historicengland.org.uk/listing/the-list/list-entry/1024747", "start-date": "1987-03-30", "name": "FORMER CHURCH OF ST JUDE, SHIELDFIELD", "listed-building": "1024747", "listed-building-grade": "II", "slug": "/listed-building/1024747", "entry-date": "2021-05-28"}}