{"type": "Feature", "geometry": {"type": "Point", "coordinates": [-2.120324, 51.416097]}, "properties": {"start-date": "1987-01-07", "point": "POINT (-2.120324 51.416097)", "documentation-url": "https://historicengland.org.uk/listing/the-list/list-entry/1022155", "name": "FEILDING MONUMENT IN CHURCHYARD EAST OF CHANCEL OF CHURCH OF ST CYRIAC", "listed-building-grade": "II", "listed-building": "1022155", "slug": "/listed-building/1022155", "entry-date": "2021-05-28"}}