{"type": "Feature", "geometry": {"type": "Point", "coordinates": [-2.252375, 51.414016]}, "properties": {"point": "POINT (-2.252375 51.414016)", "listed-building": "1022765", "documentation-url": "https://historicengland.org.uk/listing/the-list/list-entry/1022765", "listed-building-grade": "II", "start-date": "1985-07-24", "name": "LAMB COTTAGE PYE CORNER", "slug": "/listed-building/1022765", "entry-date": "2021-05-28"}}