{"type": "Feature", "geometry": {"type": "Point", "coordinates": [-2.030621, 51.455862]}, "properties": {"listed-building-grade": "II", "point": "POINT (-2.030621 51.455862)", "documentation-url": "https://historicengland.org.uk/listing/the-list/list-entry/1022421", "name": "TWO MONUMENTS IN CHURCHYARD ABOUT 9 METRES SOUTH OF TOWER OF CHURCH OF ST MARTIN", "start-date": "1987-11-25", "listed-building": "1022421", "slug": "/listed-building/1022421", "entry-date": "2021-05-28"}}