{"type": "Feature", "geometry": {"type": "Point", "coordinates": [-0.471282, 50.999322]}, "properties": {"listed-building-grade": "II", "point": "POINT (-0.471282 50.999322)", "listed-building": "1027110", "start-date": "1980-11-28", "name": "BARN TO SOUTH WEST OF SOUTHLANDS FARMHOUSE", "documentation-url": "https://historicengland.org.uk/listing/the-list/list-entry/1027110", "slug": "/listed-building/1027110", "entry-date": "2021-05-28"}}