{"type": "Feature", "geometry": {"type": "Point", "coordinates": [-0.718156, 50.90891]}, "properties": {"name": "Yew Cottage", "listed-building-grade": "II", "documentation-url": "https://historicengland.org.uk/listing/the-list/list-entry/1026370", "listed-building": "1026370", "start-date": "1986-01-28", "point": "POINT (-0.718156 50.908910)", "slug": "/listed-building/1026370", "entry-date": "2021-05-28"}}