{"type": "Feature", "geometry": {"type": "Point", "coordinates": [-0.696665, 50.982674]}, "properties": {"documentation-url": "https://historicengland.org.uk/listing/the-list/list-entry/1025971", "name": "AMBERSHAM BRIDGE", "start-date": "1959-06-18", "listed-building-grade": "II", "listed-building": "1025971", "point": "POINT (-0.696665 50.982674)", "slug": "/listed-building/1025971", "entry-date": "2021-05-28"}}