{"type": "Feature", "geometry": {"type": "Point", "coordinates": [-0.015715, 51.252501]}, "properties": {"start-date": "1984-11-19", "documentation-url": "https://historicengland.org.uk/listing/the-list/list-entry/1029703", "name": "THE NEST", "listed-building": "1029703", "listed-building-grade": "II", "point": "POINT (-0.015715 51.252501)", "slug": "/listed-building/1029703", "entry-date": "2021-05-28"}}