{"type": "Feature", "geometry": {"type": "Point", "coordinates": [-0.658406, 51.195681]}, "properties": {"name": "NORNEY GRANGE", "listed-building-grade": "II*", "point": "POINT (-0.658406 51.195681)", "documentation-url": "https://historicengland.org.uk/listing/the-list/list-entry/1029515", "start-date": "1985-05-21", "listed-building": "1029515", "slug": "/listed-building/1029515", "entry-date": "2021-05-28"}}