{"type": "Feature", "geometry": {"type": "Point", "coordinates": [-0.662709, 50.841957]}, "properties": {"documentation-url": "https://historicengland.org.uk/listing/the-list/list-entry/1027742", "point": "POINT (-0.662709 50.841957)", "listed-building-grade": "II", "name": "MERRYEND", "listed-building": "1027742", "start-date": "1984-09-20", "slug": "/listed-building/1027742", "entry-date": "2021-05-28"}}