{"type": "Feature", "geometry": {"type": "Point", "coordinates": [-0.116074, 51.023119]}, "properties": {"start-date": "1957-10-28", "listed-building-grade": "II", "documentation-url": "https://historicengland.org.uk/listing/the-list/list-entry/1025728", "name": "BORDE HILL PLACE", "listed-building": "1025728", "point": "POINT (-0.116074 51.023119)", "slug": "/listed-building/1025728", "entry-date": "2021-05-28"}}