{"type": "Feature", "geometry": {"type": "Point", "coordinates": [-0.539048, 50.909253]}, "properties": {"documentation-url": "https://historicengland.org.uk/listing/the-list/list-entry/1027463", "name": "WESTFIELD", "listed-building": "1027463", "start-date": "1980-05-09", "point": "POINT (-0.539048 50.909253)", "listed-building-grade": "II", "slug": "/listed-building/1027463", "entry-date": "2021-05-28"}}