{"type": "Feature", "geometry": {"type": "Point", "coordinates": [-0.815174, 50.819224]}, "properties": {"listed-building-grade": "II", "point": "POINT (-0.815174 50.819224)", "documentation-url": "https://historicengland.org.uk/listing/the-list/list-entry/1026479", "start-date": "1986-01-28", "name": "THE CROWN AND ANCHOR INN", "listed-building": "1026479", "slug": "/listed-building/1026479", "entry-date": "2021-05-28"}}