{"type": "Feature", "geometry": {"type": "Point", "coordinates": [0.229301, 51.034486]}, "properties": {"name": "HOLME PARK", "start-date": "1990-11-29", "listed-building-grade": "II", "listed-building": "1027962", "point": "POINT (0.229301 51.034486)", "documentation-url": "https://historicengland.org.uk/listing/the-list/list-entry/1027962", "slug": "/listed-building/1027962", "entry-date": "2021-05-28"}}