{"type": "Feature", "geometry": {"type": "Point", "coordinates": [1.300154, 52.232306]}, "properties": {"point": "POINT (1.300154 52.232306)", "start-date": "1984-11-19", "listed-building-grade": "II", "name": "THE LIMES", "documentation-url": "https://historicengland.org.uk/listing/the-list/list-entry/1030539", "listed-building": "1030539", "slug": "/listed-building/1030539", "entry-date": "2021-05-28"}}