{"type": "Feature", "geometry": {"type": "Point", "coordinates": [-1.765257, 54.977621]}, "properties": {"listed-building-grade": "II", "documentation-url": "https://historicengland.org.uk/listing/the-list/list-entry/1025161", "point": "POINT (-1.765257 54.977621)", "start-date": "1985-11-18", "name": "FENWICK TOMB ABOUT 24 METRES SOUTH AND 6 METRES EAST OF CHURCH OF HOLY CROSS", "listed-building": "1025161", "slug": "/listed-building/1025161", "entry-date": "2021-05-28"}}