{"type": "Feature", "geometry": {"type": "Point", "coordinates": [-1.88615, 52.246464]}, "properties": {"point": "POINT (-1.886150 52.246464)", "listed-building": "1024508", "listed-building-grade": "II", "start-date": "1985-10-23", "name": "POOL HOUSE", "documentation-url": "https://historicengland.org.uk/listing/the-list/list-entry/1024508", "slug": "/listed-building/1024508", "entry-date": "2021-05-28"}}