{"type": "Feature", "geometry": {"type": "Point", "coordinates": [-1.49174, 54.942441]}, "properties": {"listed-building-grade": "II", "documentation-url": "https://historicengland.org.uk/listing/the-list/list-entry/1025230", "start-date": "1985-02-26", "listed-building": "1025230", "name": "STABLES AT SCOTS HOUSE", "point": "POINT (-1.491740 54.942441)", "slug": "/listed-building/1025230", "entry-date": "2021-05-28"}}