{"type": "Feature", "geometry": {"type": "Point", "coordinates": [-0.441341, 51.265903]}, "properties": {"name": "Dog kennel to south east of West Horsley Place", "point": "POINT (-0.441341 51.265903)", "documentation-url": "https://historicengland.org.uk/listing/the-list/list-entry/1029319", "listed-building-grade": "II", "start-date": "1985-11-25", "listed-building": "1029319", "slug": "/listed-building/1029319", "entry-date": "2021-05-28"}}