{"type": "Feature", "geometry": {"type": "Point", "coordinates": [-2.208187, 51.334018]}, "properties": {"start-date": "1976-11-26", "documentation-url": "https://historicengland.org.uk/listing/the-list/list-entry/1021621", "listed-building": "1021621", "listed-building-grade": "II", "point": "POINT (-2.208187 51.334018)", "name": "BRIDGE TO EAST OF AQUEDUCT OVER RAILWAY", "slug": "/listed-building/1021621", "entry-date": "2021-05-28"}}