{"type": "Feature", "geometry": {"type": "Point", "coordinates": [-0.428409, 51.357948]}, "properties": {"start-date": "1984-11-16", "point": "POINT (-0.428409 51.357948)", "listed-building-grade": "II", "documentation-url": "https://historicengland.org.uk/listing/the-list/list-entry/1030253", "listed-building": "1030253", "name": "ENTRANCE PIERS, GATES AND RAILINGS TO WHITELY VILLAGE", "slug": "/listed-building/1030253", "entry-date": "2021-05-28"}}