{"type": "Feature", "geometry": {"type": "Point", "coordinates": [-2.258672, 51.439026]}, "properties": {"listed-building-grade": "II", "name": "UNIDENTIFIED TOMB IN CHURCHYARD CIRCA 8 METRES EAST OF CHANCEL SOUTH EAST CORNER OF CHURCH OF ST JOHN", "start-date": "1985-12-09", "point": "POINT (-2.258672 51.439026)", "documentation-url": "https://historicengland.org.uk/listing/the-list/list-entry/1022926", "listed-building": "1022926", "slug": "/listed-building/1022926", "entry-date": "2021-05-28"}}