{"type": "Feature", "geometry": {"type": "Point", "coordinates": [-0.559166, 51.20353]}, "properties": {"documentation-url": "https://historicengland.org.uk/listing/the-list/list-entry/1029429", "start-date": "1986-08-27", "point": "POINT (-0.559166 51.203530)", "listed-building": "1029429", "name": "BARN AT CHINTHURST FARM", "listed-building-grade": "II", "slug": "/listed-building/1029429", "entry-date": "2021-05-28"}}