{"type": "Feature", "geometry": {"type": "Point", "coordinates": [0.059388, 50.942895]}, "properties": {"start-date": "1990-12-06", "name": "ROCKS FARM", "documentation-url": "https://historicengland.org.uk/listing/the-list/list-entry/1027964", "point": "POINT (0.059388 50.942895)", "listed-building-grade": "II", "listed-building": "1027964", "slug": "/listed-building/1027964", "entry-date": "2021-05-28"}}