{"type": "Feature", "geometry": {"type": "Point", "coordinates": [-0.251026, 51.244704]}, "properties": {"point": "POINT (-0.251026 51.244704)", "documentation-url": "https://historicengland.org.uk/listing/the-list/list-entry/1028793", "listed-building-grade": "II", "start-date": "1966-11-11", "name": "APPLECROFT LITTLE MALTINGS COTTAGE", "listed-building": "1028793", "slug": "/listed-building/1028793", "entry-date": "1987-09-29"}}