{"type": "Feature", "geometry": {"type": "Point", "coordinates": [-0.894693, 50.927154]}, "properties": {"listed-building": "1026421", "point": "POINT (-0.894693 50.927154)", "name": "THE PARISH CHURCH OF ST MARY", "listed-building-grade": "II*", "start-date": "1958-06-05", "documentation-url": "https://historicengland.org.uk/listing/the-list/list-entry/1026421", "slug": "/listed-building/1026421", "entry-date": "2021-05-28"}}