{"type": "Feature", "geometry": {"type": "Point", "coordinates": [1.446498, 52.143021]}, "properties": {"name": "NORTH HOUSE", "documentation-url": "https://historicengland.org.uk/listing/the-list/list-entry/1030861", "start-date": "1984-05-02", "point": "POINT (1.446498 52.143021)", "listed-building": "1030861", "listed-building-grade": "II", "slug": "/listed-building/1030861", "entry-date": "2021-05-28"}}