{"type": "Feature", "geometry": {"type": "Point", "coordinates": [-1.850566, 52.314175]}, "properties": {"listed-building": "1024504", "start-date": "1985-10-23", "documentation-url": "https://historicengland.org.uk/listing/the-list/list-entry/1024504", "point": "POINT (-1.850566 52.314175)", "name": "STABLE APPROXIMATELY 100 METRES SOUTH WEST OF OLDBERROW COURT", "listed-building-grade": "II", "slug": "/listed-building/1024504", "entry-date": "2021-05-28"}}