{"type": "Feature", "geometry": {"type": "Point", "coordinates": [-1.801284, 51.069049]}, "properties": {"documentation-url": "https://historicengland.org.uk/listing/the-list/list-entry/1023635", "listed-building-grade": "II", "point": "POINT (-1.801284 51.069049)", "listed-building": "1023635", "start-date": "1972-10-12", "name": "THE POPLARS", "slug": "/listed-building/1023635", "entry-date": "2021-05-28"}}