{"type": "Feature", "geometry": {"type": "Point", "coordinates": [-0.84507, 50.76572]}, "properties": {"listed-building-grade": "II", "start-date": "1986-01-28", "point": "POINT (-0.845070 50.765720)", "listed-building": "1026362", "name": "Earnley Place", "documentation-url": "https://historicengland.org.uk/listing/the-list/list-entry/1026362", "slug": "/listed-building/1026362", "entry-date": "2021-05-28"}}