{"type": "Feature", "geometry": {"type": "Point", "coordinates": [-1.512322, 54.843165]}, "properties": {"start-date": "1985-07-15", "documentation-url": "https://historicengland.org.uk/listing/the-list/list-entry/1025408", "point": "POINT (-1.512322 54.843165)", "name": "ICE HOUSE TO NORTH OF MORTON HOUSE", "listed-building": "1025408", "listed-building-grade": "II", "slug": "/listed-building/1025408", "entry-date": "2021-05-28"}}