{"type": "Feature", "geometry": {"type": "Point", "coordinates": [0.728681, 52.249993]}, "properties": {"name": "ST NICHOLAS", "documentation-url": "https://historicengland.org.uk/listing/the-list/list-entry/1022540", "start-date": "1952-08-07", "point": "POINT (0.728681 52.249993)", "listed-building-grade": "II*", "listed-building": "1022540", "slug": "/listed-building/1022540", "entry-date": "1997-10-30"}}