{"type": "Feature", "geometry": {"type": "Point", "coordinates": [-2.214619, 51.595207]}, "properties": {"listed-building": "1023253", "documentation-url": "https://historicengland.org.uk/listing/the-list/list-entry/1023253", "name": "BARN TO THE WEST OF BYAM'S FARMHOUSE", "start-date": "1951-12-12", "listed-building-grade": "II", "point": "POINT (-2.214619 51.595207)", "slug": "/listed-building/1023253", "entry-date": "2021-05-28"}}