{"type": "Feature", "geometry": {"type": "Point", "coordinates": [-2.217072, 51.480004]}, "properties": {"start-date": "1960-12-20", "listed-building": "1023022", "listed-building-grade": "II", "documentation-url": "https://historicengland.org.uk/listing/the-list/list-entry/1023022", "name": "UPPER LONG DEAN MILL", "point": "POINT (-2.217072 51.480004)", "slug": "/listed-building/1023022", "entry-date": "1985-12-09"}}