{"type": "Feature", "geometry": {"type": "Point", "coordinates": [-0.407501, 50.868224]}, "properties": {"point": "POINT (-0.407501 50.868224)", "listed-building-grade": "II", "documentation-url": "https://historicengland.org.uk/listing/the-list/list-entry/1027629", "listed-building": "1027629", "start-date": "1954-10-12", "name": "THE GUN INN", "slug": "/listed-building/1027629", "entry-date": "2021-05-28"}}