{"type": "Feature", "geometry": {"type": "Point", "coordinates": [-1.399069, 52.12673]}, "properties": {"documentation-url": "https://historicengland.org.uk/listing/the-list/list-entry/1024140", "listed-building": "1024140", "listed-building-grade": "II", "point": "POINT (-1.399069 52.126730)", "start-date": "1967-05-30", "name": "THE OLD RECTORY", "slug": "/listed-building/1024140", "entry-date": "1987-04-08"}}