{"type": "Feature", "geometry": {"type": "Point", "coordinates": [-0.332473, 51.231858]}, "properties": {"documentation-url": "https://historicengland.org.uk/listing/the-list/list-entry/1028866", "point": "POINT (-0.332473 51.231858)", "start-date": "1973-06-11", "listed-building": "1028866", "listed-building-grade": "II", "name": "THE WHEATSHEAF PUBLIC HOUSE", "slug": "/listed-building/1028866", "entry-date": "2021-05-28"}}