{"type": "Feature", "geometry": {"type": "Point", "coordinates": [-0.434789, 50.933496]}, "properties": {"documentation-url": "https://historicengland.org.uk/listing/the-list/list-entry/1027205", "start-date": "1980-05-09", "name": "GREEN DENE FARMHOUSE", "listed-building-grade": "II", "listed-building": "1027205", "point": "POINT (-0.434789 50.933496)", "slug": "/listed-building/1027205", "entry-date": "2021-05-28"}}