{"type": "Feature", "geometry": {"type": "Point", "coordinates": [-0.404543, 51.329906]}, "properties": {"listed-building": "1030161", "start-date": "1953-08-14", "point": "POINT (-0.404543 51.329906)", "name": "LEIGH HILL FARM HOUSE", "documentation-url": "https://historicengland.org.uk/listing/the-list/list-entry/1030161", "listed-building-grade": "II", "slug": "/listed-building/1030161", "entry-date": "1984-11-16"}}