{"type": "Feature", "geometry": {"type": "Point", "coordinates": [-1.763527, 54.996747]}, "properties": {"name": "FORMER VALVE HOUSE", "point": "POINT (-1.763527 54.996747)", "start-date": "1987-03-30", "documentation-url": "https://historicengland.org.uk/listing/the-list/list-entry/1024975", "listed-building-grade": "II", "listed-building": "1024975", "slug": "/listed-building/1024975", "entry-date": "2021-05-28"}}