{"type": "Feature", "geometry": {"type": "Point", "coordinates": [0.330918, 51.045895]}, "properties": {"documentation-url": "https://historicengland.org.uk/listing/the-list/list-entry/1028085", "name": "STREAM FARMHOUSE", "point": "POINT (0.330918 51.045895)", "listed-building-grade": "II", "listed-building": "1028085", "start-date": "1982-12-31", "slug": "/listed-building/1028085", "entry-date": "2021-05-28"}}