{"type": "Feature", "geometry": {"type": "Point", "coordinates": [-2.316523, 51.345515]}, "properties": {"start-date": "1988-06-14", "documentation-url": "https://historicengland.org.uk/listing/the-list/list-entry/1021823", "point": "POINT (-2.316523 51.345515)", "listed-building": "1021823", "name": "LYNTON COTTAGE", "listed-building-grade": "II", "slug": "/listed-building/1021823", "entry-date": "2021-05-28"}}