{"type": "Feature", "geometry": {"type": "Point", "coordinates": [-0.641736, 51.257749]}, "properties": {"start-date": "1967-06-14", "listed-building": "1029579", "point": "POINT (-0.641736 51.257749)", "documentation-url": "https://historicengland.org.uk/listing/the-list/list-entry/1029579", "listed-building-grade": "II", "name": "COMPTON'S FARM HOUSE", "slug": "/listed-building/1029579", "entry-date": "2021-05-28"}}