{"type": "Feature", "geometry": {"type": "Point", "coordinates": [-0.62884, 51.337229]}, "properties": {"documentation-url": "https://historicengland.org.uk/listing/the-list/list-entry/1030000", "point": "POINT (-0.628840 51.337229)", "listed-building-grade": "II", "name": "HATCHGATE FARM HOUSE", "start-date": "1984-07-19", "listed-building": "1030000", "slug": "/listed-building/1030000", "entry-date": "2021-05-28"}}