{"type": "Feature", "geometry": {"type": "Point", "coordinates": [1.665688, 52.314221]}, "properties": {"name": "THE BELL HOTEL", "start-date": "1984-01-16", "documentation-url": "https://historicengland.org.uk/listing/the-list/list-entry/1030683", "listed-building-grade": "II", "listed-building": "1030683", "point": "POINT (1.665688 52.314221)", "slug": "/listed-building/1030683", "entry-date": "2021-05-28"}}