{"type": "Feature", "geometry": {"type": "Point", "coordinates": [-1.4251, 55.017971]}, "properties": {"name": "HOLLY HOUSE AND WALLS AND PIERS IN FRONT", "listed-building-grade": "II", "listed-building": "1025371", "point": "POINT (-1.425100 55.017971)", "start-date": "1986-02-19", "documentation-url": "https://historicengland.org.uk/listing/the-list/list-entry/1025371", "slug": "/listed-building/1025371", "entry-date": "2021-05-28"}}