{"type": "Feature", "geometry": {"type": "Point", "coordinates": [-0.258561, 51.217472]}, "properties": {"listed-building-grade": "II", "listed-building": "1028780", "documentation-url": "https://historicengland.org.uk/listing/the-list/list-entry/1028780", "start-date": "1987-09-29", "name": "ABBOTS", "point": "POINT (-0.258561 51.217472)", "slug": "/listed-building/1028780", "entry-date": "2021-05-28"}}