{"type": "Feature", "geometry": {"type": "Point", "coordinates": [-2.200892, 51.330521]}, "properties": {"listed-building": "1021561", "listed-building-grade": "II", "start-date": "1976-11-26", "documentation-url": "https://historicengland.org.uk/listing/the-list/list-entry/1021561", "name": "GATE PIERS AND SCREEN WALL AND GATES TO CEMETERY", "point": "POINT (-2.200892 51.330521)", "slug": "/listed-building/1021561", "entry-date": "2021-05-28"}}