{"type": "Feature", "geometry": {"type": "Point", "coordinates": [-0.652167, 50.791268]}, "properties": {"name": "THE BARN", "documentation-url": "https://historicengland.org.uk/listing/the-list/list-entry/1027783", "listed-building-grade": "II", "point": "POINT (-0.652167 50.791268)", "listed-building": "1027783", "start-date": "1975-11-07", "slug": "/listed-building/1027783", "entry-date": "2021-05-28"}}