{"type": "Feature", "geometry": {"type": "Point", "coordinates": [-0.330444, 51.232495]}, "properties": {"start-date": "1973-06-11", "listed-building-grade": "II", "listed-building": "1028862", "documentation-url": "https://historicengland.org.uk/listing/the-list/list-entry/1028862", "point": "POINT (-0.330444 51.232495)", "name": "GRANITE SETTS ALONG THE EDGE OF THE HIGH STREET FROM NOS 108 TO 140", "slug": "/listed-building/1028862", "entry-date": "2021-05-28"}}