{"type": "Feature", "geometry": {"type": "Point", "coordinates": [-0.404089, 50.997147]}, "properties": {"documentation-url": "https://historicengland.org.uk/listing/the-list/list-entry/1026962", "point": "POINT (-0.404089 50.997147)", "start-date": "1980-11-28", "listed-building-grade": "II", "listed-building": "1026962", "name": "BAILEY'S FARMHOUSE", "slug": "/listed-building/1026962", "entry-date": "2021-05-28"}}