{"type": "Feature", "geometry": {"type": "Point", "coordinates": [1.525442, 52.262571]}, "properties": {"name": "BEVERICHE MANOR FARMHOUSE", "listed-building": "1030593", "documentation-url": "https://historicengland.org.uk/listing/the-list/list-entry/1030593", "start-date": "1984-07-27", "point": "POINT (1.525442 52.262571)", "listed-building-grade": "II", "slug": "/listed-building/1030593", "entry-date": "2021-05-28"}}