{"type": "Feature", "geometry": {"type": "Point", "coordinates": [0.888237, 52.354706]}, "properties": {"documentation-url": "https://historicengland.org.uk/listing/the-list/list-entry/1031170", "start-date": "1985-01-25", "point": "POINT (0.888237 52.354706)", "name": "MONUMENT 6.5 METRES TO THE EAST OF THE PORCH AND ONE METRE SOUTH OF THE NAVE OF THE CHURCH OF ST ANDREW", "listed-building": "1031170", "listed-building-grade": "II", "slug": "/listed-building/1031170", "entry-date": "2021-05-28"}}