{"type": "Feature", "geometry": {"type": "Point", "coordinates": [-0.06228, 51.244882]}, "properties": {"start-date": "1984-11-19", "listed-building": "1029803", "name": "THE PEST HOUSE", "documentation-url": "https://historicengland.org.uk/listing/the-list/list-entry/1029803", "point": "POINT (-0.062280 51.244882)", "listed-building-grade": "II", "slug": "/listed-building/1029803", "entry-date": "2021-05-28"}}