{"type": "Feature", "geometry": {"type": "Point", "coordinates": [-0.611136, 51.259839]}, "properties": {"listed-building-grade": "II", "listed-building": "1029580", "documentation-url": "https://historicengland.org.uk/listing/the-list/list-entry/1029580", "name": "FROSBURY FARM HOUSE", "start-date": "1967-06-14", "point": "POINT (-0.611136 51.259839)", "slug": "/listed-building/1029580", "entry-date": "2021-05-28"}}