{"type": "Feature", "geometry": {"type": "Point", "coordinates": [0.10608, 51.098009]}, "properties": {"listed-building-grade": "II", "point": "POINT (0.106080 51.098009)", "listed-building": "1028275", "documentation-url": "https://historicengland.org.uk/listing/the-list/list-entry/1028275", "name": "NEWTONS TERRACE", "start-date": "1982-12-31", "slug": "/listed-building/1028275", "entry-date": "2021-05-28"}}