{"type": "Feature", "geometry": {"type": "Point", "coordinates": [-0.345356, 51.034927]}, "properties": {"listed-building": "1026822", "point": "POINT (-0.345356 51.034927)", "start-date": "1993-02-18", "listed-building-grade": "II", "name": "WELLERS FARM", "documentation-url": "https://historicengland.org.uk/listing/the-list/list-entry/1026822", "slug": "/listed-building/1026822", "entry-date": "2021-05-28"}}