{"type": "Feature", "geometry": {"type": "Point", "coordinates": [-0.574162, 51.234262]}, "properties": {"name": "BRITANNIC ASSURANCE", "documentation-url": "https://historicengland.org.uk/listing/the-list/list-entry/1029223", "start-date": "1953-05-01", "point": "POINT (-0.574162 51.234262)", "listed-building": "1029223", "listed-building-grade": "II", "slug": "/listed-building/1029223", "entry-date": "2021-05-28"}}