{"type": "Feature", "geometry": {"type": "Point", "coordinates": [-1.675672, 51.550233]}, "properties": {"point": "POINT (-1.675672 51.550233)", "start-date": "1979-09-20", "name": "THE GROVE", "listed-building": "1023279", "documentation-url": "https://historicengland.org.uk/listing/the-list/list-entry/1023279", "listed-building-grade": "II", "slug": "/listed-building/1023279", "entry-date": "2021-05-28"}}