{"type": "Feature", "geometry": {"type": "Point", "coordinates": [1.556165, 52.325474]}, "properties": {"documentation-url": "https://historicengland.org.uk/listing/the-list/list-entry/1030620", "listed-building": "1030620", "listed-building-grade": "II", "point": "POINT (1.556165 52.325474)", "name": "OAKWOOD", "start-date": "1984-07-27", "slug": "/listed-building/1030620", "entry-date": "2021-05-28"}}