{"type": "Feature", "geometry": {"type": "Point", "coordinates": [-2.139743, 51.493466]}, "properties": {"listed-building": "1022339", "documentation-url": "https://historicengland.org.uk/listing/the-list/list-entry/1022339", "name": "Group of three chest tombs standing on the south side of the footpath to the south of the south aisle of the Church of St Michael", "listed-building-grade": "II", "point": "POINT (-2.139743 51.493466)", "start-date": "1988-02-29", "slug": "/listed-building/1022339", "entry-date": "2013-08-06"}}