{"type": "Feature", "geometry": {"type": "Point", "coordinates": [-0.536399, 50.909094]}, "properties": {"point": "POINT (-0.536399 50.909094)", "start-date": "1980-05-09", "documentation-url": "https://historicengland.org.uk/listing/the-list/list-entry/1027478", "listed-building": "1027478", "name": "BARN TO SOUTH WEST OF IVY COTTAGE", "listed-building-grade": "II", "slug": "/listed-building/1027478", "entry-date": "2021-05-28"}}