{"type": "Feature", "geometry": {"type": "Point", "coordinates": [-1.511556, 54.842611]}, "properties": {"documentation-url": "https://historicengland.org.uk/listing/the-list/list-entry/1025407", "name": "MORTON HOUSE", "point": "POINT (-1.511556 54.842611)", "listed-building-grade": "II", "start-date": "1950-04-26", "listed-building": "1025407", "slug": "/listed-building/1025407", "entry-date": "2021-05-28"}}