{"type": "Feature", "geometry": {"type": "Point", "coordinates": [-0.427094, 51.05602]}, "properties": {"name": "LUTWICKE CORNER COTTAGE", "listed-building": "1026905", "point": "POINT (-0.427094 51.056020)", "listed-building-grade": "II", "documentation-url": "https://historicengland.org.uk/listing/the-list/list-entry/1026905", "start-date": "1980-11-28", "slug": "/listed-building/1026905", "entry-date": "2021-05-28"}}