{"type": "Feature", "geometry": {"type": "Point", "coordinates": [-1.74216, 51.045014]}, "properties": {"documentation-url": "https://historicengland.org.uk/listing/the-list/list-entry/1023785", "start-date": "1985-03-28", "name": "OLD TIMBERS", "point": "POINT (-1.742160 51.045014)", "listed-building-grade": "II", "listed-building": "1023785", "slug": "/listed-building/1023785", "entry-date": "2021-05-28"}}