{"type": "Feature", "geometry": {"type": "Point", "coordinates": [-0.825584, 52.305071]}, "properties": {"documentation-url": "https://historicengland.org.uk/listing/the-list/list-entry/1025896", "point": "POINT (-0.825584 52.305071)", "listed-building": "1025896", "name": "RECTORY FARMHOUSE", "start-date": "1985-07-19", "listed-building-grade": "II", "slug": "/listed-building/1025896", "entry-date": "2021-05-28"}}