{"type": "Feature", "geometry": {"type": "Point", "coordinates": [-0.34734, 51.153473]}, "properties": {"listed-building-grade": "II*", "name": "CHURCH OF ST MARGARET", "listed-building": "1028694", "point": "POINT (-0.347340 51.153473)", "documentation-url": "https://historicengland.org.uk/listing/the-list/list-entry/1028694", "start-date": "1966-11-11", "slug": "/listed-building/1028694", "entry-date": "2021-05-28"}}