{"type": "Feature", "geometry": {"type": "Point", "coordinates": [-0.391554, 51.274249]}, "properties": {"point": "POINT (-0.391554 51.274249)", "listed-building-grade": "II*", "listed-building": "1028606", "name": "CHURCH OF ALL SAINTS", "documentation-url": "https://historicengland.org.uk/listing/the-list/list-entry/1028606", "start-date": "1951-09-07", "slug": "/listed-building/1028606", "entry-date": "1990-08-24"}}