{"type": "Feature", "geometry": {"type": "Point", "coordinates": [0.260025, 51.110369]}, "properties": {"point": "POINT (0.260025 51.110369)", "listed-building-grade": "II", "name": "1 and 2, Yew Tree Cottage", "listed-building": "1028337", "documentation-url": "https://historicengland.org.uk/listing/the-list/list-entry/1028337", "start-date": "1982-12-31", "slug": "/listed-building/1028337", "entry-date": "1983-09-08"}}