{"type": "Feature", "geometry": {"type": "Point", "coordinates": [-0.0729, 50.995516]}, "properties": {"listed-building-grade": "II", "point": "POINT (-0.072900 50.995516)", "start-date": "1987-12-11", "listed-building": "1025470", "name": "OLDFIELD", "documentation-url": "https://historicengland.org.uk/listing/the-list/list-entry/1025470", "slug": "/listed-building/1025470", "entry-date": "2021-05-28"}}