{"type": "Feature", "geometry": {"type": "Point", "coordinates": [0.035395, 51.248764]}, "properties": {"listed-building": "1029765", "documentation-url": "https://historicengland.org.uk/listing/the-list/list-entry/1029765", "point": "POINT (0.035395 51.248764)", "name": "LOMBARTON COTTAGE", "start-date": "1984-11-19", "listed-building-grade": "II", "slug": "/listed-building/1029765", "entry-date": "2021-05-28"}}