{"type": "Feature", "geometry": {"type": "Point", "coordinates": [-1.391736, 52.165971]}, "properties": {"listed-building-grade": "II", "start-date": "1987-04-08", "documentation-url": "https://historicengland.org.uk/listing/the-list/list-entry/1024229", "listed-building": "1024229", "point": "POINT (-1.391736 52.165971)", "name": "2 HEADSTONES APPROXIMATELY 20 METRES NORTH OF NORTH EAST CORNER OF NORTH AISLE OF CHURCH OF ST PETER AND ST CLARE", "slug": "/listed-building/1024229", "entry-date": "2021-05-28"}}