{"type": "Feature", "geometry": {"type": "Point", "coordinates": [-2.204493, 51.577701]}, "properties": {"name": "MILESTONE", "documentation-url": "https://historicengland.org.uk/listing/the-list/list-entry/1023247", "listed-building": "1023247", "point": "POINT (-2.204493 51.577701)", "listed-building-grade": "II", "start-date": "1986-12-03", "slug": "/listed-building/1023247", "entry-date": "2021-05-28"}}