{"type": "Feature", "geometry": {"type": "Point", "coordinates": [-1.952212, 51.45564]}, "properties": {"start-date": "1987-11-25", "listed-building": "1022480", "documentation-url": "https://historicengland.org.uk/listing/the-list/list-entry/1022480", "listed-building-grade": "II", "point": "POINT (-1.952212 51.455640)", "name": "ALLEY COTTAGE", "slug": "/listed-building/1022480", "entry-date": "2021-05-28"}}