{"type": "Feature", "geometry": {"type": "Point", "coordinates": [0.028334, 51.232231]}, "properties": {"listed-building": "1029747", "listed-building-grade": "II", "start-date": "1984-11-19", "name": "BARN AND GRANARY 35 YARDS WEST OF STOCKENDEN", "point": "POINT (0.028334 51.232231)", "documentation-url": "https://historicengland.org.uk/listing/the-list/list-entry/1029747", "slug": "/listed-building/1029747", "entry-date": "2021-05-28"}}