{"type": "Feature", "geometry": {"type": "Point", "coordinates": [-0.417143, 51.411427]}, "properties": {"start-date": "1969-12-09", "name": "THE MANOR COTTAGE", "documentation-url": "https://historicengland.org.uk/listing/the-list/list-entry/1029668", "point": "POINT (-0.417143 51.411427)", "listed-building-grade": "II", "listed-building": "1029668", "slug": "/listed-building/1029668", "entry-date": "2021-05-28"}}