{"type": "Feature", "geometry": {"type": "Point", "coordinates": [-0.721338, 51.048695]}, "properties": {"documentation-url": "https://historicengland.org.uk/listing/the-list/list-entry/1025992", "listed-building": "1025992", "listed-building-grade": "II", "start-date": "1987-11-26", "point": "POINT (-0.721338 51.048695)", "name": "PARK VIEW COTTAGE", "slug": "/listed-building/1025992", "entry-date": "2021-05-28"}}