{"type": "Feature", "geometry": {"type": "Point", "coordinates": [-0.356129, 51.175728]}, "properties": {"listed-building": "1028760", "listed-building-grade": "II", "start-date": "1987-09-29", "documentation-url": "https://historicengland.org.uk/listing/the-list/list-entry/1028760", "name": "HIGHLAND COTTAGE", "point": "POINT (-0.356129 51.175728)", "slug": "/listed-building/1028760", "entry-date": "2021-05-28"}}