{"type": "Feature", "geometry": {"type": "Point", "coordinates": [-0.401855, 51.272385]}, "properties": {"listed-building-grade": "II", "point": "POINT (-0.401855 51.272385)", "start-date": "1967-06-14", "documentation-url": "https://historicengland.org.uk/listing/the-list/list-entry/1029394", "listed-building": "1029394", "name": "OLD WESTMOOR COTTAGE", "slug": "/listed-building/1029394", "entry-date": "2021-05-28"}}