{"type": "Feature", "geometry": {"type": "Point", "coordinates": [-1.80181, 51.066078]}, "properties": {"documentation-url": "https://historicengland.org.uk/listing/the-list/list-entry/1023626", "listed-building-grade": "II", "start-date": "1972-10-12", "point": "POINT (-1.801810 51.066078)", "name": "GARDEN HOUSE OF NO 60 (NORTH CANONRY)", "listed-building": "1023626", "slug": "/listed-building/1023626", "entry-date": "2021-05-28"}}