{"type": "Feature", "geometry": {"type": "Point", "coordinates": [-2.121634, 51.415703]}, "properties": {"listed-building-grade": "II", "name": "16 AND 17, EAST STREET", "documentation-url": "https://historicengland.org.uk/listing/the-list/list-entry/1022159", "start-date": "1960-12-20", "listed-building": "1022159", "point": "POINT (-2.121634 51.415703)", "slug": "/listed-building/1022159", "entry-date": "2021-05-28"}}