{"type": "Feature", "geometry": {"type": "Point", "coordinates": [-0.169148, 50.986524]}, "properties": {"listed-building": "1025726", "name": "ROCK COTTAGE", "listed-building-grade": "II", "start-date": "1983-05-11", "point": "POINT (-0.169148 50.986524)", "documentation-url": "https://historicengland.org.uk/listing/the-list/list-entry/1025726", "slug": "/listed-building/1025726", "entry-date": "2021-05-28"}}