{"type": "Feature", "geometry": {"type": "Point", "coordinates": [-0.464706, 51.220173]}, "properties": {"start-date": "1967-06-14", "point": "POINT (-0.464706 51.220173)", "documentation-url": "https://historicengland.org.uk/listing/the-list/list-entry/1029452", "name": "BODRYN COTTAGE AND FORGE COTTAGE", "listed-building-grade": "II", "listed-building": "1029452", "slug": "/listed-building/1029452", "entry-date": "2021-05-28"}}