{"type": "Feature", "geometry": {"type": "Point", "coordinates": [-2.244896, 51.313937]}, "properties": {"listed-building-grade": "II", "name": "ARNOLDS HILL FARMHOUSE", "start-date": "1988-06-14", "listed-building": "1021901", "point": "POINT (-2.244896 51.313937)", "documentation-url": "https://historicengland.org.uk/listing/the-list/list-entry/1021901", "slug": "/listed-building/1021901", "entry-date": "2021-05-28"}}