{"type": "Feature", "geometry": {"type": "Point", "coordinates": [1.225256, 52.096292]}, "properties": {"documentation-url": "https://historicengland.org.uk/listing/the-list/list-entry/1030504", "start-date": "1966-03-16", "listed-building-grade": "II*", "listed-building": "1030504", "name": "CHURCH OF ST BOTOLPH", "point": "POINT (1.225256 52.096292)", "slug": "/listed-building/1030504", "entry-date": "2021-05-28"}}