{"type": "Feature", "geometry": {"type": "Point", "coordinates": [0.801332, 52.356008]}, "properties": {"point": "POINT (0.801332 52.356008)", "listed-building": "1031328", "start-date": "1983-12-14", "name": "FIELD COTTAGE", "documentation-url": "https://historicengland.org.uk/listing/the-list/list-entry/1031328", "listed-building-grade": "II", "slug": "/listed-building/1031328", "entry-date": "2021-05-28"}}