{"type": "Feature", "geometry": {"type": "Point", "coordinates": [-0.273665, 50.832774]}, "properties": {"start-date": "1972-09-29", "listed-building": "1027864", "listed-building-grade": "II", "point": "POINT (-0.273665 50.832774)", "documentation-url": "https://historicengland.org.uk/listing/the-list/list-entry/1027864", "name": "CHURCH HOUSE", "slug": "/listed-building/1027864", "entry-date": "2021-05-28"}}