{"type": "Feature", "geometry": {"type": "Point", "coordinates": [-1.752951, 51.525317]}, "properties": {"listed-building-grade": "II", "documentation-url": "https://historicengland.org.uk/listing/the-list/list-entry/1023323", "start-date": "1979-09-20", "listed-building": "1023323", "point": "POINT (-1.752951 51.525317)", "name": "BARN TO WEST OF NO 34", "slug": "/listed-building/1023323", "entry-date": "2021-05-28"}}