{"type": "Feature", "geometry": {"type": "Point", "coordinates": [-0.374524, 51.227873]}, "properties": {"point": "POINT (-0.374524 51.227873)", "documentation-url": "https://historicengland.org.uk/listing/the-list/list-entry/1028907", "listed-building": "1028907", "start-date": "1973-06-11", "listed-building-grade": "II", "name": "STOWE MARIES", "slug": "/listed-building/1028907", "entry-date": "2021-05-28"}}