{"type": "Feature", "geometry": {"type": "Point", "coordinates": [-1.39381, 52.166851]}, "properties": {"name": "WOAD HOUSE", "documentation-url": "https://historicengland.org.uk/listing/the-list/list-entry/1024223", "listed-building": "1024223", "start-date": "1967-05-30", "listed-building-grade": "II*", "point": "POINT (-1.393810 52.166851)", "slug": "/listed-building/1024223", "entry-date": "1987-04-08"}}