{"type": "Feature", "geometry": {"type": "Point", "coordinates": [-0.153613, 50.910826]}, "properties": {"documentation-url": "https://historicengland.org.uk/listing/the-list/list-entry/1025724", "point": "POINT (-0.153613 50.910826)", "listed-building": "1025724", "name": "HILLSIDE", "listed-building-grade": "II", "start-date": "1983-05-11", "slug": "/listed-building/1025724", "entry-date": "2021-05-28"}}