{"type": "Feature", "geometry": {"type": "Point", "coordinates": [-0.331924, 51.392685]}, "properties": {"documentation-url": "https://historicengland.org.uk/listing/the-list/list-entry/1030196", "listed-building": "1030196", "point": "POINT (-0.331924 51.392685)", "listed-building-grade": "II", "start-date": "1984-11-16", "name": "BATCHELORS HALL", "slug": "/listed-building/1030196", "entry-date": "2021-05-28"}}