{"type": "Feature", "geometry": {"type": "Point", "coordinates": [-1.628378, 51.990423]}, "properties": {"start-date": "1987-04-09", "listed-building": "1024314", "documentation-url": "https://historicengland.org.uk/listing/the-list/list-entry/1024314", "point": "POINT (-1.628378 51.990423)", "name": "MONUMENT APPROXIMATELY 12 METRES SOUTH OF CHURCH OF ST LAWRENCE", "listed-building-grade": "II", "slug": "/listed-building/1024314", "entry-date": "2021-05-28"}}