{"type": "Feature", "geometry": {"type": "Point", "coordinates": [-1.824299, 52.217221]}, "properties": {"point": "POINT (-1.824299 52.217221)", "documentation-url": "https://historicengland.org.uk/listing/the-list/list-entry/1024534", "listed-building": "1024534", "start-date": "1969-12-11", "listed-building-grade": "II", "name": "THE MOUNT", "slug": "/listed-building/1024534", "entry-date": "2021-05-28"}}