{"type": "Feature", "geometry": {"type": "Point", "coordinates": [-2.075724, 51.480676]}, "properties": {"point": "POINT (-2.075724 51.480676)", "start-date": "1988-02-29", "name": "CHURCHYARD WALL TO CHURCH OF ST GILES", "listed-building": "1022354", "listed-building-grade": "II", "documentation-url": "https://historicengland.org.uk/listing/the-list/list-entry/1022354", "slug": "/listed-building/1022354", "entry-date": "2021-05-28"}}