{"type": "Feature", "geometry": {"type": "Point", "coordinates": [-0.691129, 51.195989]}, "properties": {"name": "GATWICK END", "listed-building": "1029519", "listed-building-grade": "II", "start-date": "1985-05-21", "documentation-url": "https://historicengland.org.uk/listing/the-list/list-entry/1029519", "point": "POINT (-0.691129 51.195989)", "slug": "/listed-building/1029519", "entry-date": "2021-05-28"}}