{"type": "Feature", "geometry": {"type": "Point", "coordinates": [0.233351, 51.105018]}, "properties": {"documentation-url": "https://historicengland.org.uk/listing/the-list/list-entry/1028334", "listed-building": "1028334", "listed-building-grade": "II", "start-date": "1982-12-31", "name": "WINDMILL LODGE, WITH THE GATEWAY ADJOINING IN THE GROUNDS OF ERIDGE CASTLE", "point": "POINT (0.233351 51.105018)", "slug": "/listed-building/1028334", "entry-date": "2021-05-28"}}