{"type": "Feature", "geometry": {"type": "Point", "coordinates": [1.333936, 52.10592]}, "properties": {"documentation-url": "https://historicengland.org.uk/listing/the-list/list-entry/1030395", "name": "WILFORD LODGE", "start-date": "1966-03-16", "listed-building-grade": "II", "listed-building": "1030395", "point": "POINT (1.333936 52.105920)", "slug": "/listed-building/1030395", "entry-date": "1985-06-11"}}