{"type": "Feature", "geometry": {"type": "Point", "coordinates": [-0.319933, 51.153739]}, "properties": {"name": "LYCH GATE TO CHURCH OF ST JOHN THE BAPTIST", "listed-building": "1028736", "documentation-url": "https://historicengland.org.uk/listing/the-list/list-entry/1028736", "listed-building-grade": "II", "point": "POINT (-0.319933 51.153739)", "start-date": "1987-09-29", "slug": "/listed-building/1028736", "entry-date": "2021-05-28"}}