{"type": "Feature", "geometry": {"type": "Point", "coordinates": [-0.13203, 51.22116]}, "properties": {"documentation-url": "https://historicengland.org.uk/listing/the-list/list-entry/1029873", "listed-building-grade": "II", "listed-building": "1029873", "start-date": "1984-04-25", "name": "RIDGE GREEN FARM HOUSE", "point": "POINT (-0.132030 51.221160)", "slug": "/listed-building/1029873", "entry-date": "2021-05-28"}}