{"type": "Feature", "geometry": {"type": "Point", "coordinates": [-1.636042, 54.969108]}, "properties": {"point": "POINT (-1.636042 54.969108)", "name": "ASHFIELD PARENTS CENTRE AND ASHFIELD NURSERY SCHOOL AND WALLS, GATE PIERS AND GATE ATTACHED", "start-date": "1987-03-30", "listed-building": "1024891", "listed-building-grade": "II", "documentation-url": "https://historicengland.org.uk/listing/the-list/list-entry/1024891", "slug": "/listed-building/1024891", "entry-date": "2021-05-28"}}