{"type": "Feature", "geometry": {"type": "Point", "coordinates": [-1.853211, 52.165982]}, "properties": {"listed-building-grade": "II", "start-date": "1969-12-11", "listed-building": "1024701", "name": "FOSBROKE HOUSE", "point": "POINT (-1.853211 52.165982)", "documentation-url": "https://historicengland.org.uk/listing/the-list/list-entry/1024701", "slug": "/listed-building/1024701", "entry-date": "2021-05-28"}}