{"type": "Feature", "geometry": {"type": "Point", "coordinates": [-0.532184, 50.909679]}, "properties": {"documentation-url": "https://historicengland.org.uk/listing/the-list/list-entry/1027472", "point": "POINT (-0.532184 50.909679)", "start-date": "1980-05-09", "listed-building": "1027472", "listed-building-grade": "II", "name": "BARN TO THE EAST OF GEAN COTTAGE AND PINE COTTAGE", "slug": "/listed-building/1027472", "entry-date": "2021-05-28"}}