{"type": "Feature", "geometry": {"type": "Point", "coordinates": [-1.441266, 52.12308]}, "properties": {"name": "HEADSTONE APPROXIMATELY 3 METRES NORTH OF NORTH EAST CORNER OF NAVE OF CHURCH OF ST PETER AD VINCULA", "listed-building-grade": "II", "point": "POINT (-1.441266 52.123080)", "documentation-url": "https://historicengland.org.uk/listing/the-list/list-entry/1024214", "listed-building": "1024214", "start-date": "1987-04-08", "slug": "/listed-building/1024214", "entry-date": "2021-05-28"}}