{"type": "Feature", "geometry": {"type": "Point", "coordinates": [-1.426139, 55.017508]}, "properties": {"listed-building-grade": "II", "documentation-url": "https://historicengland.org.uk/listing/the-list/list-entry/1025370", "point": "POINT (-1.426139 55.017508)", "listed-building": "1025370", "start-date": "1986-02-19", "name": "5 AND 6, DAWSON SQUARE", "slug": "/listed-building/1025370", "entry-date": "2021-05-28"}}