{"type": "Feature", "geometry": {"type": "Point", "coordinates": [-1.696769, 52.102193]}, "properties": {"documentation-url": "https://historicengland.org.uk/listing/the-list/list-entry/1024109", "listed-building": "1024109", "start-date": "1988-05-16", "point": "POINT (-1.696769 52.102193)", "listed-building-grade": "II", "name": "YORK FARMHOUSE", "slug": "/listed-building/1024109", "entry-date": "2021-05-28"}}