{"type": "Feature", "geometry": {"type": "Point", "coordinates": [-0.404185, 50.915779]}, "properties": {"documentation-url": "https://historicengland.org.uk/listing/the-list/list-entry/1027194", "name": "APPLE BARN", "listed-building": "1027194", "listed-building-grade": "II", "start-date": "1980-05-09", "point": "POINT (-0.404185 50.915779)", "slug": "/listed-building/1027194", "entry-date": "2021-05-28"}}