{"type": "Feature", "geometry": {"type": "Point", "coordinates": [-0.355346, 50.964204]}, "properties": {"start-date": "1980-11-28", "point": "POINT (-0.355346 50.964204)", "documentation-url": "https://historicengland.org.uk/listing/the-list/list-entry/1026870", "listed-building": "1026870", "listed-building-grade": "II", "name": "NEW LODGE", "slug": "/listed-building/1026870", "entry-date": "2021-05-28"}}