{"type": "Feature", "geometry": {"type": "Point", "coordinates": [-1.858821, 51.082737]}, "properties": {"listed-building": "1023703", "documentation-url": "https://historicengland.org.uk/listing/the-list/list-entry/1023703", "point": "POINT (-1.858821 51.082737)", "listed-building-grade": "II", "start-date": "1951-08-04", "name": "ROAD BLOCK AT ROYAL WILTON CARPET FACTORY", "slug": "/listed-building/1023703", "entry-date": "2021-05-28"}}