{"type": "Feature", "geometry": {"type": "Point", "coordinates": [-1.861112, 51.582986]}, "properties": {"start-date": "1986-04-17", "documentation-url": "https://historicengland.org.uk/listing/the-list/list-entry/1023163", "listed-building-grade": "II", "listed-building": "1023163", "name": "WARMAN MONUMENT IN CHURCHYARD, 35 METRES SOUTH EAST OF SOUTH EAST CORNER OF SOUTH AISLE, CHURCH OF ST MARY", "point": "POINT (-1.861112 51.582986)", "slug": "/listed-building/1023163", "entry-date": "2021-05-28"}}