{"type": "Feature", "geometry": {"type": "Point", "coordinates": [0.888863, 52.354124]}, "properties": {"listed-building": "1031168", "listed-building-grade": "II", "name": "EVERGREEN HALL", "point": "POINT (0.888863 52.354124)", "documentation-url": "https://historicengland.org.uk/listing/the-list/list-entry/1031168", "start-date": "1955-07-14", "slug": "/listed-building/1031168", "entry-date": "1985-01-25"}}