{"type": "Feature", "geometry": {"type": "Point", "coordinates": [-0.502482, 51.393197]}, "properties": {"listed-building": "1029207", "point": "POINT (-0.502482 51.393197)", "name": "CLOISTER GARTH (MUSIC SCHOOL)", "listed-building-grade": "II", "documentation-url": "https://historicengland.org.uk/listing/the-list/list-entry/1029207", "start-date": "1972-06-09", "slug": "/listed-building/1029207", "entry-date": "2021-05-28"}}