{"type": "Feature", "geometry": {"type": "Point", "coordinates": [-0.32783, 50.888216]}, "properties": {"listed-building": "1027303", "start-date": "1955-03-15", "listed-building-grade": "II", "name": "4 AND 6, CHURCH STREET", "point": "POINT (-0.327830 50.888216)", "documentation-url": "https://historicengland.org.uk/listing/the-list/list-entry/1027303", "slug": "/listed-building/1027303", "entry-date": "2021-05-28"}}