{"type": "Feature", "geometry": {"type": "Point", "coordinates": [-2.263262, 51.474119]}, "properties": {"name": "UNIDENTIFIED PAIR OF MONUMENTS ABOUT 4 METRES SOUTH OF N TAYLER MONUMENT SOUTH OF NAVE OF CHURCH OF ST JAMES", "start-date": "1985-12-09", "documentation-url": "https://historicengland.org.uk/listing/the-list/list-entry/1023004", "listed-building-grade": "II", "listed-building": "1023004", "point": "POINT (-2.263262 51.474119)", "slug": "/listed-building/1023004", "entry-date": "2021-05-28"}}