{"type": "Feature", "geometry": {"type": "Point", "coordinates": [-2.264451, 51.505344]}, "properties": {"documentation-url": "https://historicengland.org.uk/listing/the-list/list-entry/1022967", "listed-building": "1022967", "name": "GREEN FARMHOUSE", "start-date": "1985-12-09", "listed-building-grade": "II", "point": "POINT (-2.264451 51.505344)", "slug": "/listed-building/1022967", "entry-date": "2021-05-28"}}