{"type": "Feature", "geometry": {"type": "Point", "coordinates": [-0.461073, 51.089027]}, "properties": {"documentation-url": "https://historicengland.org.uk/listing/the-list/list-entry/1026973", "start-date": "1980-11-28", "name": "FIELD COTTAGE", "point": "POINT (-0.461073 51.089027)", "listed-building-grade": "II", "listed-building": "1026973", "slug": "/listed-building/1026973", "entry-date": "2021-05-28"}}