{"type": "Feature", "geometry": {"type": "Point", "coordinates": [-1.771749, 51.550855]}, "properties": {"listed-building-grade": "II", "listed-building": "1023511", "point": "POINT (-1.771749 51.550855)", "name": "GREYSTONES", "start-date": "1970-02-17", "documentation-url": "https://historicengland.org.uk/listing/the-list/list-entry/1023511", "slug": "/listed-building/1023511", "entry-date": "2021-05-28"}}