{"type": "Feature", "geometry": {"type": "Point", "coordinates": [-0.427406, 51.384291]}, "properties": {"listed-building-grade": "II", "start-date": "1973-12-21", "name": "DOWER HOUSE", "listed-building": "1030138", "point": "POINT (-0.427406 51.384291)", "documentation-url": "https://historicengland.org.uk/listing/the-list/list-entry/1030138", "slug": "/listed-building/1030138", "entry-date": "2021-05-28"}}