{"type": "Feature", "geometry": {"type": "Point", "coordinates": [-1.572578, 52.029694]}, "properties": {"point": "POINT (-1.572578 52.029694)", "listed-building": "1024274", "start-date": "1966-10-13", "listed-building-grade": "II", "name": "THE OLD BAKERY", "documentation-url": "https://historicengland.org.uk/listing/the-list/list-entry/1024274", "slug": "/listed-building/1024274", "entry-date": "1987-04-09"}}