{"type": "Feature", "geometry": {"type": "Point", "coordinates": [-1.851459, 51.561624]}, "properties": {"start-date": "1986-04-23", "listed-building": "1023476", "name": "WESTON CHEST TOMB IN CHURCHYARD 6 METRES SOUTH EAST OF SOUTH PORCH, CHURCH OF ST MARY", "point": "POINT (-1.851459 51.561624)", "documentation-url": "https://historicengland.org.uk/listing/the-list/list-entry/1023476", "listed-building-grade": "II", "slug": "/listed-building/1023476", "entry-date": "2021-05-28"}}