{"type": "Feature", "geometry": {"type": "Point", "coordinates": [0.13245, 52.21083]}, "properties": {"documentation-url": "https://historicengland.org.uk/listing/the-list/list-entry/1021928", "start-date": "1997-12-02", "listed-building-grade": "II", "point": "POINT (0.132450 52.210830)", "name": "CORPUS CHRISTI AND SIDNEY SUSSEX BOATHOUSE", "listed-building": "1021928", "slug": "/listed-building/1021928", "entry-date": "2021-05-28"}}