{"type": "Feature", "geometry": {"type": "Point", "coordinates": [-0.722832, 50.83674]}, "properties": {"start-date": "1958-06-05", "name": "MADAM GREEN FARMHOUSE", "point": "POINT (-0.722832 50.836740)", "documentation-url": "https://historicengland.org.uk/listing/the-list/list-entry/1026293", "listed-building": "1026293", "listed-building-grade": "II", "slug": "/listed-building/1026293", "entry-date": "2021-05-28"}}