{"type": "Feature", "geometry": {"type": "Point", "coordinates": [-0.465005, 51.063422]}, "properties": {"point": "POINT (-0.465005 51.063422)", "documentation-url": "https://historicengland.org.uk/listing/the-list/list-entry/1026976", "listed-building": "1026976", "name": "MORGAN'S GREEN", "start-date": "1980-11-28", "listed-building-grade": "II", "slug": "/listed-building/1026976", "entry-date": "2021-05-28"}}