{"type": "Feature", "geometry": {"type": "Point", "coordinates": [1.380393, 52.226712]}, "properties": {"start-date": "1985-12-18", "documentation-url": "https://historicengland.org.uk/listing/the-list/list-entry/1030376", "listed-building-grade": "II", "listed-building": "1030376", "name": "BOUNDARY FARMHOUSE", "point": "POINT (1.380393 52.226712)", "slug": "/listed-building/1030376", "entry-date": "2021-05-28"}}