{"type": "Feature", "geometry": {"type": "Point", "coordinates": [-0.372507, 51.40257]}, "properties": {"listed-building-grade": "II", "documentation-url": "https://historicengland.org.uk/listing/the-list/list-entry/1030079", "name": "THE VICARAGE", "listed-building": "1030079", "point": "POINT (-0.372507 51.402570)", "start-date": "1970-05-07", "slug": "/listed-building/1030079", "entry-date": "2021-05-28"}}