{"type": "Feature", "geometry": {"type": "Point", "coordinates": [-0.44006, 51.283844]}, "properties": {"listed-building-grade": "II", "point": "POINT (-0.440060 51.283844)", "start-date": "1978-06-15", "documentation-url": "https://historicengland.org.uk/listing/the-list/list-entry/1029403", "listed-building": "1029403", "name": "BLUE RYDE COTTAGE", "slug": "/listed-building/1029403", "entry-date": "2021-05-28"}}