{"type": "Feature", "geometry": {"type": "Point", "coordinates": [1.455478, 52.278054]}, "properties": {"start-date": "1984-12-21", "point": "POINT (1.455478 52.278054)", "listed-building-grade": "II", "listed-building": "1030757", "documentation-url": "https://historicengland.org.uk/listing/the-list/list-entry/1030757", "name": "NUMBERS 14 AND 15 (40 METRES NORTH WEST OF BARNYARDS COTTAGES)", "slug": "/listed-building/1030757", "entry-date": "2021-05-28"}}