{"type": "Feature", "geometry": {"type": "Point", "coordinates": [-1.40281, 52.123952]}, "properties": {"listed-building": "1024167", "start-date": "1987-04-08", "documentation-url": "https://historicengland.org.uk/listing/the-list/list-entry/1024167", "name": "GROUP OF 3 HEADSTONES APPROXIMATELY 11.5 METRES SOUTH OF SOUTH AISLE OF CHURCH OF ST MICHAEL", "point": "POINT (-1.402810 52.123952)", "listed-building-grade": "II", "slug": "/listed-building/1024167", "entry-date": "2021-05-28"}}