{"type": "Feature", "geometry": {"type": "Point", "coordinates": [-0.338548, 51.348491]}, "properties": {"point": "POINT (-0.338548 51.348491)", "documentation-url": "https://historicengland.org.uk/listing/the-list/list-entry/1030174", "listed-building": "1030174", "start-date": "1984-11-16", "name": "POST BY HOLROYDS PLANTATION AT NGR TQ 15806235", "listed-building-grade": "II", "slug": "/listed-building/1030174", "entry-date": "2021-05-28"}}