{"type": "Feature", "geometry": {"type": "Point", "coordinates": [-0.374398, 50.917333]}, "properties": {"start-date": "1980-05-09", "listed-building": "1027152", "listed-building-grade": "II", "documentation-url": "https://historicengland.org.uk/listing/the-list/list-entry/1027152", "name": "ABBOTTS FARMHOUSE", "point": "POINT (-0.374398 50.917333)", "slug": "/listed-building/1027152", "entry-date": "2021-05-28"}}