{"type": "Feature", "geometry": {"type": "Point", "coordinates": [-2.182242, 51.43408]}, "properties": {"listed-building-grade": "II", "name": "POCOCK MONUMENT IN CHURCHYARD ABOUT 1 METRE EAST OF S. GUY MONUMENT, NORTH OF NORTH AISLE DOOR OF CHURCH OF ST BARTHOLOMEW", "start-date": "1986-08-01", "documentation-url": "https://historicengland.org.uk/listing/the-list/list-entry/1021981", "listed-building": "1021981", "point": "POINT (-2.182242 51.434080)", "slug": "/listed-building/1021981", "entry-date": "2021-05-28"}}