{"type": "Feature", "geometry": {"type": "Point", "coordinates": [-0.097043, 51.522995]}, "properties": {"start-date": "1997-12-04", "documentation-url": "https://historicengland.org.uk/listing/the-list/list-entry/1021942", "listed-building": "1021942", "name": "Hatfield House, including garden walls to rear", "point": "POINT (-0.097043 51.522995)", "listed-building-grade": "II", "slug": "/listed-building/1021942", "entry-date": "2021-05-28"}}