{"type": "Feature", "geometry": {"type": "Point", "coordinates": [-2.153257, 51.537153]}, "properties": {"point": "POINT (-2.153257 51.537153)", "name": "LYCHGATE TO THE EAST OF CHURCH OF ST MARY", "listed-building-grade": "II", "documentation-url": "https://historicengland.org.uk/listing/the-list/list-entry/1023210", "listed-building": "1023210", "start-date": "1986-12-03", "slug": "/listed-building/1023210", "entry-date": "2021-05-28"}}