{"type": "Feature", "geometry": {"type": "Point", "coordinates": [-2.266195, 51.512911]}, "properties": {"listed-building": "1022957", "start-date": "1985-12-09", "name": "BEAKER MONUMENT IN CHURCHYARD ABOUT 3 METRES SOUTH OF CHANCEL SOUTH EAST WINDOW OF CHURCH OF ST MARY", "documentation-url": "https://historicengland.org.uk/listing/the-list/list-entry/1022957", "listed-building-grade": "II", "point": "POINT (-2.266195 51.512911)", "slug": "/listed-building/1022957", "entry-date": "2021-05-28"}}