{"type": "Feature", "geometry": {"type": "Point", "coordinates": [1.26412, 52.220414]}, "properties": {"point": "POINT (1.264120 52.220414)", "listed-building": "1030580", "start-date": "1984-11-19", "documentation-url": "https://historicengland.org.uk/listing/the-list/list-entry/1030580", "name": "STANWELL HOUSE", "listed-building-grade": "II", "slug": "/listed-building/1030580", "entry-date": "2021-05-28"}}