{"type": "Feature", "geometry": {"type": "Point", "coordinates": [-2.513313, 52.715303]}, "properties": {"listed-building": "1030948", "point": "POINT (-2.513313 52.715303)", "documentation-url": "https://historicengland.org.uk/listing/the-list/list-entry/1030948", "name": "FORMER KITCHEN GARDEN WALLS TO WEST OF STABLES AT APLEY CASTLE", "start-date": "1989-10-30", "listed-building-grade": "II", "slug": "/listed-building/1030948", "entry-date": "2021-05-28"}}