{"type": "Feature", "geometry": {"type": "Point", "coordinates": [-1.675518, 54.94626]}, "properties": {"documentation-url": "https://historicengland.org.uk/listing/the-list/list-entry/1025170", "start-date": "1985-11-18", "point": "POINT (-1.675518 54.946260)", "listed-building-grade": "II", "listed-building": "1025170", "name": "RESTAURANT AND HOUSE OPPOSITE NUMBER 11", "slug": "/listed-building/1025170", "entry-date": "2021-05-28"}}