{"type": "Feature", "geometry": {"type": "Point", "coordinates": [-0.570757, 51.236071]}, "properties": {"name": "ENTRANCE WALLS AND RAILINGS TO HOLY TRINITY CHURCH", "listed-building-grade": "II", "point": "POINT (-0.570757 51.236071)", "documentation-url": "https://historicengland.org.uk/listing/the-list/list-entry/1029259", "listed-building": "1029259", "start-date": "1988-03-15", "slug": "/listed-building/1029259", "entry-date": "2021-05-28"}}