{"type": "Feature", "geometry": {"type": "Point", "coordinates": [-1.870588, 51.498675]}, "properties": {"documentation-url": "https://historicengland.org.uk/listing/the-list/list-entry/1022649", "name": "BROAD TOWN FARMHOUSE", "point": "POINT (-1.870588 51.498675)", "listed-building": "1022649", "listed-building-grade": "II", "start-date": "1955-01-17", "slug": "/listed-building/1022649", "entry-date": "2021-05-28"}}