{"type": "Feature", "geometry": {"type": "Point", "coordinates": [-1.95376, 51.23095]}, "properties": {"documentation-url": "https://historicengland.org.uk/listing/the-list/list-entry/1023970", "point": "POINT (-1.953760 51.230950)", "name": "HOOPERS FARMHOUSE", "start-date": "1985-07-04", "listed-building": "1023970", "listed-building-grade": "II", "slug": "/listed-building/1023970", "entry-date": "2021-05-28"}}