{"type": "Feature", "geometry": {"type": "Point", "coordinates": [-0.363842, 51.102886]}, "properties": {"listed-building-grade": "II", "documentation-url": "https://historicengland.org.uk/listing/the-list/list-entry/1026856", "point": "POINT (-0.363842 51.102886)", "listed-building": "1026856", "name": "MALTMAYES", "start-date": "1959-09-22", "slug": "/listed-building/1026856", "entry-date": "1980-11-28"}}