{"type": "Feature", "geometry": {"type": "Point", "coordinates": [-1.323123, 52.247771]}, "properties": {"documentation-url": "https://historicengland.org.uk/listing/the-list/list-entry/1024444", "listed-building": "1024444", "start-date": "1967-05-30", "listed-building-grade": "II*", "point": "POINT (-1.323123 52.247771)", "name": "CHURCH OF ST LAWRENCE", "slug": "/listed-building/1024444", "entry-date": "2021-05-28"}}