{"type": "Feature", "geometry": {"type": "Point", "coordinates": [-0.66525, 51.222332]}, "properties": {"documentation-url": "https://historicengland.org.uk/listing/the-list/list-entry/1029601", "start-date": "1967-06-14", "listed-building": "1029601", "point": "POINT (-0.665250 51.222332)", "name": "CHURCH OF ST JOHN THE BAPTIST", "listed-building-grade": "II*", "slug": "/listed-building/1029601", "entry-date": "2021-05-28"}}