{"type": "Feature", "geometry": {"type": "Point", "coordinates": [-0.493468, 51.299363]}, "properties": {"listed-building-grade": "II", "start-date": "1985-11-25", "listed-building": "1029376", "name": "RIO COTTAGE RIO HOUSE", "point": "POINT (-0.493468 51.299363)", "documentation-url": "https://historicengland.org.uk/listing/the-list/list-entry/1029376", "slug": "/listed-building/1029376", "entry-date": "2021-05-28"}}