{"type": "Feature", "geometry": {"type": "Point", "coordinates": [-1.472469, 54.857176]}, "properties": {"listed-building": "1025413", "documentation-url": "https://historicengland.org.uk/listing/the-list/list-entry/1025413", "start-date": "1985-07-15", "point": "POINT (-1.472469 54.857176)", "name": "RUSSELL HOUSE (EAST FARM) AND FARM BUILDING ADJACENT", "listed-building-grade": "II", "slug": "/listed-building/1025413", "entry-date": "2021-05-28"}}