{"type": "Feature", "geometry": {"type": "Point", "coordinates": [-2.185013, 51.432476]}, "properties": {"listed-building": "1022036", "documentation-url": "https://historicengland.org.uk/listing/the-list/list-entry/1022036", "point": "POINT (-2.185013 51.432476)", "name": "THE VICARAGE", "listed-building-grade": "II", "start-date": "1960-12-20", "slug": "/listed-building/1022036", "entry-date": "1986-08-01"}}