{"type": "Feature", "geometry": {"type": "Point", "coordinates": [-1.18216, 53.253457]}, "properties": {"listed-building": "1025119", "name": "CHURCH OF ST WINIFRED", "documentation-url": "https://historicengland.org.uk/listing/the-list/list-entry/1025119", "point": "POINT (-1.182160 53.253457)", "start-date": "1985-04-12", "listed-building-grade": "II", "slug": "/listed-building/1025119", "entry-date": "2021-05-28"}}