{"type": "Feature", "geometry": {"type": "Point", "coordinates": [-2.281879, 51.387766]}, "properties": {"listed-building": "1021835", "point": "POINT (-2.281879 51.387766)", "name": "GATE PIERS AND FLANKING WALLS AT ENTRANCE TO THE MANOR HOUSE", "documentation-url": "https://historicengland.org.uk/listing/the-list/list-entry/1021835", "listed-building-grade": "II", "start-date": "1988-06-14", "slug": "/listed-building/1021835", "entry-date": "2021-05-28"}}