{"type": "Feature", "geometry": {"type": "Point", "coordinates": [-0.180217, 50.933367]}, "properties": {"start-date": "1957-10-28", "listed-building": "1025672", "listed-building-grade": "II", "point": "POINT (-0.180217 50.933367)", "name": "CHURCH HOUSE", "documentation-url": "https://historicengland.org.uk/listing/the-list/list-entry/1025672", "slug": "/listed-building/1025672", "entry-date": "2021-05-28"}}