{"type": "Feature", "geometry": {"type": "Point", "coordinates": [1.468578, 52.261217]}, "properties": {"listed-building": "1030799", "start-date": "1984-12-21", "name": "SOUTH GRANGE", "point": "POINT (1.468578 52.261217)", "documentation-url": "https://historicengland.org.uk/listing/the-list/list-entry/1030799", "listed-building-grade": "II", "slug": "/listed-building/1030799", "entry-date": "2021-05-28"}}