{"type": "Feature", "geometry": {"type": "Point", "coordinates": [-2.227754, 51.418671]}, "properties": {"listed-building": "1022732", "documentation-url": "https://historicengland.org.uk/listing/the-list/list-entry/1022732", "start-date": "1985-07-24", "point": "POINT (-2.227754 51.418671)", "name": "MILESTONE ABOUT 140 METRES NORTH OF JUNCTION WITH LANE TO BOX HILL", "listed-building-grade": "II", "slug": "/listed-building/1022732", "entry-date": "2021-05-28"}}