{"type": "Feature", "geometry": {"type": "Point", "coordinates": [-1.79746, 51.068404]}, "properties": {"documentation-url": "https://historicengland.org.uk/listing/the-list/list-entry/1023680", "listed-building": "1023680", "point": "POINT (-1.797460 51.068404)", "start-date": "1972-10-12", "name": "8 AND 10, HIGH STREET", "listed-building-grade": "II", "slug": "/listed-building/1023680", "entry-date": "2021-05-28"}}