{"type": "Feature", "geometry": {"type": "Point", "coordinates": [-2.056107, 51.511635]}, "properties": {"start-date": "1987-11-25", "listed-building": "1022470", "name": "THE MERMAID INN", "documentation-url": "https://historicengland.org.uk/listing/the-list/list-entry/1022470", "point": "POINT (-2.056107 51.511635)", "listed-building-grade": "II", "slug": "/listed-building/1022470", "entry-date": "2021-05-28"}}