{"type": "Feature", "geometry": {"type": "Point", "coordinates": [-2.544586, 52.692444]}, "properties": {"start-date": "1983-04-08", "listed-building": "1030930", "point": "POINT (-2.544586 52.692444)", "listed-building-grade": "II", "documentation-url": "https://historicengland.org.uk/listing/the-list/list-entry/1030930", "name": "MILEPOST APPROXIMATELY 700 YARDS SOUTH SOUTH WEST OF ORLETON HALL", "slug": "/listed-building/1030930", "entry-date": "2021-05-28"}}