{"type": "Feature", "geometry": {"type": "Point", "coordinates": [1.264875, 52.201141]}, "properties": {"listed-building-grade": "II", "listed-building": "1030324", "documentation-url": "https://historicengland.org.uk/listing/the-list/list-entry/1030324", "name": "GROVE FARMHOUSE", "point": "POINT (1.264875 52.201141)", "start-date": "1988-08-15", "slug": "/listed-building/1030324", "entry-date": "2021-05-28"}}