{"type": "Feature", "geometry": {"type": "Point", "coordinates": [-1.794122, 51.068488]}, "properties": {"listed-building": "1023573", "listed-building-grade": "II", "start-date": "1972-10-12", "documentation-url": "https://historicengland.org.uk/listing/the-list/list-entry/1023573", "name": "2 AND 4, CATHERINE STREET", "point": "POINT (-1.794122 51.068488)", "slug": "/listed-building/1023573", "entry-date": "2021-05-28"}}