{"type": "Feature", "geometry": {"type": "Point", "coordinates": [1.412654, 51.329915]}, "properties": {"start-date": "1988-02-04", "point": "POINT (1.412654 51.329915)", "listed-building": "1025310", "listed-building-grade": "II", "name": "NOS 4-44 WITH RAILED AREAS", "documentation-url": "https://historicengland.org.uk/listing/the-list/list-entry/1025310", "slug": "/listed-building/1025310", "entry-date": "2021-05-28"}}