{"type": "Feature", "geometry": {"type": "Point", "coordinates": [-1.70235, 52.072978]}, "properties": {"name": "REDLANDS BARN AT SP 2049 4168", "point": "POINT (-1.702350 52.072978)", "listed-building-grade": "II", "listed-building": "1024150", "documentation-url": "https://historicengland.org.uk/listing/the-list/list-entry/1024150", "start-date": "1988-05-16", "slug": "/listed-building/1024150", "entry-date": "2021-05-28"}}