{"type": "Feature", "geometry": {"type": "Point", "coordinates": [-0.639134, 51.185756]}, "properties": {"point": "POINT (-0.639134 51.185756)", "listed-building-grade": "II", "documentation-url": "https://historicengland.org.uk/listing/the-list/list-entry/1029554", "start-date": "1985-05-21", "listed-building": "1029554", "name": "BARN, 15 YARDS TO REAR OF EASHING FARM COTTAGE", "slug": "/listed-building/1029554", "entry-date": "2021-05-28"}}