{"type": "Feature", "geometry": {"type": "Point", "coordinates": [-0.503894, 51.391623]}, "properties": {"start-date": "1951-09-26", "name": "118 AND 120, GUILDFORD STREET", "point": "POINT (-0.503894 51.391623)", "listed-building-grade": "II", "listed-building": "1029188", "documentation-url": "https://historicengland.org.uk/listing/the-list/list-entry/1029188", "slug": "/listed-building/1029188", "entry-date": "2021-05-28"}}