{"type": "Feature", "geometry": {"type": "Point", "coordinates": [-1.863021, 51.567325]}, "properties": {"listed-building-grade": "II", "name": "PARKSIDE FARMHOUSE", "point": "POINT (-1.863021 51.567325)", "listed-building": "1023142", "documentation-url": "https://historicengland.org.uk/listing/the-list/list-entry/1023142", "start-date": "1986-04-17", "slug": "/listed-building/1023142", "entry-date": "2021-05-28"}}