{"type": "Feature", "geometry": {"type": "Point", "coordinates": [0.768519, 52.267498]}, "properties": {"listed-building": "1031157", "documentation-url": "https://historicengland.org.uk/listing/the-list/list-entry/1031157", "listed-building-grade": "II", "point": "POINT (0.768519 52.267498)", "start-date": "1985-03-28", "name": "ST JOHN'S WELL COTTAGE (THE LODGE)", "slug": "/listed-building/1031157", "entry-date": "2021-05-28"}}