{"type": "Feature", "geometry": {"type": "Point", "coordinates": [1.313171, 52.213023]}, "properties": {"listed-building-grade": "II", "documentation-url": "https://historicengland.org.uk/listing/the-list/list-entry/1030546", "point": "POINT (1.313171 52.213023)", "name": "BARN IMMEDIATELY EAST OF BRUNSWICK FARMHOUSE", "start-date": "1989-03-30", "listed-building": "1030546", "slug": "/listed-building/1030546", "entry-date": "2021-05-28"}}