{"type": "Feature", "geometry": {"type": "Point", "coordinates": [-0.492367, 50.811681]}, "properties": {"point": "POINT (-0.492367 50.811681)", "name": "WEST PRESTON MANOR SCHOOL", "documentation-url": "https://historicengland.org.uk/listing/the-list/list-entry/1027552", "start-date": "1984-09-20", "listed-building": "1027552", "listed-building-grade": "II", "slug": "/listed-building/1027552", "entry-date": "2021-05-28"}}