{"type": "Feature", "geometry": {"type": "Point", "coordinates": [1.239027, 52.118281]}, "properties": {"listed-building": "1030722", "documentation-url": "https://historicengland.org.uk/listing/the-list/list-entry/1030722", "start-date": "1988-08-31", "point": "POINT (1.239027 52.118281)", "name": "HILL FARMHOUSE", "listed-building-grade": "II", "slug": "/listed-building/1030722", "entry-date": "2021-05-28"}}