{"type": "Feature", "geometry": {"type": "Point", "coordinates": [-0.533882, 50.908262]}, "properties": {"name": "BARN ADJOINING OLD STACK COTTAGE", "listed-building": "1027482", "listed-building-grade": "II", "documentation-url": "https://historicengland.org.uk/listing/the-list/list-entry/1027482", "start-date": "1980-05-09", "point": "POINT (-0.533882 50.908262)", "slug": "/listed-building/1027482", "entry-date": "2021-05-28"}}