{"type": "Feature", "geometry": {"type": "Point", "coordinates": [-1.873452, 52.214822]}, "properties": {"listed-building": "1024590", "start-date": "1969-12-11", "name": "47-51 PRIORY ROAD", "documentation-url": "https://historicengland.org.uk/listing/the-list/list-entry/1024590", "point": "POINT (-1.873452 52.214822)", "listed-building-grade": "II", "slug": "/listed-building/1024590", "entry-date": "1985-06-21"}}