{"type": "Feature", "geometry": {"type": "Point", "coordinates": [-0.641907, 51.294839]}, "properties": {"listed-building-grade": "II", "name": "THORNER COTTAGE", "documentation-url": "https://historicengland.org.uk/listing/the-list/list-entry/1029624", "listed-building": "1029624", "start-date": "1967-06-14", "point": "POINT (-0.641907 51.294839)", "slug": "/listed-building/1029624", "entry-date": "2021-05-28"}}