{"type": "Feature", "geometry": {"type": "Point", "coordinates": [-0.05542, 51.163921]}, "properties": {"documentation-url": "https://historicengland.org.uk/listing/the-list/list-entry/1029944", "point": "POINT (-0.055420 51.163921)", "name": "CHERRY TREE FARM HOUSE", "listed-building": "1029944", "start-date": "1984-04-25", "listed-building-grade": "II", "slug": "/listed-building/1029944", "entry-date": "2021-05-28"}}