{"type": "Feature", "geometry": {"type": "Point", "coordinates": [-1.769002, 51.054971]}, "properties": {"start-date": "1985-03-28", "name": "FIVE LEWIS MEMORIALS IN GROUP, IN THE CHURCHYARD BETWEEN 5 AND 11 METRES SOUTH OF SOUTH TRANSEPT OF CHURCH OF ST PETER", "listed-building": "1023792", "point": "POINT (-1.769002 51.054971)", "listed-building-grade": "II", "documentation-url": "https://historicengland.org.uk/listing/the-list/list-entry/1023792", "slug": "/listed-building/1023792", "entry-date": "2021-05-28"}}