{"type": "Feature", "geometry": {"type": "Point", "coordinates": [-1.912416, 52.259486]}, "properties": {"documentation-url": "https://historicengland.org.uk/listing/the-list/list-entry/1024513", "name": "PERRYMILL COTTAGES", "start-date": "1985-10-23", "listed-building-grade": "II", "listed-building": "1024513", "point": "POINT (-1.912416 52.259486)", "slug": "/listed-building/1024513", "entry-date": "2021-05-28"}}