{"type": "Feature", "geometry": {"type": "Point", "coordinates": [-0.736211, 50.781462]}, "properties": {"point": "POINT (-0.736211 50.781462)", "listed-building": "1027575", "listed-building-grade": "II", "name": "GROUP OF FOUR BARNS AT MILL FARM", "documentation-url": "https://historicengland.org.uk/listing/the-list/list-entry/1027575", "start-date": "1984-09-20", "slug": "/listed-building/1027575", "entry-date": "2021-05-28"}}