{"type": "Feature", "geometry": {"type": "Point", "coordinates": [-1.866684, 51.593082]}, "properties": {"listed-building": "1023189", "point": "POINT (-1.866684 51.593082)", "start-date": "1986-04-17", "listed-building-grade": "II", "documentation-url": "https://historicengland.org.uk/listing/the-list/list-entry/1023189", "name": "WIDHAM FARMHOUSE", "slug": "/listed-building/1023189", "entry-date": "2021-05-28"}}