{"type": "Feature", "geometry": {"type": "Point", "coordinates": [-0.751511, 50.950351]}, "properties": {"documentation-url": "https://historicengland.org.uk/listing/the-list/list-entry/1026073", "point": "POINT (-0.751511 50.950351)", "listed-building": "1026073", "name": "COBWEBS", "listed-building-grade": "II", "start-date": "1986-11-25", "slug": "/listed-building/1026073", "entry-date": "2021-05-28"}}