{"type": "Feature", "geometry": {"type": "Point", "coordinates": [-1.726394, 51.569586]}, "properties": {"name": "OUTHOUSE TO NORTH OF NYTHE FARMHOUSE", "documentation-url": "https://historicengland.org.uk/listing/the-list/list-entry/1023430", "point": "POINT (-1.726394 51.569586)", "listed-building-grade": "II", "listed-building": "1023430", "start-date": "1979-09-20", "slug": "/listed-building/1023430", "entry-date": "2021-05-28"}}