{"type": "Feature", "geometry": {"type": "Point", "coordinates": [-0.099451, 51.240476]}, "properties": {"start-date": "1958-06-11", "name": "OUTBUILDING 5 YARDS WEST OF WHITE HART INN", "listed-building": "1029982", "point": "POINT (-0.099451 51.240476)", "documentation-url": "https://historicengland.org.uk/listing/the-list/list-entry/1029982", "listed-building-grade": "II", "slug": "/listed-building/1029982", "entry-date": "1984-04-25"}}