{"type": "Feature", "geometry": {"type": "Point", "coordinates": [-0.449662, 50.955607]}, "properties": {"start-date": "1980-05-09", "documentation-url": "https://historicengland.org.uk/listing/the-list/list-entry/1027140", "listed-building-grade": "II", "point": "POINT (-0.449662 50.955607)", "listed-building": "1027140", "name": "HUNTERS BARN", "slug": "/listed-building/1027140", "entry-date": "2021-05-28"}}