{"type": "Feature", "geometry": {"type": "Point", "coordinates": [0.106372, 51.017045]}, "properties": {"point": "POINT (0.106372 51.017045)", "documentation-url": "https://historicengland.org.uk/listing/the-list/list-entry/1028467", "listed-building-grade": "II", "listed-building": "1028467", "name": "CLAYGATE FARMHOUSE", "start-date": "1982-12-31", "slug": "/listed-building/1028467", "entry-date": "2021-05-28"}}