{"type": "Feature", "geometry": {"type": "Point", "coordinates": [-1.790743, 51.620142]}, "properties": {"point": "POINT (-1.790743 51.620142)", "start-date": "1979-09-20", "listed-building-grade": "II", "name": "LARGE'S HOUSE", "documentation-url": "https://historicengland.org.uk/listing/the-list/list-entry/1023294", "listed-building": "1023294", "slug": "/listed-building/1023294", "entry-date": "2021-05-28"}}