{"type": "Feature", "geometry": {"type": "Point", "coordinates": [-0.652396, 51.305949]}, "properties": {"start-date": "1984-12-13", "name": "BARN 70 YARDS SOUTH EAST OF COWSHOT MANOR", "documentation-url": "https://historicengland.org.uk/listing/the-list/list-entry/1029621", "listed-building": "1029621", "listed-building-grade": "II", "point": "POINT (-0.652396 51.305949)", "slug": "/listed-building/1029621", "entry-date": "2021-05-28"}}