{"type": "Feature", "geometry": {"type": "Point", "coordinates": [-0.756908, 50.84879]}, "properties": {"name": "OLDPLACE FARMHOUSE", "listed-building-grade": "II", "documentation-url": "https://historicengland.org.uk/listing/the-list/list-entry/1026096", "point": "POINT (-0.756908 50.848790)", "listed-building": "1026096", "start-date": "1986-01-28", "slug": "/listed-building/1026096", "entry-date": "2021-05-28"}}