{"type": "Feature", "geometry": {"type": "Point", "coordinates": [-1.61275, 54.971404]}, "properties": {"listed-building": "1024823", "documentation-url": "https://historicengland.org.uk/listing/the-list/list-entry/1024823", "name": "THE OLD GEORGE PUBLIC HOUSE", "start-date": "1977-09-06", "point": "POINT (-1.612750 54.971404)", "listed-building-grade": "II", "slug": "/listed-building/1024823", "entry-date": "2021-05-28"}}