{"type": "Feature", "geometry": {"type": "Point", "coordinates": [0.112771, 51.101702]}, "properties": {"listed-building": "1028297", "listed-building-grade": "II", "documentation-url": "https://historicengland.org.uk/listing/the-list/list-entry/1028297", "start-date": "1982-12-31", "name": "THE GRANGE", "point": "POINT (0.112771 51.101702)", "slug": "/listed-building/1028297", "entry-date": "2021-05-28"}}