{"type": "Feature", "geometry": {"type": "Point", "coordinates": [-2.864601, 53.38269]}, "properties": {"documentation-url": "https://historicengland.org.uk/listing/the-list/list-entry/1024998", "point": "POINT (-2.864601 53.382690)", "start-date": "1975-03-14", "listed-building-grade": "II", "listed-building": "1024998", "name": "10 AND 12, GATEACRE BROW", "slug": "/listed-building/1024998", "entry-date": "2021-05-28"}}