{"type": "Feature", "geometry": {"type": "Point", "coordinates": [0.061482, 50.946473]}, "properties": {"start-date": "1953-11-26", "listed-building-grade": "II", "name": "TUDOR COTTAGE", "documentation-url": "https://historicengland.org.uk/listing/the-list/list-entry/1028281", "point": "POINT (0.061482 50.946473)", "listed-building": "1028281", "slug": "/listed-building/1028281", "entry-date": "1982-12-31"}}