{"type": "Feature", "geometry": {"type": "Point", "coordinates": [1.508714, 52.262893]}, "properties": {"name": "OLD SCHOOL COTTAGES", "start-date": "1976-06-17", "point": "POINT (1.508714 52.262893)", "documentation-url": "https://historicengland.org.uk/listing/the-list/list-entry/1030626", "listed-building": "1030626", "listed-building-grade": "II", "slug": "/listed-building/1030626", "entry-date": "1984-07-27"}}