{"type": "Feature", "geometry": {"type": "Point", "coordinates": [-1.678455, 54.922508]}, "properties": {"name": "OLD SUNNISIDE FARMHOUSE", "listed-building": "1025149", "point": "POINT (-1.678455 54.922508)", "documentation-url": "https://historicengland.org.uk/listing/the-list/list-entry/1025149", "listed-building-grade": "II", "start-date": "1988-08-03", "slug": "/listed-building/1025149", "entry-date": "2021-05-28"}}