{"type": "Feature", "geometry": {"type": "Point", "coordinates": [-0.370002, 51.358984]}, "properties": {"name": "THE CLOSE", "point": "POINT (-0.370002 51.358984)", "listed-building": "1030203", "start-date": "1984-11-16", "documentation-url": "https://historicengland.org.uk/listing/the-list/list-entry/1030203", "listed-building-grade": "II", "slug": "/listed-building/1030203", "entry-date": "2021-05-28"}}