{"type": "Feature", "geometry": {"type": "Point", "coordinates": [-2.250434, 51.555682]}, "properties": {"start-date": "1988-02-29", "point": "POINT (-2.250434 51.555682)", "name": "LYPIATT BARN", "listed-building": "1022371", "listed-building-grade": "II", "documentation-url": "https://historicengland.org.uk/listing/the-list/list-entry/1022371", "slug": "/listed-building/1022371", "entry-date": "2021-05-28"}}