{"type": "Feature", "geometry": {"type": "Point", "coordinates": [-1.369044, 54.949478]}, "properties": {"listed-building": "1025221", "name": "THE RECTORY", "listed-building-grade": "II", "point": "POINT (-1.369044 54.949478)", "start-date": "1985-02-26", "documentation-url": "https://historicengland.org.uk/listing/the-list/list-entry/1025221", "slug": "/listed-building/1025221", "entry-date": "2021-05-28"}}