{"type": "Feature", "geometry": {"type": "Point", "coordinates": [-1.611337, 54.972818]}, "properties": {"documentation-url": "https://historicengland.org.uk/listing/the-list/list-entry/1024783", "start-date": "1971-12-17", "listed-building": "1024783", "point": "POINT (-1.611337 54.972818)", "listed-building-grade": "II*", "name": "11 AND 13, SHAKESPEARE STREET", "slug": "/listed-building/1024783", "entry-date": "2021-05-28"}}