{"type": "Feature", "geometry": {"type": "Point", "coordinates": [0.13951, 50.983931]}, "properties": {"listed-building-grade": "II", "point": "POINT (0.139510 50.983931)", "name": "TANYARDS", "documentation-url": "https://historicengland.org.uk/listing/the-list/list-entry/1028435", "start-date": "1982-12-31", "listed-building": "1028435", "slug": "/listed-building/1028435", "entry-date": "2021-05-28"}}