{"type": "Feature", "geometry": {"type": "Point", "coordinates": [-0.202946, 51.238771]}, "properties": {"start-date": "1985-08-20", "listed-building": "1029045", "listed-building-grade": "II", "point": "POINT (-0.202946 51.238771)", "documentation-url": "https://historicengland.org.uk/listing/the-list/list-entry/1029045", "name": "ICE HOUSE IN GROUNDS REIGATE 6TH FORM COLLEGE", "slug": "/listed-building/1029045", "entry-date": "2021-05-28"}}