{"type": "Feature", "geometry": {"type": "Point", "coordinates": [-0.321757, 51.254726]}, "properties": {"start-date": "1973-06-11", "name": "BURFORD BRIDGE HOTEL", "documentation-url": "https://historicengland.org.uk/listing/the-list/list-entry/1028876", "point": "POINT (-0.321757 51.254726)", "listed-building": "1028876", "listed-building-grade": "II", "slug": "/listed-building/1028876", "entry-date": "1975-11-17"}}