{"type": "Feature", "geometry": {"type": "Point", "coordinates": [-0.46181, 51.372181]}, "properties": {"listed-building": "1030233", "start-date": "1951-10-19", "name": "PORTMORE HOUSE AND PORTMORE COTTAGE", "listed-building-grade": "II", "point": "POINT (-0.461810 51.372181)", "documentation-url": "https://historicengland.org.uk/listing/the-list/list-entry/1030233", "slug": "/listed-building/1030233", "entry-date": "2021-05-28"}}