{"type": "Feature", "geometry": {"type": "Point", "coordinates": [-1.61656, 52.07995]}, "properties": {"point": "POINT (-1.616560 52.079950)", "listed-building": "1024339", "listed-building-grade": "II", "name": "IVY COTTAGE AND ATTACHED WALL", "start-date": "1986-06-30", "documentation-url": "https://historicengland.org.uk/listing/the-list/list-entry/1024339", "slug": "/listed-building/1024339", "entry-date": "2021-05-28"}}