{"type": "Feature", "geometry": {"type": "Point", "coordinates": [1.462727, 52.292602]}, "properties": {"documentation-url": "https://historicengland.org.uk/listing/the-list/list-entry/1030800", "start-date": "1966-12-07", "listed-building-grade": "II*", "listed-building": "1030800", "point": "POINT (1.462727 52.292602)", "name": "HEVENINGHAM HALL GATE LODGES", "slug": "/listed-building/1030800", "entry-date": "2021-05-28"}}