{"type": "Feature", "geometry": {"type": "Point", "coordinates": [0.911361, 52.360784]}, "properties": {"name": "WEAVERS", "listed-building-grade": "II", "point": "POINT (0.911361 52.360784)", "start-date": "1985-01-25", "listed-building": "1031146", "documentation-url": "https://historicengland.org.uk/listing/the-list/list-entry/1031146", "slug": "/listed-building/1031146", "entry-date": "2021-05-28"}}