{"type": "Feature", "geometry": {"type": "Point", "coordinates": [0.248502, 51.054849]}, "properties": {"documentation-url": "https://historicengland.org.uk/listing/the-list/list-entry/1027968", "point": "POINT (0.248502 51.054849)", "listed-building-grade": "II", "listed-building": "1027968", "name": "SOUTH WEST WING AT FORMER LEGAT'S SCHOOL OF DANCING", "start-date": "1991-02-01", "slug": "/listed-building/1027968", "entry-date": "2021-05-28"}}