{"type": "Feature", "geometry": {"type": "Point", "coordinates": [-0.330962, 51.387049]}, "properties": {"point": "POINT (-0.330962 51.387049)", "listed-building-grade": "II", "listed-building": "1030222", "name": "ROSENEATH", "documentation-url": "https://historicengland.org.uk/listing/the-list/list-entry/1030222", "start-date": "1973-08-14", "slug": "/listed-building/1030222", "entry-date": "2021-05-28"}}