{"type": "Feature", "geometry": {"type": "Point", "coordinates": [-2.202881, 51.319349]}, "properties": {"start-date": "1976-11-26", "name": "WORKSHOP TO SOUTH WEST OF COURTFIELD HOUSE, TOGETHER WITH LEAD PUMP", "documentation-url": "https://historicengland.org.uk/listing/the-list/list-entry/1021636", "point": "POINT (-2.202881 51.319349)", "listed-building-grade": "II", "listed-building": "1021636", "slug": "/listed-building/1021636", "entry-date": "2021-05-28"}}