{"type": "Feature", "geometry": {"type": "Point", "coordinates": [0.716909, 52.228556]}, "properties": {"start-date": "1972-07-12", "documentation-url": "https://historicengland.org.uk/listing/the-list/list-entry/1022543", "listed-building-grade": "II", "listed-building": "1022543", "point": "POINT (0.716909 52.228556)", "name": "DAIRY COTTAGE", "slug": "/listed-building/1022543", "entry-date": "2021-05-28"}}