{"type": "Feature", "geometry": {"type": "Point", "coordinates": [1.548815, 52.332169]}, "properties": {"point": "POINT (1.548815 52.332169)", "start-date": "1984-07-27", "documentation-url": "https://historicengland.org.uk/listing/the-list/list-entry/1030615", "name": "HEATH FARMHOUSE AND DAIRY COTTAGE", "listed-building-grade": "II", "listed-building": "1030615", "slug": "/listed-building/1030615", "entry-date": "2021-05-28"}}