{"type": "Feature", "geometry": {"type": "Point", "coordinates": [0.697224, 52.23551]}, "properties": {"documentation-url": "https://historicengland.org.uk/listing/the-list/list-entry/1022552", "point": "POINT (0.697224 52.235510)", "start-date": "1972-07-12", "name": "WEST HILL HOUSE", "listed-building": "1022552", "listed-building-grade": "II", "slug": "/listed-building/1022552", "entry-date": "2021-05-28"}}