{"type": "Feature", "geometry": {"type": "Point", "coordinates": [-2.258456, 51.43891]}, "properties": {"documentation-url": "https://historicengland.org.uk/listing/the-list/list-entry/1022933", "listed-building": "1022933", "listed-building-grade": "II", "point": "POINT (-2.258456 51.438910)", "name": "UNIDENTIFIED TOMB IN CHURCHYARD CIRCA 19 METRES SOUTH OF EAST END OF MEMORIAL GARDEN EAST OF CHURCH OF ST JOHN", "start-date": "1985-12-09", "slug": "/listed-building/1022933", "entry-date": "2021-05-28"}}