{"type": "Feature", "geometry": {"type": "Point", "coordinates": [-1.757063, 50.991596]}, "properties": {"name": "8 AND 10, THE BOROUGH", "documentation-url": "https://historicengland.org.uk/listing/the-list/list-entry/1023865", "point": "POINT (-1.757063 50.991596)", "start-date": "1960-03-23", "listed-building-grade": "II", "listed-building": "1023865", "slug": "/listed-building/1023865", "entry-date": "1985-07-04"}}