{"type": "Feature", "geometry": {"type": "Point", "coordinates": [-0.305263, 51.188041]}, "properties": {"listed-building": "1028763", "documentation-url": "https://historicengland.org.uk/listing/the-list/list-entry/1028763", "point": "POINT (-0.305263 51.188041)", "name": "PETERSFIELD FARM HOUSE", "listed-building-grade": "II", "start-date": "1987-09-29", "slug": "/listed-building/1028763", "entry-date": "2021-05-28"}}