{"type": "Feature", "geometry": {"type": "Point", "coordinates": [-0.617985, 51.218798]}, "properties": {"listed-building-grade": "II", "listed-building": "1029548", "start-date": "1967-06-14", "documentation-url": "https://historicengland.org.uk/listing/the-list/list-entry/1029548", "name": "LITTLE POLSTED", "point": "POINT (-0.617985 51.218798)", "slug": "/listed-building/1029548", "entry-date": "1985-05-21"}}