{"type": "Feature", "geometry": {"type": "Point", "coordinates": [0.737866, 52.306075]}, "properties": {"documentation-url": "https://historicengland.org.uk/listing/the-list/list-entry/1031272", "name": "AMPTON HALL", "point": "POINT (0.737866 52.306075)", "listed-building": "1031272", "start-date": "1984-04-27", "listed-building-grade": "II", "slug": "/listed-building/1031272", "entry-date": "2021-05-28"}}