{"type": "Feature", "geometry": {"type": "Point", "coordinates": [-1.6321, 54.978981]}, "properties": {"start-date": "1971-12-17", "listed-building-grade": "II", "listed-building": "1024950", "documentation-url": "https://historicengland.org.uk/listing/the-list/list-entry/1024950", "point": "POINT (-1.632100 54.978981)", "name": "FORMER NORTH GUARD HOUSE AND ATTACHED WALL TO NORTH WEST, FENHAM BARRACKS", "slug": "/listed-building/1024950", "entry-date": "1999-02-04"}}