{"type": "Feature", "geometry": {"type": "Point", "coordinates": [0.133937, 50.976433]}, "properties": {"name": "GREAT STREELE", "documentation-url": "https://historicengland.org.uk/listing/the-list/list-entry/1028389", "start-date": "1953-11-26", "listed-building-grade": "II", "point": "POINT (0.133937 50.976433)", "listed-building": "1028389", "slug": "/listed-building/1028389", "entry-date": "2021-05-28"}}