{"type": "Feature", "geometry": {"type": "Point", "coordinates": [-1.638076, 50.980255]}, "properties": {"listed-building": "1023916", "name": "WHITEHOUSE FARMHOUSE", "documentation-url": "https://historicengland.org.uk/listing/the-list/list-entry/1023916", "start-date": "1985-07-04", "listed-building-grade": "II", "point": "POINT (-1.638076 50.980255)", "slug": "/listed-building/1023916", "entry-date": "2021-05-28"}}