{"type": "Feature", "geometry": {"type": "Point", "coordinates": [-0.779672, 50.864875]}, "properties": {"name": "RAUGHMERE FARM, THE FARM BUILDINGS TO THE NORTH OF THE FARMHOUSE", "point": "POINT (-0.779672 50.864875)", "start-date": "1980-11-28", "documentation-url": "https://historicengland.org.uk/listing/the-list/list-entry/1026313", "listed-building": "1026313", "listed-building-grade": "II", "slug": "/listed-building/1026313", "entry-date": "1986-01-28"}}