{"type": "Feature", "geometry": {"type": "Point", "coordinates": [-1.615201, 54.97014]}, "properties": {"point": "POINT (-1.615201 54.970140)", "documentation-url": "https://historicengland.org.uk/listing/the-list/list-entry/1024730", "listed-building": "1024730", "start-date": "1987-03-30", "listed-building-grade": "II", "name": "HODGSON TOMB ABOUT 15 METRES EAST OF CHURCH OF ST JOHN THE BAPTIST", "slug": "/listed-building/1024730", "entry-date": "2021-05-28"}}