{"type": "Feature", "geometry": {"type": "Point", "coordinates": [-0.331842, 51.392906]}, "properties": {"start-date": "1984-11-16", "name": "THE OLD SWAN INN", "listed-building-grade": "II", "listed-building": "1030113", "documentation-url": "https://historicengland.org.uk/listing/the-list/list-entry/1030113", "point": "POINT (-0.331842 51.392906)", "slug": "/listed-building/1030113", "entry-date": "2021-05-28"}}