{"type": "Feature", "geometry": {"type": "Point", "coordinates": [-0.140044, 50.951476]}, "properties": {"documentation-url": "https://historicengland.org.uk/listing/the-list/list-entry/1025859", "start-date": "1975-11-27", "listed-building": "1025859", "listed-building-grade": "II", "name": "BARN AT HAMMONDS FARM TO THE EAST OF THE FARMHOUSE", "point": "POINT (-0.140044 50.951476)", "slug": "/listed-building/1025859", "entry-date": "2021-05-28"}}