{"type": "Feature", "geometry": {"type": "Point", "coordinates": [0.27014, 51.096943]}, "properties": {"listed-building": "1028306", "listed-building-grade": "II", "name": "VIRGINIA COTTAGE", "start-date": "1982-12-31", "documentation-url": "https://historicengland.org.uk/listing/the-list/list-entry/1028306", "point": "POINT (0.270140 51.096943)", "slug": "/listed-building/1028306", "entry-date": "2021-05-28"}}