{"type": "Feature", "geometry": {"type": "Point", "coordinates": [-0.12269, 50.930217]}, "properties": {"documentation-url": "https://historicengland.org.uk/listing/the-list/list-entry/1025653", "start-date": "1983-05-11", "name": "Oldland Cottage", "listed-building": "1025653", "listed-building-grade": "II", "point": "POINT (-0.122690 50.930217)", "slug": "/listed-building/1025653", "entry-date": "1983-08-18"}}