{"type": "Feature", "geometry": {"type": "Point", "coordinates": [-1.797866, 51.067316]}, "properties": {"listed-building": "1023686", "name": "52 AND 54, HIGH STREET", "start-date": "1952-02-28", "documentation-url": "https://historicengland.org.uk/listing/the-list/list-entry/1023686", "listed-building-grade": "II*", "point": "POINT (-1.797866 51.067316)", "slug": "/listed-building/1023686", "entry-date": "2021-05-28"}}