{"type": "Feature", "geometry": {"type": "Point", "coordinates": [0.916565, 52.361069]}, "properties": {"documentation-url": "https://historicengland.org.uk/listing/the-list/list-entry/1031189", "name": "VILLAGE FARM COTTAGES", "listed-building-grade": "II", "start-date": "1985-01-25", "listed-building": "1031189", "point": "POINT (0.916565 52.361069)", "slug": "/listed-building/1031189", "entry-date": "2021-05-28"}}