{"type": "Feature", "geometry": {"type": "Point", "coordinates": [-0.56857, 51.21922]}, "properties": {"start-date": "1967-06-14", "listed-building": "1029499", "name": "MILL COTTAGE WATERMILL COTTAGE", "listed-building-grade": "II", "point": "POINT (-0.568570 51.219220)", "documentation-url": "https://historicengland.org.uk/listing/the-list/list-entry/1029499", "slug": "/listed-building/1029499", "entry-date": "2021-05-28"}}