{"type": "Feature", "geometry": {"type": "Point", "coordinates": [-2.20686, 51.574703]}, "properties": {"point": "POINT (-2.206860 51.574703)", "name": "OUTBUILDINGS TO THE NORTH OF HOME FARMHOUSE", "documentation-url": "https://historicengland.org.uk/listing/the-list/list-entry/1023235", "start-date": "1951-12-12", "listed-building": "1023235", "listed-building-grade": "II", "slug": "/listed-building/1023235", "entry-date": "2021-05-28"}}