{"type": "Feature", "geometry": {"type": "Point", "coordinates": [-2.196106, 51.442405]}, "properties": {"documentation-url": "https://historicengland.org.uk/listing/the-list/list-entry/1022024", "listed-building": "1022024", "point": "POINT (-2.196106 51.442405)", "name": "GATES, PIERS AND RAILINGS ADJOINING CHURCH LODGE", "listed-building-grade": "II", "start-date": "1986-08-01", "slug": "/listed-building/1022024", "entry-date": "2021-05-28"}}