{"type": "Feature", "geometry": {"type": "Point", "coordinates": [-1.334601, 53.656638]}, "properties": {"documentation-url": "https://historicengland.org.uk/listing/the-list/list-entry/1025000", "name": "VILLAGE CROSS", "point": "POINT (-1.334601 53.656638)", "start-date": "1968-03-25", "listed-building-grade": "II", "listed-building": "1025000", "slug": "/listed-building/1025000", "entry-date": "2021-05-28"}}