{"type": "Feature", "geometry": {"type": "Point", "coordinates": [-1.525967, 54.992084]}, "properties": {"point": "POINT (-1.525967 54.992084)", "listed-building": "1025331", "listed-building-grade": "II", "start-date": "1986-02-19", "documentation-url": "https://historicengland.org.uk/listing/the-list/list-entry/1025331", "name": "COACH AND HORSES PUBLIC HOUSE", "slug": "/listed-building/1025331", "entry-date": "2021-05-28"}}