{"type": "Feature", "geometry": {"type": "Point", "coordinates": [0.18605, 51.110732]}, "properties": {"listed-building-grade": "II", "point": "POINT (0.186050 51.110732)", "start-date": "1973-04-18", "name": "CHURCH OF ST THOMAS THE APOSTLE", "documentation-url": "https://historicengland.org.uk/listing/the-list/list-entry/1028038", "listed-building": "1028038", "slug": "/listed-building/1028038", "entry-date": "2021-05-28"}}