{"type": "Feature", "geometry": {"type": "Point", "coordinates": [-1.448584, 55.04812]}, "properties": {"listed-building-grade": "II", "listed-building": "1025338", "name": "SEWER GAS LAMP", "documentation-url": "https://historicengland.org.uk/listing/the-list/list-entry/1025338", "point": "POINT (-1.448584 55.048120)", "start-date": "1986-02-19", "slug": "/listed-building/1025338", "entry-date": "2021-05-28"}}