{"type": "Feature", "geometry": {"type": "Point", "coordinates": [0.033738, 51.097979]}, "properties": {"listed-building-grade": "II", "start-date": "1982-12-31", "listed-building": "1028379", "point": "POINT (0.033738 51.097979)", "documentation-url": "https://historicengland.org.uk/listing/the-list/list-entry/1028379", "name": "LIVING ART MIDLAND BANK THE PREMISES OF G N MORICE SOLICITOR", "slug": "/listed-building/1028379", "entry-date": "2021-05-28"}}