{"type": "Feature", "geometry": {"type": "Point", "coordinates": [-1.285786, 52.211347]}, "properties": {"start-date": "1986-04-21", "documentation-url": "https://historicengland.org.uk/listing/the-list/list-entry/1024434", "point": "POINT (-1.285786 52.211347)", "listed-building-grade": "II", "name": "Garden wall approximately 10 metres northwest of The Cedars", "listed-building": "1024434", "slug": "/listed-building/1024434", "entry-date": "2021-05-28"}}