{"type": "Feature", "geometry": {"type": "Point", "coordinates": [-0.732077, 50.858226]}, "properties": {"name": "THE OLD HOUSE", "point": "POINT (-0.732077 50.858226)", "listed-building": "1026413", "start-date": "1986-01-28", "documentation-url": "https://historicengland.org.uk/listing/the-list/list-entry/1026413", "listed-building-grade": "II", "slug": "/listed-building/1026413", "entry-date": "2021-05-28"}}