{"type": "Feature", "geometry": {"type": "Point", "coordinates": [-0.426395, 51.285064]}, "properties": {"documentation-url": "https://historicengland.org.uk/listing/the-list/list-entry/1029413", "start-date": "1985-04-11", "listed-building": "1029413", "name": "FOREST FARMHOUSE", "point": "POINT (-0.426395 51.285064)", "listed-building-grade": "II", "slug": "/listed-building/1029413", "entry-date": "2021-05-28"}}