{"type": "Feature", "geometry": {"type": "Point", "coordinates": [-1.457147, 55.010366]}, "properties": {"point": "POINT (-1.457147 55.010366)", "listed-building-grade": "II", "documentation-url": "https://historicengland.org.uk/listing/the-list/list-entry/1025341", "name": "Outpatients building of Victoria Jubilee Infirmary", "start-date": "1987-12-09", "listed-building": "1025341", "slug": "/listed-building/1025341", "entry-date": "2021-05-28"}}