{"type": "Feature", "geometry": {"type": "Point", "coordinates": [-1.608218, 54.969032]}, "properties": {"point": "POINT (-1.608218 54.969032)", "name": "WORKSHOPS, STAIRS AND WALL BEHIND NUMBERS 5-13 ODD", "listed-building": "1024750", "documentation-url": "https://historicengland.org.uk/listing/the-list/list-entry/1024750", "listed-building-grade": "II", "start-date": "1987-03-30", "slug": "/listed-building/1024750", "entry-date": "2021-05-28"}}