{"type": "Feature", "geometry": {"type": "Point", "coordinates": [-0.190535, 50.912474]}, "properties": {"listed-building-grade": "II", "listed-building": "1025628", "point": "POINT (-0.190535 50.912474)", "documentation-url": "https://historicengland.org.uk/listing/the-list/list-entry/1025628", "name": "STAR HOUSE", "start-date": "1983-05-11", "slug": "/listed-building/1025628", "entry-date": "2021-05-28"}}