{"type": "Feature", "geometry": {"type": "Point", "coordinates": [-1.871252, 51.081879]}, "properties": {"documentation-url": "https://historicengland.org.uk/listing/the-list/list-entry/1023736", "start-date": "1978-06-08", "listed-building": "1023736", "listed-building-grade": "II", "point": "POINT (-1.871252 51.081879)", "name": "37 39 AND 41, SHAFTSBURY ROAD", "slug": "/listed-building/1023736", "entry-date": "1995-11-21"}}