{"type": "Feature", "geometry": {"type": "Point", "coordinates": [1.316747, 52.133235]}, "properties": {"documentation-url": "https://historicengland.org.uk/listing/the-list/list-entry/1030744", "listed-building-grade": "II", "listed-building": "1030744", "point": "POINT (1.316747 52.133235)", "start-date": "1988-08-31", "name": "MOAT FARMHOUSE", "slug": "/listed-building/1030744", "entry-date": "2021-05-28"}}