{"type": "Feature", "geometry": {"type": "Point", "coordinates": [-0.778462, 50.83878]}, "properties": {"name": "62 AND 63, NORTH STREET", "listed-building": "1026720", "listed-building-grade": "II", "point": "POINT (-0.778462 50.838780)", "documentation-url": "https://historicengland.org.uk/listing/the-list/list-entry/1026720", "start-date": "1970-06-18", "slug": "/listed-building/1026720", "entry-date": "2021-05-28"}}