{"type": "Feature", "geometry": {"type": "Point", "coordinates": [-0.446569, 51.220074]}, "properties": {"point": "POINT (-0.446569 51.220074)", "documentation-url": "https://historicengland.org.uk/listing/the-list/list-entry/1029464", "listed-building-grade": "II", "name": "BARN 8 YARDS EAST OF EDMONDS FARM HOUSE", "listed-building": "1029464", "start-date": "1985-05-21", "slug": "/listed-building/1029464", "entry-date": "2021-05-28"}}