{"type": "Feature", "geometry": {"type": "Point", "coordinates": [-2.468268, 52.730025]}, "properties": {"listed-building-grade": "II*", "documentation-url": "https://historicengland.org.uk/listing/the-list/list-entry/1025044", "name": "HOO HALL", "point": "POINT (-2.468268 52.730025)", "start-date": "1959-06-18", "listed-building": "1025044", "slug": "/listed-building/1025044", "entry-date": "2021-05-28"}}