{"type": "Feature", "geometry": {"type": "Point", "coordinates": [-0.346898, 51.091371]}, "properties": {"start-date": "1980-11-28", "listed-building-grade": "II", "documentation-url": "https://historicengland.org.uk/listing/the-list/list-entry/1026879", "listed-building": "1026879", "name": "THE SUSSEX OAK INN", "point": "POINT (-0.346898 51.091371)", "slug": "/listed-building/1026879", "entry-date": "2021-05-28"}}