{"type": "Feature", "geometry": {"type": "Point", "coordinates": [1.384859, 52.25998]}, "properties": {"name": "THE OLD RECTORY", "start-date": "1984-12-21", "listed-building-grade": "II", "point": "POINT (1.384859 52.259980)", "documentation-url": "https://historicengland.org.uk/listing/the-list/list-entry/1030810", "listed-building": "1030810", "slug": "/listed-building/1030810", "entry-date": "2021-05-28"}}