{"type": "Feature", "geometry": {"type": "Point", "coordinates": [-1.741643, 50.991817]}, "properties": {"listed-building-grade": "I", "name": "THE MOOT WITH ATTACHED KITCHEN", "point": "POINT (-1.741643 50.991817)", "start-date": "1960-03-23", "documentation-url": "https://historicengland.org.uk/listing/the-list/list-entry/1023898", "listed-building": "1023898", "slug": "/listed-building/1023898", "entry-date": "1985-07-04"}}