{"type": "Feature", "geometry": {"type": "Point", "coordinates": [-1.321855, 52.212897]}, "properties": {"listed-building-grade": "II", "listed-building": "1024419", "point": "POINT (-1.321855 52.212897)", "documentation-url": "https://historicengland.org.uk/listing/the-list/list-entry/1024419", "name": "OXFORD CANAL, CANAL BRIDGE NUMBER 122", "start-date": "1986-04-21", "slug": "/listed-building/1024419", "entry-date": "2021-05-28"}}