{"type": "Feature", "geometry": {"type": "Point", "coordinates": [-1.868366, 52.214898]}, "properties": {"name": "4 AND 8 MALT MILL LANE", "point": "POINT (-1.868366 52.214898)", "listed-building": "1024623", "start-date": "1969-12-11", "listed-building-grade": "II", "documentation-url": "https://historicengland.org.uk/listing/the-list/list-entry/1024623", "slug": "/listed-building/1024623", "entry-date": "1985-06-21"}}