{"type": "Feature", "geometry": {"type": "Point", "coordinates": [-1.630066, 54.971701]}, "properties": {"listed-building": "1024890", "documentation-url": "https://historicengland.org.uk/listing/the-list/list-entry/1024890", "start-date": "1987-03-30", "listed-building-grade": "II", "point": "POINT (-1.630066 54.971701)", "name": "DRINKING FOUNTAIN IN WALL OF WESTGATE CEMETERY ONE METRE FROM EAST CORNER", "slug": "/listed-building/1024890", "entry-date": "2021-05-28"}}