{"type": "Feature", "geometry": {"type": "Point", "coordinates": [-0.333865, 51.049117]}, "properties": {"start-date": "1980-11-28", "listed-building": "1027068", "name": "GARDEN BALUSTRADE AND PIERS TO THE WEST OF DENNE PARK HOUSE", "listed-building-grade": "II", "point": "POINT (-0.333865 51.049117)", "documentation-url": "https://historicengland.org.uk/listing/the-list/list-entry/1027068", "slug": "/listed-building/1027068", "entry-date": "1982-01-28"}}