{"type": "Feature", "geometry": {"type": "Point", "coordinates": [-0.55651, 51.247722]}, "properties": {"name": "BARN ATTACHED TO BURCHATTS FARM COTTAGES", "point": "POINT (-0.556510 51.247722)", "start-date": "1987-10-13", "listed-building-grade": "II", "listed-building": "1029270", "documentation-url": "https://historicengland.org.uk/listing/the-list/list-entry/1029270", "slug": "/listed-building/1029270", "entry-date": "2021-05-28"}}