{"type": "Feature", "geometry": {"type": "Point", "coordinates": [-0.472863, 51.031483]}, "properties": {"name": "ROWNER", "start-date": "1980-11-28", "listed-building-grade": "II", "listed-building": "1027106", "documentation-url": "https://historicengland.org.uk/listing/the-list/list-entry/1027106", "point": "POINT (-0.472863 51.031483)", "slug": "/listed-building/1027106", "entry-date": "2021-05-28"}}