{"type": "Feature", "geometry": {"type": "Point", "coordinates": [0.685204, 52.301062]}, "properties": {"start-date": "1955-07-14", "point": "POINT (0.685204 52.301062)", "documentation-url": "https://historicengland.org.uk/listing/the-list/list-entry/1031236", "listed-building-grade": "II*", "name": "CULFORD HALL", "listed-building": "1031236", "slug": "/listed-building/1031236", "entry-date": "2021-05-28"}}