{"type": "Feature", "geometry": {"type": "Point", "coordinates": [-4.465478, 50.455217]}, "properties": {"name": "LISKERRIT HOUSE", "point": "POINT (-4.465478 50.455217)", "listed-building": "1024987", "documentation-url": "https://historicengland.org.uk/listing/the-list/list-entry/1024987", "listed-building-grade": "II", "start-date": "1981-07-22", "slug": "/listed-building/1024987", "entry-date": "2021-05-28"}}