{"type": "Feature", "geometry": {"type": "Point", "coordinates": [-0.361231, 51.148039]}, "properties": {"listed-building-grade": "II", "name": "ELDERSLIE, INCLUDING THE STABLES", "point": "POINT (-0.361231 51.148039)", "documentation-url": "https://historicengland.org.uk/listing/the-list/list-entry/1028701", "listed-building": "1028701", "start-date": "1966-11-11", "slug": "/listed-building/1028701", "entry-date": "2021-05-28"}}