{"type": "Feature", "geometry": {"type": "Point", "coordinates": [-0.333663, 50.951306]}, "properties": {"documentation-url": "https://historicengland.org.uk/listing/the-list/list-entry/1026841", "name": "POSBROOK COTTAGE", "point": "POINT (-0.333663 50.951306)", "start-date": "1980-11-28", "listed-building-grade": "II", "listed-building": "1026841", "slug": "/listed-building/1026841", "entry-date": "2021-05-28"}}