{"type": "Feature", "geometry": {"type": "Point", "coordinates": [-1.398532, 52.125657]}, "properties": {"point": "POINT (-1.398532 52.125657)", "name": "THE COURT HOUSE", "documentation-url": "https://historicengland.org.uk/listing/the-list/list-entry/1024137", "listed-building-grade": "II", "listed-building": "1024137", "start-date": "1987-04-08", "slug": "/listed-building/1024137", "entry-date": "2021-05-28"}}