{"type": "Feature", "geometry": {"type": "Point", "coordinates": [-2.258557, 51.439018]}, "properties": {"listed-building": "1022931", "start-date": "1985-12-09", "listed-building-grade": "II", "documentation-url": "https://historicengland.org.uk/listing/the-list/list-entry/1022931", "name": "UNIDENTIFIED TOMB IN CHURCHYARD, CIRCA 2 METES EAST OF GIBBONS TOMB, IN MEMORIAL GARDEN EAST OF CHURCH OF ST JOHN", "point": "POINT (-2.258557 51.439018)", "slug": "/listed-building/1022931", "entry-date": "2021-05-28"}}