{"type": "Feature", "geometry": {"type": "Point", "coordinates": [-2.120395, 51.415809]}, "properties": {"documentation-url": "https://historicengland.org.uk/listing/the-list/list-entry/1022154", "listed-building": "1022154", "point": "POINT (-2.120395 51.415809)", "start-date": "1987-01-07", "listed-building-grade": "II", "name": "THREE MONUMENTS IN CHURCHYARD ABOUT 25 METRES SOUTH OF CHANCEL OF CHURCH OF ST CYRIAC", "slug": "/listed-building/1022154", "entry-date": "2021-05-28"}}