{"type": "Feature", "geometry": {"type": "Point", "coordinates": [0.23482, 51.048067]}, "properties": {"listed-building-grade": "II", "documentation-url": "https://historicengland.org.uk/listing/the-list/list-entry/1028109", "start-date": "1982-12-31", "name": "OLD DORMERS", "point": "POINT (0.234820 51.048067)", "listed-building": "1028109", "slug": "/listed-building/1028109", "entry-date": "2021-05-28"}}