{"type": "Feature", "geometry": {"type": "Point", "coordinates": [-0.787464, 50.772563]}, "properties": {"documentation-url": "https://historicengland.org.uk/listing/the-list/list-entry/1026255", "listed-building-grade": "II", "point": "POINT (-0.787464 50.772563)", "start-date": "1986-01-28", "listed-building": "1026255", "name": "MUTTON'S FARMHOUSE", "slug": "/listed-building/1026255", "entry-date": "2021-05-28"}}