{"type": "Feature", "geometry": {"type": "Point", "coordinates": [-0.258803, 51.117242]}, "properties": {"point": "POINT (-0.258803 51.117242)", "listed-building-grade": "II", "start-date": "1971-09-02", "documentation-url": "https://historicengland.org.uk/listing/the-list/list-entry/1026952", "listed-building": "1026952", "name": "LAMBS COTTAGES", "slug": "/listed-building/1026952", "entry-date": "2021-05-28"}}