{"type": "Feature", "geometry": {"type": "Point", "coordinates": [0.106591, 51.119934]}, "properties": {"start-date": "1953-11-26", "point": "POINT (0.106591 51.119934)", "listed-building": "1028286", "name": "OUTBUILDING, NOW GARAGE, TO THE SOUTH EAST OF BOLEBROKE CASTLE", "documentation-url": "https://historicengland.org.uk/listing/the-list/list-entry/1028286", "listed-building-grade": "II", "slug": "/listed-building/1028286", "entry-date": "1982-12-31"}}