{"type": "Feature", "geometry": {"type": "Point", "coordinates": [-2.184867, 51.332327]}, "properties": {"start-date": "1988-06-14", "listed-building": "1021788", "name": "GARDEN WALLS ON NORTH, SOUTH AND EAST SIDES OF HILPERTON HOUSE", "documentation-url": "https://historicengland.org.uk/listing/the-list/list-entry/1021788", "point": "POINT (-2.184867 51.332327)", "listed-building-grade": "II", "slug": "/listed-building/1021788", "entry-date": "2021-05-28"}}