{"type": "Feature", "geometry": {"type": "Point", "coordinates": [-2.270725, 51.496698]}, "properties": {"start-date": "1985-12-09", "name": "UNIDENTIFIED MONUMENT IN CHURCHYARD ABOUT 2 METRES NORTH EAST OF CHANCEL SOUTH EAST ANGLE OF CHURCH OF ST MARY", "documentation-url": "https://historicengland.org.uk/listing/the-list/list-entry/1022978", "listed-building-grade": "II", "listed-building": "1022978", "point": "POINT (-2.270725 51.496698)", "slug": "/listed-building/1022978", "entry-date": "2021-05-28"}}