{"type": "Feature", "geometry": {"type": "Point", "coordinates": [-0.279491, 50.890734]}, "properties": {"documentation-url": "https://historicengland.org.uk/listing/the-list/list-entry/1027188", "name": "BURRELLS FARMHOUSE", "listed-building-grade": "II", "listed-building": "1027188", "start-date": "1980-05-09", "point": "POINT (-0.279491 50.890734)", "slug": "/listed-building/1027188", "entry-date": "2021-05-28"}}