{"type": "Feature", "geometry": {"type": "Point", "coordinates": [-0.77055, 50.909132]}, "properties": {"documentation-url": "https://historicengland.org.uk/listing/the-list/list-entry/1026113", "listed-building-grade": "II", "start-date": "1986-01-28", "listed-building": "1026113", "point": "POINT (-0.770550 50.909132)", "name": "131 AND 132, CHICHESTER ROAD", "slug": "/listed-building/1026113", "entry-date": "2021-05-28"}}