{"type": "Feature", "geometry": {"type": "Point", "coordinates": [-1.90084, 52.180937]}, "properties": {"listed-building-grade": "II", "start-date": "1969-12-11", "documentation-url": "https://historicengland.org.uk/listing/the-list/list-entry/1024685", "point": "POINT (-1.900840 52.180937)", "listed-building": "1024685", "name": "FOREST THATCH", "slug": "/listed-building/1024685", "entry-date": "2021-05-28"}}