{"type": "Feature", "geometry": {"type": "Point", "coordinates": [-1.801535, 51.566473]}, "properties": {"listed-building": "1023525", "listed-building-grade": "II", "point": "POINT (-1.801535 51.566473)", "start-date": "1970-02-17", "documentation-url": "https://historicengland.org.uk/listing/the-list/list-entry/1023525", "name": "CHURCH OF ST AUGUSTINE", "slug": "/listed-building/1023525", "entry-date": "2021-05-28"}}