{"type": "Feature", "geometry": {"type": "Point", "coordinates": [-1.915612, 51.208418]}, "properties": {"start-date": "1985-07-04", "point": "POINT (-1.915612 51.208418)", "listed-building-grade": "II", "documentation-url": "https://historicengland.org.uk/listing/the-list/list-entry/1023986", "listed-building": "1023986", "name": "GRANARY AT COZENS", "slug": "/listed-building/1023986", "entry-date": "2021-05-28"}}