{"type": "Feature", "geometry": {"type": "Point", "coordinates": [-0.544374, 50.828472]}, "properties": {"documentation-url": "https://historicengland.org.uk/listing/the-list/list-entry/1027819", "listed-building": "1027819", "point": "POINT (-0.544374 50.828472)", "listed-building-grade": "II", "name": "THE 6 BELLS PUBLIC HOUSE", "start-date": "1975-08-21", "slug": "/listed-building/1027819", "entry-date": "2021-05-28"}}