{"type": "Feature", "geometry": {"type": "Point", "coordinates": [-2.194217, 51.486141]}, "properties": {"point": "POINT (-2.194217 51.486141)", "documentation-url": "https://historicengland.org.uk/listing/the-list/list-entry/1023029", "name": "J HOLBOROW MONUMENT IN CHURCHYARD ABOUT 6 METRES NORTH OF NAVE, NORTH WEST OF PORCH OF CHURCH OF ST MARGARET", "listed-building": "1023029", "start-date": "1985-12-09", "listed-building-grade": "II", "slug": "/listed-building/1023029", "entry-date": "2021-05-28"}}