{"type": "Feature", "geometry": {"type": "Point", "coordinates": [0.234453, 50.808537]}, "properties": {"start-date": "1981-08-12", "name": "THATCHED COTTAGE", "listed-building-grade": "II", "listed-building": "1028506", "point": "POINT (0.234453 50.808537)", "documentation-url": "https://historicengland.org.uk/listing/the-list/list-entry/1028506", "slug": "/listed-building/1028506", "entry-date": "2021-05-28"}}