{"type": "Feature", "geometry": {"type": "Point", "coordinates": [-2.314523, 52.992053]}, "properties": {"listed-building": "1028005", "documentation-url": "https://historicengland.org.uk/listing/the-list/list-entry/1028005", "listed-building-grade": "II", "start-date": "1985-05-14", "name": "Farmbuildings to north of Lower Stoney Low House", "point": "POINT (-2.314523 52.992053)", "slug": "/listed-building/1028005", "entry-date": "2021-05-28"}}