{"type": "Feature", "geometry": {"type": "Point", "coordinates": [-0.08032, 51.001484]}, "properties": {"listed-building": "1025624", "start-date": "1973-02-28", "point": "POINT (-0.080320 51.001484)", "name": "GRAVELYE HOUSE", "listed-building-grade": "II", "documentation-url": "https://historicengland.org.uk/listing/the-list/list-entry/1025624", "slug": "/listed-building/1025624", "entry-date": "2021-05-28"}}