{"type": "Feature", "geometry": {"type": "Point", "coordinates": [-0.897674, 50.927461]}, "properties": {"point": "POINT (-0.897674 50.927461)", "name": "THE VICARAGE", "listed-building-grade": "II", "documentation-url": "https://historicengland.org.uk/listing/the-list/list-entry/1026382", "listed-building": "1026382", "start-date": "1958-06-05", "slug": "/listed-building/1026382", "entry-date": "2021-05-28"}}