{"type": "Feature", "geometry": {"type": "Point", "coordinates": [1.464829, 52.205265]}, "properties": {"documentation-url": "https://historicengland.org.uk/listing/the-list/list-entry/1030903", "listed-building-grade": "II", "start-date": "1951-10-25", "name": "OLD LODGE", "listed-building": "1030903", "point": "POINT (1.464829 52.205265)", "slug": "/listed-building/1030903", "entry-date": "2021-05-28"}}