{"type": "Feature", "geometry": {"type": "Point", "coordinates": [-0.136822, 51.267378]}, "properties": {"documentation-url": "https://historicengland.org.uk/listing/the-list/list-entry/1029064", "start-date": "1977-03-31", "listed-building-grade": "II", "point": "POINT (-0.136822 51.267378)", "listed-building": "1029064", "name": "NODDYSHALL AND NODDYSHALL COTTAGE", "slug": "/listed-building/1029064", "entry-date": "2021-05-28"}}