{"type": "Feature", "geometry": {"type": "Point", "coordinates": [-0.143422, 51.005301]}, "properties": {"listed-building-grade": "II", "start-date": "1987-12-11", "name": "CUCKFIELD CHURCH OF ENGLAND PRIMARY SCHOOL", "point": "POINT (-0.143422 51.005301)", "documentation-url": "https://historicengland.org.uk/listing/the-list/list-entry/1025520", "listed-building": "1025520", "slug": "/listed-building/1025520", "entry-date": "2021-05-28"}}