{"type": "Feature", "geometry": {"type": "Point", "coordinates": [-0.076994, 51.018166]}, "properties": {"listed-building": "1025454", "documentation-url": "https://historicengland.org.uk/listing/the-list/list-entry/1025454", "listed-building-grade": "II", "name": "CLOCK HOUSE", "start-date": "1970-04-06", "point": "POINT (-0.076994 51.018166)", "slug": "/listed-building/1025454", "entry-date": "1987-12-11"}}