{"type": "Feature", "geometry": {"type": "Point", "coordinates": [-0.400296, 51.093714]}, "properties": {"point": "POINT (-0.400296 51.093714)", "name": "BURNT HOUSE", "listed-building-grade": "II", "documentation-url": "https://historicengland.org.uk/listing/the-list/list-entry/1026903", "start-date": "1980-11-28", "listed-building": "1026903", "slug": "/listed-building/1026903", "entry-date": "1982-01-28"}}