{"type": "Feature", "geometry": {"type": "Point", "coordinates": [-0.57081, 51.235677]}, "properties": {"listed-building-grade": "II", "listed-building": "1029260", "start-date": "1988-03-15", "name": "ELKINS VAULT, APPROXIMATELY 12 METRES SOUTH WEST OF CHURCH OF HOLY TRINITY", "documentation-url": "https://historicengland.org.uk/listing/the-list/list-entry/1029260", "point": "POINT (-0.570810 51.235677)", "slug": "/listed-building/1029260", "entry-date": "2021-05-28"}}