{"type": "Feature", "geometry": {"type": "Point", "coordinates": [1.344009, 52.222528]}, "properties": {"documentation-url": "https://historicengland.org.uk/listing/the-list/list-entry/1030392", "listed-building": "1030392", "start-date": "1951-10-25", "name": "ST MICHAEL'S CLOSE", "point": "POINT (1.344009 52.222528)", "listed-building-grade": "II", "slug": "/listed-building/1030392", "entry-date": "1985-12-18"}}