{"type": "Feature", "geometry": {"type": "Point", "coordinates": [0.137195, 50.937863]}, "properties": {"listed-building-grade": "II", "documentation-url": "https://historicengland.org.uk/listing/the-list/list-entry/1028350", "start-date": "1982-12-31", "point": "POINT (0.137195 50.937863)", "listed-building": "1028350", "name": "OUTBUILDING TO THE NORTH EAST OF LOWER HONEYS GREEN FARMHOUSE", "slug": "/listed-building/1028350", "entry-date": "2021-05-28"}}