{"type": "Feature", "geometry": {"type": "Point", "coordinates": [-1.740821, 54.982541]}, "properties": {"listed-building-grade": "II", "listed-building": "1024974", "documentation-url": "https://historicengland.org.uk/listing/the-list/list-entry/1024974", "point": "POINT (-1.740821 54.982541)", "name": "HEDLEY TOMBS ABOUT ONE METRE SOUTH OF CHURCH OF ST MICHAEL AND ALL ANGELS", "start-date": "1987-03-30", "slug": "/listed-building/1024974", "entry-date": "2021-05-28"}}