{"type": "Feature", "geometry": {"type": "Point", "coordinates": [-2.098892, 51.280396]}, "properties": {"listed-building": "1021496", "point": "POINT (-2.098892 51.280396)", "name": "SHORE HOUSE", "listed-building-grade": "II", "start-date": "1968-09-11", "documentation-url": "https://historicengland.org.uk/listing/the-list/list-entry/1021496", "slug": "/listed-building/1021496", "entry-date": "2021-05-28"}}