{"type": "Feature", "geometry": {"type": "Point", "coordinates": [-0.518856, 50.871588]}, "properties": {"listed-building-grade": "II", "start-date": "1984-09-20", "listed-building": "1027662", "documentation-url": "https://historicengland.org.uk/listing/the-list/list-entry/1027662", "name": "BURPHAM FARM HOUSE", "point": "POINT (-0.518856 50.871588)", "slug": "/listed-building/1027662", "entry-date": "2021-05-28"}}