{"type": "Feature", "geometry": {"type": "Point", "coordinates": [-0.593558, 51.351612]}, "properties": {"listed-building-grade": "II", "listed-building": "1030016", "start-date": "1984-07-19", "documentation-url": "https://historicengland.org.uk/listing/the-list/list-entry/1030016", "point": "POINT (-0.593558 51.351612)", "name": "THREE WAYS COTTAGE", "slug": "/listed-building/1030016", "entry-date": "2021-05-28"}}