{"type": "Feature", "geometry": {"type": "Point", "coordinates": [-0.373478, 51.279871]}, "properties": {"start-date": "1990-08-24", "documentation-url": "https://historicengland.org.uk/listing/the-list/list-entry/1028642", "listed-building": "1028642", "name": "LAWSON HEADSTONE APPROXIMATELY 17 METRES EAST OF CHANCEL OF CHURCH OF ST NICHOLAS", "point": "POINT (-0.373478 51.279871)", "listed-building-grade": "II", "slug": "/listed-building/1028642", "entry-date": "2021-05-28"}}