{"type": "Feature", "geometry": {"type": "Point", "coordinates": [-0.146312, 50.909505]}, "properties": {"listed-building-grade": "II", "point": "POINT (-0.146312 50.909505)", "documentation-url": "https://historicengland.org.uk/listing/the-list/list-entry/1025723", "listed-building": "1025723", "start-date": "1957-10-28", "name": "CLAYTON CASTLE", "slug": "/listed-building/1025723", "entry-date": "2021-05-28"}}