{"type": "Feature", "geometry": {"type": "Point", "coordinates": [-0.73733, 50.90808]}, "properties": {"listed-building-grade": "II", "documentation-url": "https://historicengland.org.uk/listing/the-list/list-entry/1026197", "name": "THE FORMER STABLES OF FOX HALL TO THE EAST OF THE HOUSE", "start-date": "1986-01-28", "point": "POINT (-0.737330 50.908080)", "listed-building": "1026197", "slug": "/listed-building/1026197", "entry-date": "2021-05-28"}}