{"type": "Feature", "geometry": {"type": "Point", "coordinates": [-0.080682, 51.184842]}, "properties": {"listed-building-grade": "II", "listed-building": "1029945", "point": "POINT (-0.080682 51.184842)", "name": "WHITEWOOD HOUSE FARM HOUSE", "documentation-url": "https://historicengland.org.uk/listing/the-list/list-entry/1029945", "start-date": "1973-03-22", "slug": "/listed-building/1029945", "entry-date": "2021-05-28"}}