{"type": "Feature", "geometry": {"type": "Point", "coordinates": [-1.620978, 54.970419]}, "properties": {"listed-building": "1024741", "documentation-url": "https://historicengland.org.uk/listing/the-list/list-entry/1024741", "listed-building-grade": "I", "point": "POINT (-1.620978 54.970419)", "start-date": "1974-05-31", "name": "TYNE THEATRE AND OPERA HOUSE", "slug": "/listed-building/1024741", "entry-date": "1987-03-30"}}