{"type": "Feature", "geometry": {"type": "Point", "coordinates": [-0.22876, 51.284669]}, "properties": {"listed-building-grade": "II", "point": "POINT (-0.228760 51.284669)", "start-date": "1983-09-29", "listed-building": "1029057", "documentation-url": "https://historicengland.org.uk/listing/the-list/list-entry/1029057", "name": "MILLFIELD, INCLUDING GARAGE WING AND RETURN WALL", "slug": "/listed-building/1029057", "entry-date": "2021-05-28"}}