{"type": "Feature", "geometry": {"type": "Point", "coordinates": [-2.240654, 53.793694]}, "properties": {"listed-building-grade": "II", "documentation-url": "https://historicengland.org.uk/listing/the-list/list-entry/1022619", "name": "SHOREY WELL IN GARDEN OF BURNLEY COLLEGE ADULT EDUCATION CENTRE", "listed-building": "1022619", "start-date": "1977-09-29", "point": "POINT (-2.240654 53.793694)", "slug": "/listed-building/1022619", "entry-date": "1997-11-19"}}