{"type": "Feature", "geometry": {"type": "Point", "coordinates": [-1.311135, 52.201832]}, "properties": {"name": "ROW OF 6 HEADSTONES APPROXIMATELY 14 METRES SOUTH OF NAVE OF CHURCH OF ST MARY", "listed-building-grade": "II", "point": "POINT (-1.311135 52.201832)", "documentation-url": "https://historicengland.org.uk/listing/the-list/list-entry/1024456", "listed-building": "1024456", "start-date": "1986-04-21", "slug": "/listed-building/1024456", "entry-date": "2021-05-28"}}