{"type": "Feature", "geometry": {"type": "Point", "coordinates": [0.207706, 51.094164]}, "properties": {"name": "HAMSELL WOOD FARMHOUSE", "listed-building-grade": "II", "point": "POINT (0.207706 51.094164)", "start-date": "1982-12-31", "listed-building": "1028168", "documentation-url": "https://historicengland.org.uk/listing/the-list/list-entry/1028168", "slug": "/listed-building/1028168", "entry-date": "2021-05-28"}}