{"type": "Feature", "geometry": {"type": "Point", "coordinates": [-0.238699, 51.230269]}, "properties": {"name": "MILLERS COTTAGE", "listed-building-grade": "II", "point": "POINT (-0.238699 51.230269)", "start-date": "1951-10-19", "listed-building": "1029071", "documentation-url": "https://historicengland.org.uk/listing/the-list/list-entry/1029071", "slug": "/listed-building/1029071", "entry-date": "2021-05-28"}}