{"type": "Feature", "geometry": {"type": "Point", "coordinates": [-2.198236, 51.460766]}, "properties": {"listed-building": "1022831", "documentation-url": "https://historicengland.org.uk/listing/the-list/list-entry/1022831", "point": "POINT (-2.198236 51.460766)", "start-date": "1985-12-09", "name": "GATEPIERS TO ELM HOUSE FARMHOUSE", "listed-building-grade": "II", "slug": "/listed-building/1022831", "entry-date": "2021-05-28"}}