{"type": "Feature", "geometry": {"type": "Point", "coordinates": [-1.862549, 51.080242]}, "properties": {"listed-building-grade": "II", "listed-building": "1023718", "start-date": "1951-08-04", "name": "THE OLD RECTORY", "documentation-url": "https://historicengland.org.uk/listing/the-list/list-entry/1023718", "point": "POINT (-1.862549 51.080242)", "slug": "/listed-building/1023718", "entry-date": "2021-05-28"}}