{"type": "Feature", "geometry": {"type": "Point", "coordinates": [-0.717607, 51.000083]}, "properties": {"listed-building-grade": "II", "start-date": "1987-11-26", "name": "HOLLY COTTAGE", "listed-building": "1026041", "point": "POINT (-0.717607 51.000083)", "documentation-url": "https://historicengland.org.uk/listing/the-list/list-entry/1026041", "slug": "/listed-building/1026041", "entry-date": "2021-05-28"}}