{"type": "Feature", "geometry": {"type": "Point", "coordinates": [-0.501872, 50.957506]}, "properties": {"point": "POINT (-0.501872 50.957506)", "start-date": "1980-05-09", "listed-building-grade": "II", "documentation-url": "https://historicengland.org.uk/listing/the-list/list-entry/1027348", "listed-building": "1027348", "name": "50 LOWER STREET", "slug": "/listed-building/1027348", "entry-date": "2021-05-28"}}