{"type": "Feature", "geometry": {"type": "Point", "coordinates": [0.065828, 50.989574]}, "properties": {"listed-building-grade": "II", "start-date": "1972-12-28", "point": "POINT (0.065828 50.989574)", "listed-building": "1028255", "documentation-url": "https://historicengland.org.uk/listing/the-list/list-entry/1028255", "name": "PARK WOOD HOUSE", "slug": "/listed-building/1028255", "entry-date": "1982-12-31"}}