{"type": "Feature", "geometry": {"type": "Point", "coordinates": [-0.234396, 50.8345]}, "properties": {"listed-building": "1027857", "listed-building-grade": "II", "start-date": "1969-09-19", "documentation-url": "https://historicengland.org.uk/listing/the-list/list-entry/1027857", "name": "MANOR COTTAGE", "point": "POINT (-0.234396 50.834500)", "slug": "/listed-building/1027857", "entry-date": "2021-05-28"}}