{"type": "Feature", "geometry": {"type": "Point", "coordinates": [1.465833, 52.091743]}, "properties": {"start-date": "1966-03-16", "name": "BUTLEY ABBEY COTTAGE", "listed-building-grade": "II", "listed-building": "1030852", "point": "POINT (1.465833 52.091743)", "documentation-url": "https://historicengland.org.uk/listing/the-list/list-entry/1030852", "slug": "/listed-building/1030852", "entry-date": "1984-05-02"}}