{"type": "Feature", "geometry": {"type": "Point", "coordinates": [-0.343078, 51.282305]}, "properties": {"start-date": "1989-10-06", "point": "POINT (-0.343078 51.282305)", "listed-building": "1028599", "listed-building-grade": "II", "documentation-url": "https://historicengland.org.uk/listing/the-list/list-entry/1028599", "name": "WELL HOUSE APPROXIMATELY 50 METRES SOUTH OF BOCKETTS FARMHOUSE, WITH ATTACHED FARMYARD WALLS", "slug": "/listed-building/1028599", "entry-date": "2021-05-28"}}