{"type": "Feature", "geometry": {"type": "Point", "coordinates": [-0.398863, 51.066323]}, "properties": {"listed-building": "1026940", "point": "POINT (-0.398863 51.066323)", "documentation-url": "https://historicengland.org.uk/listing/the-list/list-entry/1026940", "start-date": "1959-09-22", "listed-building-grade": "II", "name": "GASKYNS", "slug": "/listed-building/1026940", "entry-date": "1980-11-28"}}