{"type": "Feature", "geometry": {"type": "Point", "coordinates": [0.140612, 51.134722]}, "properties": {"start-date": "1982-12-31", "name": "POUND FARMHOUSE", "listed-building": "1028037", "point": "POINT (0.140612 51.134722)", "listed-building-grade": "II", "documentation-url": "https://historicengland.org.uk/listing/the-list/list-entry/1028037", "slug": "/listed-building/1028037", "entry-date": "2021-05-28"}}