{"type": "Feature", "geometry": {"type": "Point", "coordinates": [-0.088982, 51.052257]}, "properties": {"start-date": "1983-05-11", "point": "POINT (-0.088982 51.052257)", "name": "Jordan's Cottage", "listed-building": "1025763", "listed-building-grade": "II", "documentation-url": "https://historicengland.org.uk/listing/the-list/list-entry/1025763", "slug": "/listed-building/1025763", "entry-date": "1983-08-18"}}