{"type": "Feature", "geometry": {"type": "Point", "coordinates": [-0.211938, 51.214512]}, "properties": {"start-date": "1951-10-19", "name": "HARTSWOOD MANOR", "documentation-url": "https://historicengland.org.uk/listing/the-list/list-entry/1029104", "point": "POINT (-0.211938 51.214512)", "listed-building-grade": "II*", "listed-building": "1029104", "slug": "/listed-building/1029104", "entry-date": "2021-05-28"}}