{"type": "Feature", "geometry": {"type": "Point", "coordinates": [-1.566496, 54.948329]}, "properties": {"start-date": "1985-11-18", "point": "POINT (-1.566496 54.948329)", "listed-building-grade": "II", "listed-building": "1025181", "documentation-url": "https://historicengland.org.uk/listing/the-list/list-entry/1025181", "name": "CROW HALL COTTAGE AND GARDEN WALL ATTACHED TO LEFT CORNER OF HOUSE", "slug": "/listed-building/1025181", "entry-date": "2021-05-28"}}