{"type": "Feature", "geometry": {"type": "Point", "coordinates": [0.749617, 52.379408]}, "properties": {"name": "ROSE COTTAGE", "listed-building-grade": "II", "listed-building": "1031279", "start-date": "1984-04-12", "point": "POINT (0.749617 52.379408)", "documentation-url": "https://historicengland.org.uk/listing/the-list/list-entry/1031279", "slug": "/listed-building/1031279", "entry-date": "2021-05-28"}}