{"type": "Feature", "geometry": {"type": "Point", "coordinates": [-0.779075, 50.836135]}, "properties": {"listed-building": "1026622", "point": "POINT (-0.779075 50.836135)", "start-date": "1971-10-08", "name": "70 AND 71, SOUTH STREET", "listed-building-grade": "II", "documentation-url": "https://historicengland.org.uk/listing/the-list/list-entry/1026622", "slug": "/listed-building/1026622", "entry-date": "2021-05-28"}}