{"type": "Feature", "geometry": {"type": "Point", "coordinates": [-0.195283, 51.049586]}, "properties": {"documentation-url": "https://historicengland.org.uk/listing/the-list/list-entry/1025612", "listed-building": "1025612", "start-date": "1981-09-29", "point": "POINT (-0.195283 51.049586)", "name": "Nymans", "listed-building-grade": "II", "slug": "/listed-building/1025612", "entry-date": "2021-05-28"}}