{"type": "Feature", "geometry": {"type": "Point", "coordinates": [-0.246277, 51.280328]}, "properties": {"listed-building": "1029051", "name": "Little Chesters, boundary wall and pavilion south of the house", "listed-building-grade": "II", "documentation-url": "https://historicengland.org.uk/listing/the-list/list-entry/1029051", "point": "POINT (-0.246277 51.280328)", "start-date": "1983-09-29", "slug": "/listed-building/1029051", "entry-date": "2021-05-28"}}