{"type": "Feature", "geometry": {"type": "Point", "coordinates": [-1.866771, 52.178855]}, "properties": {"listed-building": "1024670", "point": "POINT (-1.866771 52.178855)", "name": "The Old Cottage", "listed-building-grade": "II", "documentation-url": "https://historicengland.org.uk/listing/the-list/list-entry/1024670", "start-date": "1984-12-13", "slug": "/listed-building/1024670", "entry-date": "2021-05-28"}}