{"type": "Feature", "geometry": {"type": "Point", "coordinates": [-0.177488, 51.229745]}, "properties": {"name": "8 AND 9, PENDLETON ROAD", "start-date": "1977-03-31", "listed-building": "1029098", "point": "POINT (-0.177488 51.229745)", "documentation-url": "https://historicengland.org.uk/listing/the-list/list-entry/1029098", "listed-building-grade": "II", "slug": "/listed-building/1029098", "entry-date": "2021-05-28"}}