{"type": "Feature", "geometry": {"type": "Point", "coordinates": [-0.848187, 50.859348]}, "properties": {"listed-building": "1026325", "listed-building-grade": "II", "name": "OLD MALTHOUSE COTTAGE", "start-date": "1986-01-28", "point": "POINT (-0.848187 50.859348)", "documentation-url": "https://historicengland.org.uk/listing/the-list/list-entry/1026325", "slug": "/listed-building/1026325", "entry-date": "2021-05-28"}}