{"type": "Feature", "geometry": {"type": "Point", "coordinates": [-1.860227, 51.078342]}, "properties": {"name": "LOGGIA TO WEST OF WILTON PARK TOGETHER WITH REAR WALL AND APPROACH STEPS AND QUADRANTS", "documentation-url": "https://historicengland.org.uk/listing/the-list/list-entry/1023768", "start-date": "1951-08-04", "point": "POINT (-1.860227 51.078342)", "listed-building": "1023768", "listed-building-grade": "I", "slug": "/listed-building/1023768", "entry-date": "1978-06-08"}}