{"type": "Feature", "geometry": {"type": "Point", "coordinates": [-0.536242, 51.406671]}, "properties": {"point": "POINT (-0.536242 51.406671)", "listed-building-grade": "II", "name": "IVY COTTAGE", "documentation-url": "https://historicengland.org.uk/listing/the-list/list-entry/1028956", "start-date": "1986-11-17", "listed-building": "1028956", "slug": "/listed-building/1028956", "entry-date": "2021-05-28"}}