{"type": "Feature", "geometry": {"type": "Point", "coordinates": [0.097746, 50.973752]}, "properties": {"listed-building": "1028128", "listed-building-grade": "II", "documentation-url": "https://historicengland.org.uk/listing/the-list/list-entry/1028128", "start-date": "1982-12-31", "point": "POINT (0.097746 50.973752)", "name": "224 AND 226, HIGH STREET", "slug": "/listed-building/1028128", "entry-date": "2021-05-28"}}