{"type": "Feature", "geometry": {"type": "Point", "coordinates": [-0.522557, 51.283322]}, "properties": {"point": "POINT (-0.522557 51.283322)", "listed-building-grade": "II", "start-date": "1985-11-25", "name": "SEND BARNS", "listed-building": "1029345", "documentation-url": "https://historicengland.org.uk/listing/the-list/list-entry/1029345", "slug": "/listed-building/1029345", "entry-date": "2021-05-28"}}