{"type": "Feature", "geometry": {"type": "Point", "coordinates": [-0.451919, 50.935775]}, "properties": {"name": "ROUNDABOUT FARMHOUSE", "listed-building-grade": "II", "listed-building": "1027241", "point": "POINT (-0.451919 50.935775)", "start-date": "1980-05-09", "documentation-url": "https://historicengland.org.uk/listing/the-list/list-entry/1027241", "slug": "/listed-building/1027241", "entry-date": "2021-05-28"}}