{"type": "Feature", "geometry": {"type": "Point", "coordinates": [-1.881114, 51.5394]}, "properties": {"listed-building-grade": "II", "point": "POINT (-1.881114 51.539400)", "listed-building": "1022691", "start-date": "1985-08-15", "documentation-url": "https://historicengland.org.uk/listing/the-list/list-entry/1022691", "name": "LOWER WOODSHAW FARM", "slug": "/listed-building/1022691", "entry-date": "2021-05-28"}}