{"type": "Feature", "geometry": {"type": "Point", "coordinates": [-2.207921, 51.31694]}, "properties": {"listed-building-grade": "II", "listed-building": "1021628", "documentation-url": "https://historicengland.org.uk/listing/the-list/list-entry/1021628", "point": "POINT (-2.207921 51.316940)", "start-date": "1976-11-26", "name": "GATE AND GATEPIERS OF LONGFIELD HOUSE ON MORTIMER STREET", "slug": "/listed-building/1021628", "entry-date": "2021-05-28"}}