{"type": "Feature", "geometry": {"type": "Point", "coordinates": [-2.090262, 51.413861]}, "properties": {"point": "POINT (-2.090262 51.413861)", "listed-building-grade": "II", "listed-building": "1022133", "name": "STABLE BLOCK AT BOWDEN PARK", "documentation-url": "https://historicengland.org.uk/listing/the-list/list-entry/1022133", "start-date": "1987-01-07", "slug": "/listed-building/1022133", "entry-date": "2021-05-28"}}