{"type": "Feature", "geometry": {"type": "Point", "coordinates": [-1.677889, 51.049594]}, "properties": {"listed-building-grade": "II", "documentation-url": "https://historicengland.org.uk/listing/the-list/list-entry/1023818", "point": "POINT (-1.677889 51.049594)", "name": "MAYPOLE FARMHOUSE", "start-date": "1985-03-28", "listed-building": "1023818", "slug": "/listed-building/1023818", "entry-date": "2021-05-28"}}