{"type": "Feature", "geometry": {"type": "Point", "coordinates": [-1.677398, 54.94542]}, "properties": {"name": "WHICKHAM COTTAGE HOSPITAL", "point": "POINT (-1.677398 54.945420)", "start-date": "1985-11-18", "listed-building": "1025142", "listed-building-grade": "II", "documentation-url": "https://historicengland.org.uk/listing/the-list/list-entry/1025142", "slug": "/listed-building/1025142", "entry-date": "2021-05-28"}}