{"type": "Feature", "geometry": {"type": "Point", "coordinates": [-1.367509, 52.142492]}, "properties": {"name": "WAR MEMORIAL APPROXIMATELY 16 METRES SOUTH OF PORCH OF CHURCH OF ST BOTOLPH", "point": "POINT (-1.367509 52.142492)", "listed-building": "1024468", "start-date": "1986-04-21", "documentation-url": "https://historicengland.org.uk/listing/the-list/list-entry/1024468", "listed-building-grade": "II", "slug": "/listed-building/1024468", "entry-date": "2021-05-28"}}