{"type": "Feature", "geometry": {"type": "Point", "coordinates": [-2.255693, 51.414997]}, "properties": {"documentation-url": "https://historicengland.org.uk/listing/the-list/list-entry/1022754", "listed-building-grade": "II", "name": "UNIDENTIFIED MONUMENT IN CHURCHYARD ABOUT 2 METRES NORTH WEST OF SEYMER MONUMENT, SOUTH EAST OF ORGAN CHAMBER OF CHURCH OF ST THOMAS", "start-date": "1985-07-24", "listed-building": "1022754", "point": "POINT (-2.255693 51.414997)", "slug": "/listed-building/1022754", "entry-date": "2021-05-28"}}