{"type": "Feature", "geometry": {"type": "Point", "coordinates": [0.939392, 50.985654]}, "properties": {"documentation-url": "https://historicengland.org.uk/listing/the-list/list-entry/1025314", "listed-building-grade": "II", "listed-building": "1025314", "name": "28 AND 30, HIGH STREET", "point": "POINT (0.939392 50.985654)", "start-date": "1973-05-21", "slug": "/listed-building/1025314", "entry-date": "2021-05-28"}}