{"type": "Feature", "geometry": {"type": "Point", "coordinates": [0.770136, 52.267687]}, "properties": {"documentation-url": "https://historicengland.org.uk/listing/the-list/list-entry/1031156", "point": "POINT (0.770136 52.267687)", "listed-building-grade": "II", "name": "THINGOE COTTAGE", "listed-building": "1031156", "start-date": "1985-03-28", "slug": "/listed-building/1031156", "entry-date": "2021-05-28"}}