{"type": "Feature", "geometry": {"type": "Point", "coordinates": [-2.137358, 51.466836]}, "properties": {"start-date": "1985-12-09", "documentation-url": "https://historicengland.org.uk/listing/the-list/list-entry/1022902", "listed-building-grade": "II", "name": "MILESTONE ABOUT 100 METRES NORTH WEST OF JUNCTION WITH OLD HARDENHUISH LANE", "point": "POINT (-2.137358 51.466836)", "listed-building": "1022902", "slug": "/listed-building/1022902", "entry-date": "2021-05-28"}}