{"type": "Feature", "geometry": {"type": "Point", "coordinates": [-0.061039, 51.227712]}, "properties": {"listed-building": "1029784", "name": "FOX AND HOUNDS PUBLIC HOUSE", "point": "POINT (-0.061039 51.227712)", "listed-building-grade": "II", "documentation-url": "https://historicengland.org.uk/listing/the-list/list-entry/1029784", "start-date": "1958-06-11", "slug": "/listed-building/1029784", "entry-date": "2021-05-28"}}