{"type": "Feature", "geometry": {"type": "Point", "coordinates": [-0.389991, 51.219696]}, "properties": {"start-date": "1987-03-11", "name": "CHEST TOMB, 25 METRES SOUTH WEST OF CHURCH OF ST JOHN", "point": "POINT (-0.389991 51.219696)", "documentation-url": "https://historicengland.org.uk/listing/the-list/list-entry/1028805", "listed-building": "1028805", "listed-building-grade": "II", "slug": "/listed-building/1028805", "entry-date": "2021-05-28"}}