{"type": "Feature", "geometry": {"type": "Point", "coordinates": [-0.72872, 50.994628]}, "properties": {"start-date": "1987-11-26", "name": "IVY COTTAGE", "listed-building-grade": "II", "documentation-url": "https://historicengland.org.uk/listing/the-list/list-entry/1026034", "point": "POINT (-0.728720 50.994628)", "listed-building": "1026034", "slug": "/listed-building/1026034", "entry-date": "2021-05-28"}}