{"type": "Feature", "geometry": {"type": "Point", "coordinates": [-0.789081, 50.735754]}, "properties": {"point": "POINT (-0.789081 50.735754)", "name": "Outbuilding between 22, and 24, 26 and 28, High Street", "listed-building-grade": "II", "start-date": "1986-01-28", "documentation-url": "https://historicengland.org.uk/listing/the-list/list-entry/1026268", "listed-building": "1026268", "slug": "/listed-building/1026268", "entry-date": "2021-05-28"}}