{"type": "Feature", "geometry": {"type": "Point", "coordinates": [-1.623557, 51.014128]}, "properties": {"name": "BARN AT LOWER COWESFIELD FARM", "listed-building": "1024011", "point": "POINT (-1.623557 51.014128)", "start-date": "1985-07-04", "listed-building-grade": "II", "documentation-url": "https://historicengland.org.uk/listing/the-list/list-entry/1024011", "slug": "/listed-building/1024011", "entry-date": "2021-05-28"}}