{"type": "Feature", "geometry": {"type": "Point", "coordinates": [-0.319871, 51.157593]}, "properties": {"start-date": "1987-09-29", "point": "POINT (-0.319871 51.157593)", "documentation-url": "https://historicengland.org.uk/listing/the-list/list-entry/1028734", "name": "BAKERS COTTAGES", "listed-building": "1028734", "listed-building-grade": "II", "slug": "/listed-building/1028734", "entry-date": "2021-05-28"}}