{"type": "Feature", "geometry": {"type": "Point", "coordinates": [-1.866737, 51.572787]}, "properties": {"name": "BEWLEY MONUMENT IN CHURCHYARD, 4 METRES WEST OF SOUTH PORCH. CHURCH OF ALL SAINTS", "start-date": "1986-04-17", "listed-building": "1023146", "documentation-url": "https://historicengland.org.uk/listing/the-list/list-entry/1023146", "listed-building-grade": "II", "point": "POINT (-1.866737 51.572787)", "slug": "/listed-building/1023146", "entry-date": "2021-05-28"}}