{"type": "Feature", "geometry": {"type": "Point", "coordinates": [-0.331253, 51.392063]}, "properties": {"point": "POINT (-0.331253 51.392063)", "start-date": "1953-08-14", "documentation-url": "https://historicengland.org.uk/listing/the-list/list-entry/1030197", "listed-building": "1030197", "name": "Home of Compassion", "listed-building-grade": "II*", "slug": "/listed-building/1030197", "entry-date": "2014-06-25"}}