{"type": "Feature", "geometry": {"type": "Point", "coordinates": [-0.889686, 50.882844]}, "properties": {"name": "THE GARDEN WALLS AND GATE PIERS OF LORDINGTON HOUSE TO THE NORTH AND EAST OF THE HOUSE", "point": "POINT (-0.889686 50.882844)", "listed-building-grade": "II", "documentation-url": "https://historicengland.org.uk/listing/the-list/list-entry/1026187", "start-date": "1986-01-28", "listed-building": "1026187", "slug": "/listed-building/1026187", "entry-date": "2021-05-28"}}