{"type": "Feature", "geometry": {"type": "Point", "coordinates": [0.237497, 51.111594]}, "properties": {"name": "SPRATSBROOK FARMHOUSE", "start-date": "1987-12-10", "listed-building-grade": "II", "documentation-url": "https://historicengland.org.uk/listing/the-list/list-entry/1027992", "point": "POINT (0.237497 51.111594)", "listed-building": "1027992", "slug": "/listed-building/1027992", "entry-date": "2021-05-28"}}