{"type": "Feature", "geometry": {"type": "Point", "coordinates": [1.341164, 52.219034]}, "properties": {"listed-building": "1030338", "start-date": "1951-10-25", "point": "POINT (1.341164 52.219034)", "name": "ROUND HOUSE", "documentation-url": "https://historicengland.org.uk/listing/the-list/list-entry/1030338", "listed-building-grade": "II", "slug": "/listed-building/1030338", "entry-date": "1985-12-18"}}