{"type": "Feature", "geometry": {"type": "Point", "coordinates": [-0.352829, 51.023675]}, "properties": {"point": "POINT (-0.352829 51.023675)", "name": "THE COCK INN", "start-date": "1980-11-28", "listed-building-grade": "II", "listed-building": "1027042", "documentation-url": "https://historicengland.org.uk/listing/the-list/list-entry/1027042", "slug": "/listed-building/1027042", "entry-date": "2021-05-28"}}