{"type": "Feature", "geometry": {"type": "Point", "coordinates": [-1.795371, 51.066191]}, "properties": {"documentation-url": "https://historicengland.org.uk/listing/the-list/list-entry/1023595", "name": "THEOLOGICAL COLLEGE", "listed-building-grade": "I", "listed-building": "1023595", "start-date": "1952-02-28", "point": "POINT (-1.795371 51.066191)", "slug": "/listed-building/1023595", "entry-date": "2021-05-28"}}