{"type": "Feature", "geometry": {"type": "Point", "coordinates": [1.318465, 52.092979]}, "properties": {"documentation-url": "https://historicengland.org.uk/listing/the-list/list-entry/1030978", "point": "POINT (1.318465 52.092979)", "start-date": "1971-12-20", "name": "34 Thoroughfare, Woodbridge", "listed-building": "1030978", "listed-building-grade": "II", "slug": "/listed-building/1030978", "entry-date": "2021-05-28"}}