{"type": "Feature", "geometry": {"type": "Point", "coordinates": [-1.758508, 51.523827]}, "properties": {"name": "BARN AT LODGE FARM", "documentation-url": "https://historicengland.org.uk/listing/the-list/list-entry/1023310", "point": "POINT (-1.758508 51.523827)", "start-date": "1979-09-20", "listed-building-grade": "II", "listed-building": "1023310", "slug": "/listed-building/1023310", "entry-date": "2021-05-28"}}