{"type": "Feature", "geometry": {"type": "Point", "coordinates": [-0.363089, 51.146446]}, "properties": {"listed-building": "1028709", "point": "POINT (-0.363089 51.146446)", "name": "THE TUNS", "documentation-url": "https://historicengland.org.uk/listing/the-list/list-entry/1028709", "start-date": "1966-11-11", "listed-building-grade": "II", "slug": "/listed-building/1028709", "entry-date": "2021-05-28"}}