{"type": "Feature", "geometry": {"type": "Point", "coordinates": [-0.063098, 50.996811]}, "properties": {"start-date": "1983-05-11", "documentation-url": "https://historicengland.org.uk/listing/the-list/list-entry/1025618", "point": "POINT (-0.063098 50.996811)", "listed-building": "1025618", "name": "CUDWELLS COURT AND LORIEN", "listed-building-grade": "II", "slug": "/listed-building/1025618", "entry-date": "2021-05-28"}}