{"type": "Feature", "geometry": {"type": "Point", "coordinates": [-0.812432, 50.856814]}, "properties": {"listed-building-grade": "II*", "name": "SENNICOTTS", "start-date": "1986-01-28", "listed-building": "1026351", "documentation-url": "https://historicengland.org.uk/listing/the-list/list-entry/1026351", "point": "POINT (-0.812432 50.856814)", "slug": "/listed-building/1026351", "entry-date": "2021-05-28"}}