{"type": "Feature", "geometry": {"type": "Point", "coordinates": [-0.272177, 50.928145]}, "properties": {"start-date": "1955-03-15", "name": "GANDERS COTTAGE", "listed-building-grade": "II", "point": "POINT (-0.272177 50.928145)", "documentation-url": "https://historicengland.org.uk/listing/the-list/list-entry/1027410", "listed-building": "1027410", "slug": "/listed-building/1027410", "entry-date": "1980-05-09"}}