{"type": "Feature", "geometry": {"type": "Point", "coordinates": [-0.431342, 50.839589]}, "properties": {"listed-building": "1025838", "listed-building-grade": "II", "documentation-url": "https://historicengland.org.uk/listing/the-list/list-entry/1025838", "name": "CASTLE GORING COTTAGES", "start-date": "1976-05-21", "point": "POINT (-0.431342 50.839589)", "slug": "/listed-building/1025838", "entry-date": "1988-06-13"}}