{"type": "Feature", "geometry": {"type": "Point", "coordinates": [-1.895498, 51.491077]}, "properties": {"listed-building-grade": "II", "listed-building": "1022660", "documentation-url": "https://historicengland.org.uk/listing/the-list/list-entry/1022660", "start-date": "1955-01-17", "point": "POINT (-1.895498 51.491077)", "name": "FINCHES", "slug": "/listed-building/1022660", "entry-date": "2021-05-28"}}