{"type": "Feature", "geometry": {"type": "Point", "coordinates": [-2.078208, 51.467538]}, "properties": {"name": "CHURCH OF ST NICHOLAS", "point": "POINT (-2.078208 51.467538)", "start-date": "1987-11-25", "documentation-url": "https://historicengland.org.uk/listing/the-list/list-entry/1022442", "listed-building": "1022442", "listed-building-grade": "II*", "slug": "/listed-building/1022442", "entry-date": "2021-05-28"}}