{"type": "Feature", "geometry": {"type": "Point", "coordinates": [-0.639499, 51.201542]}, "properties": {"documentation-url": "https://historicengland.org.uk/listing/the-list/list-entry/1029546", "listed-building-grade": "II", "listed-building": "1029546", "point": "POINT (-0.639499 51.201542)", "start-date": "1985-05-21", "name": "BARN, 20 YARDS EAST OF HURTMORE FARM HOUSE", "slug": "/listed-building/1029546", "entry-date": "2021-05-28"}}