{"type": "Feature", "geometry": {"type": "Point", "coordinates": [0.1744, 51.064921]}, "properties": {"start-date": "1982-12-31", "point": "POINT (0.174400 51.064921)", "listed-building": "1028446", "documentation-url": "https://historicengland.org.uk/listing/the-list/list-entry/1028446", "name": "HOURNE FARMHOUSE", "listed-building-grade": "II", "slug": "/listed-building/1028446", "entry-date": "2021-05-28"}}