{"type": "Feature", "geometry": {"type": "Point", "coordinates": [0.114757, 51.024583]}, "properties": {"point": "POINT (0.114757 51.024583)", "name": "TEMPLE GROVE PREPARATORY SCHOOL", "documentation-url": "https://historicengland.org.uk/listing/the-list/list-entry/1028471", "start-date": "1973-04-18", "listed-building": "1028471", "listed-building-grade": "II", "slug": "/listed-building/1028471", "entry-date": "1982-12-31"}}