{"type": "Feature", "geometry": {"type": "Point", "coordinates": [0.234453, 50.81017]}, "properties": {"name": "THE OLD MILL HOUSE", "documentation-url": "https://historicengland.org.uk/listing/the-list/list-entry/1028505", "listed-building-grade": "II", "point": "POINT (0.234453 50.810170)", "start-date": "1981-08-12", "listed-building": "1028505", "slug": "/listed-building/1028505", "entry-date": "2021-05-28"}}