{"type": "Feature", "geometry": {"type": "Point", "coordinates": [-1.691514, 51.572763]}, "properties": {"name": "LOWER EARLSCOURT FARMHOUSE", "start-date": "1979-09-20", "listed-building-grade": "II", "documentation-url": "https://historicengland.org.uk/listing/the-list/list-entry/1023277", "listed-building": "1023277", "point": "POINT (-1.691514 51.572763)", "slug": "/listed-building/1023277", "entry-date": "2021-05-28"}}