{"type": "Feature", "geometry": {"type": "Point", "coordinates": [0.146804, 50.991936]}, "properties": {"name": "OLD HEATHERWODE", "start-date": "1982-12-31", "point": "POINT (0.146804 50.991936)", "documentation-url": "https://historicengland.org.uk/listing/the-list/list-entry/1028476", "listed-building": "1028476", "listed-building-grade": "II", "slug": "/listed-building/1028476", "entry-date": "2021-05-28"}}