{"type": "Feature", "geometry": {"type": "Point", "coordinates": [0.714152, 52.243602]}, "properties": {"point": "POINT (0.714152 52.243602)", "start-date": "1952-08-07", "listed-building-grade": "II", "listed-building": "1022530", "documentation-url": "https://historicengland.org.uk/listing/the-list/list-entry/1022530", "name": "16 AND 17, HATTER STREET", "slug": "/listed-building/1022530", "entry-date": "1997-10-30"}}