{"type": "Feature", "geometry": {"type": "Point", "coordinates": [0.692583, 52.29776]}, "properties": {"start-date": "1984-04-27", "listed-building-grade": "II", "name": "GATES TO CULFORD HALL", "documentation-url": "https://historicengland.org.uk/listing/the-list/list-entry/1031238", "point": "POINT (0.692583 52.297760)", "listed-building": "1031238", "slug": "/listed-building/1031238", "entry-date": "2021-05-28"}}