{"type": "Feature", "geometry": {"type": "Point", "coordinates": [-1.760482, 51.04098]}, "properties": {"documentation-url": "https://historicengland.org.uk/listing/the-list/list-entry/1023839", "listed-building": "1023839", "point": "POINT (-1.760482 51.040980)", "name": "OLD FIRE STATION TO REAR OF NOS 1, 2, 3 AND 4 ESTATE HOUSE", "listed-building-grade": "II", "start-date": "1985-03-28", "slug": "/listed-building/1023839", "entry-date": "2021-05-28"}}