{"type": "Feature", "geometry": {"type": "Point", "coordinates": [-0.696905, 50.779923]}, "properties": {"documentation-url": "https://historicengland.org.uk/listing/the-list/list-entry/1027744", "name": "THATCHED COTTAGE", "listed-building-grade": "II", "start-date": "1975-11-07", "point": "POINT (-0.696905 50.779923)", "listed-building": "1027744", "slug": "/listed-building/1027744", "entry-date": "2021-05-28"}}