{"type": "Feature", "geometry": {"type": "Point", "coordinates": [-0.745846, 50.998941]}, "properties": {"listed-building-grade": "II", "listed-building": "1026013", "documentation-url": "https://historicengland.org.uk/listing/the-list/list-entry/1026013", "point": "POINT (-0.745846 50.998941)", "start-date": "1984-11-09", "name": "HOLLIST FARM BARN", "slug": "/listed-building/1026013", "entry-date": "2021-05-28"}}