{"type": "Feature", "geometry": {"type": "Point", "coordinates": [-0.142249, 51.006838]}, "properties": {"start-date": "1951-09-10", "point": "POINT (-0.142249 51.006838)", "documentation-url": "https://historicengland.org.uk/listing/the-list/list-entry/1025522", "name": "MARSHALLS", "listed-building-grade": "II*", "listed-building": "1025522", "slug": "/listed-building/1025522", "entry-date": "2021-05-28"}}