{"type": "Feature", "geometry": {"type": "Point", "coordinates": [-1.608518, 54.973793]}, "properties": {"listed-building": "1024838", "name": "PLUMMER HOUSE", "listed-building-grade": "II", "start-date": "1987-03-30", "documentation-url": "https://historicengland.org.uk/listing/the-list/list-entry/1024838", "point": "POINT (-1.608518 54.973793)", "slug": "/listed-building/1024838", "entry-date": "2021-05-28"}}