{"type": "Feature", "geometry": {"type": "Point", "coordinates": [1.4303, 52.347776]}, "properties": {"start-date": "1966-12-07", "name": "CHURCH OF ST MARGARET", "listed-building": "1030442", "listed-building-grade": "I", "point": "POINT (1.430300 52.347776)", "documentation-url": "https://historicengland.org.uk/listing/the-list/list-entry/1030442", "slug": "/listed-building/1030442", "entry-date": "2021-05-28"}}