{"type": "Feature", "geometry": {"type": "Point", "coordinates": [0.06221, 50.962204]}, "properties": {"start-date": "1982-12-31", "listed-building-grade": "II", "documentation-url": "https://historicengland.org.uk/listing/the-list/list-entry/1028242", "listed-building": "1028242", "name": "BARN TO THE SOUTH EAST OF BUCKHAM HILL FARMHOUSE", "point": "POINT (0.062210 50.962204)", "slug": "/listed-building/1028242", "entry-date": "2021-05-28"}}