{"type": "Feature", "geometry": {"type": "Point", "coordinates": [-0.673597, 51.221697]}, "properties": {"listed-building": "1029594", "start-date": "1988-01-20", "listed-building-grade": "II", "point": "POINT (-0.673597 51.221697)", "documentation-url": "https://historicengland.org.uk/listing/the-list/list-entry/1029594", "name": "K6 telephone kiosk next to Stile Cottage, at the junction with Dark Lane", "slug": "/listed-building/1029594", "entry-date": "2021-05-28"}}