{"type": "Feature", "geometry": {"type": "Point", "coordinates": [-1.424692, 55.017016]}, "properties": {"listed-building": "1025402", "start-date": "1986-02-19", "name": "1-11 (INC 6A, 7A AND 11A), BATH TERRACE", "documentation-url": "https://historicengland.org.uk/listing/the-list/list-entry/1025402", "listed-building-grade": "II", "point": "POINT (-1.424692 55.017016)", "slug": "/listed-building/1025402", "entry-date": "2021-05-28"}}