{"type": "Feature", "geometry": {"type": "Point", "coordinates": [0.732414, 52.334259]}, "properties": {"listed-building": "1031245", "point": "POINT (0.732414 52.334259)", "documentation-url": "https://historicengland.org.uk/listing/the-list/list-entry/1031245", "name": "SEVEN HILLS HOUSE", "start-date": "1984-04-27", "listed-building-grade": "II", "slug": "/listed-building/1031245", "entry-date": "2021-05-28"}}