{"type": "Feature", "geometry": {"type": "Point", "coordinates": [0.154048, 51.086774]}, "properties": {"name": "THE FORGE", "listed-building-grade": "II", "point": "POINT (0.154048 51.086774)", "documentation-url": "https://historicengland.org.uk/listing/the-list/list-entry/1028018", "listed-building": "1028018", "start-date": "1982-12-31", "slug": "/listed-building/1028018", "entry-date": "2021-05-28"}}