{"type": "Feature", "geometry": {"type": "Point", "coordinates": [-1.332661, 53.656097]}, "properties": {"point": "POINT (-1.332661 53.656097)", "listed-building": "1025126", "documentation-url": "https://historicengland.org.uk/listing/the-list/list-entry/1025126", "start-date": "1968-03-25", "name": "EDEN PLACE", "listed-building-grade": "II", "slug": "/listed-building/1025126", "entry-date": "2021-05-28"}}