{"type": "Feature", "geometry": {"type": "Point", "coordinates": [-0.461608, 50.963907]}, "properties": {"documentation-url": "https://historicengland.org.uk/listing/the-list/list-entry/1027334", "point": "POINT (-0.461608 50.963907)", "listed-building-grade": "II", "start-date": "1955-03-15", "name": "UPPER JORDANS FARMHOUSE", "listed-building": "1027334", "slug": "/listed-building/1027334", "entry-date": "2021-05-28"}}