{"type": "Feature", "geometry": {"type": "Point", "coordinates": [-0.228826, 50.888056]}, "properties": {"listed-building": "1025680", "listed-building-grade": "II", "name": "THE STABLES TO THE SOUTH WEST OF SHEPHERD AND DOG PUBLIC HOUSE", "point": "POINT (-0.228826 50.888056)", "documentation-url": "https://historicengland.org.uk/listing/the-list/list-entry/1025680", "start-date": "1983-05-11", "slug": "/listed-building/1025680", "entry-date": "2021-05-28"}}