{"type": "Feature", "geometry": {"type": "Point", "coordinates": [-2.030112, 51.456469]}, "properties": {"start-date": "1987-11-25", "name": "TWO PINNIGER MONUMENTS IN CHURCHYARD ABOUT 20 METRES NORTH EAST OF CHURCHYARD CROSS", "listed-building": "1022420", "point": "POINT (-2.030112 51.456469)", "listed-building-grade": "II", "documentation-url": "https://historicengland.org.uk/listing/the-list/list-entry/1022420", "slug": "/listed-building/1022420", "entry-date": "2021-05-28"}}