{"type": "Feature", "geometry": {"type": "Point", "coordinates": [-0.67592, 50.793698]}, "properties": {"point": "POINT (-0.675920 50.793698)", "start-date": "1975-11-07", "listed-building-grade": "II", "listed-building": "1027775", "name": "CHURCHYARD WALL OF ST MARY MAGDALEN", "documentation-url": "https://historicengland.org.uk/listing/the-list/list-entry/1027775", "slug": "/listed-building/1027775", "entry-date": "2021-05-28"}}