{"type": "Feature", "geometry": {"type": "Point", "coordinates": [-2.126801, 51.420246]}, "properties": {"listed-building": "1022146", "start-date": "1987-01-07", "listed-building-grade": "II", "documentation-url": "https://historicengland.org.uk/listing/the-list/list-entry/1022146", "point": "POINT (-2.126801 51.420246)", "name": "MILESTONE AT JUNCTION WITH CORSHAM ROAD", "slug": "/listed-building/1022146", "entry-date": "2021-05-28"}}