{"type": "Feature", "geometry": {"type": "Point", "coordinates": [1.274628, 52.178521]}, "properties": {"documentation-url": "https://historicengland.org.uk/listing/the-list/list-entry/1030282", "listed-building": "1030282", "start-date": "1990-09-27", "listed-building-grade": "II", "name": "THE MOAT HOUSE", "point": "POINT (1.274628 52.178521)", "slug": "/listed-building/1030282", "entry-date": "2021-05-28"}}