{"type": "Feature", "geometry": {"type": "Point", "coordinates": [0.217397, 51.046252]}, "properties": {"documentation-url": "https://historicengland.org.uk/listing/the-list/list-entry/1028163", "listed-building-grade": "II", "name": "CHAPEL COTTAGES", "start-date": "1982-12-31", "point": "POINT (0.217397 51.046252)", "listed-building": "1028163", "slug": "/listed-building/1028163", "entry-date": "2021-05-28"}}