{"type": "Feature", "geometry": {"type": "Point", "coordinates": [-1.711095, 51.630677]}, "properties": {"start-date": "1979-09-20", "listed-building": "1023360", "documentation-url": "https://historicengland.org.uk/listing/the-list/list-entry/1023360", "name": "33 AND 33A, HIGH STREET", "point": "POINT (-1.711095 51.630677)", "listed-building-grade": "II", "slug": "/listed-building/1023360", "entry-date": "2021-05-28"}}