{"type": "Feature", "geometry": {"type": "Point", "coordinates": [-0.899862, 50.841888]}, "properties": {"point": "POINT (-0.899862 50.841888)", "listed-building": "1026175", "start-date": "1980-04-23", "documentation-url": "https://historicengland.org.uk/listing/the-list/list-entry/1026175", "name": "THE FORGE", "listed-building-grade": "II", "slug": "/listed-building/1026175", "entry-date": "2021-05-28"}}