{"type": "Feature", "geometry": {"type": "Point", "coordinates": [-0.345373, 51.054874]}, "properties": {"documentation-url": "https://historicengland.org.uk/listing/the-list/list-entry/1027030", "point": "POINT (-0.345373 51.054874)", "listed-building-grade": "II", "name": "BUTLER'S COTTAGE", "listed-building": "1027030", "start-date": "1980-11-28", "slug": "/listed-building/1027030", "entry-date": "2021-05-28"}}