{"type": "Feature", "geometry": {"type": "Point", "coordinates": [-0.650391, 50.790357]}, "properties": {"start-date": "1975-11-07", "point": "POINT (-0.650391 50.790357)", "name": "THE MANOR HOUSE INCLUDING GARDEN WALL TO EAST", "listed-building-grade": "II", "listed-building": "1027752", "documentation-url": "https://historicengland.org.uk/listing/the-list/list-entry/1027752", "slug": "/listed-building/1027752", "entry-date": "2021-05-28"}}