{"type": "Feature", "geometry": {"type": "Point", "coordinates": [0.30891, 51.008152]}, "properties": {"name": "FROGHOLE FARMHOUSE", "listed-building": "1028232", "documentation-url": "https://historicengland.org.uk/listing/the-list/list-entry/1028232", "point": "POINT (0.308910 51.008152)", "start-date": "1953-11-26", "listed-building-grade": "II", "slug": "/listed-building/1028232", "entry-date": "2021-05-28"}}