{"type": "Feature", "geometry": {"type": "Point", "coordinates": [-2.183621, 51.434148]}, "properties": {"listed-building": "1022005", "point": "POINT (-2.183621 51.434148)", "name": "THE COACH HOUSE", "listed-building-grade": "II", "start-date": "1986-08-01", "documentation-url": "https://historicengland.org.uk/listing/the-list/list-entry/1022005", "slug": "/listed-building/1022005", "entry-date": "2021-05-28"}}