{"type": "Feature", "geometry": {"type": "Point", "coordinates": [-1.992499, 51.621182]}, "properties": {"point": "POINT (-1.992499 51.621182)", "documentation-url": "https://historicengland.org.uk/listing/the-list/list-entry/1022257", "start-date": "1951-12-12", "listed-building-grade": "II", "name": "THE MANSELLS", "listed-building": "1022257", "slug": "/listed-building/1022257", "entry-date": "2021-05-28"}}