{"type": "Feature", "geometry": {"type": "Point", "coordinates": [-0.017528, 51.253008]}, "properties": {"listed-building": "1029737", "listed-building-grade": "II", "documentation-url": "https://historicengland.org.uk/listing/the-list/list-entry/1029737", "name": "BROOK HOUSE", "start-date": "1984-11-19", "point": "POINT (-0.017528 51.253008)", "slug": "/listed-building/1029737", "entry-date": "2021-05-28"}}