{"type": "Feature", "geometry": {"type": "Point", "coordinates": [-0.172339, 50.930353]}, "properties": {"listed-building-grade": "II", "start-date": "1983-05-11", "documentation-url": "https://historicengland.org.uk/listing/the-list/list-entry/1025669", "listed-building": "1025669", "name": "TOTT FARMHOUSE", "point": "POINT (-0.172339 50.930353)", "slug": "/listed-building/1025669", "entry-date": "2021-05-28"}}