{"type": "Feature", "geometry": {"type": "Point", "coordinates": [-2.081396, 51.527652]}, "properties": {"listed-building": "1022389", "listed-building-grade": "II", "point": "POINT (-2.081396 51.527652)", "start-date": "1988-02-29", "name": "GATEPIERS AT SEAGRY HOUSE ON ENTRANCE DRIVE", "documentation-url": "https://historicengland.org.uk/listing/the-list/list-entry/1022389", "slug": "/listed-building/1022389", "entry-date": "2021-05-28"}}