{"type": "Feature", "geometry": {"type": "Point", "coordinates": [-0.77956, 50.773308]}, "properties": {"documentation-url": "https://historicengland.org.uk/listing/the-list/list-entry/1026224", "listed-building-grade": "II", "point": "POINT (-0.779560 50.773308)", "name": "ROOKERY FARMHOUSE", "start-date": "1986-01-28", "listed-building": "1026224", "slug": "/listed-building/1026224", "entry-date": "2021-05-28"}}