{"type": "Feature", "geometry": {"type": "Point", "coordinates": [-0.804922, 50.83323]}, "properties": {"start-date": "1950-07-05", "name": "FISHBOURNE MANOR", "listed-building": "1026827", "point": "POINT (-0.804922 50.833230)", "documentation-url": "https://historicengland.org.uk/listing/the-list/list-entry/1026827", "listed-building-grade": "II", "slug": "/listed-building/1026827", "entry-date": "2021-05-28"}}