{"type": "Feature", "geometry": {"type": "Point", "coordinates": [-1.85819, 51.641048]}, "properties": {"start-date": "1976-08-26", "documentation-url": "https://historicengland.org.uk/listing/the-list/list-entry/1023087", "name": "ENTRANCE QUADRANTS, WALL AND STABLE SOUTH WEST OF CANDLETREE", "point": "POINT (-1.858190 51.641048)", "listed-building-grade": "II", "listed-building": "1023087", "slug": "/listed-building/1023087", "entry-date": "2021-05-28"}}