{"type": "Feature", "geometry": {"type": "Point", "coordinates": [0.716455, 52.241255]}, "properties": {"listed-building-grade": "II", "point": "POINT (0.716455 52.241255)", "documentation-url": "https://historicengland.org.uk/listing/the-list/list-entry/1031121", "start-date": "1997-10-30", "listed-building": "1031121", "name": "GREEN KING MALTINGS", "slug": "/listed-building/1031121", "entry-date": "2021-05-28"}}