{"type": "Feature", "geometry": {"type": "Point", "coordinates": [0.248332, 51.069008]}, "properties": {"name": "GREENHEDGES HALL", "start-date": "1982-12-31", "listed-building": "1028139", "point": "POINT (0.248332 51.069008)", "documentation-url": "https://historicengland.org.uk/listing/the-list/list-entry/1028139", "listed-building-grade": "II", "slug": "/listed-building/1028139", "entry-date": "2021-05-28"}}