{"type": "Feature", "geometry": {"type": "Point", "coordinates": [-2.135505, 51.37455]}, "properties": {"name": "13a-13b and 15a-15b Lowbourne", "documentation-url": "https://historicengland.org.uk/listing/the-list/list-entry/1021738", "start-date": "1985-02-13", "listed-building": "1021738", "point": "POINT (-2.135505 51.374550)", "listed-building-grade": "II", "slug": "/listed-building/1021738", "entry-date": "2018-11-29"}}