{"type": "Feature", "geometry": {"type": "Point", "coordinates": [0.134614, 50.991818]}, "properties": {"point": "POINT (0.134614 50.991818)", "start-date": "1982-12-31", "listed-building-grade": "II", "documentation-url": "https://historicengland.org.uk/listing/the-list/list-entry/1028460", "listed-building": "1028460", "name": "TOTEASE FARMHOUSE", "slug": "/listed-building/1028460", "entry-date": "2021-05-28"}}