{"type": "Feature", "geometry": {"type": "Point", "coordinates": [-0.510184, 50.95718]}, "properties": {"start-date": "1980-05-09", "listed-building": "1027344", "name": "TEMPLEMEAD TEMPLEMEAD HOUSE TEMPLEMEAD LODGE", "documentation-url": "https://historicengland.org.uk/listing/the-list/list-entry/1027344", "listed-building-grade": "II", "point": "POINT (-0.510184 50.957180)", "slug": "/listed-building/1027344", "entry-date": "2021-05-28"}}