{"type": "Feature", "geometry": {"type": "Point", "coordinates": [-0.402067, 51.13241]}, "properties": {"listed-building": "1028813", "listed-building-grade": "II", "name": "K6 TELEPHONE KIOSK, WALLISWOOD GREEN ROAD", "point": "POINT (-0.402067 51.132410)", "documentation-url": "https://historicengland.org.uk/listing/the-list/list-entry/1028813", "start-date": "1989-04-17", "slug": "/listed-building/1028813", "entry-date": "2021-05-28"}}