{"type": "Feature", "geometry": {"type": "Point", "coordinates": [-0.093568, 51.041289]}, "properties": {"start-date": "1983-05-11", "documentation-url": "https://historicengland.org.uk/listing/the-list/list-entry/1025795", "name": "THE FORMER FARM BUILDINGS TO THE NORTH OF COLLEGE (NOW CLASSROOMS OF ARDINGLY COLLEGE)", "listed-building-grade": "II", "listed-building": "1025795", "point": "POINT (-0.093568 51.041289)", "slug": "/listed-building/1025795", "entry-date": "2021-05-28"}}