{"type": "Feature", "geometry": {"type": "Point", "coordinates": [1.445881, 52.346717]}, "properties": {"listed-building": "1030490", "start-date": "1985-03-19", "listed-building-grade": "II", "documentation-url": "https://historicengland.org.uk/listing/the-list/list-entry/1030490", "name": "UPPER FARMHOUSE", "point": "POINT (1.445881 52.346717)", "slug": "/listed-building/1030490", "entry-date": "2021-05-28"}}