{"type": "Feature", "geometry": {"type": "Point", "coordinates": [1.389534, 52.231959]}, "properties": {"documentation-url": "https://historicengland.org.uk/listing/the-list/list-entry/1030816", "name": "CHURCH FARMHOUSE", "start-date": "1984-12-21", "listed-building": "1030816", "listed-building-grade": "II", "point": "POINT (1.389534 52.231959)", "slug": "/listed-building/1030816", "entry-date": "2021-05-28"}}