{"type": "Feature", "geometry": {"type": "Point", "coordinates": [0.264683, 51.020612]}, "properties": {"listed-building": "1028211", "listed-building-grade": "II", "documentation-url": "https://historicengland.org.uk/listing/the-list/list-entry/1028211", "point": "POINT (0.264683 51.020612)", "start-date": "1982-12-31", "name": "POUND HILL HOUSE", "slug": "/listed-building/1028211", "entry-date": "2021-05-28"}}