{"type": "Feature", "geometry": {"type": "Point", "coordinates": [-0.556978, 50.853107]}, "properties": {"documentation-url": "https://historicengland.org.uk/listing/the-list/list-entry/1027930", "listed-building-grade": "II", "start-date": "1974-10-07", "point": "POINT (-0.556978 50.853107)", "name": "11 AND 13, ARUN STREET", "listed-building": "1027930", "slug": "/listed-building/1027930", "entry-date": "2021-05-28"}}