{"type": "Feature", "geometry": {"type": "Point", "coordinates": [-0.27139, 51.249013]}, "properties": {"start-date": "1986-01-21", "documentation-url": "https://historicengland.org.uk/listing/the-list/list-entry/1028781", "listed-building": "1028781", "name": "HOFFMAN KILN AT BETCHWORTH PITS TQ20755140", "point": "POINT (-0.271390 51.249013)", "listed-building-grade": "II", "slug": "/listed-building/1028781", "entry-date": "2021-05-28"}}