{"type": "Feature", "geometry": {"type": "Point", "coordinates": [1.536165, 52.093448]}, "properties": {"documentation-url": "https://historicengland.org.uk/listing/the-list/list-entry/1030884", "listed-building-grade": "II", "name": "BELL HOUSE CONNISTON LISMORE", "listed-building": "1030884", "point": "POINT (1.536165 52.093448)", "start-date": "1966-03-16", "slug": "/listed-building/1030884", "entry-date": "1984-01-16"}}