{"type": "Feature", "geometry": {"type": "Point", "coordinates": [-0.126836, 51.239143]}, "properties": {"name": "The Queens Head Public House", "start-date": "1984-04-25", "listed-building": "1029867", "point": "POINT (-0.126836 51.239143)", "listed-building-grade": "II", "documentation-url": "https://historicengland.org.uk/listing/the-list/list-entry/1029867", "slug": "/listed-building/1029867", "entry-date": "2014-03-13"}}