{"type": "Feature", "geometry": {"type": "Point", "coordinates": [0.76662, 52.306781]}, "properties": {"documentation-url": "https://historicengland.org.uk/listing/the-list/list-entry/1031242", "start-date": "1984-04-27", "listed-building-grade": "II", "listed-building": "1031242", "point": "POINT (0.766620 52.306781)", "name": "POST OFFICE", "slug": "/listed-building/1031242", "entry-date": "2021-05-28"}}