{"type": "Feature", "geometry": {"type": "Point", "coordinates": [-0.282298, 51.176209]}, "properties": {"point": "POINT (-0.282298 51.176209)", "documentation-url": "https://historicengland.org.uk/listing/the-list/list-entry/1028724", "name": "LANCE'S COTTAGE NIGHTINGALES", "listed-building-grade": "II", "start-date": "1987-08-06", "listed-building": "1028724", "slug": "/listed-building/1028724", "entry-date": "2021-05-28"}}