{"type": "Feature", "geometry": {"type": "Point", "coordinates": [-2.311055, 52.942765]}, "properties": {"name": "PARK BRIDGE, STEPS AND REVETMENT WALLS ABOUT 100 METRES NORTH OF MAER HALL", "start-date": "1985-05-14", "listed-building-grade": "II", "point": "POINT (-2.311055 52.942765)", "listed-building": "1027836", "documentation-url": "https://historicengland.org.uk/listing/the-list/list-entry/1027836", "slug": "/listed-building/1027836", "entry-date": "2021-05-28"}}