{"type": "Feature", "geometry": {"type": "Point", "coordinates": [-2.09572, 51.457166]}, "properties": {"listed-building-grade": "II", "name": "HARDEN'S FARMHOUSE", "point": "POINT (-2.095720 51.457166)", "start-date": "1987-11-25", "documentation-url": "https://historicengland.org.uk/listing/the-list/list-entry/1022430", "listed-building": "1022430", "slug": "/listed-building/1022430", "entry-date": "2021-05-28"}}