{"type": "Feature", "geometry": {"type": "Point", "coordinates": [-2.203747, 51.572344]}, "properties": {"documentation-url": "https://historicengland.org.uk/listing/the-list/list-entry/1023236", "start-date": "1951-12-12", "listed-building": "1023236", "listed-building-grade": "II", "point": "POINT (-2.203747 51.572344)", "name": "EASTON TOWN FARMHOUSE", "slug": "/listed-building/1023236", "entry-date": "2021-05-28"}}