{"type": "Feature", "geometry": {"type": "Point", "coordinates": [1.465883, 52.089771]}, "properties": {"documentation-url": "https://historicengland.org.uk/listing/the-list/list-entry/1030853", "name": "BUTLEY ABBEY AND PRIORY RERE-DORTER (REFECTORY)", "listed-building": "1030853", "point": "POINT (1.465883 52.089771)", "start-date": "1966-03-16", "listed-building-grade": "II", "slug": "/listed-building/1030853", "entry-date": "1984-05-02"}}