{"type": "Feature", "geometry": {"type": "Point", "coordinates": [-0.240229, 51.253232]}, "properties": {"documentation-url": "https://historicengland.org.uk/listing/the-list/list-entry/1028755", "listed-building-grade": "II", "name": "CART SHED AT UNDERHILL FARM", "start-date": "1987-09-29", "point": "POINT (-0.240229 51.253232)", "listed-building": "1028755", "slug": "/listed-building/1028755", "entry-date": "2021-05-28"}}