{"type": "Feature", "geometry": {"type": "Point", "coordinates": [-0.780532, 50.841161]}, "properties": {"name": "GATE PIERS FLANKING CHURCH YARD ENTRANCE ON WEST SIDE", "listed-building": "1026676", "documentation-url": "https://historicengland.org.uk/listing/the-list/list-entry/1026676", "start-date": "1971-10-08", "listed-building-grade": "II", "point": "POINT (-0.780532 50.841161)", "slug": "/listed-building/1026676", "entry-date": "2021-05-28"}}