{"type": "Feature", "geometry": {"type": "Point", "coordinates": [-0.365146, 51.369205]}, "properties": {"listed-building-grade": "II", "start-date": "1969-05-28", "documentation-url": "https://historicengland.org.uk/listing/the-list/list-entry/1030193", "listed-building": "1030193", "name": "THE BEAR HOTEL", "point": "POINT (-0.365146 51.369205)", "slug": "/listed-building/1030193", "entry-date": "2021-05-28"}}