{"type": "Feature", "geometry": {"type": "Point", "coordinates": [-1.367167, 52.1427]}, "properties": {"listed-building": "1024466", "point": "POINT (-1.367167 52.142700)", "listed-building-grade": "II", "documentation-url": "https://historicengland.org.uk/listing/the-list/list-entry/1024466", "name": "CHEST TOMB APPROXIMATELY 6 METRES EAST OF SOUTH EAST CORNER OF CHANCEL OF CHURCH OF ST BOTOLPH", "start-date": "1986-04-21", "slug": "/listed-building/1024466", "entry-date": "2021-05-28"}}