{"type": "Feature", "geometry": {"type": "Point", "coordinates": [0.786513, 52.315639]}, "properties": {"name": "CHURCH OF ST MARY", "listed-building-grade": "I", "documentation-url": "https://historicengland.org.uk/listing/the-list/list-entry/1031250", "start-date": "1955-07-14", "point": "POINT (0.786513 52.315639)", "listed-building": "1031250", "slug": "/listed-building/1031250", "entry-date": "2021-05-28"}}