{"type": "Feature", "geometry": {"type": "Point", "coordinates": [-0.779, 50.956909]}, "properties": {"documentation-url": "https://historicengland.org.uk/listing/the-list/list-entry/1026058", "listed-building": "1026058", "name": "UPPER FARMHOUSE", "listed-building-grade": "II", "point": "POINT (-0.779000 50.956909)", "start-date": "1987-11-26", "slug": "/listed-building/1026058", "entry-date": "2021-05-28"}}