{"type": "Feature", "geometry": {"type": "Point", "coordinates": [-1.610848, 52.048788]}, "properties": {"listed-building-grade": "II", "start-date": "1986-06-30", "point": "POINT (-1.610848 52.048788)", "name": "COLLEGE FARMHOUSE", "documentation-url": "https://historicengland.org.uk/listing/the-list/list-entry/1024412", "listed-building": "1024412", "slug": "/listed-building/1024412", "entry-date": "2021-05-28"}}