{"type": "Feature", "geometry": {"type": "Point", "coordinates": [-1.701123, 50.975216]}, "properties": {"documentation-url": "https://historicengland.org.uk/listing/the-list/list-entry/1023927", "listed-building": "1023927", "start-date": "1985-07-04", "listed-building-grade": "II", "point": "POINT (-1.701123 50.975216)", "name": "LOOSEHANGER FARMHOUSE", "slug": "/listed-building/1023927", "entry-date": "2021-05-28"}}