{"type": "Feature", "geometry": {"type": "Point", "coordinates": [-1.837435, 52.190478]}, "properties": {"point": "POINT (-1.837435 52.190478)", "name": "HILLSIDE", "listed-building": "1024682", "listed-building-grade": "II", "documentation-url": "https://historicengland.org.uk/listing/the-list/list-entry/1024682", "start-date": "1984-12-13", "slug": "/listed-building/1024682", "entry-date": "2021-05-28"}}