{"type": "Feature", "geometry": {"type": "Point", "coordinates": [1.260471, 52.1244]}, "properties": {"listed-building-grade": "II", "listed-building": "1030749", "name": "LOOMS COTTAGE", "start-date": "1988-08-31", "point": "POINT (1.260471 52.124400)", "documentation-url": "https://historicengland.org.uk/listing/the-list/list-entry/1030749", "slug": "/listed-building/1030749", "entry-date": "2021-05-28"}}