{"type": "Feature", "geometry": {"type": "Point", "coordinates": [-3.00008, 51.128513]}, "properties": {"start-date": "1974-12-16", "listed-building": "1024991", "documentation-url": "https://historicengland.org.uk/listing/the-list/list-entry/1024991", "name": "7 AND 8, SALMON PARADE", "point": "POINT (-3.000080 51.128513)", "listed-building-grade": "II", "slug": "/listed-building/1024991", "entry-date": "1994-01-31"}}