{"type": "Feature", "geometry": {"type": "Point", "coordinates": [0.764494, 52.307739]}, "properties": {"listed-building-grade": "II", "documentation-url": "https://historicengland.org.uk/listing/the-list/list-entry/1031240", "point": "POINT (0.764494 52.307739)", "name": "CHURCH CLOSE", "start-date": "1984-04-27", "listed-building": "1031240", "slug": "/listed-building/1031240", "entry-date": "2021-05-28"}}