{"type": "Feature", "geometry": {"type": "Point", "coordinates": [-0.777812, 50.837053]}, "properties": {"name": "2 AND 3, ST MARTIN'S STREET", "listed-building-grade": "II", "listed-building": "1026662", "start-date": "1950-07-05", "point": "POINT (-0.777812 50.837053)", "documentation-url": "https://historicengland.org.uk/listing/the-list/list-entry/1026662", "slug": "/listed-building/1026662", "entry-date": "2021-05-28"}}