{"type": "Feature", "geometry": {"type": "Point", "coordinates": [-2.209992, 51.321]}, "properties": {"documentation-url": "https://historicengland.org.uk/listing/the-list/list-entry/1021569", "start-date": "1976-11-26", "point": "POINT (-2.209992 51.321000)", "name": "BUILDING AT REAR OF NOS 1 AND 1A", "listed-building": "1021569", "listed-building-grade": "II", "slug": "/listed-building/1021569", "entry-date": "2021-05-28"}}