{"type": "Feature", "geometry": {"type": "Point", "coordinates": [-0.432705, 51.35074]}, "properties": {"start-date": "1984-11-16", "listed-building": "1030116", "point": "POINT (-0.432705 51.350740)", "documentation-url": "https://historicengland.org.uk/listing/the-list/list-entry/1030116", "name": "ADMINISTRATION BLOCK", "listed-building-grade": "II", "slug": "/listed-building/1030116", "entry-date": "2021-05-28"}}