{"type": "Feature", "geometry": {"type": "Point", "coordinates": [-2.228588, 51.491959]}, "properties": {"documentation-url": "https://historicengland.org.uk/listing/the-list/list-entry/1022890", "name": "WEAVERS HOUSE", "listed-building": "1022890", "start-date": "1985-12-09", "point": "POINT (-2.228588 51.491959)", "listed-building-grade": "II", "slug": "/listed-building/1022890", "entry-date": "2021-05-28"}}