{"type": "Feature", "geometry": {"type": "Point", "coordinates": [-1.615636, 54.971019]}, "properties": {"start-date": "1971-12-17", "documentation-url": "https://historicengland.org.uk/listing/the-list/list-entry/1024864", "listed-building": "1024864", "name": "CHAUCER BUILDINGS", "point": "POINT (-1.615636 54.971019)", "listed-building-grade": "II", "slug": "/listed-building/1024864", "entry-date": "2021-05-28"}}