{"type": "Feature", "geometry": {"type": "Point", "coordinates": [1.341973, 52.115919]}, "properties": {"name": "MELTON LODGE", "documentation-url": "https://historicengland.org.uk/listing/the-list/list-entry/1030399", "listed-building-grade": "II", "start-date": "1985-06-11", "point": "POINT (1.341973 52.115919)", "listed-building": "1030399", "slug": "/listed-building/1030399", "entry-date": "2021-05-28"}}