{"type": "Feature", "geometry": {"type": "Point", "coordinates": [-0.668051, 50.836406]}, "properties": {"start-date": "1984-09-20", "listed-building": "1027707", "documentation-url": "https://historicengland.org.uk/listing/the-list/list-entry/1027707", "name": "MILLIARDS MANOR FARMHOUSE", "listed-building-grade": "II", "point": "POINT (-0.668051 50.836406)", "slug": "/listed-building/1027707", "entry-date": "2021-05-28"}}