{"type": "Feature", "geometry": {"type": "Point", "coordinates": [-2.089904, 51.410018]}, "properties": {"start-date": "1987-01-07", "name": "MILESTONE SOUTH EAST OF CHURCH OF ST ANNE", "listed-building-grade": "II", "listed-building": "1022136", "point": "POINT (-2.089904 51.410018)", "documentation-url": "https://historicengland.org.uk/listing/the-list/list-entry/1022136", "slug": "/listed-building/1022136", "entry-date": "2021-05-28"}}