{"type": "Feature", "geometry": {"type": "Point", "coordinates": [0.170104, 51.013475]}, "properties": {"point": "POINT (0.170104 51.013475)", "listed-building-grade": "II", "listed-building": "1028013", "start-date": "1984-04-26", "name": "HASTINGFORD COTTAGE", "documentation-url": "https://historicengland.org.uk/listing/the-list/list-entry/1028013", "slug": "/listed-building/1028013", "entry-date": "2021-05-28"}}