{"type": "Feature", "geometry": {"type": "Point", "coordinates": [-2.205546, 51.353711]}, "properties": {"listed-building": "1021809", "name": "DEVON COTTAGE", "listed-building-grade": "II", "point": "POINT (-2.205546 51.353711)", "start-date": "1962-11-13", "documentation-url": "https://historicengland.org.uk/listing/the-list/list-entry/1021809", "slug": "/listed-building/1021809", "entry-date": "2021-05-28"}}