{"type": "Feature", "geometry": {"type": "Point", "coordinates": [-0.882411, 50.969995]}, "properties": {"point": "POINT (-0.882411 50.969995)", "listed-building-grade": "II", "start-date": "1959-06-18", "documentation-url": "https://historicengland.org.uk/listing/the-list/list-entry/1025959", "name": "Port Cottage and Starboard Cottage", "listed-building": "1025959", "slug": "/listed-building/1025959", "entry-date": "2021-05-28"}}