{"type": "Feature", "geometry": {"type": "Point", "coordinates": [-0.759551, 50.94621]}, "properties": {"listed-building": "1026066", "point": "POINT (-0.759551 50.946210)", "start-date": "1959-06-18", "listed-building-grade": "II", "documentation-url": "https://historicengland.org.uk/listing/the-list/list-entry/1026066", "name": "CRYPT FARMHOUSE", "slug": "/listed-building/1026066", "entry-date": "2021-05-28"}}