{"type": "Feature", "geometry": {"type": "Point", "coordinates": [0.262189, 51.020652]}, "properties": {"documentation-url": "https://historicengland.org.uk/listing/the-list/list-entry/1028178", "listed-building-grade": "II", "listed-building": "1028178", "point": "POINT (0.262189 51.020652)", "start-date": "1953-11-26", "name": "THE GATEHOUSE OF THE OLD PALACE (THE CONVENT OF THE HOLY CHILD JESUS, ST LEONARD'S MAYFIELD SCHOOL)", "slug": "/listed-building/1028178", "entry-date": "2021-05-28"}}