{"type": "Feature", "geometry": {"type": "Point", "coordinates": [0.359838, 50.87167]}, "properties": {"documentation-url": "https://historicengland.org.uk/listing/the-list/list-entry/1028555", "listed-building-grade": "II", "name": "CHAMPNEYS FARMHOUSE", "point": "POINT (0.359838 50.871670)", "listed-building": "1028555", "start-date": "1966-08-30", "slug": "/listed-building/1028555", "entry-date": "2021-05-28"}}