{"type": "Feature", "geometry": {"type": "Point", "coordinates": [-1.629161, 54.971328]}, "properties": {"documentation-url": "https://historicengland.org.uk/listing/the-list/list-entry/1024757", "listed-building": "1024757", "point": "POINT (-1.629161 54.971328)", "listed-building-grade": "II*", "name": "CHURCH OF ST MATTHEW", "start-date": "1954-06-14", "slug": "/listed-building/1024757", "entry-date": "2021-05-28"}}