{"type": "Feature", "geometry": {"type": "Point", "coordinates": [-1.712124, 51.629738]}, "properties": {"name": "30 AND 31, SWINDON STREET", "listed-building": "1023382", "point": "POINT (-1.712124 51.629738)", "start-date": "1979-09-20", "listed-building-grade": "II", "documentation-url": "https://historicengland.org.uk/listing/the-list/list-entry/1023382", "slug": "/listed-building/1023382", "entry-date": "2021-05-28"}}