{"type": "Feature", "geometry": {"type": "Point", "coordinates": [-0.176567, 51.228769]}, "properties": {"listed-building-grade": "II", "documentation-url": "https://historicengland.org.uk/listing/the-list/list-entry/1029112", "start-date": "1976-03-17", "listed-building": "1029112", "point": "POINT (-0.176567 51.228769)", "name": "117 AND 119, FOUNTAIN ROAD", "slug": "/listed-building/1029112", "entry-date": "2021-05-28"}}