{"type": "Feature", "geometry": {"type": "Point", "coordinates": [1.576948, 52.295626]}, "properties": {"documentation-url": "https://historicengland.org.uk/listing/the-list/list-entry/1030704", "start-date": "1951-10-25", "listed-building-grade": "II", "point": "POINT (1.576948 52.295626)", "listed-building": "1030704", "name": "HINTON HALL", "slug": "/listed-building/1030704", "entry-date": "2021-05-28"}}