{"type": "Feature", "geometry": {"type": "Point", "coordinates": [-1.732339, 54.919744]}, "properties": {"name": "GARDEN WALL TO NORTH OF CHAPEL HOUSE AND GARDEN HOUSE", "listed-building-grade": "II", "point": "POINT (-1.732339 54.919744)", "documentation-url": "https://historicengland.org.uk/listing/the-list/list-entry/1025168", "start-date": "1985-11-18", "listed-building": "1025168", "slug": "/listed-building/1025168", "entry-date": "2021-05-28"}}