{"type": "Feature", "geometry": {"type": "Point", "coordinates": [-0.403482, 51.406898]}, "properties": {"start-date": "1987-09-24", "name": "RIVERBANK", "point": "POINT (-0.403482 51.406898)", "documentation-url": "https://historicengland.org.uk/listing/the-list/list-entry/1029644", "listed-building-grade": "II", "listed-building": "1029644", "slug": "/listed-building/1029644", "entry-date": "2021-05-28"}}